Workbook
Name Nav_DealAssumptions: 'UW Model'!$C$5
Name Nav_Expenses: 'UW Model'!$C$76
Name Nav_GrowthRates: 'UW Model'!$C$102
Name Nav_Income: 'UW Model'!$C$46
Name Nav_QuikUw: 'UW Model'!$T$6
Name Nav_Summary: #REF!
Name Nav_UnitMix: 'UW Model'!$C$26
Name RentGraphInPlaceRent: INDIRECT(#REF!)
Name RentGraphLabels: INDIRECT(#REF!)
Name RentGraphMarket: INDIRECT(#REF!)
Name RentGraphMarketRentAdd: INDIRECT(#REF!)
Name RentGraphReno: INDIRECT(#REF!)
Name RentGraphRenoUnits: INDIRECT(#REF!)
Name RentGraphTotal: INDIRECT(#REF!)
Name RentGraphTotalUnits: INDIRECT(#REF!)
Name ROIAbove: INDIRECT(#REF!)
Name ROIBelow: INDIRECT(#REF!)
Name ROIGoal: INDIRECT(#REF!)
Name T12_Flow: #REF!
Name T12Data: #REF!
Name UnitMixLabels: INDIRECT(#REF!)
Name UnitMixValues: INDIRECT(#REF!)
Name UW_Baths: 'UW Model'!$F$28:$F$42
Name UW_Beds: 'UW Model'!$E$28:$E$42
Name UW_InPlaceRent: 'UW Model'!$I$28:$I$42
Name UW_MarketRent: 'UW Model'!$L$28:$L$42
Name UW_SF: 'UW Model'!$G$28:$G$42
Name UW_UnitNames: 'UW Model'!$C$28:$C$42
Name UW_Units: 'UW Model'!$H$28:$H$42

Sheet Disclaimer
N1: ="Version "&MAX(Version!B2:B1000) -> Version 1.01
E3: Disclaimer: This spreadsheet is for your personal use only. You may use and access this spreadsheet on multiple devices but you may not share it with other users. All of the information contained herein is believed to be true and accurate. The author shall not be held liable to you for any damages arising from the use or the inability to use this software
B12: Compatibility | C12: Excel 2021, Excel 2021 for Mac ONLY (Not Excel for web, older versions of Excel, or Google sheets)
B15: Font Color Ledged | C15: BLUE | D15: Input / Manual entry
C16: ORANGE | D16: Formulas, but can be overwritten
C17: BLACK | D17: Formulas - do not change
B24: Copyright © MFA 2022 - MFAUnderwriting.com

Sheet UW Process
C2: UNDERWRITING STEPS & DATA INPUT CHECK
C3: STEP | D3: UNDERWRITING TASKS (link to tab) | E3: VIDEO TUTORIALS | F3: INPUT CHECK | AH3: Required | AI3: Completed | AJ3: Indicator | AK3: Section Indicator
A4: =AJ4 -> 0 | C4: Step 1 | D4: Input Deal Assumptions | E4: Deal Assumptions | F4: =IF(AJ4=1,"✅ "&AG4,"⬜ "&AG4) -> ⬜ Property Info | AF4: Deal Assumptions | AG4: Property Info | AH4: 4 | AI4: =COUNTA('UW Model'!E7:G7,'UW Model'!E8:G8,'UW Model'!E9,'UW Model'!G9) -> 1 | AJ4: =IF(AI4=AH4,1,0) -> 0 | AK4: =IF(SUM(AJ4:AJ10)=7,1,0) -> 0
A5: =AJ5 -> 0 | F5: =IF(AJ5=1,"✅ "&AG5,"⬜ "&AG5) -> ⬜ Purchase Assumptions | AG5: Purchase Assumptions | AH5: 7 | AI5: =COUNTA('UW Model'!G11:G14,'UW Model'!G16:G18) -> 5 | AJ5: =IF(AI5=AH5,1,0) -> 0
A6: =AJ6 -> 1 | F6: =IF(AJ6=1,"✅ "&AG6,"⬜ "&AG6) -> ✅ Exit Assumptions | AG6: Exit Assumptions | AH6: 4 | AI6: =COUNTA('UW Model'!G20:G22,'UW Model'!F23) -> 4 | AJ6: =IF(AI6=AH6,1,0) -> 1
A7: =AJ7 -> 0 | F7: =IF(AJ7=1,"✅ "&AG7,"⬜ "&AG7) -> ⬜ Debt Structure | AG7: Debt Structure | AH7: 1 | AI7: =IF('UW Model'!K8>0,1,0) -> 0 | AJ7: =IF(AI7=AH7,1,0) -> 0
A8: =AJ8 -> 1 | F8: =IF(AJ8=1,"✅ "&AG8,"⬜ "&AG8) -> ✅ Deal Structure | AG8: Deal Structure | AH8: 6 | AI8: =COUNTA('UW Model'!O7:O12) -> 6 | AJ8: =IF(AI8=AH8,1,0) -> 1
A9: =AJ9 -> 0 | F9: =IF(AJ9=1,"✅ "&AG9,"⬜ "&AG9) -> ⬜ Renovation Assumptions | AG9: Renovation Assumptions | AH9: 1 | AI9: =IF(AND('UW Model'!O15>'UW Model'!O14,'UW Model'!O23>0),1,0) -> 0 | AJ9: =IF(AI9=AH9,1,0) -> 0
A10: =AJ10 -> 1 | F10: =IF(AJ10=1,"✅ "&AG10,"⬜ "&AG10) -> ✅ KPIs | AG10: KPIs | AH10: 4 | AI10: =COUNTA('UW Model'!R7:R10) -> 4 | AJ10: =IF(AI10=AH10,1,0) -> 1
A11: =AJ11 -> 0 | C11: Step 2 | D11: Unit Mix, Rents, Interior Renovation Strategy | E11: Unit Mix, Rent, & Interior Renovation | F11: =IF(AJ11=1,"✅ "&AG11,"⬜ "&AG11) -> ⬜ Bed | AF11: Unit Mix Table | AG11: Bed | AH11: 1 | AI11: =IF(COUNTA(UW_Beds)>0,1,0) -> 0 | AJ11: =IF(AI11=AH11,1,0) -> 0 | AK11: =IF(SUM(AJ11:AJ17)=7,1,0) -> 0
A12: =AJ12 -> 0 | F12: =IF(AJ12=1,"✅ "&AG12,"⬜ "&AG12) -> ⬜ Bath | AG12: Bath | AH12: 1 | AI12: =IF(COUNTA(UW_Baths)>0,1,0) -> 0 | AJ12: =IF(AI12=AH12,1,0) -> 0
A13: =AJ13 -> 0 | F13: =IF(AJ13=1,"✅ "&AG13,"⬜ "&AG13) -> ⬜ Sqft | AG13: Sqft | AH13: 1 | AI13: =IF(COUNTA(UW_SF)>0,1,0) -> 0 | AJ13: =IF(AI13=AH13,1,0) -> 0
A14: =AJ14 -> 0 | F14: =IF(AJ14=1,"✅ "&AG14,"⬜ "&AG14) -> ⬜ Units | AG14: Units | AH14: 1 | AI14: =IF(COUNTA(UW_Units)>0,1,0) -> 0 | AJ14: =IF(AI14=AH14,1,0) -> 0
A15: =AJ15 -> 0 | F15: =IF(AJ15=1,"✅ "&AG15,"⬜ "&AG15) -> ⬜ In-Place Rents | AG15: In-Place Rents | AH15: 1 | AI15: =IF(COUNTA(UW_InPlaceRent)>0,1,0) -> 0 | AJ15: =IF(AI15=AH15,1,0) -> 0
A16: =AJ16 -> 0 | F16: =IF(AJ16=1,"✅ "&AG16,"⬜ "&AG16) -> ⬜ Market Rents | AG16: Market Rents | AH16: 1 | AI16: =IF(COUNTA(UW_MarketRent)>0,1,0) -> 0 | AJ16: =IF(AI16=AH16,1,0) -> 0
A17: =AJ17 -> 0 | F17: =IF(AJ17=1,"✅ "&AG17,"⬜ "&AG17) -> ⬜ Interior Renovations | AG17: Interior Renovations | AH17: 1 | AI17: =IF(AND('UW Model'!O43>0,'UW Model'!P43>0,'UW Model'!R43>0),1,0) -> 0 | AJ17: =IF(AI17=AH17,1,0) -> 0
A18: =AJ18 -> 0 | C18: Step 3 | D18: Income | E18: Income, Expenses, & Growth | F18: =IF(AJ18=1,"✅ "&AG18,"⬜ "&AG18) -> ⬜ GPR | AF18: Income | AG18: GPR | AH18: 1 | AI18: =IF('UW Model'!M48>0,1,0) -> 0 | AJ18: =IF(AI18=AH18,1,0) -> 0 | AK18: =IF(SUM(AJ18:AJ21)=4,1,0) -> 0
A19: =AJ19 -> 0 | F19: =IF(AJ19=1,"✅ "&AG19,"⬜ "&AG19) -> ⬜ Income Detractors | AG19: Income Detractors | AH19: 1 | AI19: =IF(SUM('UW Model'!K56:K60)>0,1,0) -> 0 | AJ19: =IF(AI19=AH19,1,0) -> 0
A20: =AJ20 -> 0 | F20: =IF(AJ20=1,"✅ "&AG20,"⬜ "&AG20) -> ⬜ RUBS | AG20: RUBS | AH20: 1 | AI20: =IF('UW Model'!M64>0,1,0) -> 0 | AJ20: =IF(AI20=AH20,1,0) -> 0
A21: =AJ21 -> 0 | F21: =IF(AJ21=1,"✅ "&AG21,"⬜ "&AG21) -> ⬜ Other Income | AG21: Other Income | AH21: 1 | AI21: =IF('UW Model'!M65>0,1,0) -> 0 | AJ21: =IF(AI21=AH21,1,0) -> 0
A22: =AJ22 -> 0 | C22: Step 4 | D22: Expenses | E22: Income, Expenses, & Growth | F22: =IF(AJ22=1,"✅ "&AG22,"⬜ "&AG22) -> ⬜ Payroll | AF22: Expenses | AG22: Payroll | AH22: 1 | AI22: =IF('UW Model'!M78>1,1,0) -> 0 | AJ22: =IF(AI22=AH22,1,0) -> 0 | AK22: =IF(SUM(AJ22:AJ31)=10,1,0) -> 0
A23: =AJ23 -> 0 | F23: =IF(AJ23=1,"✅ "&AG23,"⬜ "&AG23) -> ⬜ Advertising & Marketing | AG23: Advertising & Marketing | AH23: 1 | AI23: =IF('UW Model'!M79>1,1,0) -> 0 | AJ23: =IF(AI23=AH23,1,0) -> 0
A24: =AJ24 -> 0 | F24: =IF(AJ24=1,"✅ "&AG24,"⬜ "&AG24) -> ⬜ General & Administrative | AG24: General & Administrative | AH24: 1 | AI24: =IF('UW Model'!M80>1,1,0) -> 0 | AJ24: =IF(AI24=AH24,1,0) -> 0 | AL24: Used for UW Aid Conditional Formatting
A25: =AJ25 -> 0 | F25: =IF(AJ25=1,"✅ "&AG25,"⬜ "&AG25) -> ⬜ Utilities | AG25: Utilities | AH25: 1 | AI25: =IF('UW Model'!M81>1,1,0) -> 0 | AJ25: =IF(AI25=AH25,1,0) -> 0 | AN25: T-12 Mapped | AP25: =IF(AND(#REF!>0,#REF!>0),TRUE,FALSE) -> #REF!
A26: =AJ26 -> 0 | F26: =IF(AJ26=1,"✅ "&AG26,"⬜ "&AG26) -> ⬜ Repairs & Maintenance | AG26: Repairs & Maintenance | AH26: 1 | AI26: =IF('UW Model'!M82>1,1,0) -> 0 | AJ26: =IF(AI26=AH26,1,0) -> 0
A27: =AJ27 -> 0 | F27: =IF(AJ27=1,"✅ "&AG27,"⬜ "&AG27) -> ⬜ Contract Services | AG27: Contract Services | AH27: 1 | AI27: =IF('UW Model'!M83>1,1,0) -> 0 | AJ27: =IF(AI27=AH27,1,0) -> 0
A28: =AJ28 -> 0 | F28: =IF(AJ28=1,"✅ "&AG28,"⬜ "&AG28) -> ⬜ Management Fee | AG28: Management Fee | AH28: 1 | AI28: =IF('UW Model'!M84>1,1,0) -> 0 | AJ28: =IF(AI28=AH28,1,0) -> 0
A29: =AJ29 -> 0 | F29: =IF(AJ29=1,"✅ "&AG29,"⬜ "&AG29) -> ⬜ Make Ready | AG29: Make Ready | AH29: 1 | AI29: =IF('UW Model'!M85>1,1,0) -> 0 | AJ29: =IF(AI29=AH29,1,0) -> 0
A30: =AJ30 -> 0 | F30: =IF(AJ30=1,"✅ "&AG30,"⬜ "&AG30) -> ⬜ Taxes | AG30: Taxes | AH30: 1 | AI30: =IF('UW Model'!M86>1,1,0) -> 0 | AJ30: =IF(AI30=AH30,1,0) -> 0
A31: =AJ31 -> 0 | F31: =IF(AJ31=1,"✅ "&AG31,"⬜ "&AG31) -> ⬜ Insurance | AG31: Insurance | AH31: 1 | AI31: =IF('UW Model'!M87>1,1,0) -> 0 | AJ31: =IF(AI31=AH31,1,0) -> 0
A32: =AJ32 -> 1 | C32: Step 5 | D32: Growth Rates & % GPR Assumptions | E32: Income, Expenses, & Growth | F32: =IF(AJ32=1,"✅ "&AG32,"⬜ "&AG32) -> ✅ Rent | AF32: Growth Rate | AG32: Rent | AH32: 1 | AI32: =IF(SUM('UW Model'!M104:Q104)>0,1,0) -> 1 | AJ32: =IF(AI32=AH32,1,0) -> 1 | AK32: =IF(SUM(AJ32:AJ37)=6,1,0) -> 1
A33: =AJ33 -> 1 | F33: =IF(AJ33=1,"✅ "&AG33,"⬜ "&AG33) -> ✅ Other Income | AG33: Other Income | AH33: 1 | AI33: =IF(SUM('UW Model'!N112:Q112)>0,1,0) -> 1 | AJ33: =IF(AI33=AH33,1,0) -> 1
A34: =AJ34 -> 1 | F34: =IF(AJ34=1,"✅ "&AG34,"⬜ "&AG34) -> ✅ Vacancy | AG34: Vacancy | AH34: 1 | AI34: =IF(SUM('UW Model'!N107:Q107)>0,1,0) -> 1 | AJ34: =IF(AI34=AH34,1,0) -> 1
A35: =AJ35 -> 1 | F35: =IF(AJ35=1,"✅ "&AG35,"⬜ "&AG35) -> ✅ % GPR | AG35: % GPR | AH35: 1 | AI35: =IF(SUM('UW Model'!N108:Q110)>0,1,0) -> 1 | AJ35: =IF(AI35=AH35,1,0) -> 1
A36: =AJ36 -> 1 | F36: =IF(AJ36=1,"✅ "&AG36,"⬜ "&AG36) -> ✅ Expense Growth | AG36: Expense Growth | AH36: 1 | AI36: =IF(SUM('UW Model'!N113:Q113)>0,1,0) -> 1 | AJ36: =IF(AI36=AH36,1,0) -> 1
A37: =AJ37 -> 1 | F37: =IF(AJ37=1,"✅ "&AG37,"⬜ "&AG37) -> ✅ Tax Growth | AG37: Tax Growth | AH37: 1 | AI37: =IF(SUM('UW Model'!N114:Q114)>0,1,0) -> 1 | AJ37: =IF(AI37=AH37,1,0) -> 1

Sheet UW Model
E2: Offer Price | G2: Price / Unit | I2: Cap (at purchase) | K2: Total Units | M2: Interior Renovation Strategy | O2: CoC (LP) | Q2: AAR (LP) | S2: IRR (LP) | U2: EMx (LP)
E3: =IFERROR(G12,"") -> 0 | G3: =IFERROR(G12/H43,0) -> 0 | I3: =IFERROR(J94/G12,0) -> 0 | K3: =IFERROR(H43,"") -> 0 | M3: =TEXT(O43,"#,##")& " units • "&TEXT(P43/1000,"$0.0")&"k/unit • " &TEXT(S43,"0%")&" ROI" -> units • $0.0k/unit • 0% ROI | O3: =IFERROR(I196,0) -> 0 | Q3: =IFERROR(I204,0) -> 0 | S3: =IFERROR(I207,0) -> 0 | U3: =IFERROR(I208,0) -> 0
C5: DEAL ASSUMPTIONS | V5: Video Tutorial ▶️
C6: 1. PROPERTY INFORMATION | H6: 4. DEBT STRUCTURE | L6: 5. DEAL STRUCTURE | P6: KPIs | T6: UNDERWRITING NOTES
C7: Name | H7: Acquisition Loan Amount | K7: =K8*G12 -> 0 | L7: Preferred Return | O7: 0.08 | P7: LP CoC | R7: 0.07 | S7: =IFERROR(ROUND(I196,3),0) -> 0 | T7: Use this section to document all UW assumptions, findings, anomalies, & conclusions
C8: Address | H8: Loan to Value (LTV) | J8: =IFERROR(IF(_xlfn.ISFORMULA(K7)=TRUE,"",K7/G12),"") | K8: 0 | L8: Partner Split | N8: =1-O8 -> 0.7 | O8: 0.3 | P8: LP IRR | R8: 0.15 | S8: =ROUND(S3,3) -> 0
C9: Year Built | F9: Occupancy | G9: 1 | H9: Interest Rate | K9: 0 | L9: Acquisition Fee | N9: =J215 -> 0 | O9: 0.02 | P9: LP Equity Multiple (EMx) | R9: 1.65 | S9: =IFERROR(I208,0) -> 0
C10: 2. PURCHASE ASSUMPTIONS | H10: Loan Fee | J10: =K10*K7 -> 0 | K10: 0 | L10: Asset Mgt Fee | N10: =I216 -> 0 | O10: 0.02 | P10: Min DSCR | R10: 1.25 | S10: =IFERROR(MIN(K143:V143),0) -> 0
C11: Whisper Price | F11: =IFERROR(TEXT(G11/$A$43,"#")&" /SF" & " · "&TEXT(G11/$H$43/1000,"#,##")&"k /unit","") | H11: I/O Period | K11: 0 | L11: Refinance Fee | N11: =I217 -> 0 | O11: 0 | P11: Negative Cash Flow | S11: =IF(MIN(K142:V142)<0,"CHECK","OK") -> OK
C12: Offer Price | F12: =IFERROR(TEXT(G12/$A$43,"#")&" /SF" & " · "&TEXT(G12/$H$43/1000,"#,##")&"k /unit","") | H12: Amortization | K12: 30 | L12: Disposition Fee | N12: =IFERROR(I218,0) -> 0 | O12: 0 | P12: All Capital Returned | S12: =IF(MAX(K165:V165)=100%,"OK","CHECK") -> CHECK
C13: Acquisition Date | G13: =EDATE(NOW(),3) -> 45163 | H13: DSCR In-Place | I13: =IFERROR(J143,0) -> 0 | J13: DSCR Yr 1 | K13: =IFERROR(M143,0) -> 0 | L13: 6. RENOVATION ASSUMPTIONS | P13: SOURCES & USES
C14: Cap Rate (Market) | G14: 0.05 | H14: Refinance Loan Amount | J14: =IF(K15>1,IF(HLOOKUP(K15,C148:V159,12,0)<0,"ERROR",""),"") | K14: =IFERROR(HLOOKUP(K15,$K$77:$V$96,20,0)*K16,"0") -> 0 | L14: Interior Renovation Start Month | O14: 2 | P14: Sources | Q14: Loan | R14: =IFERROR(S14/S16,0) -> 0 | S14: =K7 -> 0
C15: Cap Rate (Yr1 Proforma) | G15: =IFERROR(M94/G12,0) -> 0 | H15: Refinance End of Year | L15: Interior Renovation End Month | O15: 12 | Q15: Equity | R15: =IFERROR(S15/S16,0) -> 0 | S15: =S23-S14 -> 0
C16: Closing Costs | F16: =G12*G16 -> 0 | G16: 0.025 | H16: Loan to Value (LTV) | J16: =IFERROR(IF(_xlfn.ISFORMULA(K14)=TRUE,"",K14/HLOOKUP(K15,$K$77:$V$96,20,0)),"") | K16: 0 | L16: Unit Renovations per Month | O16: =O43/(O15-1-O14) -> 0 | P16: TOTAL SOURCES | R16: =IFERROR(SUM(R14:R15),0) -> 0 | S16: =SUM(S14:S15) -> 0
C17: Operating Reserves | F17: =IFERROR(G17/('UW Model'!$M$88/12),0) -> 0 | G17: =IF(V6="ON",V17*V8*0.5,M88*0.5) -> 0 | H17: Interest Rate | K17: 0.06 | L17: Interior Renovation Completions per Year:
C18: Lender CapEx Reserves | G18: 250 | H18: Refinance Fee | J18: =K14*K18 -> 0 | K18: 0.015 | L18: ='GPR Logic'!R5 -> 0 | M18: ='GPR Logic'!S5-'GPR Logic'!R5 -> 0 | N18: ='GPR Logic'!T5-'GPR Logic'!S5 -> 0 | O18: =SUM(L18:N18) -> 0 | P18: Uses | Q18: Acquisition | R18: =IFERROR(S18/$S$23,0) -> 0 | S18: =G12 -> 0
A19: Sale Price | C19: 3. EXIT ASSUMPTIONS | H19: I/O Period | K19: 0 | L19: Renovation Costs | N19: /SF · /unit | O19: Total | Q19: All Closing Costs | R19: =IFERROR(S19/$S$23,0) -> 0 | S19: =J10+F16 -> 0
A20: =IFERROR(VLOOKUP("Property Value",$G$77:$V$100,MATCH(G20,$G$77:$V$77,0),0),0) -> 0 | B20: =IF('IRR Sensitivity'!C3="",G23,'IRR Sensitivity'!C3) -> 0.0575 | C20: Sale Year | F20: =IFERROR(TEXT(A20/A43,"#"),0)&" /SF · "&IFERROR(TEXT(ROUND((A20/H43)/1000,0),"#,##"),0) &"k /unit · "&IFERROR(TEXT(ROUND(A20/1000000,1),"0.0"),0)&"M" -> 0 /SF · 0k /unit · 0.0M | G20: 5 | H20: Amortization | K20: 30 | L20: Interior Reno Cost | N20: =IFERROR(TEXT(Q43/SUMIF(O28:O42,">0",A28:A42),"0.00") &" · " & TEXT(IFERROR(P43,0),"0,##"),"") | O20: =Q43 -> 0 | Q20: Renovation Costs | R20: =IFERROR(S20/$S$23,0) -> 0 | S20: =O23 -> 0
C21: Sale Costs | F21: =IFERROR(HLOOKUP(MATCH(G20,$M$148:$V$148,0),$M$148:$V$155,8,0),0) -> 0 | G21: 0.03 | H21: Cap Rate at Refinance | K21: =IFERROR(HLOOKUP(K15,$K$77:$V$96,MATCH("Market CAP Rate",$G$77:$G$96,0),0),0) -> 0 | L21: Exterior Reno Cost | N21: =IFERROR(TEXT(O21/SUMIF(H28:H42,">0",A28:A42),"0.00") &" · " &TEXT(IFERROR(O21/H43,0),"0,##"),"") | O21: 0 | Q21: Operating Reserves | R21: =IFERROR(S21/$S$23,0) -> 0 | S21: =G17 -> 0
C22: Reserves Returned at Sale | F22: =G22*G17 -> 0 | G22: 0.5 | H22: Value at Refinance | K22: =IFERROR(HLOOKUP(K15,$K$77:$V$96,MATCH("Property Value",$G$77:$G$96,0),0),0) -> 0 | L22: Contingency | M22: 0 | N22: =IFERROR(TEXT(O22/SUMIF(H28:H42,">0",A28:A42),"0.00") &" · " &TEXT(IFERROR(O22/H43,0),"0,##"),"") | O22: =M22*(O21+O20) -> 0 | Q22: Acquisition Fee | R22: =IFERROR(S22/$S$23,0) -> 0 | S22: =G12*O9 -> 0
C23: Sale / Exit Cap Rate | F23: 0.0015 | G23: =(F23*G20)+G14 -> 0.0575 | H23: ="DSCR Yr "&IF(OR(K15=0,K15="")," - ",K15+1) -> DSCR Yr - | I23: =IFERROR(HLOOKUP(K15+1,$N$123:$V$143,MATCH("DSCR",$G$123:$G$143,0),0),0) -> 0 | K23: ="Return of Capital "&TEXT(HLOOKUP(K15,C148:V165,MATCH("% of Capital Returned",$C$148:$C$165,0),0),"0.0%") -> Return of Capital 0.0% | L23: TOTAL RENO | N23: =IFERROR(TEXT(O23/SUMIF(H28:H42,">0",A28:A42),"0.00") &" · " &TEXT(IFERROR(O23/H43,0),"0,##"),"") | O23: =SUM(O20:O22) -> 0 | P23: TOTAL USES | R23: =IFERROR(SUM(R18:R22),0) -> 0 | S23: =SUM(S18:S22) -> 0
C25: UNIT MIX, RENT, & INTERIOR RENOVATION STRATEGY | V25: Video Tutorial ▶️
C26: UNIT TYPE INFORMATION | I26: IN PLACE RENTS | L26: CURRENT MARKET RENTS | O26: RENOVATION PLAN | T26: POST-RENOVATION RENTS
A27: NRA SF | C27: Unit Type | D27: Reno? | E27: Beds | F27: Baths | G27: Avg. SF | H27: # of Units | I27: /Unit/Mo | J27: /SF/Mo | K27: Total/Mo | L27: /Unit/Mo | M27: /SF/Mo | N27: Total/Mo | O27: Units to Renovate | P27: Cost /unit | Q27: Total Reno Cost | R27: Rent Premium /unit | S27: 1 Year ROI | T27: /Unit/Mo | U27: /SF/Mo | V27: Total/Mo
A28: =IF(G28="","",G28*H28) | C28: =IF(H28>0,E28&"/"&F28&" "&TEXT(G28,"#,##")&"sf"&IF(D28="Y"," - R",""),"") | J28: =IFERROR(IF(I28="","",I28/$G28),"") | K28: =IF(I28="","",I28*$H28) | M28: =IFERROR(IF(L28="","",L28/$G28),"") | N28: =IF(L28="","",L28*$H28) | Q28: =IF(O28<1,"",O28*P28) | S28: =IFERROR(IF(O28>0,(R28*12)/P28,""),0) | T28: =IF(H28>0,V28/H28,"") | U28: =IFERROR(IF(T28="","",T28/$G28),0) | V28: =IF(O28="",N28,(L28*(H28-O28)+(O28*(L28+R28))))
A29: =IF(G29="","",G29*H29) | C29: =IF(H29>0,E29&"/"&F29&" "&TEXT(G29,"#,##")&"sf"&IF(D29="Y"," - R",""),"") | J29: =IFERROR(IF(I29="","",I29/$G29),"") | K29: =IF(I29="","",I29*$H29) | M29: =IFERROR(IF(L29="","",L29/$G29),"") | N29: =IF(L29="","",L29*$H29) | Q29: =IF(O29<1,"",O29*P29) | S29: =IFERROR(IF(O29>0,(R29*12)/P29,""),0) | T29: =IF(H29>0,V29/H29,"") | U29: =IFERROR(IF(T29="","",T29/$G29),0) | V29: =IF(O29="",N29,(L29*(H29-O29)+(O29*(L29+R29))))
A30: =IF(G30="","",G30*H30) | C30: =IF(H30>0,E30&"/"&F30&" "&TEXT(G30,"#,##")&"sf"&IF(D30="Y"," - R",""),"") | J30: =IFERROR(IF(I30="","",I30/$G30),"") | K30: =IF(I30="","",I30*$H30) | M30: =IFERROR(IF(L30="","",L30/$G30),"") | N30: =IF(L30="","",L30*$H30) | Q30: =IF(O30<1,"",O30*P30) | S30: =IFERROR(IF(O30>0,(R30*12)/P30,""),0) | T30: =IF(H30>0,V30/H30,"") | U30: =IFERROR(IF(T30="","",T30/$G30),0) | V30: =IF(O30="",N30,(L30*(H30-O30)+(O30*(L30+R30))))
A31: =IF(G31="","",G31*H31) | C31: =IF(H31>0,E31&"/"&F31&" "&TEXT(G31,"#,##")&"sf"&IF(D31="Y"," - R",""),"") | J31: =IFERROR(IF(I31="","",I31/$G31),"") | K31: =IF(I31="","",I31*$H31) | M31: =IFERROR(IF(L31="","",L31/$G31),"") | N31: =IF(L31="","",L31*$H31) | Q31: =IF(O31<1,"",O31*P31) | S31: =IFERROR(IF(O31>0,(R31*12)/P31,""),0) | T31: =IF(H31>0,V31/H31,"") | U31: =IFERROR(IF(T31="","",T31/$G31),0) | V31: =IF(O31="",N31,(L31*(H31-O31)+(O31*(L31+R31))))
A32: =IF(G32="","",G32*H32) | C32: =IF(H32>0,E32&"/"&F32&" "&TEXT(G32,"#,##")&"sf"&IF(D32="Y"," - R",""),"") | J32: =IFERROR(IF(I32="","",I32/$G32),"") | K32: =IF(I32="","",I32*$H32) | M32: =IFERROR(IF(L32="","",L32/$G32),"") | N32: =IF(L32="","",L32*$H32) | Q32: =IF(O32<1,"",O32*P32) | S32: =IFERROR(IF(O32>0,(R32*12)/P32,""),0) | T32: =IF(H32>0,V32/H32,"") | U32: =IFERROR(IF(T32="","",T32/$G32),0) | V32: =IF(O32="",N32,(L32*(H32-O32)+(O32*(L32+R32))))
A33: =IF(G33="","",G33*H33) | C33: =IF(H33>0,E33&"/"&F33&" "&TEXT(G33,"#,##")&"sf"&IF(D33="Y"," - R",""),"") | J33: =IFERROR(IF(I33="","",I33/$G33),"") | K33: =IF(I33="","",I33*$H33) | M33: =IFERROR(IF(L33="","",L33/$G33),"") | N33: =IF(L33="","",L33*$H33) | Q33: =IF(O33<1,"",O33*P33) | S33: =IFERROR(IF(O33>0,(R33*12)/P33,""),0) | T33: =IF(H33>0,V33/H33,"") | U33: =IFERROR(IF(T33="","",T33/$G33),0) | V33: =IF(O33="",N33,(L33*(H33-O33)+(O33*(L33+R33))))
A34: =IF(G34="","",G34*H34) | C34: =IF(H34>0,E34&"/"&F34&" "&TEXT(G34,"#,##")&"sf"&IF(D34="Y"," - R",""),"") | J34: =IFERROR(IF(I34="","",I34/$G34),"") | K34: =IF(I34="","",I34*$H34) | M34: =IFERROR(IF(L34="","",L34/$G34),"") | N34: =IF(L34="","",L34*$H34) | Q34: =IF(O34<1,"",O34*P34) | S34: =IFERROR(IF(O34>0,(R34*12)/P34,""),0) | T34: =IF(H34>0,V34/H34,"") | U34: =IFERROR(IF(T34="","",T34/$G34),0) | V34: =IF(O34="",N34,(L34*(H34-O34)+(O34*(L34+R34))))
A35: =IF(G35="","",G35*H35) | C35: =IF(H35>0,E35&"/"&F35&" "&TEXT(G35,"#,##")&"sf"&IF(D35="Y"," - R",""),"") | J35: =IFERROR(IF(I35="","",I35/$G35),"") | K35: =IF(I35="","",I35*$H35) | M35: =IFERROR(IF(L35="","",L35/$G35),"") | N35: =IF(L35="","",L35*$H35) | Q35: =IF(O35<1,"",O35*P35) | S35: =IFERROR(IF(O35>0,(R35*12)/P35,""),0) | T35: =IF(H35>0,V35/H35,"") | U35: =IFERROR(IF(T35="","",T35/$G35),0) | V35: =IF(O35="",N35,(L35*(H35-O35)+(O35*(L35+R35))))
A36: =IF(G36="","",G36*H36) | C36: =IF(H36>0,E36&"/"&F36&" "&TEXT(G36,"#,##")&"sf"&IF(D36="Y"," - R",""),"") | J36: =IFERROR(IF(I36="","",I36/$G36),"") | K36: =IF(I36="","",I36*$H36) | M36: =IFERROR(IF(L36="","",L36/$G36),"") | N36: =IF(L36="","",L36*$H36) | Q36: =IF(O36<1,"",O36*P36) | S36: =IFERROR(IF(O36>0,(R36*12)/P36,""),0) | T36: =IF(H36>0,V36/H36,"") | U36: =IFERROR(IF(T36="","",T36/$G36),0) | V36: =IF(O36="",N36,(L36*(H36-O36)+(O36*(L36+R36))))
A37: =IF(G37="","",G37*H37) | C37: =IF(H37>0,E37&"/"&F37&" "&TEXT(G37,"#,##")&"sf"&IF(D37="Y"," - R",""),"") | J37: =IFERROR(IF(I37="","",I37/$G37),"") | K37: =IF(I37="","",I37*$H37) | M37: =IFERROR(IF(L37="","",L37/$G37),"") | N37: =IF(L37="","",L37*$H37) | Q37: =IF(O37<1,"",O37*P37) | S37: =IFERROR(IF(O37>0,(R37*12)/P37,""),0) | T37: =IF(H37>0,V37/H37,"") | U37: =IFERROR(IF(T37="","",T37/$G37),0) | V37: =IF(O37="",N37,(L37*(H37-O37)+(O37*(L37+R37))))
A38: =IF(G38="","",G38*H38) | C38: =IF(H38>0,E38&"/"&F38&" "&TEXT(G38,"#,##")&"sf"&IF(D38="Y"," - R",""),"") | J38: =IFERROR(IF(I38="","",I38/$G38),"") | K38: =IF(I38="","",I38*$H38) | M38: =IFERROR(IF(L38="","",L38/$G38),"") | N38: =IF(L38="","",L38*$H38) | Q38: =IF(O38<1,"",O38*P38) | S38: =IFERROR(IF(O38>0,(R38*12)/P38,""),0) | T38: =IF(H38>0,V38/H38,"") | U38: =IFERROR(IF(T38="","",T38/$G38),0) | V38: =IF(O38="",N38,(L38*(H38-O38)+(O38*(L38+R38))))
A39: =IF(G39="","",G39*H39) | C39: =IF(H39>0,E39&"/"&F39&" "&TEXT(G39,"#,##")&"sf"&IF(D39="Y"," - R",""),"") | J39: =IFERROR(IF(I39="","",I39/$G39),"") | K39: =IF(I39="","",I39*$H39) | M39: =IFERROR(IF(L39="","",L39/$G39),"") | N39: =IF(L39="","",L39*$H39) | Q39: =IF(O39<1,"",O39*P39) | S39: =IFERROR(IF(O39>0,(R39*12)/P39,""),0) | T39: =IF(H39>0,V39/H39,"") | U39: =IFERROR(IF(T39="","",T39/$G39),0) | V39: =IF(O39="",N39,(L39*(H39-O39)+(O39*(L39+R39))))
... A42: =IF(G42="","",G42*H42) | C42: =IF(H42>0,E42&"/"&F42&" "&TEXT(G42,"#,##")&"sf"&IF(D42="Y"," - R",""),"") | J42: =IFERROR(IF(I42="","",I42/$G42),"") | K42: =IF(I42="","",I42*$H42) | M42: =IFERROR(IF(L42="","",L42/$G42),"") | N42: =IF(L42="","",L42*$H42) | Q42: =IF(O42<1,"",O42*P42) | S42: =IFERROR(IF(O42>0,(R42*12)/P42,""),0) | T42: =IF(H42>0,V42/H42,"") | U42: =IFERROR(IF(T42="","",T42/$G42),0) | V42: =IF(O42="",N42,(L42*(H42-O42)+(O42*(L42+R42))))
A43: =IF(V6="ON",V10,SUM(A28:A42)) -> 0 | C43: Average / Total | G43: =IFERROR(IF($V$6="ON",V9,A43/H43),0) -> 0 | H43: =IF(V6="ON",V8,SUM(H28:H42)) -> 0 | I43: =IFERROR(K43/H43,0) -> 0 | J43: =IFERROR(K43/$A43,0) -> 0 | K43: =IF(S6="ON",S7*S12,SUM(K28:K42)) -> 0 | L43: =IFERROR(IF(V8="ON",V13,N43/$H43),0) -> 0 | M43: =IFERROR(N43/$A43,0) -> 0 | N43: =IF(V6="ON",V8*V13,SUM(N28:N42)) -> 0 | O43: =IF(V6="ON",V20,SUM(O28:O42)) -> 0 | P43: =IFERROR(IF(V6="ON",V22,Q43/O43),0) -> 0 | Q43: =IF(V6="ON",V20*V22,SUM(Q28:Q42)) -> 0 | R43: =IFERROR(IF(V6="ON",V21,SUMPRODUCT(O28:O42,R28:R42)/O43),0) -> 0 | S43: =IFERROR((R43*12)/P43,0) -> 0 | T43: =IFERROR(IF(V6="ON",((V20*(V13+V21))+((V8-V20)*V13))/V8,V43/$H43),0) -> 0 | U43: =IFERROR(T43/$G43,0) -> 0 | V43: =IF(V6="ON",T43*H43,SUM(V28:V42)) -> 0
J44: Annual GPR | K44: =K43*12 -> 0 | L44: =(N43-K43)*12 -> 0 | M44: Annual GPR | N44: =N43*12 -> 0 | R44: =IFERROR(TEXT(R43,"$#,##")&" / "&TEXT(R43/(SUMPRODUCT(O28:O42,L28:L42)/O43),"0%"),0) -> 0 | T44: =IFERROR(TEXT(T43-L43,"$#,##")& " / " & TEXT(T43/L43-1,"0%"),0) -> 0 | U44: Annual GPR | V44: =V43*12 -> 0
C46: INCOME | V46: Video Tutorial ▶️
B47: =MID(ADDRESS(1,MATCH(J47,#REF!,0)),2,SEARCH("$",ADDRESS(1,MATCH(J47,#REF!,0)),2)-2)&"6:"&MID(ADDRESS(1,MATCH(J47,#REF!,0)),2,SEARCH("$",ADDRESS(1,MATCH(J47,#REF!,0)),2)-2)&"300" -> #REF! | H47: % GPR | I47: $/Unit | J47: T-3 | K47: % GPR | L47: $/Unit | M47: 1 | N47: =M47+1 -> 2 | O47: =N47+1 -> 3 | P47: =O47+1 -> 4 | Q47: =P47+1 -> 5 | R47: =Q47+1 -> 6 | S47: =R47+1 -> 7 | T47: =S47+1 -> 8 | U47: =T47+1 -> 9 | V47: =U47+1 -> 10
C48: Gross Potential Rent (GPR) | H48: =IFERROR(J48/J48,0) -> 0 | I48: =IFERROR(J48/$H$43,0) -> 0 | J48: 0 | K48: =IFERROR(M48/M48,0) -> 0 | L48: =IFERROR(M48/H43,0) -> 0 | M48: =IFERROR(IF($V$6="ON",'GPR Logic'!R150,M53*H43*12),0) -> 0 | N48: =IFERROR( IF($V$6="ON",'GPR Logic'!S150, IF(SUM($M$54:N54)>0, IF(N54>0,N54*$H$43*12,M48*(1+N104)), N53*$H$43*12)),0) -> 0 | O48: =IFERROR( IF($V$6="ON",'GPR Logic'!T150, IF(SUM($M$54:O54)>0, IF(O54>0,O54*$H$43*12,N48*(1+O104)), O53*$H$43*12)),0) -> 0 | P48: =IFERROR( IF($V$6="ON",'GPR Logic'!U150, IF(SUM($M$54:P54)>0, IF(P54>0,P54*$H$43*12,O48*(1+P104)), P53*$H$43*12)),0) -> 0 | Q48: =IFERROR( IF($V$6="ON",'GPR Logic'!V150, IF(SUM($M$54:Q54)>0, IF(Q54>0,Q54*$H$43*12,P48*(1+Q104)), Q53*$H$43*12)),0) -> 0 | R48: =IFERROR( IF($V$6="ON",Q48*(1+R104), IF(SUM($M$54:R54)>0, IF(R54>0,R54*$H$43*12,Q48*(1+R104)), R53*$H$43*12)),0) -> 0 | S48: =IFERROR( IF($V$6="ON",R48*(1+S104), IF(SUM($M$54:S54)>0, IF(S54>0,S54*$H$43*12,R48*(1+S104)), S53*$H$43*12)),0) -> 0 | T48: =IFERROR( IF($V$6="ON",S48*(1+T104), IF(SUM($M$54:T54)>0, IF(T54>0,T54*$H$43*12,S48*(1+T104)), T53*$H$43*12)),0) -> 0 | U48: =IFERROR( IF($V$6="ON",T48*(1+U104), IF(SUM($M$54:U54)>0, IF(U54>0,U54*$H$43*12,T48*(1+U104)), U53*$H$43*12)),0) -> 0 | V48: =IFERROR( IF($V$6="ON",U48*(1+V104), IF(SUM($M$54:V54)>0, IF(V54>0,V54*$H$43*12,U48*(1+V104)), V53*$H$43*12)),0) -> 0
G49: Renovated Units | M49: ='GPR Logic'!R5 -> 0 | N49: ='GPR Logic'!S5 -> 0 | O49: ='GPR Logic'!T5 -> 0 | P49: =IFERROR(O49,0) -> 0 | Q49: =IFERROR(P49,0) -> 0 | R49: =IFERROR(Q49,0) -> 0 | S49: =IFERROR(R49,0) -> 0 | T49: =IFERROR(S49,0) -> 0 | U49: =IFERROR(T49,0) -> 0 | V49: =IFERROR(U49,0) -> 0
G50: Unrenovated Units | M50: ='GPR Logic'!R85 -> 0 | N50: ='GPR Logic'!S85 -> 0 | O50: ='GPR Logic'!T85 -> 0 | P50: =IFERROR(ROUND($H$43-P49,0),0) -> 0 | Q50: =IFERROR(ROUND($H$43-Q49,0),0) -> 0 | R50: =IFERROR(ROUND($H$43-R49,0),0) -> 0 | S50: =IFERROR(ROUND($H$43-S49,0),0) -> 0 | T50: =IFERROR(ROUND($H$43-T49,0),0) -> 0 | U50: =IFERROR(ROUND($H$43-U49,0),0) -> 0 | V50: =IFERROR(ROUND($H$43-V49,0),0) -> 0
G51: Renovated Rent | L51: ='GPR Logic'!R37 -> 0 | M51: ='GPR Logic'!R133 -> 0 | N51: ='GPR Logic'!S37 -> 0 | O51: ='GPR Logic'!T37 -> 0 | P51: =IFERROR(O51*(1+P$104),0) -> 0 | Q51: =IFERROR(P51*(1+Q$104),0) -> 0 | R51: =IFERROR(Q51*(1+R$104),0) -> 0 | S51: =IFERROR(R51*(1+S$104),0) -> 0 | T51: =IFERROR(S51*(1+T$104),0) -> 0 | U51: =IFERROR(T51*(1+U$104),0) -> 0 | V51: =IFERROR(U51*(1+V$104),0) -> 0
G52: Unrenovated Rent | L52: ='GPR Logic'!R117 -> 0 | M52: ='GPR Logic'!R134 -> 0 | N52: ='GPR Logic'!S117 -> 0 | O52: ='GPR Logic'!T117 -> 0 | P52: =IFERROR(O52*(1+P$104),0) -> 0 | Q52: =IFERROR(P52*(1+Q$104),0) -> 0 | R52: =IFERROR(Q52*(1+R$104),0) -> 0 | S52: =IFERROR(R52*(1+S$104),0) -> 0 | T52: =IFERROR(S52*(1+T$104),0) -> 0 | U52: =IFERROR(T52*(1+U$104),0) -> 0 | V52: =IFERROR(U52*(1+V$104),0) -> 0
G53: GPR/Unit/Mo | I53: =IFERROR(J48/H43/12,0) -> 0 | M53: =IFERROR(IF($V$6="ON",M48/$V$8/12,IF(M54>0,M54,'GPR Logic'!R136)),0) -> 0 | N53: =IFERROR(IF($V$6="ON",N48/$V$8/12,IF(SUM($M$54:N54)>0,N48/$H$43/12,'GPR Logic'!S136)),0) -> 0 | O53: =IFERROR(IF($V$6="ON",O48/$V$8/12,IF(SUM($M$54:O54)>0,O48/$H$43/12,'GPR Logic'!T136)),0) -> 0 | P53: =IFERROR(IF($V$6="ON",P48/$V$8/12,IF(SUM($M$54:P54)>0,P48/$H$43/12,'GPR Logic'!U136)),0) -> 0 | Q53: =IFERROR(IF(SUM($M$54:Q54)>0,Q48/$H$43/12,P53*(1+Q104)),0) -> 0 | R53: =IFERROR(IF(SUM($M$54:R54)>0,R48/$H$43/12,Q53*(1+R104)),0) -> 0 | S53: =IFERROR(IF(SUM($M$54:S54)>0,S48/$H$43/12,R53*(1+S104)),0) -> 0 | T53: =IFERROR(IF(SUM($M$54:T54)>0,T48/$H$43/12,S53*(1+T104)),0) -> 0 | U53: =IFERROR(IF(SUM($M$54:U54)>0,U48/$H$43/12,T53*(1+U104)),0) -> 0 | V53: =IFERROR(IF(SUM($M$54:V54)>0,V48/$H$43/12,U53*(1+V104)),0) -> 0
G54: GPR/Unit/Mo OVERRIDE
G55: YoY GPR Growth | M55: =IFERROR(M53/I53-1,0) -> 0 | N55: =IFERROR(N53/M53-1,0) -> 0 | O55: =IFERROR(O53/N53-1,0) -> 0 | P55: =IFERROR(P53/O53-1,0) -> 0 | Q55: =IFERROR(Q53/P53-1,0) -> 0 | R55: =IFERROR(R53/Q53-1,0) -> 0 | S55: =IFERROR(S53/R53-1,0) -> 0 | T55: =IFERROR(T53/S53-1,0) -> 0 | U55: =IFERROR(U53/T53-1,0) -> 0 | V55: =IFERROR(V53/U53-1,0) -> 0
C56: - Downtime Vacancy (renovation) | K56: =IFERROR(-M56/$M$48,0) -> 0 | L56: =IFERROR(M56/$H$43,0) -> 0 | M56: =IF(SUM($M$54:M54)>0,0,-'GPR Logic'!R53) -> 0 | N56: =IF(SUM($M$54:N54)>0,0,-'GPR Logic'!S53) -> 0 | O56: =IF(SUM($M$54:O54)>0,0,-'GPR Logic'!T53) -> 0 | P56: =IF(SUM($M$54:P54)>0,0,-'GPR Logic'!U53) -> 0 | Q56: =-(Q49-P49)*2*Q52 -> 0 | R56: =-(R49-Q49)*2*R52 -> 0 | S56: =-(S49-R49)*2*S52 -> 0 | T56: =-(T49-S49)*2*T52 -> 0 | U56: =-(U49-T49)*2*U52 -> 0 | V56: =-(V49-U49)*2*V52 -> 0
C57: - General Vacancy | D57: (% of GPR + RUBS + Other Inc) | H57: =IFERROR(-J57/$J$48,0) -> 0 | I57: =IFERROR(J57/$H$43,0) -> 0 | J57: 0 | K57: 0 | L57: =IFERROR(M57/$H$43,0) -> 0 | M57: =-($M$48+M64+M65)*K57 -> 0 | N57: =-(N$48+N64+N65)*N107 -> 0 | O57: =-(O$48+O64+O65)*O107 -> 0 | P57: =-(P$48+P64+P65)*P107 -> 0 | Q57: =-(Q$48+Q64+Q65)*Q107 -> 0 | R57: =-(R$48+R64+R65)*R107 -> 0 | S57: =-(S$48+S64+S65)*S107 -> 0 | T57: =-(T$48+T64+T65)*T107 -> 0 | U57: =-(U$48+U64+U65)*U107 -> 0 | V57: =-(V$48+V64+V65)*V107 -> 0
C58: - Concessions | H58: =IFERROR(-J58/$J$48,0) -> 0 | I58: =IFERROR(J58/$H$43,0) -> 0 | J58: 0 | K58: 0 | L58: =IFERROR(M58/$H$43,0) -> 0 | M58: =-$M$48*K58 -> 0 | N58: =-N$48*N108 -> 0 | O58: =-O$48*O108 -> 0 | P58: =-P$48*P108 -> 0 | Q58: =-Q$48*Q108 -> 0 | R58: =-R$48*R108 -> 0 | S58: =-S$48*S108 -> 0 | T58: =-T$48*T108 -> 0 | U58: =-U$48*U108 -> 0 | V58: =-V$48*V108 -> 0
C59: - Bad Debt | H59: =IFERROR(-J59/$J$48,0) -> 0 | I59: =IFERROR(J59/$H$43,0) -> 0 | J59: 0 | K59: 0 | L59: =IFERROR(M59/$H$43,0) -> 0 | M59: =-$M$48*K59 -> 0 | N59: =-N$48*N109 -> 0 | O59: =-O$48*O109 -> 0 | P59: =-P$48*P109 -> 0 | Q59: =-Q$48*Q109 -> 0 | R59: =-R$48*R109 -> 0 | S59: =-S$48*S109 -> 0 | T59: =-T$48*T109 -> 0 | U59: =-U$48*U109 -> 0 | V59: =-V$48*V109 -> 0
C60: - Loss-to-Lease | H60: =IFERROR(-J60/$J$48,0) -> 0 | I60: =IFERROR(J60/$H$43,0) -> 0 | J60: 0 | K60: 0 | L60: =IFERROR(M60/$H$43,0) -> 0 | M60: =-$M$48*K60 -> 0 | N60: =-N$48*N110 -> 0 | O60: =-O$48*O110 -> 0 | P60: =-P$48*P110 -> 0 | Q60: =-Q$48*Q110 -> 0 | R60: =-R$48*R110 -> 0 | S60: =-S$48*S110 -> 0 | T60: =-T$48*T110 -> 0 | U60: =-U$48*U110 -> 0 | V60: =-V$48*V110 -> 0
C61: Total Rental Revenue | H61: =IFERROR(H48-SUM(H56:H60),0) -> 0 | I61: =IFERROR(J61/$H$43,0) -> 0 | J61: =IFERROR(SUM(J56:J60,J48),0) -> 0 | K61: =IFERROR(K48-SUM(K56:K60),0) -> 0 | L61: =IFERROR(M61/$H$43,0) -> 0 | M61: =IFERROR(IF($V$6="ON",M48-(M48*(IF(M47>(ROUNDUP($O$15/12,0)),$V$15,$V$14))-(-M56/M48)),SUM(M56:M60,M48)),0) -> 0 | N61: =IFERROR(IF($V$6="ON",N48-(N48*(IF(N47>(ROUNDUP($O$15/12,0)),$V$15,$V$14))-(-N56/N48)),SUM(N56:N60,N48)),0) -> 0 | O61: =IFERROR(IF($V$6="ON",O48-(O48*(IF(O47>(ROUNDUP($O$15/12,0)),$V$15,$V$14))-(-O56/O48)),SUM(O56:O60,O48)),0) -> 0 | P61: =IFERROR(IF($V$6="ON",P48-(P48*(IF(P47>(ROUNDUP($O$15/12,0)),$V$15,$V$14))-(-P56/P48)),SUM(P56:P60,P48)),0) -> 0 | Q61: =IFERROR(IF($V$6="ON",Q48-(Q48*(IF(Q47>(ROUNDUP($O$15/12,0)),$V$15,$V$14))-(-Q56/Q48)),SUM(Q56:Q60,Q48)),0) -> 0 | R61: =IFERROR(IF($V$6="ON",R48-(R48*(IF(R47>(ROUNDUP($O$15/12,0)),$V$15,$V$14))-(-R56/R48)),SUM(R56:R60,R48)),0) -> 0 | S61: =IFERROR(IF($V$6="ON",S48-(S48*(IF(S47>(ROUNDUP($O$15/12,0)),$V$15,$V$14))-(-S56/S48)),SUM(S56:S60,S48)),0) -> 0 | T61: =IFERROR(IF($V$6="ON",T48-(T48*(IF(T47>(ROUNDUP($O$15/12,0)),$V$15,$V$14))-(-T56/T48)),SUM(T56:T60,T48)),0) -> 0 | ... V61: =IFERROR(IF($V$6="ON",V48-(V48*(IF(V47>(ROUNDUP($O$15/12,0)),$V$15,$V$14))-(-V56/V48)),SUM(V56:V60,V48)),0) -> 0
G62: /Unit/Mo | I62: =IFERROR(J61/$H$43/12,0) -> 0 | L62: =IFERROR(M61/$H$43/12,0) -> 0 | N62: =IFERROR(N61/$H$43/12,0) -> 0 | O62: =IFERROR(O61/$H$43/12,0) -> 0 | P62: =IFERROR(P61/$H$43/12,0) -> 0 | Q62: =IFERROR(Q61/$H$43/12,0) -> 0 | R62: =IFERROR(R61/$H$43/12,0) -> 0 | S62: =IFERROR(S61/$H$43/12,0) -> 0 | T62: =IFERROR(T61/$H$43/12,0) -> 0 | U62: =IFERROR(U61/$H$43/12,0) -> 0 | V62: =IFERROR(V61/$H$43/12,0) -> 0
B63: =MID(ADDRESS(1,MATCH(J63,#REF!,0)),2,SEARCH("$",ADDRESS(1,MATCH(J63,#REF!,0)),2)-2)&"6:"&MID(ADDRESS(1,MATCH(J63,#REF!,0)),2,SEARCH("$",ADDRESS(1,MATCH(J63,#REF!,0)),2)-2)&"300" -> #REF! | J63: T-3
C64: Utility Reimbursement (RUBS) | H64: =IFERROR(J64/$J$48,0) -> 0 | I64: =IFERROR(J64/$H$43,0) -> 0 | J64: 0 | K64: =IFERROR(M64/$M$48,0) -> 0 | L64: =IFERROR(M64/$H$43,0) -> 0 | M64: 0 | N64: =M64*(1+N$112) -> 0 | O64: =N64*(1+O$112) -> 0 | P64: =O64*(1+P$112) -> 0 | Q64: =P64*(1+Q$112) -> 0 | R64: =Q64*(1+R$112) -> 0 | S64: =R64*(1+S$112) -> 0 | T64: =S64*(1+T$112) -> 0 | U64: =T64*(1+U$112) -> 0 | V64: =U64*(1+V$112) -> 0
C65: Other Income | H65: =IFERROR(J65/$J$48,0) -> 0 | I65: =IFERROR(J65/$H$43,0) -> 0 | J65: 0 | K65: =IFERROR(M65/$M$48,0) -> 0 | L65: =IFERROR(M65/$H$43,0) -> 0 | M65: 0 | N65: =M65*(1+N$112) -> 0 | O65: =N65*(1+O$112) -> 0 | P65: =O65*(1+P$112) -> 0 | Q65: =P65*(1+Q$112) -> 0 | R65: =Q65*(1+R$112) -> 0 | S65: =R65*(1+S$112) -> 0 | T65: =S65*(1+T$112) -> 0 | U65: =T65*(1+U$112) -> 0 | V65: =U65*(1+V$112) -> 0
C66: Total Other Income | H66: =IFERROR(J66/J48,0) -> 0 | I66: =IFERROR(J66/$H$43,0) -> 0 | J66: =SUM(J64:J65) -> 0 | K66: =IFERROR(M66/M48,0) -> 0 | L66: =IFERROR(M66/$H$43,0) -> 0 | M66: =IFERROR(IF($V$6="ON",$V$16*V8,SUM(M64:M65)),0) -> 0 | N66: =IF($V$6="ON",M66*(1+N112),SUM(N64:N65)) -> 0 | O66: =IF($V$6="ON",N66*(1+O112),SUM(O64:O65)) -> 0 | P66: =IF($V$6="ON",O66*(1+P112),SUM(P64:P65)) -> 0 | Q66: =IF($V$6="ON",P66*(1+Q112),SUM(Q64:Q65)) -> 0 | R66: =IF($V$6="ON",Q66*(1+R112),SUM(R64:R65)) -> 0 | S66: =IF($V$6="ON",R66*(1+S112),SUM(S64:S65)) -> 0 | T66: =IF($V$6="ON",S66*(1+T112),SUM(T64:T65)) -> 0 | U66: =IF($V$6="ON",T66*(1+U112),SUM(U64:U65)) -> 0 | V66: =IF($V$6="ON",U66*(1+V112),SUM(V64:V65)) -> 0
C68: Effective Gross Income (EGI) | H68: =IFERROR(J68/J48,0) -> 0 | I68: =IFERROR(J68/$H$43,0) -> 0 | J68: =J61+J66 -> 0 | K68: =IFERROR(M68/M48,0) -> 0 | L68: =IFERROR(M68/$H$43,0) -> 0 | M68: =M61+M66 -> 0 | N68: =N61+N66 -> 0 | O68: =O61+O66 -> 0 | P68: =P61+P66 -> 0 | Q68: =Q61+Q66 -> 0 | R68: =R61+R66 -> 0 | S68: =S61+S66 -> 0 | T68: =T61+T66 -> 0 | ... V68: =V61+V66 -> 0
C69: YoY Income Growth | G69: /Unit/Mo | J69: =IFERROR(J68/$H$43/12,0) -> 0 | M69: =IFERROR(M68/$H$43/12,0) -> 0 | N69: =IFERROR(N68/$H$43/12,0) -> 0 | O69: =IFERROR(O68/$H$43/12,0) -> 0 | P69: =IFERROR(P68/$H$43/12,0) -> 0 | Q69: =IFERROR(Q68/$H$43/12,0) -> 0 | R69: =IFERROR(R68/$H$43/12,0) -> 0 | S69: =IFERROR(S68/$H$43/12,0) -> 0 | T69: =IFERROR(T68/$H$43/12,0) -> 0 | ... V69: =IFERROR(V68/$H$43/12,0) -> 0
G70: /Unit | J70: =IFERROR(J68/$H$43,0) -> 0 | M70: =IFERROR(M68/$H$43,0) -> 0 | N70: =IFERROR(N68/$H$43,0) -> 0 | O70: =IFERROR(O68/$H$43,0) -> 0 | P70: =IFERROR(P68/$H$43,0) -> 0 | Q70: =IFERROR(Q68/$H$43,0) -> 0 | R70: =IFERROR(R68/$H$43,0) -> 0 | S70: =IFERROR(S68/$H$43,0) -> 0 | T70: =IFERROR(T68/$H$43,0) -> 0 | ... V70: =IFERROR(V68/$H$43,0) -> 0
G71: /SF | J71: =IFERROR(J68/$A$43,0) -> 0 | M71: =IFERROR(M68/$A$43,0) -> 0 | N71: =IFERROR(N68/$A$43,0) -> 0 | O71: =IFERROR(O68/$A$43,0) -> 0 | P71: =IFERROR(P68/$A$43,0) -> 0 | Q71: =IFERROR(Q68/$A$43,0) -> 0 | R71: =IFERROR(R68/$A$43,0) -> 0 | S71: =IFERROR(S68/$A$43,0) -> 0 | T71: =IFERROR(T68/$A$43,0) -> 0 | ... V71: =IFERROR(V68/$A$43,0) -> 0
G72: Vacancy Total | J72: =IFERROR(-SUM(J56:J57)/J48,0) -> 0 | M72: =IFERROR(-SUM(M56:M57)/M48,0) -> 0 | N72: =IFERROR(-SUM(N56:N57)/N48,0) -> 0 | O72: =IFERROR(-SUM(O56:O57)/O48,0) -> 0 | P72: =IFERROR(-SUM(P56:P57)/P48,0) -> 0 | Q72: =IFERROR(-SUM(Q56:Q57)/Q48,0) -> 0 | R72: =IFERROR(-SUM(R56:R57)/R48,0) -> 0 | S72: =IFERROR(-SUM(S56:S57)/S48,0) -> 0 | T72: =IFERROR(-SUM(T56:T57)/T48,0) -> 0 | ... V72: =IFERROR(-SUM(V56:V57)/V48,0) -> 0
G73: Total Economic Vacancy | J73: =IFERROR((J48-J61)/J48,0) -> 0 | M73: =IFERROR((M48-M61)/M48,0) -> 0 | N73: =IFERROR((N48-N61)/N48,0) -> 0 | O73: =IFERROR((O48-O61)/O48,0) -> 0 | P73: =IFERROR((P48-P61)/P48,0) -> 0 | Q73: =IFERROR((Q48-Q61)/Q48,0) -> 0 | R73: =IFERROR((R48-R61)/R48,0) -> 0 | S73: =IFERROR((S48-S61)/S48,0) -> 0 | T73: =IFERROR((T48-T61)/T48,0) -> 0 | ... V73: =IFERROR((V48-V61)/V48,0) -> 0
G74: YoY Income Growth | M74: =IFERROR(M68/J68-1,0) -> 0 | N74: =IFERROR(N68/M68-1,0) -> 0 | O74: =IFERROR(O68/N68-1,0) -> 0 | P74: =IFERROR(P68/O68-1,0) -> 0 | Q74: =IFERROR(Q68/P68-1,0) -> 0 | R74: =IFERROR(R68/Q68-1,0) -> 0 | S74: =IFERROR(S68/R68-1,0) -> 0 | T74: =IFERROR(T68/S68-1,0) -> 0 | U74: =IFERROR(U68/T68-1,0) -> 0 | V74: =IFERROR(V68/U68-1,0) -> 0
C76: EXPENSES & NOI | V76: Video Tutorial ▶️
H77: % EGI | I77: $/Unit | J77: T-12 | K77: % EGI | L77: $/Unit | M77: 1 | N77: =M77+1 -> 2 | O77: =N77+1 -> 3 | P77: =O77+1 -> 4 | Q77: =P77+1 -> 5 | R77: =Q77+1 -> 6 | S77: =R77+1 -> 7 | T77: =S77+1 -> 8 | U77: =T77+1 -> 9 | V77: =U77+1 -> 10
B78: =MID(ADDRESS(1,MATCH(J77,#REF!,0)),2,SEARCH("$",ADDRESS(1,MATCH(J77,#REF!,0)),2)-2)&"6:"&MID(ADDRESS(1,MATCH(J77,#REF!,0)),2,SEARCH("$",ADDRESS(1,MATCH(J77,#REF!,0)),2)-2)&"300" -> #REF! | C78: Payroll | H78: =IFERROR(J78/J$68,0) -> 0 | I78: =IFERROR(J78/$H$43,0) -> 0 | J78: 0 | K78: =IFERROR(M78/M$68,0) -> 0 | L78: 0 | M78: =IFERROR(L78*$H$43,0) -> 0 | N78: =IFERROR(M78*(1+N$113),0) -> 0 | O78: =IFERROR(N78*(1+O$113),0) -> 0 | P78: =IFERROR(O78*(1+P$113),0) -> 0 | Q78: =IFERROR(P78*(1+Q$113),0) -> 0 | R78: =IFERROR(Q78*(1+R$113),0) -> 0 | S78: =IFERROR(R78*(1+S$113),0) -> 0 | T78: =IFERROR(S78*(1+T$113),0) -> 0 | U78: =IFERROR(T78*(1+U$113),0) -> 0 | V78: =IFERROR(U78*(1+V$113),0) -> 0
C79: Advertising & Marketing | H79: =IFERROR(J79/J$68,0) -> 0 | I79: =IFERROR(J79/$H$43,0) -> 0 | J79: 0 | K79: =IFERROR(M79/M$68,0) -> 0 | L79: 0 | M79: =IFERROR(L79*$H$43,0) -> 0 | N79: =IFERROR(M79*(1+N$113),0) -> 0 | O79: =IFERROR(N79*(1+O$113),0) -> 0 | P79: =IFERROR(O79*(1+P$113),0) -> 0 | Q79: =IFERROR(P79*(1+Q$113),0) -> 0 | R79: =IFERROR(Q79*(1+R$113),0) -> 0 | S79: =IFERROR(R79*(1+S$113),0) -> 0 | T79: =IFERROR(S79*(1+T$113),0) -> 0 | U79: =IFERROR(T79*(1+U$113),0) -> 0 | V79: =IFERROR(U79*(1+V$113),0) -> 0
C80: General & Administrative | H80: =IFERROR(J80/J$68,0) -> 0 | I80: =IFERROR(J80/$H$43,0) -> 0 | J80: 0 | K80: =IFERROR(M80/M$68,0) -> 0 | L80: 0 | M80: =IFERROR(L80*$H$43,0) -> 0 | N80: =IFERROR(M80*(1+N$113),0) -> 0 | O80: =IFERROR(N80*(1+O$113),0) -> 0 | P80: =IFERROR(O80*(1+P$113),0) -> 0 | Q80: =IFERROR(P80*(1+Q$113),0) -> 0 | R80: =IFERROR(Q80*(1+R$113),0) -> 0 | S80: =IFERROR(R80*(1+S$113),0) -> 0 | T80: =IFERROR(S80*(1+T$113),0) -> 0 | U80: =IFERROR(T80*(1+U$113),0) -> 0 | V80: =IFERROR(U80*(1+V$113),0) -> 0
C81: Utilities | H81: =IFERROR(J81/J$68,0) -> 0 | I81: =IFERROR(J81/$H$43,0) -> 0 | J81: 0 | K81: =IFERROR(M81/M$68,0) -> 0 | L81: 0 | M81: =IFERROR(L81*$H$43,0) -> 0 | N81: =IFERROR(M81*(1+N$113),0) -> 0 | O81: =IFERROR(N81*(1+O$113),0) -> 0 | P81: =IFERROR(O81*(1+P$113),0) -> 0 | Q81: =IFERROR(P81*(1+Q$113),0) -> 0 | R81: =IFERROR(Q81*(1+R$113),0) -> 0 | S81: =IFERROR(R81*(1+S$113),0) -> 0 | T81: =IFERROR(S81*(1+T$113),0) -> 0 | U81: =IFERROR(T81*(1+U$113),0) -> 0 | V81: =IFERROR(U81*(1+V$113),0) -> 0
C82: Repairs & Maintenance | H82: =IFERROR(J82/J$68,0) -> 0 | I82: =IFERROR(J82/$H$43,0) -> 0 | J82: 0 | K82: =IFERROR(M82/M$68,0) -> 0 | L82: 0 | M82: =IFERROR(L82*$H$43,0) -> 0 | N82: =IFERROR(M82*(1+N$113),0) -> 0 | O82: =IFERROR(N82*(1+O$113),0) -> 0 | P82: =IFERROR(O82*(1+P$113),0) -> 0 | Q82: =IFERROR(P82*(1+Q$113),0) -> 0 | R82: =IFERROR(Q82*(1+R$113),0) -> 0 | S82: =IFERROR(R82*(1+S$113),0) -> 0 | T82: =IFERROR(S82*(1+T$113),0) -> 0 | U82: =IFERROR(T82*(1+U$113),0) -> 0 | V82: =IFERROR(U82*(1+V$113),0) -> 0
C83: Contract Services | H83: =IFERROR(J83/J$68,0) -> 0 | I83: =IFERROR(J83/$H$43,0) -> 0 | J83: 0 | K83: =IFERROR(M83/M$68,0) -> 0 | L83: 0 | M83: =IFERROR(L83*$H$43,0) -> 0 | N83: =IFERROR(M83*(1+N$113),0) -> 0 | O83: =IFERROR(N83*(1+O$113),0) -> 0 | P83: =IFERROR(O83*(1+P$113),0) -> 0 | Q83: =IFERROR(P83*(1+Q$113),0) -> 0 | R83: =IFERROR(Q83*(1+R$113),0) -> 0 | S83: =IFERROR(R83*(1+S$113),0) -> 0 | T83: =IFERROR(S83*(1+T$113),0) -> 0 | U83: =IFERROR(T83*(1+U$113),0) -> 0 | V83: =IFERROR(U83*(1+V$113),0) -> 0
C84: Management Fee | H84: =IFERROR(J84/J$68,0) -> 0 | I84: =IFERROR(J84/$H$43,0) -> 0 | J84: 0 | K84: 0 | L84: =IFERROR(M84/$H$43,0) -> 0 | M84: =IFERROR($K$84*M68,0) -> 0 | N84: =IFERROR($K$84*N68,0) -> 0 | O84: =IFERROR($K$84*O68,0) -> 0 | P84: =IFERROR($K$84*P68,0) -> 0 | Q84: =IFERROR($K$84*Q68,0) -> 0 | R84: =IFERROR($K$84*R68,0) -> 0 | S84: =IFERROR($K$84*S68,0) -> 0 | T84: =IFERROR($K$84*T68,0) -> 0 | ... V84: =IFERROR($K$84*V68,0) -> 0
C85: Make Ready | H85: =IFERROR(J85/J$68,0) -> 0 | I85: =IFERROR(J85/$H$43,0) -> 0 | J85: 0 | K85: =IFERROR(M85/M$68,0) -> 0 | L85: 0 | M85: =IFERROR(L85*$H$43,0) -> 0 | N85: =IFERROR(M85*(1+N$113),0) -> 0 | O85: =IFERROR(N85*(1+O$113),0) -> 0 | P85: =IFERROR(O85*(1+P$113),0) -> 0 | Q85: =IFERROR(P85*(1+Q$113),0) -> 0 | R85: =IFERROR(Q85*(1+R$113),0) -> 0 | S85: =IFERROR(R85*(1+S$113),0) -> 0 | T85: =IFERROR(S85*(1+T$113),0) -> 0 | U85: =IFERROR(T85*(1+U$113),0) -> 0 | V85: =IFERROR(U85*(1+V$113),0) -> 0
C86: Taxes | H86: =IFERROR(J86/J$68,0) -> 0 | I86: =IFERROR(J86/$H$43,0) -> 0 | J86: 0 | K86: =IFERROR(M86/M$68,0) -> 0 | L86: =IFERROR(M86/$H$43,0) -> 0 | M86: 0 | N86: =IFERROR(M86*(1+N$114),0) -> 0 | O86: =IFERROR(N86*(1+O$114),0) -> 0 | P86: =IFERROR(O86*(1+P$114),0) -> 0 | Q86: =IFERROR(P86*(1+Q$114),0) -> 0 | R86: =IFERROR(Q86*(1+R$114),0) -> 0 | S86: =IFERROR(R86*(1+S$114),0) -> 0 | T86: =IFERROR(S86*(1+T$114),0) -> 0 | U86: =IFERROR(T86*(1+U$114),0) -> 0 | V86: =IFERROR(U86*(1+V$114),0) -> 0
C87: Insurance | H87: =IFERROR(J87/J$68,0) -> 0 | I87: =IFERROR(J87/$H$43,0) -> 0 | J87: 0 | K87: =IFERROR(M87/M$68,0) -> 0 | L87: 0 | M87: =IFERROR(L87*$H$43,0) -> 0 | N87: =IFERROR(M87*(1+N$113),0) -> 0 | O87: =IFERROR(N87*(1+O$113),0) -> 0 | P87: =IFERROR(O87*(1+P$113),0) -> 0 | Q87: =IFERROR(P87*(1+Q$113),0) -> 0 | R87: =IFERROR(Q87*(1+R$113),0) -> 0 | S87: =IFERROR(R87*(1+S$113),0) -> 0 | T87: =IFERROR(S87*(1+T$113),0) -> 0 | U87: =IFERROR(T87*(1+U$113),0) -> 0 | V87: =IFERROR(U87*(1+V$113),0) -> 0
C88: Total Operating Expenses | H88: =IFERROR(J88/J$68,0) -> 0 | I88: =IFERROR(J88/$H$43,0) -> 0 | J88: =SUM(J78:J87) -> 0 | K88: =IFERROR(M88/M68,0) -> 0 | L88: =IFERROR(IF(V6="ON",V17,M88/$H$43),0) -> 0 | M88: =IF($V$6="ON",L88*V8,IF(L90>0,H43*L90,SUM(M78:M87))) -> 0 | N88: =IFERROR(IF(OR($L$90>0,$V$6="ON"),M88*(1+N113),SUM(N78:N87)),0) -> 0 | O88: =IFERROR(IF(OR($L$90>0,$V$6="ON"),N88*(1+O113),SUM(O78:O87)),0) -> 0 | P88: =IFERROR(IF(OR($L$90>0,$V$6="ON"),O88*(1+P113),SUM(P78:P87)),0) -> 0 | Q88: =IFERROR(IF(OR($L$90>0,$V$6="ON"),P88*(1+Q113),SUM(Q78:Q87)),0) -> 0 | R88: =IFERROR(IF(OR($L$90>0,$V$6="ON"),Q88*(1+R113),SUM(R78:R87)),0) -> 0 | S88: =IFERROR(IF(OR($L$90>0,$V$6="ON"),R88*(1+S113),SUM(S78:S87)),0) -> 0 | T88: =IFERROR(IF(OR($L$90>0,$V$6="ON"),S88*(1+T113),SUM(T78:T87)),0) -> 0 | U88: =IFERROR(IF(OR($L$90>0,$V$6="ON"),T88*(1+U113),SUM(U78:U87)),0) -> 0 | V88: =IFERROR(IF(OR($L$90>0,$V$6="ON"),U88*(1+V113),SUM(V78:V87)),0) -> 0
G89: Expense Ratio (% of EGI) | J89: =IFERROR(J88/J68,0) -> 0 | M89: =IFERROR(M88/M68,0) -> 0 | N89: =IFERROR(N88/N68,0) -> 0 | O89: =IFERROR(O88/O68,0) -> 0 | P89: =IFERROR(P88/P68,0) -> 0 | Q89: =IFERROR(Q88/Q68,0) -> 0 | R89: =IFERROR(R88/R68,0) -> 0 | S89: =IFERROR(S88/S68,0) -> 0 | T89: =IFERROR(T88/T68,0) -> 0 | ... V89: =IFERROR(V88/V68,0) -> 0
G90: /Unit | J90: =IFERROR(J88/$H$43,0) -> 0 | K90: OVERRIDE | L90: 0 | M90: =IFERROR(M88/$H$43,0) -> 0 | N90: =IFERROR(N88/$H$43,0) -> 0 | O90: =IFERROR(O88/$H$43,0) -> 0 | P90: =IFERROR(P88/$H$43,0) -> 0 | Q90: =IFERROR(Q88/$H$43,0) -> 0 | R90: =IFERROR(R88/$H$43,0) -> 0 | S90: =IFERROR(S88/$H$43,0) -> 0 | T90: =IFERROR(T88/$H$43,0) -> 0 | ... V90: =IFERROR(V88/$H$43,0) -> 0
G91: /SF | J91: =IFERROR(J88/$A$43,0) -> 0 | M91: =IFERROR(M88/$A$43,0) -> 0 | N91: =IFERROR(N88/$A$43,0) -> 0 | O91: =IFERROR(O88/$A$43,0) -> 0 | P91: =IFERROR(P88/$A$43,0) -> 0 | Q91: =IFERROR(Q88/$A$43,0) -> 0 | R91: =IFERROR(R88/$A$43,0) -> 0 | S91: =IFERROR(S88/$A$43,0) -> 0 | T91: =IFERROR(T88/$A$43,0) -> 0 | ... V91: =IFERROR(V88/$A$43,0) -> 0
G92: YoY Expense Growth | M92: =IFERROR(M88/J88-1,0) -> 0 | N92: =IFERROR(N88/M88-1,0) -> 0 | O92: =IFERROR(O88/N88-1,0) -> 0 | P92: =IFERROR(P88/O88-1,0) -> 0 | Q92: =IFERROR(Q88/P88-1,0) -> 0 | R92: =IFERROR(R88/Q88-1,0) -> 0 | S92: =IFERROR(S88/R88-1,0) -> 0 | T92: =IFERROR(T88/S88-1,0) -> 0 | U92: =IFERROR(U88/T88-1,0) -> 0 | V92: =IFERROR(V88/U88-1,0) -> 0
C94: Net Operating Income (NOI) | I94: =IFERROR(J94/$H$43,0) -> 0 | J94: =J68-J88 -> 0 | L94: =IFERROR(M94/$H$43,0) -> 0 | M94: =M68-M88 -> 0 | N94: =N68-N88 -> 0 | O94: =O68-O88 -> 0 | P94: =P68-P88 -> 0 | Q94: =Q68-Q88 -> 0 | R94: =R68-R88 -> 0 | S94: =S68-S88 -> 0 | T94: =T68-T88 -> 0 | ... V94: =V68-V88 -> 0
G95: Market CAP Rate | J95: =IFERROR(G14,0) -> 0.05 | M95: =IFERROR(J95+(($B$20-$G$14)/$G$20),0) -> 0.0515 | N95: =IFERROR(M95+(($B$20-$G$14)/$G$20),0) -> 0.053 | O95: =IFERROR(N95+(($B$20-$G$14)/$G$20),0) -> 0.0545 | P95: =IFERROR(O95+(($B$20-$G$14)/$G$20),0) -> 0.056 | Q95: =IFERROR(P95+(($B$20-$G$14)/$G$20),0) -> 0.0575 | R95: =IFERROR(Q95+(($B$20-$G$14)/$G$20),0) -> 0.059 | S95: =IFERROR(R95+(($B$20-$G$14)/$G$20),0) -> 0.0605 | T95: =IFERROR(S95+(($B$20-$G$14)/$G$20),0) -> 0.062 | U95: =IFERROR(T95+(($B$20-$G$14)/$G$20),0) -> 0.0635 | V95: =IFERROR(U95+(($B$20-$G$14)/$G$20),0) -> 0.065
C96: Property Value | G96: Property Value | J96: =IFERROR(J94/J95,0) -> 0 | M96: =IFERROR(M94/M95,0) -> 0 | N96: =IFERROR(N94/N95,0) -> 0 | O96: =IFERROR(O94/O95,0) -> 0 | P96: =IFERROR(P94/P95,0) -> 0 | Q96: =IFERROR(Q94/Q95,0) -> 0 | R96: =IFERROR(R94/R95,0) -> 0 | S96: =IFERROR(S94/S95,0) -> 0 | T96: =IFERROR(T94/T95,0) -> 0 | ... V96: =IFERROR(V94/V95,0) -> 0
G97: /Unit/Mo | J97: =IFERROR(J94/$H$43/12,0) -> 0 | M97: =IFERROR(M94/$H$43/12,0) -> 0 | N97: =IFERROR(N94/$H$43/12,0) -> 0 | O97: =IFERROR(O94/$H$43/12,0) -> 0 | P97: =IFERROR(P94/$H$43/12,0) -> 0 | Q97: =IFERROR(Q94/$H$43/12,0) -> 0 | R97: =IFERROR(R94/$H$43/12,0) -> 0 | S97: =IFERROR(S94/$H$43/12,0) -> 0 | T97: =IFERROR(T94/$H$43/12,0) -> 0 | ... V97: =IFERROR(V94/$H$43/12,0) -> 0
G98: /SF | J98: =IFERROR(J94/$A$43,0) -> 0 | M98: =IFERROR(M94/$A$43,0) -> 0 | N98: =IFERROR(N94/$A$43,0) -> 0 | O98: =IFERROR(O94/$A$43,0) -> 0 | P98: =IFERROR(P94/$A$43,0) -> 0 | Q98: =IFERROR(Q94/$A$43,0) -> 0 | R98: =IFERROR(R94/$A$43,0) -> 0 | S98: =IFERROR(S94/$A$43,0) -> 0 | T98: =IFERROR(T94/$A$43,0) -> 0 | ... V98: =IFERROR(V94/$A$43,0) -> 0
G99: Breakeven Occupancy | J99: =IFERROR((J88+J140)/J68,0) -> 0 | M99: =IFERROR((M88+M140)/M68,0) -> 0 | N99: =IFERROR((N88+N140)/N68,0) -> 0 | O99: =IFERROR((O88+O140)/O68,0) -> 0 | P99: =IFERROR((P88+P140)/P68,0) -> 0 | Q99: =IFERROR((Q88+Q140)/Q68,0) -> 0 | R99: =IFERROR((R88+R140)/R68,0) -> 0 | S99: =IFERROR((S88+S140)/S68,0) -> 0 | T99: =IFERROR((T88+T140)/T68,0) -> 0 | ... V99: =IFERROR((V88+V140)/V68,0) -> 0
G100: YoY NOI Growth | M100: =IFERROR(M94/J94-1,0) -> 0 | N100: =IFERROR(N94/M94-1,0) -> 0 | O100: =IFERROR(O94/N94-1,0) -> 0 | P100: =IFERROR(P94/O94-1,0) -> 0 | Q100: =IFERROR(Q94/P94-1,0) -> 0 | R100: =IFERROR(R94/Q94-1,0) -> 0 | S100: =IFERROR(S94/R94-1,0) -> 0 | T100: =IFERROR(T94/S94-1,0) -> 0 | U100: =IFERROR(U94/T94-1,0) -> 0 | V100: =IFERROR(V94/U94-1,0) -> 0
C102: GROWTH RATES & % GPR ASSUMPTIONS | V102: Video Tutorial ▶️
J103: =J47 -> T-3 | M103: 1 | N103: =M103+1 -> 2 | O103: =N103+1 -> 3 | P103: =O103+1 -> 4 | Q103: =P103+1 -> 5 | R103: =Q103+1 -> 6 | S103: =R103+1 -> 7 | T103: =S103+1 -> 8 | U103: =T103+1 -> 9 | V103: =U103+1 -> 10
C104: Rent Growth | M104: 0.03 | N104: 0.03 | O104: 0.03 | P104: 0.03 | Q104: 0.03 | R104: =Q104 -> 0.03 | S104: =R104 -> 0.03 | T104: =S104 -> 0.03 | U104: =T104 -> 0.03 | V104: =U104 -> 0.03
C105: GPR / Unit / Mo | J105: =I53 -> 0 | M105: =M53 -> 0 | N105: =N53 -> 0 | O105: =O53 -> 0 | P105: =P53 -> 0 | Q105: =Q53 -> 0 | R105: =R53 -> 0 | S105: =S53 -> 0 | T105: =T53 -> 0 | ... V105: =V53 -> 0
C106: Downtime Vacancy (renovation) | M106: =IFERROR(K56,0) -> 0 | N106: =IFERROR(N56/-N48,0) -> 0 | O106: =IFERROR(O56/-O48,0) -> 0 | P106: =IFERROR(P56/-P48,0) -> 0 | Q106: =IFERROR(Q56/-Q48,0) -> 0 | R106: =IFERROR(R56/-R48,0) -> 0 | S106: =IFERROR(S56/-S48,0) -> 0 | T106: =IFERROR(T56/-T48,0) -> 0 | U106: =IFERROR(U56/-U48,0) -> 0 | V106: =IFERROR(V56/-V48,0) -> 0
C107: General Vacancy (% of GPR + RUBS + Other Inc) | J107: =H57 -> 0 | M107: =K57 -> 0 | N107: 0.05 | O107: 0.05 | P107: 0.05 | Q107: 0.05 | R107: =Q107 -> 0.05 | S107: =R107 -> 0.05 | T107: =S107 -> 0.05 | U107: =T107 -> 0.05 | V107: =U107 -> 0.05
C108: Concessions (% GPR) | J108: =H58 -> 0 | M108: =K58 -> 0 | N108: 0.005 | O108: 0.005 | P108: 0.005 | Q108: 0.005 | R108: =Q108 -> 0.005 | S108: =R108 -> 0.005 | T108: =S108 -> 0.005 | U108: =T108 -> 0.005 | V108: =U108 -> 0.005
C109: Bad Debt (% GPR) | J109: =H59 -> 0 | M109: =K59 -> 0 | N109: 0.005 | O109: 0.005 | P109: 0.005 | Q109: 0.005 | R109: =Q109 -> 0.005 | S109: =R109 -> 0.005 | T109: =S109 -> 0.005 | U109: =T109 -> 0.005 | V109: =U109 -> 0.005
C110: Loss to Lease (% GPR) | J110: =H60 -> 0 | M110: =K60 -> 0 | N110: 0.02 | O110: 0.02 | P110: 0.02 | Q110: 0.02 | R110: =Q110 -> 0.02 | S110: =R110 -> 0.02 | T110: =S110 -> 0.02 | U110: =T110 -> 0.02 | V110: =U110 -> 0.02
...

Sheet IRR Sensitivity
B2: Inputs | F2: Data Table | K2: Baseline
B3: Exit Cap | D3: ='UW Model'!B20 -> 0.0575 | F3: Exit Cap Rate | H3: =I3-$D$4 -> 0.053 | I3: =J3-$D$4 -> 0.0545 | J3: =K3-$D$4 -> 0.056 | K3: ='UW Model'!G23 -> 0.0575 | L3: =K3+$D$4 -> 0.059 | M3: =L3+$D$4 -> 0.0605 | N3: =M3+$D$4 -> 0.062
B4: Cap Escalator | D4: =('UW Model'!G23-'UW Model'!G14)/'UW Model'!G20 -> 0.0015 | F4: IRR (LP) | G4: ='UW Model'!I207 -> 0 | H4: 0 | I4: 0 | J4: 0 | K4: 0 | L4: 0 | M4: 0 | N4: 0
B5: Exit Year | D5: ='UW Model'!G20 -> 5

Sheet Administrative -->

Sheet GPR Logic
B1: Video Tutorial ▶️ | W1: =IF(W3='UW Model'!$O$14,"Reno Start", IF(AND(W3>'UW Model'!$O$14,W3<'UW Model'!$O$15),"Rolling", IF(W3='UW Model'!$O$15,"Reno End",""))) | X1: =IF(X3='UW Model'!$O$14,"Reno Start", IF(AND(X3>'UW Model'!$O$14,X3<'UW Model'!$O$15),"Rolling", IF(X3='UW Model'!$O$15,"Reno End",""))) | Y1: =IF(Y3='UW Model'!$O$14,"Reno Start", IF(AND(Y3>'UW Model'!$O$14,Y3<'UW Model'!$O$15),"Rolling", IF(Y3='UW Model'!$O$15,"Reno End",""))) -> Reno Start | Z1: =IF(Z3='UW Model'!$O$14,"Reno Start", IF(AND(Z3>'UW Model'!$O$14,Z3<'UW Model'!$O$15),"Rolling", IF(Z3='UW Model'!$O$15,"Reno End",""))) -> Rolling | AA1: =IF(AA3='UW Model'!$O$14,"Reno Start", IF(AND(AA3>'UW Model'!$O$14,AA3<'UW Model'!$O$15),"Rolling", IF(AA3='UW Model'!$O$15,"Reno End",""))) -> Rolling | AB1: =IF(AB3='UW Model'!$O$14,"Reno Start", IF(AND(AB3>'UW Model'!$O$14,AB3<'UW Model'!$O$15),"Rolling", IF(AB3='UW Model'!$O$15,"Reno End",""))) -> Rolling | AC1: =IF(AC3='UW Model'!$O$14,"Reno Start", IF(AND(AC3>'UW Model'!$O$14,AC3<'UW Model'!$O$15),"Rolling", IF(AC3='UW Model'!$O$15,"Reno End",""))) -> Rolling | AD1: =IF(AD3='UW Model'!$O$14,"Reno Start", IF(AND(AD3>'UW Model'!$O$14,AD3<'UW Model'!$O$15),"Rolling", IF(AD3='UW Model'!$O$15,"Reno End",""))) -> Rolling | ... CE1: =IF(CE3='UW Model'!$O$14,"Reno Start", IF(AND(CE3>'UW Model'!$O$14,CE3<'UW Model'!$O$15),"Rolling", IF(CE3='UW Model'!$O$15,"Reno End","")))
B2: INTERIOR RENOVATION GRAPHS | F2: The purpose of this tab is to reveal the logic utilized by the UW model to determine Gross Potential Rent (GPR) and Renovation Vacancy. Each unit type that is to be renovated is moved to Reno Vacancy for 2 months & then moved to the post-renovation revenue based on the renovation start & duration set on the UW Model tab. The below graph helps to illustrate this process | Q2: Year | R2: 1 | S2: 2 | T2: 3 | U2: 4 | V2: 5 | W2: 0 | X2: 1 | Y2: 1 | Z2: 1 | AA2: 1 | AB2: 1 | AC2: 1 | AD2: 1 | AE2: 1 | AF2: 1 | AG2: 1 | AH2: 1 | AI2: 1 | AJ2: 2 | AK2: 2 | AL2: 2 | AM2: 2 | AN2: 2 | AO2: 2 | AP2: 2 | AQ2: 2 | AR2: 2 | AS2: 2 | AT2: 2 | AU2: 2 | AV2: 3 | AW2: 3 | AX2: 3 | AY2: 3 | AZ2: 3 | BA2: 3 | BB2: 3 | BC2: 3 | BD2: 3 | BE2: 3 | BF2: 3 | BG2: 3 | BH2: 4 | BI2: 4 | BJ2: 4 | BK2: 4 | BL2: 4 | BM2: 4 | BN2: 4 | BO2: 4 | BP2: 4 | BQ2: 4 | BR2: 4 | BS2: 4 | BT2: 5 | BU2: =BT2 -> 5 | BV2: =BU2 -> 5 | BW2: =BV2 -> 5 | BX2: =BW2 -> 5 | BY2: =BX2 -> 5 | BZ2: =BY2 -> 5 | CA2: =BZ2 -> 5 | CB2: =CA2 -> 5 | ... CE2: =CD2 -> 5
Q3: Month | R3: N/A | S3: N/A | T3: N/A | U3: N/A | V3: N/A | W3: 0 | X3: 1 | Y3: 2 | Z3: 3 | AA3: 4 | AB3: 5 | AC3: 6 | AD3: 7 | AE3: 8 | AF3: 9 | AG3: 10 | AH3: 11 | AI3: 12 | AJ3: 13 | AK3: 14 | AL3: 15 | AM3: 16 | AN3: 17 | AO3: 18 | AP3: 19 | AQ3: 20 | AR3: 21 | AS3: 22 | AT3: 23 | AU3: 24 | AV3: 25 | AW3: 26 | AX3: 27 | AY3: 28 | AZ3: 29 | BA3: 30 | BB3: 31 | BC3: 32 | BD3: 33 | BE3: 34 | BF3: 35 | BG3: 36 | BH3: =BG3+1 -> 37 | BI3: =BH3+1 -> 38 | BJ3: =BI3+1 -> 39 | BK3: =BJ3+1 -> 40 | BL3: =BK3+1 -> 41 | BM3: =BL3+1 -> 42 | BN3: =BM3+1 -> 43 | BO3: =BN3+1 -> 44 | ... CE3: =CD3+1 -> 60
Q4: Date | R4: =_xlfn.MAXIFS($X4:$BS4,$X$2:$BS$2,R$2) -> 45529 | S4: =_xlfn.MAXIFS($X4:$BS4,$X$2:$BS$2,S$2) -> 45894 | T4: =_xlfn.MAXIFS($X4:$BS4,$X$2:$BS$2,T$2) -> 46259 | U4: =_xlfn.MAXIFS($X4:$BS4,$X$2:$BS$2,U$2) -> 46624 | V4: =_xlfn.MAXIFS($X4:$CE4,$X$2:$CE$2,V$2) -> 46990 | W4: ='UW Model'!G13 -> 45163 | X4: =EDATE(W4,1) -> 45194 | Y4: =EDATE(X4,1) -> 45224 | Z4: =EDATE(Y4,1) -> 45255 | AA4: =EDATE(Z4,1) -> 45285 | AB4: =EDATE(AA4,1) -> 45316 | AC4: =EDATE(AB4,1) -> 45347 | AD4: =EDATE(AC4,1) -> 45376 | AE4: =EDATE(AD4,1) -> 45407 | ... CE4: =EDATE(CD4,1) -> 46990
P5: Gross Rents for Planned Renovations | Q5: Reno Unit Completions Total | R5: =SUM(R6:R20) -> 0 | S5: =SUM(S6:S20) -> 0 | T5: =SUM(T6:T20) -> 0 | U5: =SUM(U6:U20) -> 0 | V5: =SUM(V6:V20) -> 0 | W5: =SUM(W6:W20) -> 0 | X5: =SUM(X6:X20) -> 0 | Y5: =SUM(Y6:Y20) -> 0 | ... CE5: =SUM(CE6:CE20) -> 0
Q6: =IF('UW Model'!C28="","",'UW Model'!C28) | R6: =_xlfn.MAXIFS($X6:$CE6,$X$2:$CE$2,R$2) -> 0 | S6: =_xlfn.MAXIFS($X6:$CE6,$X$2:$CE$2,S$2) -> 0 | T6: =_xlfn.MAXIFS($X6:$CE6,$X$2:$CE$2,T$2) -> 0 | U6: =_xlfn.MAXIFS($X6:$CE6,$X$2:$CE$2,U$2) -> 0 | V6: =_xlfn.MAXIFS($X6:$CE6,$X$2:$CE$2,V$2) -> 0 | W6: 0 | X6: =IF(AND(X$3>'UW Model'!$O$14+1,X$3<='UW Model'!$O$15),'UW Model'!$O28/('UW Model'!$O$15-'UW Model'!$O$14-1)+W6,0) -> 0 | Y6: =IF(AND(Y$3>'UW Model'!$O$14+1,Y$3<='UW Model'!$O$15),'UW Model'!$O28/('UW Model'!$O$15-'UW Model'!$O$14-1)+X6,X6) -> 0 | Z6: =IF(AND(Z$3>'UW Model'!$O$14+1,Z$3<='UW Model'!$O$15),'UW Model'!$O28/('UW Model'!$O$15-'UW Model'!$O$14-1)+Y6,Y6) -> 0 | AA6: =IF(AND(AA$3>'UW Model'!$O$14+1,AA$3<='UW Model'!$O$15),'UW Model'!$O28/('UW Model'!$O$15-'UW Model'!$O$14-1)+Z6,Z6) -> 0 | AB6: =IF(AND(AB$3>'UW Model'!$O$14+1,AB$3<='UW Model'!$O$15),'UW Model'!$O28/('UW Model'!$O$15-'UW Model'!$O$14-1)+AA6,AA6) -> 0 | AC6: =IF(AND(AC$3>'UW Model'!$O$14+1,AC$3<='UW Model'!$O$15),'UW Model'!$O28/('UW Model'!$O$15-'UW Model'!$O$14-1)+AB6,AB6) -> 0 | AD6: =IF(AND(AD$3>'UW Model'!$O$14+1,AD$3<='UW Model'!$O$15),'UW Model'!$O28/('UW Model'!$O$15-'UW Model'!$O$14-1)+AC6,AC6) -> 0 | AE6: =IF(AND(AE$3>'UW Model'!$O$14+1,AE$3<='UW Model'!$O$15),'UW Model'!$O28/('UW Model'!$O$15-'UW Model'!$O$14-1)+AD6,AD6) -> 0 | AF6: =IF(AND(AF$3>'UW Model'!$O$14+1,AF$3<='UW Model'!$O$15),'UW Model'!$O28/('UW Model'!$O$15-'UW Model'!$O$14-1)+AE6,AE6) -> 0 | ... CE6: =IF(AND(CE$3>'UW Model'!$O$14+1,CE$3<='UW Model'!$O$15),'UW Model'!$O28/('UW Model'!$O$15-'UW Model'!$O$14-1)+CD6,CD6) -> 0
Q7: =IF('UW Model'!C29="","",'UW Model'!C29) | R7: =_xlfn.MAXIFS($X7:$CE7,$X$2:$CE$2,R$2) -> 0 | S7: =_xlfn.MAXIFS($X7:$CE7,$X$2:$CE$2,S$2) -> 0 | T7: =_xlfn.MAXIFS($X7:$CE7,$X$2:$CE$2,T$2) -> 0 | U7: =_xlfn.MAXIFS($X7:$CE7,$X$2:$CE$2,U$2) -> 0 | V7: =_xlfn.MAXIFS($X7:$CE7,$X$2:$CE$2,V$2) -> 0 | W7: 0 | X7: =IF(AND(X$3>'UW Model'!$O$14+1,X$3<='UW Model'!$O$15),'UW Model'!$O29/('UW Model'!$O$15-'UW Model'!$O$14-1)+W7,0) -> 0 | Y7: =IF(AND(Y$3>'UW Model'!$O$14+1,Y$3<='UW Model'!$O$15),'UW Model'!$O29/('UW Model'!$O$15-'UW Model'!$O$14-1)+X7,X7) -> 0 | Z7: =IF(AND(Z$3>'UW Model'!$O$14+1,Z$3<='UW Model'!$O$15),'UW Model'!$O29/('UW Model'!$O$15-'UW Model'!$O$14-1)+Y7,Y7) -> 0 | AA7: =IF(AND(AA$3>'UW Model'!$O$14+1,AA$3<='UW Model'!$O$15),'UW Model'!$O29/('UW Model'!$O$15-'UW Model'!$O$14-1)+Z7,Z7) -> 0 | AB7: =IF(AND(AB$3>'UW Model'!$O$14+1,AB$3<='UW Model'!$O$15),'UW Model'!$O29/('UW Model'!$O$15-'UW Model'!$O$14-1)+AA7,AA7) -> 0 | AC7: =IF(AND(AC$3>'UW Model'!$O$14+1,AC$3<='UW Model'!$O$15),'UW Model'!$O29/('UW Model'!$O$15-'UW Model'!$O$14-1)+AB7,AB7) -> 0 | AD7: =IF(AND(AD$3>'UW Model'!$O$14+1,AD$3<='UW Model'!$O$15),'UW Model'!$O29/('UW Model'!$O$15-'UW Model'!$O$14-1)+AC7,AC7) -> 0 | AE7: =IF(AND(AE$3>'UW Model'!$O$14+1,AE$3<='UW Model'!$O$15),'UW Model'!$O29/('UW Model'!$O$15-'UW Model'!$O$14-1)+AD7,AD7) -> 0 | AF7: =IF(AND(AF$3>'UW Model'!$O$14+1,AF$3<='UW Model'!$O$15),'UW Model'!$O29/('UW Model'!$O$15-'UW Model'!$O$14-1)+AE7,AE7) -> 0 | ... CE7: =IF(AND(CE$3>'UW Model'!$O$14+1,CE$3<='UW Model'!$O$15),'UW Model'!$O29/('UW Model'!$O$15-'UW Model'!$O$14-1)+CD7,CD7) -> 0
Q8: =IF('UW Model'!C30="","",'UW Model'!C30) | R8: =_xlfn.MAXIFS($X8:$CE8,$X$2:$CE$2,R$2) -> 0 | S8: =_xlfn.MAXIFS($X8:$CE8,$X$2:$CE$2,S$2) -> 0 | T8: =_xlfn.MAXIFS($X8:$CE8,$X$2:$CE$2,T$2) -> 0 | U8: =_xlfn.MAXIFS($X8:$CE8,$X$2:$CE$2,U$2) -> 0 | V8: =_xlfn.MAXIFS($X8:$CE8,$X$2:$CE$2,V$2) -> 0 | W8: 0 | X8: =IF(AND(X$3>'UW Model'!$O$14+1,X$3<='UW Model'!$O$15),'UW Model'!$O30/('UW Model'!$O$15-'UW Model'!$O$14-1)+W8,0) -> 0 | Y8: =IF(AND(Y$3>'UW Model'!$O$14+1,Y$3<='UW Model'!$O$15),'UW Model'!$O30/('UW Model'!$O$15-'UW Model'!$O$14-1)+X8,X8) -> 0 | Z8: =IF(AND(Z$3>'UW Model'!$O$14+1,Z$3<='UW Model'!$O$15),'UW Model'!$O30/('UW Model'!$O$15-'UW Model'!$O$14-1)+Y8,Y8) -> 0 | AA8: =IF(AND(AA$3>'UW Model'!$O$14+1,AA$3<='UW Model'!$O$15),'UW Model'!$O30/('UW Model'!$O$15-'UW Model'!$O$14-1)+Z8,Z8) -> 0 | AB8: =IF(AND(AB$3>'UW Model'!$O$14+1,AB$3<='UW Model'!$O$15),'UW Model'!$O30/('UW Model'!$O$15-'UW Model'!$O$14-1)+AA8,AA8) -> 0 | AC8: =IF(AND(AC$3>'UW Model'!$O$14+1,AC$3<='UW Model'!$O$15),'UW Model'!$O30/('UW Model'!$O$15-'UW Model'!$O$14-1)+AB8,AB8) -> 0 | AD8: =IF(AND(AD$3>'UW Model'!$O$14+1,AD$3<='UW Model'!$O$15),'UW Model'!$O30/('UW Model'!$O$15-'UW Model'!$O$14-1)+AC8,AC8) -> 0 | AE8: =IF(AND(AE$3>'UW Model'!$O$14+1,AE$3<='UW Model'!$O$15),'UW Model'!$O30/('UW Model'!$O$15-'UW Model'!$O$14-1)+AD8,AD8) -> 0 | AF8: =IF(AND(AF$3>'UW Model'!$O$14+1,AF$3<='UW Model'!$O$15),'UW Model'!$O30/('UW Model'!$O$15-'UW Model'!$O$14-1)+AE8,AE8) -> 0 | ... CE8: =IF(AND(CE$3>'UW Model'!$O$14+1,CE$3<='UW Model'!$O$15),'UW Model'!$O30/('UW Model'!$O$15-'UW Model'!$O$14-1)+CD8,CD8) -> 0
Q9: =IF('UW Model'!C31="","",'UW Model'!C31) | R9: =_xlfn.MAXIFS($X9:$CE9,$X$2:$CE$2,R$2) -> 0 | S9: =_xlfn.MAXIFS($X9:$CE9,$X$2:$CE$2,S$2) -> 0 | T9: =_xlfn.MAXIFS($X9:$CE9,$X$2:$CE$2,T$2) -> 0 | U9: =_xlfn.MAXIFS($X9:$CE9,$X$2:$CE$2,U$2) -> 0 | V9: =_xlfn.MAXIFS($X9:$CE9,$X$2:$CE$2,V$2) -> 0 | W9: 0 | X9: =IF(AND(X$3>'UW Model'!$O$14+1,X$3<='UW Model'!$O$15),'UW Model'!$O31/('UW Model'!$O$15-'UW Model'!$O$14-1)+W9,0) -> 0 | Y9: =IF(AND(Y$3>'UW Model'!$O$14+1,Y$3<='UW Model'!$O$15),'UW Model'!$O31/('UW Model'!$O$15-'UW Model'!$O$14-1)+X9,X9) -> 0 | Z9: =IF(AND(Z$3>'UW Model'!$O$14+1,Z$3<='UW Model'!$O$15),'UW Model'!$O31/('UW Model'!$O$15-'UW Model'!$O$14-1)+Y9,Y9) -> 0 | AA9: =IF(AND(AA$3>'UW Model'!$O$14+1,AA$3<='UW Model'!$O$15),'UW Model'!$O31/('UW Model'!$O$15-'UW Model'!$O$14-1)+Z9,Z9) -> 0 | AB9: =IF(AND(AB$3>'UW Model'!$O$14+1,AB$3<='UW Model'!$O$15),'UW Model'!$O31/('UW Model'!$O$15-'UW Model'!$O$14-1)+AA9,AA9) -> 0 | AC9: =IF(AND(AC$3>'UW Model'!$O$14+1,AC$3<='UW Model'!$O$15),'UW Model'!$O31/('UW Model'!$O$15-'UW Model'!$O$14-1)+AB9,AB9) -> 0 | AD9: =IF(AND(AD$3>'UW Model'!$O$14+1,AD$3<='UW Model'!$O$15),'UW Model'!$O31/('UW Model'!$O$15-'UW Model'!$O$14-1)+AC9,AC9) -> 0 | AE9: =IF(AND(AE$3>'UW Model'!$O$14+1,AE$3<='UW Model'!$O$15),'UW Model'!$O31/('UW Model'!$O$15-'UW Model'!$O$14-1)+AD9,AD9) -> 0 | AF9: =IF(AND(AF$3>'UW Model'!$O$14+1,AF$3<='UW Model'!$O$15),'UW Model'!$O31/('UW Model'!$O$15-'UW Model'!$O$14-1)+AE9,AE9) -> 0 | ... CE9: =IF(AND(CE$3>'UW Model'!$O$14+1,CE$3<='UW Model'!$O$15),'UW Model'!$O31/('UW Model'!$O$15-'UW Model'!$O$14-1)+CD9,CD9) -> 0
Q10: =IF('UW Model'!C32="","",'UW Model'!C32) | R10: =_xlfn.MAXIFS($X10:$CE10,$X$2:$CE$2,R$2) -> 0 | S10: =_xlfn.MAXIFS($X10:$CE10,$X$2:$CE$2,S$2) -> 0 | T10: =_xlfn.MAXIFS($X10:$CE10,$X$2:$CE$2,T$2) -> 0 | U10: =_xlfn.MAXIFS($X10:$CE10,$X$2:$CE$2,U$2) -> 0 | V10: =_xlfn.MAXIFS($X10:$CE10,$X$2:$CE$2,V$2) -> 0 | W10: 0 | X10: =IF(AND(X$3>'UW Model'!$O$14+1,X$3<='UW Model'!$O$15),'UW Model'!$O32/('UW Model'!$O$15-'UW Model'!$O$14-1)+W10,0) -> 0 | Y10: =IF(AND(Y$3>'UW Model'!$O$14+1,Y$3<='UW Model'!$O$15),'UW Model'!$O32/('UW Model'!$O$15-'UW Model'!$O$14-1)+X10,X10) -> 0 | Z10: =IF(AND(Z$3>'UW Model'!$O$14+1,Z$3<='UW Model'!$O$15),'UW Model'!$O32/('UW Model'!$O$15-'UW Model'!$O$14-1)+Y10,Y10) -> 0 | AA10: =IF(AND(AA$3>'UW Model'!$O$14+1,AA$3<='UW Model'!$O$15),'UW Model'!$O32/('UW Model'!$O$15-'UW Model'!$O$14-1)+Z10,Z10) -> 0 | AB10: =IF(AND(AB$3>'UW Model'!$O$14+1,AB$3<='UW Model'!$O$15),'UW Model'!$O32/('UW Model'!$O$15-'UW Model'!$O$14-1)+AA10,AA10) -> 0 | AC10: =IF(AND(AC$3>'UW Model'!$O$14+1,AC$3<='UW Model'!$O$15),'UW Model'!$O32/('UW Model'!$O$15-'UW Model'!$O$14-1)+AB10,AB10) -> 0 | AD10: =IF(AND(AD$3>'UW Model'!$O$14+1,AD$3<='UW Model'!$O$15),'UW Model'!$O32/('UW Model'!$O$15-'UW Model'!$O$14-1)+AC10,AC10) -> 0 | AE10: =IF(AND(AE$3>'UW Model'!$O$14+1,AE$3<='UW Model'!$O$15),'UW Model'!$O32/('UW Model'!$O$15-'UW Model'!$O$14-1)+AD10,AD10) -> 0 | AF10: =IF(AND(AF$3>'UW Model'!$O$14+1,AF$3<='UW Model'!$O$15),'UW Model'!$O32/('UW Model'!$O$15-'UW Model'!$O$14-1)+AE10,AE10) -> 0 | ... CE10: =IF(AND(CE$3>'UW Model'!$O$14+1,CE$3<='UW Model'!$O$15),'UW Model'!$O32/('UW Model'!$O$15-'UW Model'!$O$14-1)+CD10,CD10) -> 0
Q11: =IF('UW Model'!C33="","",'UW Model'!C33) | R11: =_xlfn.MAXIFS($X11:$CE11,$X$2:$CE$2,R$2) -> 0 | S11: =_xlfn.MAXIFS($X11:$CE11,$X$2:$CE$2,S$2) -> 0 | T11: =_xlfn.MAXIFS($X11:$CE11,$X$2:$CE$2,T$2) -> 0 | U11: =_xlfn.MAXIFS($X11:$CE11,$X$2:$CE$2,U$2) -> 0 | V11: =_xlfn.MAXIFS($X11:$CE11,$X$2:$CE$2,V$2) -> 0 | W11: 0 | X11: =IF(AND(X$3>'UW Model'!$O$14+1,X$3<='UW Model'!$O$15),'UW Model'!$O33/('UW Model'!$O$15-'UW Model'!$O$14-1)+W11,0) -> 0 | Y11: =IF(AND(Y$3>'UW Model'!$O$14+1,Y$3<='UW Model'!$O$15),'UW Model'!$O33/('UW Model'!$O$15-'UW Model'!$O$14-1)+X11,X11) -> 0 | Z11: =IF(AND(Z$3>'UW Model'!$O$14+1,Z$3<='UW Model'!$O$15),'UW Model'!$O33/('UW Model'!$O$15-'UW Model'!$O$14-1)+Y11,Y11) -> 0 | AA11: =IF(AND(AA$3>'UW Model'!$O$14+1,AA$3<='UW Model'!$O$15),'UW Model'!$O33/('UW Model'!$O$15-'UW Model'!$O$14-1)+Z11,Z11) -> 0 | AB11: =IF(AND(AB$3>'UW Model'!$O$14+1,AB$3<='UW Model'!$O$15),'UW Model'!$O33/('UW Model'!$O$15-'UW Model'!$O$14-1)+AA11,AA11) -> 0 | AC11: =IF(AND(AC$3>'UW Model'!$O$14+1,AC$3<='UW Model'!$O$15),'UW Model'!$O33/('UW Model'!$O$15-'UW Model'!$O$14-1)+AB11,AB11) -> 0 | AD11: =IF(AND(AD$3>'UW Model'!$O$14+1,AD$3<='UW Model'!$O$15),'UW Model'!$O33/('UW Model'!$O$15-'UW Model'!$O$14-1)+AC11,AC11) -> 0 | AE11: =IF(AND(AE$3>'UW Model'!$O$14+1,AE$3<='UW Model'!$O$15),'UW Model'!$O33/('UW Model'!$O$15-'UW Model'!$O$14-1)+AD11,AD11) -> 0 | AF11: =IF(AND(AF$3>'UW Model'!$O$14+1,AF$3<='UW Model'!$O$15),'UW Model'!$O33/('UW Model'!$O$15-'UW Model'!$O$14-1)+AE11,AE11) -> 0 | ... CE11: =IF(AND(CE$3>'UW Model'!$O$14+1,CE$3<='UW Model'!$O$15),'UW Model'!$O33/('UW Model'!$O$15-'UW Model'!$O$14-1)+CD11,CD11) -> 0
Q12: =IF('UW Model'!C34="","",'UW Model'!C34) | R12: =_xlfn.MAXIFS($X12:$CE12,$X$2:$CE$2,R$2) -> 0 | S12: =_xlfn.MAXIFS($X12:$CE12,$X$2:$CE$2,S$2) -> 0 | T12: =_xlfn.MAXIFS($X12:$CE12,$X$2:$CE$2,T$2) -> 0 | U12: =_xlfn.MAXIFS($X12:$CE12,$X$2:$CE$2,U$2) -> 0 | V12: =_xlfn.MAXIFS($X12:$CE12,$X$2:$CE$2,V$2) -> 0 | W12: 0 | X12: =IF(AND(X$3>'UW Model'!$O$14+1,X$3<='UW Model'!$O$15),'UW Model'!$O34/('UW Model'!$O$15-'UW Model'!$O$14-1)+W12,0) -> 0 | Y12: =IF(AND(Y$3>'UW Model'!$O$14+1,Y$3<='UW Model'!$O$15),'UW Model'!$O34/('UW Model'!$O$15-'UW Model'!$O$14-1)+X12,X12) -> 0 | Z12: =IF(AND(Z$3>'UW Model'!$O$14+1,Z$3<='UW Model'!$O$15),'UW Model'!$O34/('UW Model'!$O$15-'UW Model'!$O$14-1)+Y12,Y12) -> 0 | AA12: =IF(AND(AA$3>'UW Model'!$O$14+1,AA$3<='UW Model'!$O$15),'UW Model'!$O34/('UW Model'!$O$15-'UW Model'!$O$14-1)+Z12,Z12) -> 0 | AB12: =IF(AND(AB$3>'UW Model'!$O$14+1,AB$3<='UW Model'!$O$15),'UW Model'!$O34/('UW Model'!$O$15-'UW Model'!$O$14-1)+AA12,AA12) -> 0 | AC12: =IF(AND(AC$3>'UW Model'!$O$14+1,AC$3<='UW Model'!$O$15),'UW Model'!$O34/('UW Model'!$O$15-'UW Model'!$O$14-1)+AB12,AB12) -> 0 | AD12: =IF(AND(AD$3>'UW Model'!$O$14+1,AD$3<='UW Model'!$O$15),'UW Model'!$O34/('UW Model'!$O$15-'UW Model'!$O$14-1)+AC12,AC12) -> 0 | AE12: =IF(AND(AE$3>'UW Model'!$O$14+1,AE$3<='UW Model'!$O$15),'UW Model'!$O34/('UW Model'!$O$15-'UW Model'!$O$14-1)+AD12,AD12) -> 0 | AF12: =IF(AND(AF$3>'UW Model'!$O$14+1,AF$3<='UW Model'!$O$15),'UW Model'!$O34/('UW Model'!$O$15-'UW Model'!$O$14-1)+AE12,AE12) -> 0 | ... CE12: =IF(AND(CE$3>'UW Model'!$O$14+1,CE$3<='UW Model'!$O$15),'UW Model'!$O34/('UW Model'!$O$15-'UW Model'!$O$14-1)+CD12,CD12) -> 0
Q13: =IF('UW Model'!C35="","",'UW Model'!C35) | R13: =_xlfn.MAXIFS($X13:$CE13,$X$2:$CE$2,R$2) -> 0 | S13: =_xlfn.MAXIFS($X13:$CE13,$X$2:$CE$2,S$2) -> 0 | T13: =_xlfn.MAXIFS($X13:$CE13,$X$2:$CE$2,T$2) -> 0 | U13: =_xlfn.MAXIFS($X13:$CE13,$X$2:$CE$2,U$2) -> 0 | V13: =_xlfn.MAXIFS($X13:$CE13,$X$2:$CE$2,V$2) -> 0 | W13: 0 | X13: =IF(AND(X$3>'UW Model'!$O$14+1,X$3<='UW Model'!$O$15),'UW Model'!$O35/('UW Model'!$O$15-'UW Model'!$O$14-1)+W13,0) -> 0 | Y13: =IF(AND(Y$3>'UW Model'!$O$14+1,Y$3<='UW Model'!$O$15),'UW Model'!$O35/('UW Model'!$O$15-'UW Model'!$O$14-1)+X13,X13) -> 0 | Z13: =IF(AND(Z$3>'UW Model'!$O$14+1,Z$3<='UW Model'!$O$15),'UW Model'!$O35/('UW Model'!$O$15-'UW Model'!$O$14-1)+Y13,Y13) -> 0 | AA13: =IF(AND(AA$3>'UW Model'!$O$14+1,AA$3<='UW Model'!$O$15),'UW Model'!$O35/('UW Model'!$O$15-'UW Model'!$O$14-1)+Z13,Z13) -> 0 | AB13: =IF(AND(AB$3>'UW Model'!$O$14+1,AB$3<='UW Model'!$O$15),'UW Model'!$O35/('UW Model'!$O$15-'UW Model'!$O$14-1)+AA13,AA13) -> 0 | AC13: =IF(AND(AC$3>'UW Model'!$O$14+1,AC$3<='UW Model'!$O$15),'UW Model'!$O35/('UW Model'!$O$15-'UW Model'!$O$14-1)+AB13,AB13) -> 0 | AD13: =IF(AND(AD$3>'UW Model'!$O$14+1,AD$3<='UW Model'!$O$15),'UW Model'!$O35/('UW Model'!$O$15-'UW Model'!$O$14-1)+AC13,AC13) -> 0 | AE13: =IF(AND(AE$3>'UW Model'!$O$14+1,AE$3<='UW Model'!$O$15),'UW Model'!$O35/('UW Model'!$O$15-'UW Model'!$O$14-1)+AD13,AD13) -> 0 | AF13: =IF(AND(AF$3>'UW Model'!$O$14+1,AF$3<='UW Model'!$O$15),'UW Model'!$O35/('UW Model'!$O$15-'UW Model'!$O$14-1)+AE13,AE13) -> 0 | ... CE13: =IF(AND(CE$3>'UW Model'!$O$14+1,CE$3<='UW Model'!$O$15),'UW Model'!$O35/('UW Model'!$O$15-'UW Model'!$O$14-1)+CD13,CD13) -> 0
Q14: =IF('UW Model'!C36="","",'UW Model'!C36) | R14: =_xlfn.MAXIFS($X14:$CE14,$X$2:$CE$2,R$2) -> 0 | S14: =_xlfn.MAXIFS($X14:$CE14,$X$2:$CE$2,S$2) -> 0 | T14: =_xlfn.MAXIFS($X14:$CE14,$X$2:$CE$2,T$2) -> 0 | U14: =_xlfn.MAXIFS($X14:$CE14,$X$2:$CE$2,U$2) -> 0 | V14: =_xlfn.MAXIFS($X14:$CE14,$X$2:$CE$2,V$2) -> 0 | W14: 0 | X14: =IF(AND(X$3>'UW Model'!$O$14+1,X$3<='UW Model'!$O$15),'UW Model'!$O36/('UW Model'!$O$15-'UW Model'!$O$14-1)+W14,0) -> 0 | Y14: =IF(AND(Y$3>'UW Model'!$O$14+1,Y$3<='UW Model'!$O$15),'UW Model'!$O36/('UW Model'!$O$15-'UW Model'!$O$14-1)+X14,X14) -> 0 | Z14: =IF(AND(Z$3>'UW Model'!$O$14+1,Z$3<='UW Model'!$O$15),'UW Model'!$O36/('UW Model'!$O$15-'UW Model'!$O$14-1)+Y14,Y14) -> 0 | AA14: =IF(AND(AA$3>'UW Model'!$O$14+1,AA$3<='UW Model'!$O$15),'UW Model'!$O36/('UW Model'!$O$15-'UW Model'!$O$14-1)+Z14,Z14) -> 0 | AB14: =IF(AND(AB$3>'UW Model'!$O$14+1,AB$3<='UW Model'!$O$15),'UW Model'!$O36/('UW Model'!$O$15-'UW Model'!$O$14-1)+AA14,AA14) -> 0 | AC14: =IF(AND(AC$3>'UW Model'!$O$14+1,AC$3<='UW Model'!$O$15),'UW Model'!$O36/('UW Model'!$O$15-'UW Model'!$O$14-1)+AB14,AB14) -> 0 | AD14: =IF(AND(AD$3>'UW Model'!$O$14+1,AD$3<='UW Model'!$O$15),'UW Model'!$O36/('UW Model'!$O$15-'UW Model'!$O$14-1)+AC14,AC14) -> 0 | AE14: =IF(AND(AE$3>'UW Model'!$O$14+1,AE$3<='UW Model'!$O$15),'UW Model'!$O36/('UW Model'!$O$15-'UW Model'!$O$14-1)+AD14,AD14) -> 0 | AF14: =IF(AND(AF$3>'UW Model'!$O$14+1,AF$3<='UW Model'!$O$15),'UW Model'!$O36/('UW Model'!$O$15-'UW Model'!$O$14-1)+AE14,AE14) -> 0 | ... CE14: =IF(AND(CE$3>'UW Model'!$O$14+1,CE$3<='UW Model'!$O$15),'UW Model'!$O36/('UW Model'!$O$15-'UW Model'!$O$14-1)+CD14,CD14) -> 0
Q15: =IF('UW Model'!C37="","",'UW Model'!C37) | R15: =_xlfn.MAXIFS($X15:$CE15,$X$2:$CE$2,R$2) -> 0 | S15: =_xlfn.MAXIFS($X15:$CE15,$X$2:$CE$2,S$2) -> 0 | T15: =_xlfn.MAXIFS($X15:$CE15,$X$2:$CE$2,T$2) -> 0 | U15: =_xlfn.MAXIFS($X15:$CE15,$X$2:$CE$2,U$2) -> 0 | V15: =_xlfn.MAXIFS($X15:$CE15,$X$2:$CE$2,V$2) -> 0 | W15: 0 | X15: =IF(AND(X$3>'UW Model'!$O$14+1,X$3<='UW Model'!$O$15),'UW Model'!$O37/('UW Model'!$O$15-'UW Model'!$O$14-1)+W15,0) -> 0 | Y15: =IF(AND(Y$3>'UW Model'!$O$14+1,Y$3<='UW Model'!$O$15),'UW Model'!$O37/('UW Model'!$O$15-'UW Model'!$O$14-1)+X15,X15) -> 0 | Z15: =IF(AND(Z$3>'UW Model'!$O$14+1,Z$3<='UW Model'!$O$15),'UW Model'!$O37/('UW Model'!$O$15-'UW Model'!$O$14-1)+Y15,Y15) -> 0 | AA15: =IF(AND(AA$3>'UW Model'!$O$14+1,AA$3<='UW Model'!$O$15),'UW Model'!$O37/('UW Model'!$O$15-'UW Model'!$O$14-1)+Z15,Z15) -> 0 | AB15: =IF(AND(AB$3>'UW Model'!$O$14+1,AB$3<='UW Model'!$O$15),'UW Model'!$O37/('UW Model'!$O$15-'UW Model'!$O$14-1)+AA15,AA15) -> 0 | AC15: =IF(AND(AC$3>'UW Model'!$O$14+1,AC$3<='UW Model'!$O$15),'UW Model'!$O37/('UW Model'!$O$15-'UW Model'!$O$14-1)+AB15,AB15) -> 0 | AD15: =IF(AND(AD$3>'UW Model'!$O$14+1,AD$3<='UW Model'!$O$15),'UW Model'!$O37/('UW Model'!$O$15-'UW Model'!$O$14-1)+AC15,AC15) -> 0 | AE15: =IF(AND(AE$3>'UW Model'!$O$14+1,AE$3<='UW Model'!$O$15),'UW Model'!$O37/('UW Model'!$O$15-'UW Model'!$O$14-1)+AD15,AD15) -> 0 | AF15: =IF(AND(AF$3>'UW Model'!$O$14+1,AF$3<='UW Model'!$O$15),'UW Model'!$O37/('UW Model'!$O$15-'UW Model'!$O$14-1)+AE15,AE15) -> 0 | ... CE15: =IF(AND(CE$3>'UW Model'!$O$14+1,CE$3<='UW Model'!$O$15),'UW Model'!$O37/('UW Model'!$O$15-'UW Model'!$O$14-1)+CD15,CD15) -> 0
Q16: =IF('UW Model'!C38="","",'UW Model'!C38) | R16: =_xlfn.MAXIFS($X16:$CE16,$X$2:$CE$2,R$2) -> 0 | S16: =_xlfn.MAXIFS($X16:$CE16,$X$2:$CE$2,S$2) -> 0 | T16: =_xlfn.MAXIFS($X16:$CE16,$X$2:$CE$2,T$2) -> 0 | U16: =_xlfn.MAXIFS($X16:$CE16,$X$2:$CE$2,U$2) -> 0 | V16: =_xlfn.MAXIFS($X16:$CE16,$X$2:$CE$2,V$2) -> 0 | W16: 0 | X16: =IF(AND(X$3>'UW Model'!$O$14+1,X$3<='UW Model'!$O$15),'UW Model'!$O38/('UW Model'!$O$15-'UW Model'!$O$14-1)+W16,0) -> 0 | Y16: =IF(AND(Y$3>'UW Model'!$O$14+1,Y$3<='UW Model'!$O$15),'UW Model'!$O38/('UW Model'!$O$15-'UW Model'!$O$14-1)+X16,X16) -> 0 | Z16: =IF(AND(Z$3>'UW Model'!$O$14+1,Z$3<='UW Model'!$O$15),'UW Model'!$O38/('UW Model'!$O$15-'UW Model'!$O$14-1)+Y16,Y16) -> 0 | AA16: =IF(AND(AA$3>'UW Model'!$O$14+1,AA$3<='UW Model'!$O$15),'UW Model'!$O38/('UW Model'!$O$15-'UW Model'!$O$14-1)+Z16,Z16) -> 0 | AB16: =IF(AND(AB$3>'UW Model'!$O$14+1,AB$3<='UW Model'!$O$15),'UW Model'!$O38/('UW Model'!$O$15-'UW Model'!$O$14-1)+AA16,AA16) -> 0 | AC16: =IF(AND(AC$3>'UW Model'!$O$14+1,AC$3<='UW Model'!$O$15),'UW Model'!$O38/('UW Model'!$O$15-'UW Model'!$O$14-1)+AB16,AB16) -> 0 | AD16: =IF(AND(AD$3>'UW Model'!$O$14+1,AD$3<='UW Model'!$O$15),'UW Model'!$O38/('UW Model'!$O$15-'UW Model'!$O$14-1)+AC16,AC16) -> 0 | AE16: =IF(AND(AE$3>'UW Model'!$O$14+1,AE$3<='UW Model'!$O$15),'UW Model'!$O38/('UW Model'!$O$15-'UW Model'!$O$14-1)+AD16,AD16) -> 0 | AF16: =IF(AND(AF$3>'UW Model'!$O$14+1,AF$3<='UW Model'!$O$15),'UW Model'!$O38/('UW Model'!$O$15-'UW Model'!$O$14-1)+AE16,AE16) -> 0 | ... CE16: =IF(AND(CE$3>'UW Model'!$O$14+1,CE$3<='UW Model'!$O$15),'UW Model'!$O38/('UW Model'!$O$15-'UW Model'!$O$14-1)+CD16,CD16) -> 0
Q17: =IF('UW Model'!C39="","",'UW Model'!C39) | R17: =_xlfn.MAXIFS($X17:$CE17,$X$2:$CE$2,R$2) -> 0 | S17: =_xlfn.MAXIFS($X17:$CE17,$X$2:$CE$2,S$2) -> 0 | T17: =_xlfn.MAXIFS($X17:$CE17,$X$2:$CE$2,T$2) -> 0 | U17: =_xlfn.MAXIFS($X17:$CE17,$X$2:$CE$2,U$2) -> 0 | V17: =_xlfn.MAXIFS($X17:$CE17,$X$2:$CE$2,V$2) -> 0 | W17: 0 | X17: =IF(AND(X$3>'UW Model'!$O$14+1,X$3<='UW Model'!$O$15),'UW Model'!$O39/('UW Model'!$O$15-'UW Model'!$O$14-1)+W17,0) -> 0 | Y17: =IF(AND(Y$3>'UW Model'!$O$14+1,Y$3<='UW Model'!$O$15),'UW Model'!$O39/('UW Model'!$O$15-'UW Model'!$O$14-1)+X17,X17) -> 0 | Z17: =IF(AND(Z$3>'UW Model'!$O$14+1,Z$3<='UW Model'!$O$15),'UW Model'!$O39/('UW Model'!$O$15-'UW Model'!$O$14-1)+Y17,Y17) -> 0 | AA17: =IF(AND(AA$3>'UW Model'!$O$14+1,AA$3<='UW Model'!$O$15),'UW Model'!$O39/('UW Model'!$O$15-'UW Model'!$O$14-1)+Z17,Z17) -> 0 | AB17: =IF(AND(AB$3>'UW Model'!$O$14+1,AB$3<='UW Model'!$O$15),'UW Model'!$O39/('UW Model'!$O$15-'UW Model'!$O$14-1)+AA17,AA17) -> 0 | AC17: =IF(AND(AC$3>'UW Model'!$O$14+1,AC$3<='UW Model'!$O$15),'UW Model'!$O39/('UW Model'!$O$15-'UW Model'!$O$14-1)+AB17,AB17) -> 0 | AD17: =IF(AND(AD$3>'UW Model'!$O$14+1,AD$3<='UW Model'!$O$15),'UW Model'!$O39/('UW Model'!$O$15-'UW Model'!$O$14-1)+AC17,AC17) -> 0 | AE17: =IF(AND(AE$3>'UW Model'!$O$14+1,AE$3<='UW Model'!$O$15),'UW Model'!$O39/('UW Model'!$O$15-'UW Model'!$O$14-1)+AD17,AD17) -> 0 | AF17: =IF(AND(AF$3>'UW Model'!$O$14+1,AF$3<='UW Model'!$O$15),'UW Model'!$O39/('UW Model'!$O$15-'UW Model'!$O$14-1)+AE17,AE17) -> 0 | ... CE17: =IF(AND(CE$3>'UW Model'!$O$14+1,CE$3<='UW Model'!$O$15),'UW Model'!$O39/('UW Model'!$O$15-'UW Model'!$O$14-1)+CD17,CD17) -> 0
... Q20: =IF('UW Model'!C42="","",'UW Model'!C42) | R20: =_xlfn.MAXIFS($X20:$CE20,$X$2:$CE$2,R$2) -> 0 | S20: =_xlfn.MAXIFS($X20:$CE20,$X$2:$CE$2,S$2) -> 0 | T20: =_xlfn.MAXIFS($X20:$CE20,$X$2:$CE$2,T$2) -> 0 | U20: =_xlfn.MAXIFS($X20:$CE20,$X$2:$CE$2,U$2) -> 0 | V20: =_xlfn.MAXIFS($X20:$CE20,$X$2:$CE$2,V$2) -> 0 | W20: 0 | X20: =IF(AND(X$3>'UW Model'!$O$14+1,X$3<='UW Model'!$O$15),'UW Model'!$O42/('UW Model'!$O$15-'UW Model'!$O$14-1)+W20,0) -> 0 | Y20: =IF(AND(Y$3>'UW Model'!$O$14+1,Y$3<='UW Model'!$O$15),'UW Model'!$O42/('UW Model'!$O$15-'UW Model'!$O$14-1)+X20,X20) -> 0 | Z20: =IF(AND(Z$3>'UW Model'!$O$14+1,Z$3<='UW Model'!$O$15),'UW Model'!$O42/('UW Model'!$O$15-'UW Model'!$O$14-1)+Y20,Y20) -> 0 | AA20: =IF(AND(AA$3>'UW Model'!$O$14+1,AA$3<='UW Model'!$O$15),'UW Model'!$O42/('UW Model'!$O$15-'UW Model'!$O$14-1)+Z20,Z20) -> 0 | AB20: =IF(AND(AB$3>'UW Model'!$O$14+1,AB$3<='UW Model'!$O$15),'UW Model'!$O42/('UW Model'!$O$15-'UW Model'!$O$14-1)+AA20,AA20) -> 0 | AC20: =IF(AND(AC$3>'UW Model'!$O$14+1,AC$3<='UW Model'!$O$15),'UW Model'!$O42/('UW Model'!$O$15-'UW Model'!$O$14-1)+AB20,AB20) -> 0 | AD20: =IF(AND(AD$3>'UW Model'!$O$14+1,AD$3<='UW Model'!$O$15),'UW Model'!$O42/('UW Model'!$O$15-'UW Model'!$O$14-1)+AC20,AC20) -> 0 | AE20: =IF(AND(AE$3>'UW Model'!$O$14+1,AE$3<='UW Model'!$O$15),'UW Model'!$O42/('UW Model'!$O$15-'UW Model'!$O$14-1)+AD20,AD20) -> 0 | AF20: =IF(AND(AF$3>'UW Model'!$O$14+1,AF$3<='UW Model'!$O$15),'UW Model'!$O42/('UW Model'!$O$15-'UW Model'!$O$14-1)+AE20,AE20) -> 0 | ... CE20: =IF(AND(CE$3>'UW Model'!$O$14+1,CE$3<='UW Model'!$O$15),'UW Model'!$O42/('UW Model'!$O$15-'UW Model'!$O$14-1)+CD20,CD20) -> 0
Q21: Reno GPR Total | R21: =SUM(R22:R36) -> 0 | S21: =SUM(S22:S36) -> 0 | T21: =SUM(T22:T36) -> 0 | U21: =SUM(U22:U36) -> 0 | V21: =SUM(V22:V36) -> 0 | W21: =SUM(W22:W36) -> 0 | X21: =SUM(X22:X36) -> 0 | Y21: =SUM(Y22:Y36) -> 0 | ... CE21: =SUM(CE22:CE36) -> 0
Q22: =$Q$6 | R22: =SUMIF($X$2:$CE$2,R$2,$X22:$CE22) -> 0 | S22: =SUMIF($X$2:$CE$2,S$2,$X22:$CE22) -> 0 | T22: =SUMIF($X$2:$CE$2,T$2,$X22:$CE22) -> 0 | U22: =SUMIF($X$2:$CE$2,U$2,$X22:$CE22) -> 0 | V22: =SUMIF($X$2:$CE$2,V$2,$X22:$CE22) -> 0 | W22: 0 | X22: =X6*X38 -> 0 | Y22: =Y6*Y38 -> 0 | Z22: =Z6*Z38 -> 0 | AA22: =AA6*AA38 -> 0 | AB22: =AB6*AB38 -> 0 | AC22: =AC6*AC38 -> 0 | AD22: =AD6*AD38 -> 0 | AE22: =AE6*AE38 -> 0 | ... CE22: =CE6*CE38 -> 0
Q23: =$Q$7 | R23: =SUMIF($X$2:$CE$2,R$2,$X23:$CE23) -> 0 | S23: =SUMIF($X$2:$CE$2,S$2,$X23:$CE23) -> 0 | T23: =SUMIF($X$2:$CE$2,T$2,$X23:$CE23) -> 0 | U23: =SUMIF($X$2:$CE$2,U$2,$X23:$CE23) -> 0 | V23: =SUMIF($X$2:$CE$2,V$2,$X23:$CE23) -> 0 | W23: 0 | X23: =X7*X39 -> 0 | Y23: =Y7*Y39 -> 0 | Z23: =Z7*Z39 -> 0 | AA23: =AA7*AA39 -> 0 | AB23: =AB7*AB39 -> 0 | AC23: =AC7*AC39 -> 0 | AD23: =AD7*AD39 -> 0 | AE23: =AE7*AE39 -> 0 | ... CE23: =CE7*CE39 -> 0
Q24: =$Q$8 | R24: =SUMIF($X$2:$CE$2,R$2,$X24:$CE24) -> 0 | S24: =SUMIF($X$2:$CE$2,S$2,$X24:$CE24) -> 0 | T24: =SUMIF($X$2:$CE$2,T$2,$X24:$CE24) -> 0 | U24: =SUMIF($X$2:$CE$2,U$2,$X24:$CE24) -> 0 | V24: =SUMIF($X$2:$CE$2,V$2,$X24:$CE24) -> 0 | W24: 0 | X24: =X8*X40 -> 0 | Y24: =Y8*Y40 -> 0 | Z24: =Z8*Z40 -> 0 | AA24: =AA8*AA40 -> 0 | AB24: =AB8*AB40 -> 0 | AC24: =AC8*AC40 -> 0 | AD24: =AD8*AD40 -> 0 | AE24: =AE8*AE40 -> 0 | ... CE24: =CE8*CE40 -> 0
Q25: =$Q$9 | R25: =SUMIF($X$2:$CE$2,R$2,$X25:$CE25) -> 0 | S25: =SUMIF($X$2:$CE$2,S$2,$X25:$CE25) -> 0 | T25: =SUMIF($X$2:$CE$2,T$2,$X25:$CE25) -> 0 | U25: =SUMIF($X$2:$CE$2,U$2,$X25:$CE25) -> 0 | V25: =SUMIF($X$2:$CE$2,V$2,$X25:$CE25) -> 0 | W25: 0 | X25: =X9*X41 -> 0 | Y25: =Y9*Y41 -> 0 | Z25: =Z9*Z41 -> 0 | AA25: =AA9*AA41 -> 0 | AB25: =AB9*AB41 -> 0 | AC25: =AC9*AC41 -> 0 | AD25: =AD9*AD41 -> 0 | AE25: =AE9*AE41 -> 0 | ... CE25: =CE9*CE41 -> 0
Q26: =$Q$10 | R26: =SUMIF($X$2:$CE$2,R$2,$X26:$CE26) -> 0 | S26: =SUMIF($X$2:$CE$2,S$2,$X26:$CE26) -> 0 | T26: =SUMIF($X$2:$CE$2,T$2,$X26:$CE26) -> 0 | U26: =SUMIF($X$2:$CE$2,U$2,$X26:$CE26) -> 0 | V26: =SUMIF($X$2:$CE$2,V$2,$X26:$CE26) -> 0 | W26: 0 | X26: =X10*X42 -> 0 | Y26: =Y10*Y42 -> 0 | Z26: =Z10*Z42 -> 0 | AA26: =AA10*AA42 -> 0 | AB26: =AB10*AB42 -> 0 | AC26: =AC10*AC42 -> 0 | AD26: =AD10*AD42 -> 0 | AE26: =AE10*AE42 -> 0 | ... CE26: =CE10*CE42 -> 0
Q27: =$Q$11 | R27: =SUMIF($X$2:$CE$2,R$2,$X27:$CE27) -> 0 | S27: =SUMIF($X$2:$CE$2,S$2,$X27:$CE27) -> 0 | T27: =SUMIF($X$2:$CE$2,T$2,$X27:$CE27) -> 0 | U27: =SUMIF($X$2:$CE$2,U$2,$X27:$CE27) -> 0 | V27: =SUMIF($X$2:$CE$2,V$2,$X27:$CE27) -> 0 | W27: 0 | X27: =X11*X43 -> 0 | Y27: =Y11*Y43 -> 0 | Z27: =Z11*Z43 -> 0 | AA27: =AA11*AA43 -> 0 | AB27: =AB11*AB43 -> 0 | AC27: =AC11*AC43 -> 0 | AD27: =AD11*AD43 -> 0 | AE27: =AE11*AE43 -> 0 | ... CE27: =CE11*CE43 -> 0
Q28: =$Q$12 | R28: =SUMIF($X$2:$CE$2,R$2,$X28:$CE28) -> 0 | S28: =SUMIF($X$2:$CE$2,S$2,$X28:$CE28) -> 0 | T28: =SUMIF($X$2:$CE$2,T$2,$X28:$CE28) -> 0 | U28: =SUMIF($X$2:$CE$2,U$2,$X28:$CE28) -> 0 | V28: =SUMIF($X$2:$CE$2,V$2,$X28:$CE28) -> 0 | W28: 0 | X28: =X12*X44 -> 0 | Y28: =Y12*Y44 -> 0 | Z28: =Z12*Z44 -> 0 | AA28: =AA12*AA44 -> 0 | AB28: =AB12*AB44 -> 0 | AC28: =AC12*AC44 -> 0 | AD28: =AD12*AD44 -> 0 | AE28: =AE12*AE44 -> 0 | ... CE28: =CE12*CE44 -> 0
Q29: =$Q$13 | R29: =SUMIF($X$2:$CE$2,R$2,$X29:$CE29) -> 0 | S29: =SUMIF($X$2:$CE$2,S$2,$X29:$CE29) -> 0 | T29: =SUMIF($X$2:$CE$2,T$2,$X29:$CE29) -> 0 | U29: =SUMIF($X$2:$CE$2,U$2,$X29:$CE29) -> 0 | V29: =SUMIF($X$2:$CE$2,V$2,$X29:$CE29) -> 0 | W29: 0 | X29: =X13*X45 -> 0 | Y29: =Y13*Y45 -> 0 | Z29: =Z13*Z45 -> 0 | AA29: =AA13*AA45 -> 0 | AB29: =AB13*AB45 -> 0 | AC29: =AC13*AC45 -> 0 | AD29: =AD13*AD45 -> 0 | AE29: =AE13*AE45 -> 0 | ... CE29: =CE13*CE45 -> 0
Q30: =$Q$14 | R30: =SUMIF($X$2:$CE$2,R$2,$X30:$CE30) -> 0 | S30: =SUMIF($X$2:$CE$2,S$2,$X30:$CE30) -> 0 | T30: =SUMIF($X$2:$CE$2,T$2,$X30:$CE30) -> 0 | U30: =SUMIF($X$2:$CE$2,U$2,$X30:$CE30) -> 0 | V30: =SUMIF($X$2:$CE$2,V$2,$X30:$CE30) -> 0 | W30: 0 | X30: =X14*X46 -> 0 | Y30: =Y14*Y46 -> 0 | Z30: =Z14*Z46 -> 0 | AA30: =AA14*AA46 -> 0 | AB30: =AB14*AB46 -> 0 | AC30: =AC14*AC46 -> 0 | AD30: =AD14*AD46 -> 0 | AE30: =AE14*AE46 -> 0 | ... CE30: =CE14*CE46 -> 0
Q31: =$Q$15 | R31: =SUMIF($X$2:$CE$2,R$2,$X31:$CE31) -> 0 | S31: =SUMIF($X$2:$CE$2,S$2,$X31:$CE31) -> 0 | T31: =SUMIF($X$2:$CE$2,T$2,$X31:$CE31) -> 0 | U31: =SUMIF($X$2:$CE$2,U$2,$X31:$CE31) -> 0 | V31: =SUMIF($X$2:$CE$2,V$2,$X31:$CE31) -> 0 | W31: 0 | X31: =X15*X47 -> 0 | Y31: =Y15*Y47 -> 0 | Z31: =Z15*Z47 -> 0 | AA31: =AA15*AA47 -> 0 | AB31: =AB15*AB47 -> 0 | AC31: =AC15*AC47 -> 0 | AD31: =AD15*AD47 -> 0 | AE31: =AE15*AE47 -> 0 | ... CE31: =CE15*CE47 -> 0
Q32: =$Q$16 | R32: =SUMIF($X$2:$CE$2,R$2,$X32:$CE32) -> 0 | S32: =SUMIF($X$2:$CE$2,S$2,$X32:$CE32) -> 0 | T32: =SUMIF($X$2:$CE$2,T$2,$X32:$CE32) -> 0 | U32: =SUMIF($X$2:$CE$2,U$2,$X32:$CE32) -> 0 | V32: =SUMIF($X$2:$CE$2,V$2,$X32:$CE32) -> 0 | W32: 0 | X32: =X16*X48 -> 0 | Y32: =Y16*Y48 -> 0 | Z32: =Z16*Z48 -> 0 | AA32: =AA16*AA48 -> 0 | AB32: =AB16*AB48 -> 0 | AC32: =AC16*AC48 -> 0 | AD32: =AD16*AD48 -> 0 | AE32: =AE16*AE48 -> 0 | ... CE32: =CE16*CE48 -> 0
Q33: =$Q$17 | R33: =SUMIF($X$2:$CE$2,R$2,$X33:$CE33) -> 0 | S33: =SUMIF($X$2:$CE$2,S$2,$X33:$CE33) -> 0 | T33: =SUMIF($X$2:$CE$2,T$2,$X33:$CE33) -> 0 | U33: =SUMIF($X$2:$CE$2,U$2,$X33:$CE33) -> 0 | V33: =SUMIF($X$2:$CE$2,V$2,$X33:$CE33) -> 0 | W33: 0 | X33: =X17*X49 -> 0 | Y33: =Y17*Y49 -> 0 | Z33: =Z17*Z49 -> 0 | AA33: =AA17*AA49 -> 0 | AB33: =AB17*AB49 -> 0 | AC33: =AC17*AC49 -> 0 | AD33: =AD17*AD49 -> 0 | AE33: =AE17*AE49 -> 0 | ... CE33: =CE17*CE49 -> 0
Q34: =$Q$18 | R34: =SUMIF($X$2:$CE$2,R$2,$X34:$CE34) -> 0 | S34: =SUMIF($X$2:$CE$2,S$2,$X34:$CE34) -> 0 | T34: =SUMIF($X$2:$CE$2,T$2,$X34:$CE34) -> 0 | U34: =SUMIF($X$2:$CE$2,U$2,$X34:$CE34) -> 0 | V34: =SUMIF($X$2:$CE$2,V$2,$X34:$CE34) -> 0 | W34: 0 | X34: =X18*X50 -> 0 | Y34: =Y18*Y50 -> 0 | Z34: =Z18*Z50 -> 0 | AA34: =AA18*AA50 -> 0 | AB34: =AB18*AB50 -> 0 | AC34: =AC18*AC50 -> 0 | AD34: =AD18*AD50 -> 0 | AE34: =AE18*AE50 -> 0 | ... CE34: =CE18*CE50 -> 0
Q35: =$Q$19 | R35: =SUMIF($X$2:$CE$2,R$2,$X35:$CE35) -> 0 | S35: =SUMIF($X$2:$CE$2,S$2,$X35:$CE35) -> 0 | T35: =SUMIF($X$2:$CE$2,T$2,$X35:$CE35) -> 0 | U35: =SUMIF($X$2:$CE$2,U$2,$X35:$CE35) -> 0 | V35: =SUMIF($X$2:$CE$2,V$2,$X35:$CE35) -> 0 | W35: 0 | X35: =X19*X51 -> 0 | Y35: =Y19*Y51 -> 0 | Z35: =Z19*Z51 -> 0 | AA35: =AA19*AA51 -> 0 | AB35: =AB19*AB51 -> 0 | AC35: =AC19*AC51 -> 0 | AD35: =AD19*AD51 -> 0 | AE35: =AE19*AE51 -> 0 | ... CE35: =CE19*CE51 -> 0
Q36: =$Q$20 | R36: =SUMIF($X$2:$CE$2,R$2,$X36:$CE36) -> 0 | S36: =SUMIF($X$2:$CE$2,S$2,$X36:$CE36) -> 0 | T36: =SUMIF($X$2:$CE$2,T$2,$X36:$CE36) -> 0 | U36: =SUMIF($X$2:$CE$2,U$2,$X36:$CE36) -> 0 | V36: =SUMIF($X$2:$CE$2,V$2,$X36:$CE36) -> 0 | W36: 0 | X36: =X20*X52 -> 0 | Y36: =Y20*Y52 -> 0 | Z36: =Z20*Z52 -> 0 | AA36: =AA20*AA52 -> 0 | AB36: =AB20*AB52 -> 0 | AC36: =AC20*AC52 -> 0 | AD36: =AD20*AD52 -> 0 | AE36: =AE20*AE52 -> 0 | ... CE36: =CE20*CE52 -> 0
Q37: Reno Rent Total | R37: =IFERROR(SUMIF($X$2:$CE$2,R$2,$X21:$CE21)/SUMIF($X$2:$CE$2,R$2,$X5:$CE5),0) -> 0 | S37: =IFERROR(SUMIF($X$2:$CE$2,S$2,$X21:$CE21)/SUMIF($X$2:$CE$2,S$2,$X5:$CE5),0) -> 0 | T37: =IFERROR(SUMIF($X$2:$CE$2,T$2,$X21:$CE21)/SUMIF($X$2:$CE$2,T$2,$X5:$CE5),0) -> 0 | U37: =IFERROR(SUMIF($X$2:$CE$2,U$2,$X21:$CE21)/SUMIF($X$2:$CE$2,U$2,$X5:$CE5),0) -> 0 | V37: =IFERROR(SUMIF($X$2:$CE$2,V$2,$X21:$CE21)/SUMIF($X$2:$CE$2,V$2,$X5:$CE5),0) -> 0 | W37: =IFERROR(W21/W5,0) -> 0 | X37: =IFERROR(X21/X5,0) -> 0 | Y37: =IFERROR(Y21/Y5,0) -> 0 | Z37: =IFERROR(Z21/Z5,0) -> 0 | AA37: =IFERROR(AA21/AA5,0) -> 0 | AB37: =IFERROR(AB21/AB5,0) -> 0 | AC37: =IFERROR(AC21/AC5,0) -> 0 | AD37: =IFERROR(AD21/AD5,0) -> 0 | ... CE37: =IFERROR(CE21/CE5,0) -> 0
Q38: =$Q$6 | R38: =IFERROR(SUMIF($X$2:$CE$2,R$2,$X22:$CE22)/SUMIF($X$2:$CE$2,R$2,$X6:$CE6),0) -> 0 | S38: =IFERROR(SUMIF($X$2:$CE$2,S$2,$X22:$CE22)/SUMIF($X$2:$CE$2,S$2,$X6:$CE6),0) -> 0 | T38: =IFERROR(SUMIF($X$2:$CE$2,T$2,$X22:$CE22)/SUMIF($X$2:$CE$2,T$2,$X6:$CE6),0) -> 0 | U38: =IFERROR(SUMIF($X$2:$CE$2,U$2,$X22:$CE22)/SUMIF($X$2:$CE$2,U$2,$X6:$CE6),0) -> 0 | V38: =IFERROR(SUMIF($X$2:$CE$2,V$2,$X22:$CE22)/SUMIF($X$2:$CE$2,V$2,$X6:$CE6),0) -> 0 | W38: =IF(SUM(R6:V6)>0,'UW Model'!T28,0) -> 0 | X38: =HLOOKUP((X$2-1)*12,$W$3:$CE$52,ROW()-2,0)*(1+(HLOOKUP(X$2,'UW Model'!$M$103:$Q$104,2,0)/12)*(X$3-((X$2-1)*12))) -> 0 | Y38: =HLOOKUP((Y$2-1)*12,$W$3:$CE$52,ROW()-2,0)*(1+(HLOOKUP(Y$2,'UW Model'!$M$103:$Q$104,2,0)/12)*(Y$3-((Y$2-1)*12))) -> 0 | Z38: =HLOOKUP((Z$2-1)*12,$W$3:$CE$52,ROW()-2,0)*(1+(HLOOKUP(Z$2,'UW Model'!$M$103:$Q$104,2,0)/12)*(Z$3-((Z$2-1)*12))) -> 0 | AA38: =HLOOKUP((AA$2-1)*12,$W$3:$CE$52,ROW()-2,0)*(1+(HLOOKUP(AA$2,'UW Model'!$M$103:$Q$104,2,0)/12)*(AA$3-((AA$2-1)*12))) -> 0 | AB38: =HLOOKUP((AB$2-1)*12,$W$3:$CE$52,ROW()-2,0)*(1+(HLOOKUP(AB$2,'UW Model'!$M$103:$Q$104,2,0)/12)*(AB$3-((AB$2-1)*12))) -> 0 | AC38: =HLOOKUP((AC$2-1)*12,$W$3:$CE$52,ROW()-2,0)*(1+(HLOOKUP(AC$2,'UW Model'!$M$103:$Q$104,2,0)/12)*(AC$3-((AC$2-1)*12))) -> 0 | AD38: =HLOOKUP((AD$2-1)*12,$W$3:$CE$52,ROW()-2,0)*(1+(HLOOKUP(AD$2,'UW Model'!$M$103:$Q$104,2,0)/12)*(AD$3-((AD$2-1)*12))) -> 0 | AE38: =HLOOKUP((AE$2-1)*12,$W$3:$CE$52,ROW()-2,0)*(1+(HLOOKUP(AE$2,'UW Model'!$M$103:$Q$104,2,0)/12)*(AE$3-((AE$2-1)*12))) -> 0 | ... CE38: =HLOOKUP((CE$2-1)*12,$W$3:$CE$52,ROW()-2,0)*(1+(HLOOKUP(CE$2,'UW Model'!$M$103:$Q$104,2,0)/12)*(CE$3-((CE$2-1)*12))) -> 0
Q39: =$Q$7 | R39: =IFERROR(SUMIF($X$2:$CE$2,R$2,$X23:$CE23)/SUMIF($X$2:$CE$2,R$2,$X7:$CE7),0) -> 0 | S39: =IFERROR(SUMIF($X$2:$CE$2,S$2,$X23:$CE23)/SUMIF($X$2:$CE$2,S$2,$X7:$CE7),0) -> 0 | T39: =IFERROR(SUMIF($X$2:$CE$2,T$2,$X23:$CE23)/SUMIF($X$2:$CE$2,T$2,$X7:$CE7),0) -> 0 | U39: =IFERROR(SUMIF($X$2:$CE$2,U$2,$X23:$CE23)/SUMIF($X$2:$CE$2,U$2,$X7:$CE7),0) -> 0 | V39: =IFERROR(SUMIF($X$2:$CE$2,V$2,$X23:$CE23)/SUMIF($X$2:$CE$2,V$2,$X7:$CE7),0) -> 0 | W39: =IF(SUM(R7:V7)>0,'UW Model'!T29,0) -> 0 | X39: =HLOOKUP((X$2-1)*12,$W$3:$CE$52,ROW()-2,0)*(1+(HLOOKUP(X$2,'UW Model'!$M$103:$Q$104,2,0)/12)*(X$3-((X$2-1)*12))) -> 0 | Y39: =HLOOKUP((Y$2-1)*12,$W$3:$CE$52,ROW()-2,0)*(1+(HLOOKUP(Y$2,'UW Model'!$M$103:$Q$104,2,0)/12)*(Y$3-((Y$2-1)*12))) -> 0 | Z39: =HLOOKUP((Z$2-1)*12,$W$3:$CE$52,ROW()-2,0)*(1+(HLOOKUP(Z$2,'UW Model'!$M$103:$Q$104,2,0)/12)*(Z$3-((Z$2-1)*12))) -> 0 | AA39: =HLOOKUP((AA$2-1)*12,$W$3:$CE$52,ROW()-2,0)*(1+(HLOOKUP(AA$2,'UW Model'!$M$103:$Q$104,2,0)/12)*(AA$3-((AA$2-1)*12))) -> 0 | AB39: =HLOOKUP((AB$2-1)*12,$W$3:$CE$52,ROW()-2,0)*(1+(HLOOKUP(AB$2,'UW Model'!$M$103:$Q$104,2,0)/12)*(AB$3-((AB$2-1)*12))) -> 0 | AC39: =HLOOKUP((AC$2-1)*12,$W$3:$CE$52,ROW()-2,0)*(1+(HLOOKUP(AC$2,'UW Model'!$M$103:$Q$104,2,0)/12)*(AC$3-((AC$2-1)*12))) -> 0 | AD39: =HLOOKUP((AD$2-1)*12,$W$3:$CE$52,ROW()-2,0)*(1+(HLOOKUP(AD$2,'UW Model'!$M$103:$Q$104,2,0)/12)*(AD$3-((AD$2-1)*12))) -> 0 | AE39: =HLOOKUP((AE$2-1)*12,$W$3:$CE$52,ROW()-2,0)*(1+(HLOOKUP(AE$2,'UW Model'!$M$103:$Q$104,2,0)/12)*(AE$3-((AE$2-1)*12))) -> 0 | ... CE39: =HLOOKUP((CE$2-1)*12,$W$3:$CE$52,ROW()-2,0)*(1+(HLOOKUP(CE$2,'UW Model'!$M$103:$Q$104,2,0)/12)*(CE$3-((CE$2-1)*12))) -> 0
Q40: =$Q$8 | R40: =IFERROR(SUMIF($X$2:$CE$2,R$2,$X24:$CE24)/SUMIF($X$2:$CE$2,R$2,$X8:$CE8),0) -> 0 | S40: =IFERROR(SUMIF($X$2:$CE$2,S$2,$X24:$CE24)/SUMIF($X$2:$CE$2,S$2,$X8:$CE8),0) -> 0 | T40: =IFERROR(SUMIF($X$2:$CE$2,T$2,$X24:$CE24)/SUMIF($X$2:$CE$2,T$2,$X8:$CE8),0) -> 0 | U40: =IFERROR(SUMIF($X$2:$CE$2,U$2,$X24:$CE24)/SUMIF($X$2:$CE$2,U$2,$X8:$CE8),0) -> 0 | V40: =IFERROR(SUMIF($X$2:$CE$2,V$2,$X24:$CE24)/SUMIF($X$2:$CE$2,V$2,$X8:$CE8),0) -> 0 | W40: =IF(SUM(R8:V8)>0,'UW Model'!T30,0) -> 0 | X40: =HLOOKUP((X$2-1)*12,$W$3:$CE$52,ROW()-2,0)*(1+(HLOOKUP(X$2,'UW Model'!$M$103:$Q$104,2,0)/12)*(X$3-((X$2-1)*12))) -> 0 | Y40: =HLOOKUP((Y$2-1)*12,$W$3:$CE$52,ROW()-2,0)*(1+(HLOOKUP(Y$2,'UW Model'!$M$103:$Q$104,2,0)/12)*(Y$3-((Y$2-1)*12))) -> 0 | Z40: =HLOOKUP((Z$2-1)*12,$W$3:$CE$52,ROW()-2,0)*(1+(HLOOKUP(Z$2,'UW Model'!$M$103:$Q$104,2,0)/12)*(Z$3-((Z$2-1)*12))) -> 0 | AA40: =HLOOKUP((AA$2-1)*12,$W$3:$CE$52,ROW()-2,0)*(1+(HLOOKUP(AA$2,'UW Model'!$M$103:$Q$104,2,0)/12)*(AA$3-((AA$2-1)*12))) -> 0 | AB40: =HLOOKUP((AB$2-1)*12,$W$3:$CE$52,ROW()-2,0)*(1+(HLOOKUP(AB$2,'UW Model'!$M$103:$Q$104,2,0)/12)*(AB$3-((AB$2-1)*12))) -> 0 | AC40: =HLOOKUP((AC$2-1)*12,$W$3:$CE$52,ROW()-2,0)*(1+(HLOOKUP(AC$2,'UW Model'!$M$103:$Q$104,2,0)/12)*(AC$3-((AC$2-1)*12))) -> 0 | AD40: =HLOOKUP((AD$2-1)*12,$W$3:$CE$52,ROW()-2,0)*(1+(HLOOKUP(AD$2,'UW Model'!$M$103:$Q$104,2,0)/12)*(AD$3-((AD$2-1)*12))) -> 0 | AE40: =HLOOKUP((AE$2-1)*12,$W$3:$CE$52,ROW()-2,0)*(1+(HLOOKUP(AE$2,'UW Model'!$M$103:$Q$104,2,0)/12)*(AE$3-((AE$2-1)*12))) -> 0 | ... CE40: =HLOOKUP((CE$2-1)*12,$W$3:$CE$52,ROW()-2,0)*(1+(HLOOKUP(CE$2,'UW Model'!$M$103:$Q$104,2,0)/12)*(CE$3-((CE$2-1)*12))) -> 0
Q41: =$Q$9 | R41: =IFERROR(SUMIF($X$2:$CE$2,R$2,$X25:$CE25)/SUMIF($X$2:$CE$2,R$2,$X9:$CE9),0) -> 0 | S41: =IFERROR(SUMIF($X$2:$CE$2,S$2,$X25:$CE25)/SUMIF($X$2:$CE$2,S$2,$X9:$CE9),0) -> 0 | T41: =IFERROR(SUMIF($X$2:$CE$2,T$2,$X25:$CE25)/SUMIF($X$2:$CE$2,T$2,$X9:$CE9),0) -> 0 | U41: =IFERROR(SUMIF($X$2:$CE$2,U$2,$X25:$CE25)/SUMIF($X$2:$CE$2,U$2,$X9:$CE9),0) -> 0 | V41: =IFERROR(SUMIF($X$2:$CE$2,V$2,$X25:$CE25)/SUMIF($X$2:$CE$2,V$2,$X9:$CE9),0) -> 0 | W41: =IF(SUM(R9:V9)>0,'UW Model'!T31,0) -> 0 | X41: =HLOOKUP((X$2-1)*12,$W$3:$CE$52,ROW()-2,0)*(1+(HLOOKUP(X$2,'UW Model'!$M$103:$Q$104,2,0)/12)*(X$3-((X$2-1)*12))) -> 0 | Y41: =HLOOKUP((Y$2-1)*12,$W$3:$CE$52,ROW()-2,0)*(1+(HLOOKUP(Y$2,'UW Model'!$M$103:$Q$104,2,0)/12)*(Y$3-((Y$2-1)*12))) -> 0 | Z41: =HLOOKUP((Z$2-1)*12,$W$3:$CE$52,ROW()-2,0)*(1+(HLOOKUP(Z$2,'UW Model'!$M$103:$Q$104,2,0)/12)*(Z$3-((Z$2-1)*12))) -> 0 | AA41: =HLOOKUP((AA$2-1)*12,$W$3:$CE$52,ROW()-2,0)*(1+(HLOOKUP(AA$2,'UW Model'!$M$103:$Q$104,2,0)/12)*(AA$3-((AA$2-1)*12))) -> 0 | AB41: =HLOOKUP((AB$2-1)*12,$W$3:$CE$52,ROW()-2,0)*(1+(HLOOKUP(AB$2,'UW Model'!$M$103:$Q$104,2,0)/12)*(AB$3-((AB$2-1)*12))) -> 0 | AC41: =HLOOKUP((AC$2-1)*12,$W$3:$CE$52,ROW()-2,0)*(1+(HLOOKUP(AC$2,'UW Model'!$M$103:$Q$104,2,0)/12)*(AC$3-((AC$2-1)*12))) -> 0 | AD41: =HLOOKUP((AD$2-1)*12,$W$3:$CE$52,ROW()-2,0)*(1+(HLOOKUP(AD$2,'UW Model'!$M$103:$Q$104,2,0)/12)*(AD$3-((AD$2-1)*12))) -> 0 | AE41: =HLOOKUP((AE$2-1)*12,$W$3:$CE$52,ROW()-2,0)*(1+(HLOOKUP(AE$2,'UW Model'!$M$103:$Q$104,2,0)/12)*(AE$3-((AE$2-1)*12))) -> 0 | ... CE41: =HLOOKUP((CE$2-1)*12,$W$3:$CE$52,ROW()-2,0)*(1+(HLOOKUP(CE$2,'UW Model'!$M$103:$Q$104,2,0)/12)*(CE$3-((CE$2-1)*12))) -> 0
Q42: =$Q$10 | R42: =IFERROR(SUMIF($X$2:$CE$2,R$2,$X26:$CE26)/SUMIF($X$2:$CE$2,R$2,$X10:$CE10),0) -> 0 | S42: =IFERROR(SUMIF($X$2:$CE$2,S$2,$X26:$CE26)/SUMIF($X$2:$CE$2,S$2,$X10:$CE10),0) -> 0 | T42: =IFERROR(SUMIF($X$2:$CE$2,T$2,$X26:$CE26)/SUMIF($X$2:$CE$2,T$2,$X10:$CE10),0) -> 0 | U42: =IFERROR(SUMIF($X$2:$CE$2,U$2,$X26:$CE26)/SUMIF($X$2:$CE$2,U$2,$X10:$CE10),0) -> 0 | V42: =IFERROR(SUMIF($X$2:$CE$2,V$2,$X26:$CE26)/SUMIF($X$2:$CE$2,V$2,$X10:$CE10),0) -> 0 | W42: =IF(SUM(R10:V10)>0,'UW Model'!T32,0) -> 0 | X42: =HLOOKUP((X$2-1)*12,$W$3:$CE$52,ROW()-2,0)*(1+(HLOOKUP(X$2,'UW Model'!$M$103:$Q$104,2,0)/12)*(X$3-((X$2-1)*12))) -> 0 | Y42: =HLOOKUP((Y$2-1)*12,$W$3:$CE$52,ROW()-2,0)*(1+(HLOOKUP(Y$2,'UW Model'!$M$103:$Q$104,2,0)/12)*(Y$3-((Y$2-1)*12))) -> 0 | Z42: =HLOOKUP((Z$2-1)*12,$W$3:$CE$52,ROW()-2,0)*(1+(HLOOKUP(Z$2,'UW Model'!$M$103:$Q$104,2,0)/12)*(Z$3-((Z$2-1)*12))) -> 0 | AA42: =HLOOKUP((AA$2-1)*12,$W$3:$CE$52,ROW()-2,0)*(1+(HLOOKUP(AA$2,'UW Model'!$M$103:$Q$104,2,0)/12)*(AA$3-((AA$2-1)*12))) -> 0 | AB42: =HLOOKUP((AB$2-1)*12,$W$3:$CE$52,ROW()-2,0)*(1+(HLOOKUP(AB$2,'UW Model'!$M$103:$Q$104,2,0)/12)*(AB$3-((AB$2-1)*12))) -> 0 | AC42: =HLOOKUP((AC$2-1)*12,$W$3:$CE$52,ROW()-2,0)*(1+(HLOOKUP(AC$2,'UW Model'!$M$103:$Q$104,2,0)/12)*(AC$3-((AC$2-1)*12))) -> 0 | AD42: =HLOOKUP((AD$2-1)*12,$W$3:$CE$52,ROW()-2,0)*(1+(HLOOKUP(AD$2,'UW Model'!$M$103:$Q$104,2,0)/12)*(AD$3-((AD$2-1)*12))) -> 0 | AE42: =HLOOKUP((AE$2-1)*12,$W$3:$CE$52,ROW()-2,0)*(1+(HLOOKUP(AE$2,'UW Model'!$M$103:$Q$104,2,0)/12)*(AE$3-((AE$2-1)*12))) -> 0 | ... CE42: =HLOOKUP((CE$2-1)*12,$W$3:$CE$52,ROW()-2,0)*(1+(HLOOKUP(CE$2,'UW Model'!$M$103:$Q$104,2,0)/12)*(CE$3-((CE$2-1)*12))) -> 0
Q43: =$Q$11 | R43: =IFERROR(SUMIF($X$2:$CE$2,R$2,$X27:$CE27)/SUMIF($X$2:$CE$2,R$2,$X11:$CE11),0) -> 0 | S43: =IFERROR(SUMIF($X$2:$CE$2,S$2,$X27:$CE27)/SUMIF($X$2:$CE$2,S$2,$X11:$CE11),0) -> 0 | T43: =IFERROR(SUMIF($X$2:$CE$2,T$2,$X27:$CE27)/SUMIF($X$2:$CE$2,T$2,$X11:$CE11),0) -> 0 | U43: =IFERROR(SUMIF($X$2:$CE$2,U$2,$X27:$CE27)/SUMIF($X$2:$CE$2,U$2,$X11:$CE11),0) -> 0 | V43: =IFERROR(SUMIF($X$2:$CE$2,V$2,$X27:$CE27)/SUMIF($X$2:$CE$2,V$2,$X11:$CE11),0) -> 0 | W43: =IF(SUM(R11:V11)>0,'UW Model'!T33,0) -> 0 | X43: =HLOOKUP((X$2-1)*12,$W$3:$CE$52,ROW()-2,0)*(1+(HLOOKUP(X$2,'UW Model'!$M$103:$Q$104,2,0)/12)*(X$3-((X$2-1)*12))) -> 0 | Y43: =HLOOKUP((Y$2-1)*12,$W$3:$CE$52,ROW()-2,0)*(1+(HLOOKUP(Y$2,'UW Model'!$M$103:$Q$104,2,0)/12)*(Y$3-((Y$2-1)*12))) -> 0 | Z43: =HLOOKUP((Z$2-1)*12,$W$3:$CE$52,ROW()-2,0)*(1+(HLOOKUP(Z$2,'UW Model'!$M$103:$Q$104,2,0)/12)*(Z$3-((Z$2-1)*12))) -> 0 | AA43: =HLOOKUP((AA$2-1)*12,$W$3:$CE$52,ROW()-2,0)*(1+(HLOOKUP(AA$2,'UW Model'!$M$103:$Q$104,2,0)/12)*(AA$3-((AA$2-1)*12))) -> 0 | AB43: =HLOOKUP((AB$2-1)*12,$W$3:$CE$52,ROW()-2,0)*(1+(HLOOKUP(AB$2,'UW Model'!$M$103:$Q$104,2,0)/12)*(AB$3-((AB$2-1)*12))) -> 0 | AC43: =HLOOKUP((AC$2-1)*12,$W$3:$CE$52,ROW()-2,0)*(1+(HLOOKUP(AC$2,'UW Model'!$M$103:$Q$104,2,0)/12)*(AC$3-((AC$2-1)*12))) -> 0 | AD43: =HLOOKUP((AD$2-1)*12,$W$3:$CE$52,ROW()-2,0)*(1+(HLOOKUP(AD$2,'UW Model'!$M$103:$Q$104,2,0)/12)*(AD$3-((AD$2-1)*12))) -> 0 | AE43: =HLOOKUP((AE$2-1)*12,$W$3:$CE$52,ROW()-2,0)*(1+(HLOOKUP(AE$2,'UW Model'!$M$103:$Q$104,2,0)/12)*(AE$3-((AE$2-1)*12))) -> 0 | ... CE43: =HLOOKUP((CE$2-1)*12,$W$3:$CE$52,ROW()-2,0)*(1+(HLOOKUP(CE$2,'UW Model'!$M$103:$Q$104,2,0)/12)*(CE$3-((CE$2-1)*12))) -> 0
Q44: =$Q$12 | R44: =IFERROR(SUMIF($X$2:$CE$2,R$2,$X28:$CE28)/SUMIF($X$2:$CE$2,R$2,$X12:$CE12),0) -> 0 | S44: =IFERROR(SUMIF($X$2:$CE$2,S$2,$X28:$CE28)/SUMIF($X$2:$CE$2,S$2,$X12:$CE12),0) -> 0 | T44: =IFERROR(SUMIF($X$2:$CE$2,T$2,$X28:$CE28)/SUMIF($X$2:$CE$2,T$2,$X12:$CE12),0) -> 0 | U44: =IFERROR(SUMIF($X$2:$CE$2,U$2,$X28:$CE28)/SUMIF($X$2:$CE$2,U$2,$X12:$CE12),0) -> 0 | V44: =IFERROR(SUMIF($X$2:$CE$2,V$2,$X28:$CE28)/SUMIF($X$2:$CE$2,V$2,$X12:$CE12),0) -> 0 | W44: =IF(SUM(R12:V12)>0,'UW Model'!T34,0) -> 0 | X44: =HLOOKUP((X$2-1)*12,$W$3:$CE$52,ROW()-2,0)*(1+(HLOOKUP(X$2,'UW Model'!$M$103:$Q$104,2,0)/12)*(X$3-((X$2-1)*12))) -> 0 | Y44: =HLOOKUP((Y$2-1)*12,$W$3:$CE$52,ROW()-2,0)*(1+(HLOOKUP(Y$2,'UW Model'!$M$103:$Q$104,2,0)/12)*(Y$3-((Y$2-1)*12))) -> 0 | Z44: =HLOOKUP((Z$2-1)*12,$W$3:$CE$52,ROW()-2,0)*(1+(HLOOKUP(Z$2,'UW Model'!$M$103:$Q$104,2,0)/12)*(Z$3-((Z$2-1)*12))) -> 0 | AA44: =HLOOKUP((AA$2-1)*12,$W$3:$CE$52,ROW()-2,0)*(1+(HLOOKUP(AA$2,'UW Model'!$M$103:$Q$104,2,0)/12)*(AA$3-((AA$2-1)*12))) -> 0 | AB44: =HLOOKUP((AB$2-1)*12,$W$3:$CE$52,ROW()-2,0)*(1+(HLOOKUP(AB$2,'UW Model'!$M$103:$Q$104,2,0)/12)*(AB$3-((AB$2-1)*12))) -> 0 | AC44: =HLOOKUP((AC$2-1)*12,$W$3:$CE$52,ROW()-2,0)*(1+(HLOOKUP(AC$2,'UW Model'!$M$103:$Q$104,2,0)/12)*(AC$3-((AC$2-1)*12))) -> 0 | AD44: =HLOOKUP((AD$2-1)*12,$W$3:$CE$52,ROW()-2,0)*(1+(HLOOKUP(AD$2,'UW Model'!$M$103:$Q$104,2,0)/12)*(AD$3-((AD$2-1)*12))) -> 0 | AE44: =HLOOKUP((AE$2-1)*12,$W$3:$CE$52,ROW()-2,0)*(1+(HLOOKUP(AE$2,'UW Model'!$M$103:$Q$104,2,0)/12)*(AE$3-((AE$2-1)*12))) -> 0 | ... CE44: =HLOOKUP((CE$2-1)*12,$W$3:$CE$52,ROW()-2,0)*(1+(HLOOKUP(CE$2,'UW Model'!$M$103:$Q$104,2,0)/12)*(CE$3-((CE$2-1)*12))) -> 0
Q45: =$Q$13 | R45: =IFERROR(SUMIF($X$2:$CE$2,R$2,$X29:$CE29)/SUMIF($X$2:$CE$2,R$2,$X13:$CE13),0) -> 0 | S45: =IFERROR(SUMIF($X$2:$CE$2,S$2,$X29:$CE29)/SUMIF($X$2:$CE$2,S$2,$X13:$CE13),0) -> 0 | T45: =IFERROR(SUMIF($X$2:$CE$2,T$2,$X29:$CE29)/SUMIF($X$2:$CE$2,T$2,$X13:$CE13),0) -> 0 | U45: =IFERROR(SUMIF($X$2:$CE$2,U$2,$X29:$CE29)/SUMIF($X$2:$CE$2,U$2,$X13:$CE13),0) -> 0 | V45: =IFERROR(SUMIF($X$2:$CE$2,V$2,$X29:$CE29)/SUMIF($X$2:$CE$2,V$2,$X13:$CE13),0) -> 0 | W45: =IF(SUM(R13:V13)>0,'UW Model'!T35,0) -> 0 | X45: =HLOOKUP((X$2-1)*12,$W$3:$CE$52,ROW()-2,0)*(1+(HLOOKUP(X$2,'UW Model'!$M$103:$Q$104,2,0)/12)*(X$3-((X$2-1)*12))) -> 0 | Y45: =HLOOKUP((Y$2-1)*12,$W$3:$CE$52,ROW()-2,0)*(1+(HLOOKUP(Y$2,'UW Model'!$M$103:$Q$104,2,0)/12)*(Y$3-((Y$2-1)*12))) -> 0 | Z45: =HLOOKUP((Z$2-1)*12,$W$3:$CE$52,ROW()-2,0)*(1+(HLOOKUP(Z$2,'UW Model'!$M$103:$Q$104,2,0)/12)*(Z$3-((Z$2-1)*12))) -> 0 | AA45: =HLOOKUP((AA$2-1)*12,$W$3:$CE$52,ROW()-2,0)*(1+(HLOOKUP(AA$2,'UW Model'!$M$103:$Q$104,2,0)/12)*(AA$3-((AA$2-1)*12))) -> 0 | AB45: =HLOOKUP((AB$2-1)*12,$W$3:$CE$52,ROW()-2,0)*(1+(HLOOKUP(AB$2,'UW Model'!$M$103:$Q$104,2,0)/12)*(AB$3-((AB$2-1)*12))) -> 0 | AC45: =HLOOKUP((AC$2-1)*12,$W$3:$CE$52,ROW()-2,0)*(1+(HLOOKUP(AC$2,'UW Model'!$M$103:$Q$104,2,0)/12)*(AC$3-((AC$2-1)*12))) -> 0 | AD45: =HLOOKUP((AD$2-1)*12,$W$3:$CE$52,ROW()-2,0)*(1+(HLOOKUP(AD$2,'UW Model'!$M$103:$Q$104,2,0)/12)*(AD$3-((AD$2-1)*12))) -> 0 | AE45: =HLOOKUP((AE$2-1)*12,$W$3:$CE$52,ROW()-2,0)*(1+(HLOOKUP(AE$2,'UW Model'!$M$103:$Q$104,2,0)/12)*(AE$3-((AE$2-1)*12))) -> 0 | ... CE45: =HLOOKUP((CE$2-1)*12,$W$3:$CE$52,ROW()-2,0)*(1+(HLOOKUP(CE$2,'UW Model'!$M$103:$Q$104,2,0)/12)*(CE$3-((CE$2-1)*12))) -> 0
Q46: =$Q$14 | R46: =IFERROR(SUMIF($X$2:$CE$2,R$2,$X30:$CE30)/SUMIF($X$2:$CE$2,R$2,$X14:$CE14),0) -> 0 | S46: =IFERROR(SUMIF($X$2:$CE$2,S$2,$X30:$CE30)/SUMIF($X$2:$CE$2,S$2,$X14:$CE14),0) -> 0 | T46: =IFERROR(SUMIF($X$2:$CE$2,T$2,$X30:$CE30)/SUMIF($X$2:$CE$2,T$2,$X14:$CE14),0) -> 0 | U46: =IFERROR(SUMIF($X$2:$CE$2,U$2,$X30:$CE30)/SUMIF($X$2:$CE$2,U$2,$X14:$CE14),0) -> 0 | V46: =IFERROR(SUMIF($X$2:$CE$2,V$2,$X30:$CE30)/SUMIF($X$2:$CE$2,V$2,$X14:$CE14),0) -> 0 | W46: =IF(SUM(R14:V14)>0,'UW Model'!T36,0) -> 0 | X46: =HLOOKUP((X$2-1)*12,$W$3:$CE$52,ROW()-2,0)*(1+(HLOOKUP(X$2,'UW Model'!$M$103:$Q$104,2,0)/12)*(X$3-((X$2-1)*12))) -> 0 | Y46: =HLOOKUP((Y$2-1)*12,$W$3:$CE$52,ROW()-2,0)*(1+(HLOOKUP(Y$2,'UW Model'!$M$103:$Q$104,2,0)/12)*(Y$3-((Y$2-1)*12))) -> 0 | Z46: =HLOOKUP((Z$2-1)*12,$W$3:$CE$52,ROW()-2,0)*(1+(HLOOKUP(Z$2,'UW Model'!$M$103:$Q$104,2,0)/12)*(Z$3-((Z$2-1)*12))) -> 0 | AA46: =HLOOKUP((AA$2-1)*12,$W$3:$CE$52,ROW()-2,0)*(1+(HLOOKUP(AA$2,'UW Model'!$M$103:$Q$104,2,0)/12)*(AA$3-((AA$2-1)*12))) -> 0 | AB46: =HLOOKUP((AB$2-1)*12,$W$3:$CE$52,ROW()-2,0)*(1+(HLOOKUP(AB$2,'UW Model'!$M$103:$Q$104,2,0)/12)*(AB$3-((AB$2-1)*12))) -> 0 | AC46: =HLOOKUP((AC$2-1)*12,$W$3:$CE$52,ROW()-2,0)*(1+(HLOOKUP(AC$2,'UW Model'!$M$103:$Q$104,2,0)/12)*(AC$3-((AC$2-1)*12))) -> 0 | AD46: =HLOOKUP((AD$2-1)*12,$W$3:$CE$52,ROW()-2,0)*(1+(HLOOKUP(AD$2,'UW Model'!$M$103:$Q$104,2,0)/12)*(AD$3-((AD$2-1)*12))) -> 0 | AE46: =HLOOKUP((AE$2-1)*12,$W$3:$CE$52,ROW()-2,0)*(1+(HLOOKUP(AE$2,'UW Model'!$M$103:$Q$104,2,0)/12)*(AE$3-((AE$2-1)*12))) -> 0 | ... CE46: =HLOOKUP((CE$2-1)*12,$W$3:$CE$52,ROW()-2,0)*(1+(HLOOKUP(CE$2,'UW Model'!$M$103:$Q$104,2,0)/12)*(CE$3-((CE$2-1)*12))) -> 0
Q47: =$Q$15 | R47: =IFERROR(SUMIF($X$2:$CE$2,R$2,$X31:$CE31)/SUMIF($X$2:$CE$2,R$2,$X15:$CE15),0) -> 0 | S47: =IFERROR(SUMIF($X$2:$CE$2,S$2,$X31:$CE31)/SUMIF($X$2:$CE$2,S$2,$X15:$CE15),0) -> 0 | T47: =IFERROR(SUMIF($X$2:$CE$2,T$2,$X31:$CE31)/SUMIF($X$2:$CE$2,T$2,$X15:$CE15),0) -> 0 | U47: =IFERROR(SUMIF($X$2:$CE$2,U$2,$X31:$CE31)/SUMIF($X$2:$CE$2,U$2,$X15:$CE15),0) -> 0 | V47: =IFERROR(SUMIF($X$2:$CE$2,V$2,$X31:$CE31)/SUMIF($X$2:$CE$2,V$2,$X15:$CE15),0) -> 0 | W47: =IF(SUM(R15:V15)>0,'UW Model'!T37,0) -> 0 | X47: =HLOOKUP((X$2-1)*12,$W$3:$CE$52,ROW()-2,0)*(1+(HLOOKUP(X$2,'UW Model'!$M$103:$Q$104,2,0)/12)*(X$3-((X$2-1)*12))) -> 0 | Y47: =HLOOKUP((Y$2-1)*12,$W$3:$CE$52,ROW()-2,0)*(1+(HLOOKUP(Y$2,'UW Model'!$M$103:$Q$104,2,0)/12)*(Y$3-((Y$2-1)*12))) -> 0 | Z47: =HLOOKUP((Z$2-1)*12,$W$3:$CE$52,ROW()-2,0)*(1+(HLOOKUP(Z$2,'UW Model'!$M$103:$Q$104,2,0)/12)*(Z$3-((Z$2-1)*12))) -> 0 | AA47: =HLOOKUP((AA$2-1)*12,$W$3:$CE$52,ROW()-2,0)*(1+(HLOOKUP(AA$2,'UW Model'!$M$103:$Q$104,2,0)/12)*(AA$3-((AA$2-1)*12))) -> 0 | AB47: =HLOOKUP((AB$2-1)*12,$W$3:$CE$52,ROW()-2,0)*(1+(HLOOKUP(AB$2,'UW Model'!$M$103:$Q$104,2,0)/12)*(AB$3-((AB$2-1)*12))) -> 0 | AC47: =HLOOKUP((AC$2-1)*12,$W$3:$CE$52,ROW()-2,0)*(1+(HLOOKUP(AC$2,'UW Model'!$M$103:$Q$104,2,0)/12)*(AC$3-((AC$2-1)*12))) -> 0 | AD47: =HLOOKUP((AD$2-1)*12,$W$3:$CE$52,ROW()-2,0)*(1+(HLOOKUP(AD$2,'UW Model'!$M$103:$Q$104,2,0)/12)*(AD$3-((AD$2-1)*12))) -> 0 | AE47: =HLOOKUP((AE$2-1)*12,$W$3:$CE$52,ROW()-2,0)*(1+(HLOOKUP(AE$2,'UW Model'!$M$103:$Q$104,2,0)/12)*(AE$3-((AE$2-1)*12))) -> 0 | ... CE47: =HLOOKUP((CE$2-1)*12,$W$3:$CE$52,ROW()-2,0)*(1+(HLOOKUP(CE$2,'UW Model'!$M$103:$Q$104,2,0)/12)*(CE$3-((CE$2-1)*12))) -> 0
Q48: =$Q$16 | R48: =IFERROR(SUMIF($X$2:$CE$2,R$2,$X32:$CE32)/SUMIF($X$2:$CE$2,R$2,$X16:$CE16),0) -> 0 | S48: =IFERROR(SUMIF($X$2:$CE$2,S$2,$X32:$CE32)/SUMIF($X$2:$CE$2,S$2,$X16:$CE16),0) -> 0 | T48: =IFERROR(SUMIF($X$2:$CE$2,T$2,$X32:$CE32)/SUMIF($X$2:$CE$2,T$2,$X16:$CE16),0) -> 0 | U48: =IFERROR(SUMIF($X$2:$CE$2,U$2,$X32:$CE32)/SUMIF($X$2:$CE$2,U$2,$X16:$CE16),0) -> 0 | V48: =IFERROR(SUMIF($X$2:$CE$2,V$2,$X32:$CE32)/SUMIF($X$2:$CE$2,V$2,$X16:$CE16),0) -> 0 | W48: =IF(SUM(R16:V16)>0,'UW Model'!T38,0) -> 0 | X48: =HLOOKUP((X$2-1)*12,$W$3:$CE$52,ROW()-2,0)*(1+(HLOOKUP(X$2,'UW Model'!$M$103:$Q$104,2,0)/12)*(X$3-((X$2-1)*12))) -> 0 | Y48: =HLOOKUP((Y$2-1)*12,$W$3:$CE$52,ROW()-2,0)*(1+(HLOOKUP(Y$2,'UW Model'!$M$103:$Q$104,2,0)/12)*(Y$3-((Y$2-1)*12))) -> 0 | Z48: =HLOOKUP((Z$2-1)*12,$W$3:$CE$52,ROW()-2,0)*(1+(HLOOKUP(Z$2,'UW Model'!$M$103:$Q$104,2,0)/12)*(Z$3-((Z$2-1)*12))) -> 0 | AA48: =HLOOKUP((AA$2-1)*12,$W$3:$CE$52,ROW()-2,0)*(1+(HLOOKUP(AA$2,'UW Model'!$M$103:$Q$104,2,0)/12)*(AA$3-((AA$2-1)*12))) -> 0 | AB48: =HLOOKUP((AB$2-1)*12,$W$3:$CE$52,ROW()-2,0)*(1+(HLOOKUP(AB$2,'UW Model'!$M$103:$Q$104,2,0)/12)*(AB$3-((AB$2-1)*12))) -> 0 | AC48: =HLOOKUP((AC$2-1)*12,$W$3:$CE$52,ROW()-2,0)*(1+(HLOOKUP(AC$2,'UW Model'!$M$103:$Q$104,2,0)/12)*(AC$3-((AC$2-1)*12))) -> 0 | AD48: =HLOOKUP((AD$2-1)*12,$W$3:$CE$52,ROW()-2,0)*(1+(HLOOKUP(AD$2,'UW Model'!$M$103:$Q$104,2,0)/12)*(AD$3-((AD$2-1)*12))) -> 0 | AE48: =HLOOKUP((AE$2-1)*12,$W$3:$CE$52,ROW()-2,0)*(1+(HLOOKUP(AE$2,'UW Model'!$M$103:$Q$104,2,0)/12)*(AE$3-((AE$2-1)*12))) -> 0 | ... CE48: =HLOOKUP((CE$2-1)*12,$W$3:$CE$52,ROW()-2,0)*(1+(HLOOKUP(CE$2,'UW Model'!$M$103:$Q$104,2,0)/12)*(CE$3-((CE$2-1)*12))) -> 0
Q49: =$Q$17 | R49: =IFERROR(SUMIF($X$2:$CE$2,R$2,$X33:$CE33)/SUMIF($X$2:$CE$2,R$2,$X17:$CE17),0) -> 0 | S49: =IFERROR(SUMIF($X$2:$CE$2,S$2,$X33:$CE33)/SUMIF($X$2:$CE$2,S$2,$X17:$CE17),0) -> 0 | T49: =IFERROR(SUMIF($X$2:$CE$2,T$2,$X33:$CE33)/SUMIF($X$2:$CE$2,T$2,$X17:$CE17),0) -> 0 | U49: =IFERROR(SUMIF($X$2:$CE$2,U$2,$X33:$CE33)/SUMIF($X$2:$CE$2,U$2,$X17:$CE17),0) -> 0 | V49: =IFERROR(SUMIF($X$2:$CE$2,V$2,$X33:$CE33)/SUMIF($X$2:$CE$2,V$2,$X17:$CE17),0) -> 0 | W49: =IF(SUM(R17:V17)>0,'UW Model'!T39,0) -> 0 | X49: =HLOOKUP((X$2-1)*12,$W$3:$CE$52,ROW()-2,0)*(1+(HLOOKUP(X$2,'UW Model'!$M$103:$Q$104,2,0)/12)*(X$3-((X$2-1)*12))) -> 0 | Y49: =HLOOKUP((Y$2-1)*12,$W$3:$CE$52,ROW()-2,0)*(1+(HLOOKUP(Y$2,'UW Model'!$M$103:$Q$104,2,0)/12)*(Y$3-((Y$2-1)*12))) -> 0 | Z49: =HLOOKUP((Z$2-1)*12,$W$3:$CE$52,ROW()-2,0)*(1+(HLOOKUP(Z$2,'UW Model'!$M$103:$Q$104,2,0)/12)*(Z$3-((Z$2-1)*12))) -> 0 | AA49: =HLOOKUP((AA$2-1)*12,$W$3:$CE$52,ROW()-2,0)*(1+(HLOOKUP(AA$2,'UW Model'!$M$103:$Q$104,2,0)/12)*(AA$3-((AA$2-1)*12))) -> 0 | AB49: =HLOOKUP((AB$2-1)*12,$W$3:$CE$52,ROW()-2,0)*(1+(HLOOKUP(AB$2,'UW Model'!$M$103:$Q$104,2,0)/12)*(AB$3-((AB$2-1)*12))) -> 0 | AC49: =HLOOKUP((AC$2-1)*12,$W$3:$CE$52,ROW()-2,0)*(1+(HLOOKUP(AC$2,'UW Model'!$M$103:$Q$104,2,0)/12)*(AC$3-((AC$2-1)*12))) -> 0 | AD49: =HLOOKUP((AD$2-1)*12,$W$3:$CE$52,ROW()-2,0)*(1+(HLOOKUP(AD$2,'UW Model'!$M$103:$Q$104,2,0)/12)*(AD$3-((AD$2-1)*12))) -> 0 | AE49: =HLOOKUP((AE$2-1)*12,$W$3:$CE$52,ROW()-2,0)*(1+(HLOOKUP(AE$2,'UW Model'!$M$103:$Q$104,2,0)/12)*(AE$3-((AE$2-1)*12))) -> 0 | ... CE49: =HLOOKUP((CE$2-1)*12,$W$3:$CE$52,ROW()-2,0)*(1+(HLOOKUP(CE$2,'UW Model'!$M$103:$Q$104,2,0)/12)*(CE$3-((CE$2-1)*12))) -> 0
Q50: =$Q$18 | R50: =IFERROR(SUMIF($X$2:$CE$2,R$2,$X34:$CE34)/SUMIF($X$2:$CE$2,R$2,$X18:$CE18),0) -> 0 | S50: =IFERROR(SUMIF($X$2:$CE$2,S$2,$X34:$CE34)/SUMIF($X$2:$CE$2,S$2,$X18:$CE18),0) -> 0 | T50: =IFERROR(SUMIF($X$2:$CE$2,T$2,$X34:$CE34)/SUMIF($X$2:$CE$2,T$2,$X18:$CE18),0) -> 0 | U50: =IFERROR(SUMIF($X$2:$CE$2,U$2,$X34:$CE34)/SUMIF($X$2:$CE$2,U$2,$X18:$CE18),0) -> 0 | V50: =IFERROR(SUMIF($X$2:$CE$2,V$2,$X34:$CE34)/SUMIF($X$2:$CE$2,V$2,$X18:$CE18),0) -> 0 | W50: =IF(SUM(R18:V18)>0,'UW Model'!T40,0) -> 0 | X50: =HLOOKUP((X$2-1)*12,$W$3:$CE$52,ROW()-2,0)*(1+(HLOOKUP(X$2,'UW Model'!$M$103:$Q$104,2,0)/12)*(X$3-((X$2-1)*12))) -> 0 | Y50: =HLOOKUP((Y$2-1)*12,$W$3:$CE$52,ROW()-2,0)*(1+(HLOOKUP(Y$2,'UW Model'!$M$103:$Q$104,2,0)/12)*(Y$3-((Y$2-1)*12))) -> 0 | Z50: =HLOOKUP((Z$2-1)*12,$W$3:$CE$52,ROW()-2,0)*(1+(HLOOKUP(Z$2,'UW Model'!$M$103:$Q$104,2,0)/12)*(Z$3-((Z$2-1)*12))) -> 0 | AA50: =HLOOKUP((AA$2-1)*12,$W$3:$CE$52,ROW()-2,0)*(1+(HLOOKUP(AA$2,'UW Model'!$M$103:$Q$104,2,0)/12)*(AA$3-((AA$2-1)*12))) -> 0 | AB50: =HLOOKUP((AB$2-1)*12,$W$3:$CE$52,ROW()-2,0)*(1+(HLOOKUP(AB$2,'UW Model'!$M$103:$Q$104,2,0)/12)*(AB$3-((AB$2-1)*12))) -> 0 | AC50: =HLOOKUP((AC$2-1)*12,$W$3:$CE$52,ROW()-2,0)*(1+(HLOOKUP(AC$2,'UW Model'!$M$103:$Q$104,2,0)/12)*(AC$3-((AC$2-1)*12))) -> 0 | AD50: =HLOOKUP((AD$2-1)*12,$W$3:$CE$52,ROW()-2,0)*(1+(HLOOKUP(AD$2,'UW Model'!$M$103:$Q$104,2,0)/12)*(AD$3-((AD$2-1)*12))) -> 0 | AE50: =HLOOKUP((AE$2-1)*12,$W$3:$CE$52,ROW()-2,0)*(1+(HLOOKUP(AE$2,'UW Model'!$M$103:$Q$104,2,0)/12)*(AE$3-((AE$2-1)*12))) -> 0 | ... CE50: =HLOOKUP((CE$2-1)*12,$W$3:$CE$52,ROW()-2,0)*(1+(HLOOKUP(CE$2,'UW Model'!$M$103:$Q$104,2,0)/12)*(CE$3-((CE$2-1)*12))) -> 0
Q51: =$Q$19 | R51: =IFERROR(SUMIF($X$2:$CE$2,R$2,$X35:$CE35)/SUMIF($X$2:$CE$2,R$2,$X19:$CE19),0) -> 0 | S51: =IFERROR(SUMIF($X$2:$CE$2,S$2,$X35:$CE35)/SUMIF($X$2:$CE$2,S$2,$X19:$CE19),0) -> 0 | T51: =IFERROR(SUMIF($X$2:$CE$2,T$2,$X35:$CE35)/SUMIF($X$2:$CE$2,T$2,$X19:$CE19),0) -> 0 | U51: =IFERROR(SUMIF($X$2:$CE$2,U$2,$X35:$CE35)/SUMIF($X$2:$CE$2,U$2,$X19:$CE19),0) -> 0 | V51: =IFERROR(SUMIF($X$2:$CE$2,V$2,$X35:$CE35)/SUMIF($X$2:$CE$2,V$2,$X19:$CE19),0) -> 0 | W51: =IF(SUM(R19:V19)>0,'UW Model'!T41,0) -> 0 | X51: =HLOOKUP((X$2-1)*12,$W$3:$CE$52,ROW()-2,0)*(1+(HLOOKUP(X$2,'UW Model'!$M$103:$Q$104,2,0)/12)*(X$3-((X$2-1)*12))) -> 0 | Y51: =HLOOKUP((Y$2-1)*12,$W$3:$CE$52,ROW()-2,0)*(1+(HLOOKUP(Y$2,'UW Model'!$M$103:$Q$104,2,0)/12)*(Y$3-((Y$2-1)*12))) -> 0 | Z51: =HLOOKUP((Z$2-1)*12,$W$3:$CE$52,ROW()-2,0)*(1+(HLOOKUP(Z$2,'UW Model'!$M$103:$Q$104,2,0)/12)*(Z$3-((Z$2-1)*12))) -> 0 | AA51: =HLOOKUP((AA$2-1)*12,$W$3:$CE$52,ROW()-2,0)*(1+(HLOOKUP(AA$2,'UW Model'!$M$103:$Q$104,2,0)/12)*(AA$3-((AA$2-1)*12))) -> 0 | AB51: =HLOOKUP((AB$2-1)*12,$W$3:$CE$52,ROW()-2,0)*(1+(HLOOKUP(AB$2,'UW Model'!$M$103:$Q$104,2,0)/12)*(AB$3-((AB$2-1)*12))) -> 0 | AC51: =HLOOKUP((AC$2-1)*12,$W$3:$CE$52,ROW()-2,0)*(1+(HLOOKUP(AC$2,'UW Model'!$M$103:$Q$104,2,0)/12)*(AC$3-((AC$2-1)*12))) -> 0 | AD51: =HLOOKUP((AD$2-1)*12,$W$3:$CE$52,ROW()-2,0)*(1+(HLOOKUP(AD$2,'UW Model'!$M$103:$Q$104,2,0)/12)*(AD$3-((AD$2-1)*12))) -> 0 | AE51: =HLOOKUP((AE$2-1)*12,$W$3:$CE$52,ROW()-2,0)*(1+(HLOOKUP(AE$2,'UW Model'!$M$103:$Q$104,2,0)/12)*(AE$3-((AE$2-1)*12))) -> 0 | ... CE51: =HLOOKUP((CE$2-1)*12,$W$3:$CE$52,ROW()-2,0)*(1+(HLOOKUP(CE$2,'UW Model'!$M$103:$Q$104,2,0)/12)*(CE$3-((CE$2-1)*12))) -> 0
Q52: =$Q$20 | R52: =IFERROR(SUMIF($X$2:$CE$2,R$2,$X36:$CE36)/SUMIF($X$2:$CE$2,R$2,$X20:$CE20),0) -> 0 | S52: =IFERROR(SUMIF($X$2:$CE$2,S$2,$X36:$CE36)/SUMIF($X$2:$CE$2,S$2,$X20:$CE20),0) -> 0 | T52: =IFERROR(SUMIF($X$2:$CE$2,T$2,$X36:$CE36)/SUMIF($X$2:$CE$2,T$2,$X20:$CE20),0) -> 0 | U52: =IFERROR(SUMIF($X$2:$CE$2,U$2,$X36:$CE36)/SUMIF($X$2:$CE$2,U$2,$X20:$CE20),0) -> 0 | V52: =IFERROR(SUMIF($X$2:$CE$2,V$2,$X36:$CE36)/SUMIF($X$2:$CE$2,V$2,$X20:$CE20),0) -> 0 | W52: =IF(SUM(R20:V20)>0,'UW Model'!T42,0) -> 0 | X52: =HLOOKUP((X$2-1)*12,$W$3:$CE$52,ROW()-2,0)*(1+(HLOOKUP(X$2,'UW Model'!$M$103:$Q$104,2,0)/12)*(X$3-((X$2-1)*12))) -> 0 | Y52: =HLOOKUP((Y$2-1)*12,$W$3:$CE$52,ROW()-2,0)*(1+(HLOOKUP(Y$2,'UW Model'!$M$103:$Q$104,2,0)/12)*(Y$3-((Y$2-1)*12))) -> 0 | Z52: =HLOOKUP((Z$2-1)*12,$W$3:$CE$52,ROW()-2,0)*(1+(HLOOKUP(Z$2,'UW Model'!$M$103:$Q$104,2,0)/12)*(Z$3-((Z$2-1)*12))) -> 0 | AA52: =HLOOKUP((AA$2-1)*12,$W$3:$CE$52,ROW()-2,0)*(1+(HLOOKUP(AA$2,'UW Model'!$M$103:$Q$104,2,0)/12)*(AA$3-((AA$2-1)*12))) -> 0 | AB52: =HLOOKUP((AB$2-1)*12,$W$3:$CE$52,ROW()-2,0)*(1+(HLOOKUP(AB$2,'UW Model'!$M$103:$Q$104,2,0)/12)*(AB$3-((AB$2-1)*12))) -> 0 | AC52: =HLOOKUP((AC$2-1)*12,$W$3:$CE$52,ROW()-2,0)*(1+(HLOOKUP(AC$2,'UW Model'!$M$103:$Q$104,2,0)/12)*(AC$3-((AC$2-1)*12))) -> 0 | AD52: =HLOOKUP((AD$2-1)*12,$W$3:$CE$52,ROW()-2,0)*(1+(HLOOKUP(AD$2,'UW Model'!$M$103:$Q$104,2,0)/12)*(AD$3-((AD$2-1)*12))) -> 0 | AE52: =HLOOKUP((AE$2-1)*12,$W$3:$CE$52,ROW()-2,0)*(1+(HLOOKUP(AE$2,'UW Model'!$M$103:$Q$104,2,0)/12)*(AE$3-((AE$2-1)*12))) -> 0 | ... CE52: =HLOOKUP((CE$2-1)*12,$W$3:$CE$52,ROW()-2,0)*(1+(HLOOKUP(CE$2,'UW Model'!$M$103:$Q$104,2,0)/12)*(CE$3-((CE$2-1)*12))) -> 0
Q53: Reno Vacancy Loss Total | R53: =SUM(R54:R68) -> 0 | S53: =SUM(S54:S68) -> 0 | T53: =SUM(T54:T68) -> 0 | U53: =SUM(U54:U68) -> 0 | V53: =SUM(V54:V68) -> 0 | W53: =SUM(W54:W68) -> 0 | X53: =SUM(X54:X68) -> 0 | Y53: =SUM(Y54:Y68) -> 0 | ... CE53: =SUM(CE54:CE68) -> 0
Q54: =$Q$6 | R54: =SUMIF($X$2:$CE$2,R$2,$X54:$CE54) -> 0 | S54: =SUMIF($X$2:$CE$2,S$2,$X54:$CE54) -> 0 | T54: =SUMIF($X$2:$CE$2,T$2,$X54:$CE54) -> 0 | U54: =SUMIF($X$2:$CE$2,U$2,$X54:$CE54) -> 0 | V54: =SUMIF($X$2:$CE$2,V$2,$X54:$CE54) -> 0 | W54: =IF(OR(W$1="Reno Start", W$1="Reno End"),Y6-X6,IF(W$1="Rolling",Y6-W6,0))*W118 -> 0 | X54: =IF(OR(X$1="Reno Start", X$1="Reno End"),Z6-Y6,IF(X$1="Rolling",Z6-X6,0))*X118 -> 0 | Y54: =IF(OR(Y$1="Reno Start", Y$1="Reno End"),AA6-Z6,IF(Y$1="Rolling",AA6-Y6,0))*Y118 -> 0 | Z54: =IF(OR(Z$1="Reno Start", Z$1="Reno End"),AB6-AA6,IF(Z$1="Rolling",AB6-Z6,0))*Z118 -> 0 | AA54: =IF(OR(AA$1="Reno Start", AA$1="Reno End"),AC6-AB6,IF(AA$1="Rolling",AC6-AA6,0))*AA118 -> 0 | AB54: =IF(OR(AB$1="Reno Start", AB$1="Reno End"),AD6-AC6,IF(AB$1="Rolling",AD6-AB6,0))*AB118 -> 0 | AC54: =IF(OR(AC$1="Reno Start", AC$1="Reno End"),AE6-AD6,IF(AC$1="Rolling",AE6-AC6,0))*AC118 -> 0 | AD54: =IF(OR(AD$1="Reno Start", AD$1="Reno End"),AF6-AE6,IF(AD$1="Rolling",AF6-AD6,0))*AD118 -> 0 | ... CE54: =IF(OR(CE$1="Reno Start", CE$1="Reno End"),CG6-CF6,IF(CE$1="Rolling",CG6-CE6,0))*CE118 -> 0
Q55: =$Q$7 | R55: =SUMIF($X$2:$CE$2,R$2,$X55:$CE55) -> 0 | S55: =SUMIF($X$2:$CE$2,S$2,$X55:$CE55) -> 0 | T55: =SUMIF($X$2:$CE$2,T$2,$X55:$CE55) -> 0 | U55: =SUMIF($X$2:$CE$2,U$2,$X55:$CE55) -> 0 | V55: =SUMIF($X$2:$CE$2,V$2,$X55:$CE55) -> 0 | W55: =IF(OR(W$1="Reno Start", W$1="Reno End"),Y7-X7,IF(W$1="Rolling",Y7-W7,0))*W119 -> 0 | X55: =IF(OR(X$1="Reno Start", X$1="Reno End"),Z7-Y7,IF(X$1="Rolling",Z7-X7,0))*X119 -> 0 | Y55: =IF(OR(Y$1="Reno Start", Y$1="Reno End"),AA7-Z7,IF(Y$1="Rolling",AA7-Y7,0))*Y119 -> 0 | Z55: =IF(OR(Z$1="Reno Start", Z$1="Reno End"),AB7-AA7,IF(Z$1="Rolling",AB7-Z7,0))*Z119 -> 0 | AA55: =IF(OR(AA$1="Reno Start", AA$1="Reno End"),AC7-AB7,IF(AA$1="Rolling",AC7-AA7,0))*AA119 -> 0 | AB55: =IF(OR(AB$1="Reno Start", AB$1="Reno End"),AD7-AC7,IF(AB$1="Rolling",AD7-AB7,0))*AB119 -> 0 | AC55: =IF(OR(AC$1="Reno Start", AC$1="Reno End"),AE7-AD7,IF(AC$1="Rolling",AE7-AC7,0))*AC119 -> 0 | AD55: =IF(OR(AD$1="Reno Start", AD$1="Reno End"),AF7-AE7,IF(AD$1="Rolling",AF7-AD7,0))*AD119 -> 0 | ... CE55: =IF(OR(CE$1="Reno Start", CE$1="Reno End"),CG7-CF7,IF(CE$1="Rolling",CG7-CE7,0))*CE119 -> 0
Q56: =$Q$8 | R56: =SUMIF($X$2:$CE$2,R$2,$X56:$CE56) -> 0 | S56: =SUMIF($X$2:$CE$2,S$2,$X56:$CE56) -> 0 | T56: =SUMIF($X$2:$CE$2,T$2,$X56:$CE56) -> 0 | U56: =SUMIF($X$2:$CE$2,U$2,$X56:$CE56) -> 0 | V56: =SUMIF($X$2:$CE$2,V$2,$X56:$CE56) -> 0 | W56: =IF(OR(W$1="Reno Start", W$1="Reno End"),Y8-X8,IF(W$1="Rolling",Y8-W8,0))*W120 -> 0 | X56: =IF(OR(X$1="Reno Start", X$1="Reno End"),Z8-Y8,IF(X$1="Rolling",Z8-X8,0))*X120 -> 0 | Y56: =IF(OR(Y$1="Reno Start", Y$1="Reno End"),AA8-Z8,IF(Y$1="Rolling",AA8-Y8,0))*Y120 -> 0 | Z56: =IF(OR(Z$1="Reno Start", Z$1="Reno End"),AB8-AA8,IF(Z$1="Rolling",AB8-Z8,0))*Z120 -> 0 | AA56: =IF(OR(AA$1="Reno Start", AA$1="Reno End"),AC8-AB8,IF(AA$1="Rolling",AC8-AA8,0))*AA120 -> 0 | AB56: =IF(OR(AB$1="Reno Start", AB$1="Reno End"),AD8-AC8,IF(AB$1="Rolling",AD8-AB8,0))*AB120 -> 0 | AC56: =IF(OR(AC$1="Reno Start", AC$1="Reno End"),AE8-AD8,IF(AC$1="Rolling",AE8-AC8,0))*AC120 -> 0 | AD56: =IF(OR(AD$1="Reno Start", AD$1="Reno End"),AF8-AE8,IF(AD$1="Rolling",AF8-AD8,0))*AD120 -> 0 | ... CE56: =IF(OR(CE$1="Reno Start", CE$1="Reno End"),CG8-CF8,IF(CE$1="Rolling",CG8-CE8,0))*CE120 -> 0
Q57: =$Q$9 | R57: =SUMIF($X$2:$CE$2,R$2,$X57:$CE57) -> 0 | S57: =SUMIF($X$2:$CE$2,S$2,$X57:$CE57) -> 0 | T57: =SUMIF($X$2:$CE$2,T$2,$X57:$CE57) -> 0 | U57: =SUMIF($X$2:$CE$2,U$2,$X57:$CE57) -> 0 | V57: =SUMIF($X$2:$CE$2,V$2,$X57:$CE57) -> 0 | W57: =IF(OR(W$1="Reno Start", W$1="Reno End"),Y9-X9,IF(W$1="Rolling",Y9-W9,0))*W121 -> 0 | X57: =IF(OR(X$1="Reno Start", X$1="Reno End"),Z9-Y9,IF(X$1="Rolling",Z9-X9,0))*X121 -> 0 | Y57: =IF(OR(Y$1="Reno Start", Y$1="Reno End"),AA9-Z9,IF(Y$1="Rolling",AA9-Y9,0))*Y121 -> 0 | Z57: =IF(OR(Z$1="Reno Start", Z$1="Reno End"),AB9-AA9,IF(Z$1="Rolling",AB9-Z9,0))*Z121 -> 0 | AA57: =IF(OR(AA$1="Reno Start", AA$1="Reno End"),AC9-AB9,IF(AA$1="Rolling",AC9-AA9,0))*AA121 -> 0 | AB57: =IF(OR(AB$1="Reno Start", AB$1="Reno End"),AD9-AC9,IF(AB$1="Rolling",AD9-AB9,0))*AB121 -> 0 | AC57: =IF(OR(AC$1="Reno Start", AC$1="Reno End"),AE9-AD9,IF(AC$1="Rolling",AE9-AC9,0))*AC121 -> 0 | AD57: =IF(OR(AD$1="Reno Start", AD$1="Reno End"),AF9-AE9,IF(AD$1="Rolling",AF9-AD9,0))*AD121 -> 0 | ... CE57: =IF(OR(CE$1="Reno Start", CE$1="Reno End"),CG9-CF9,IF(CE$1="Rolling",CG9-CE9,0))*CE121 -> 0
Q58: =$Q$10 | R58: =SUMIF($X$2:$CE$2,R$2,$X58:$CE58) -> 0 | S58: =SUMIF($X$2:$CE$2,S$2,$X58:$CE58) -> 0 | T58: =SUMIF($X$2:$CE$2,T$2,$X58:$CE58) -> 0 | U58: =SUMIF($X$2:$CE$2,U$2,$X58:$CE58) -> 0 | V58: =SUMIF($X$2:$CE$2,V$2,$X58:$CE58) -> 0 | W58: =IF(OR(W$1="Reno Start", W$1="Reno End"),Y10-X10,IF(W$1="Rolling",Y10-W10,0))*W122 -> 0 | X58: =IF(OR(X$1="Reno Start", X$1="Reno End"),Z10-Y10,IF(X$1="Rolling",Z10-X10,0))*X122 -> 0 | Y58: =IF(OR(Y$1="Reno Start", Y$1="Reno End"),AA10-Z10,IF(Y$1="Rolling",AA10-Y10,0))*Y122 -> 0 | Z58: =IF(OR(Z$1="Reno Start", Z$1="Reno End"),AB10-AA10,IF(Z$1="Rolling",AB10-Z10,0))*Z122 -> 0 | AA58: =IF(OR(AA$1="Reno Start", AA$1="Reno End"),AC10-AB10,IF(AA$1="Rolling",AC10-AA10,0))*AA122 -> 0 | AB58: =IF(OR(AB$1="Reno Start", AB$1="Reno End"),AD10-AC10,IF(AB$1="Rolling",AD10-AB10,0))*AB122 -> 0 | AC58: =IF(OR(AC$1="Reno Start", AC$1="Reno End"),AE10-AD10,IF(AC$1="Rolling",AE10-AC10,0))*AC122 -> 0 | AD58: =IF(OR(AD$1="Reno Start", AD$1="Reno End"),AF10-AE10,IF(AD$1="Rolling",AF10-AD10,0))*AD122 -> 0 | ... CE58: =IF(OR(CE$1="Reno Start", CE$1="Reno End"),CG10-CF10,IF(CE$1="Rolling",CG10-CE10,0))*CE122 -> 0
Q59: =$Q$11 | R59: =SUMIF($X$2:$CE$2,R$2,$X59:$CE59) -> 0 | S59: =SUMIF($X$2:$CE$2,S$2,$X59:$CE59) -> 0 | T59: =SUMIF($X$2:$CE$2,T$2,$X59:$CE59) -> 0 | U59: =SUMIF($X$2:$CE$2,U$2,$X59:$CE59) -> 0 | V59: =SUMIF($X$2:$CE$2,V$2,$X59:$CE59) -> 0 | W59: =IF(OR(W$1="Reno Start", W$1="Reno End"),Y11-X11,IF(W$1="Rolling",Y11-W11,0))*W123 -> 0 | X59: =IF(OR(X$1="Reno Start", X$1="Reno End"),Z11-Y11,IF(X$1="Rolling",Z11-X11,0))*X123 -> 0 | Y59: =IF(OR(Y$1="Reno Start", Y$1="Reno End"),AA11-Z11,IF(Y$1="Rolling",AA11-Y11,0))*Y123 -> 0 | Z59: =IF(OR(Z$1="Reno Start", Z$1="Reno End"),AB11-AA11,IF(Z$1="Rolling",AB11-Z11,0))*Z123 -> 0 | AA59: =IF(OR(AA$1="Reno Start", AA$1="Reno End"),AC11-AB11,IF(AA$1="Rolling",AC11-AA11,0))*AA123 -> 0 | AB59: =IF(OR(AB$1="Reno Start", AB$1="Reno End"),AD11-AC11,IF(AB$1="Rolling",AD11-AB11,0))*AB123 -> 0 | AC59: =IF(OR(AC$1="Reno Start", AC$1="Reno End"),AE11-AD11,IF(AC$1="Rolling",AE11-AC11,0))*AC123 -> 0 | AD59: =IF(OR(AD$1="Reno Start", AD$1="Reno End"),AF11-AE11,IF(AD$1="Rolling",AF11-AD11,0))*AD123 -> 0 | ... CE59: =IF(OR(CE$1="Reno Start", CE$1="Reno End"),CG11-CF11,IF(CE$1="Rolling",CG11-CE11,0))*CE123 -> 0
Q60: =$Q$12 | R60: =SUMIF($X$2:$CE$2,R$2,$X60:$CE60) -> 0 | S60: =SUMIF($X$2:$CE$2,S$2,$X60:$CE60) -> 0 | T60: =SUMIF($X$2:$CE$2,T$2,$X60:$CE60) -> 0 | U60: =SUMIF($X$2:$CE$2,U$2,$X60:$CE60) -> 0 | V60: =SUMIF($X$2:$CE$2,V$2,$X60:$CE60) -> 0 | W60: =IF(OR(W$1="Reno Start", W$1="Reno End"),Y12-X12,IF(W$1="Rolling",Y12-W12,0))*W124 -> 0 | X60: =IF(OR(X$1="Reno Start", X$1="Reno End"),Z12-Y12,IF(X$1="Rolling",Z12-X12,0))*X124 -> 0 | Y60: =IF(OR(Y$1="Reno Start", Y$1="Reno End"),AA12-Z12,IF(Y$1="Rolling",AA12-Y12,0))*Y124 -> 0 | Z60: =IF(OR(Z$1="Reno Start", Z$1="Reno End"),AB12-AA12,IF(Z$1="Rolling",AB12-Z12,0))*Z124 -> 0 | AA60: =IF(OR(AA$1="Reno Start", AA$1="Reno End"),AC12-AB12,IF(AA$1="Rolling",AC12-AA12,0))*AA124 -> 0 | AB60: =IF(OR(AB$1="Reno Start", AB$1="Reno End"),AD12-AC12,IF(AB$1="Rolling",AD12-AB12,0))*AB124 -> 0 | AC60: =IF(OR(AC$1="Reno Start", AC$1="Reno End"),AE12-AD12,IF(AC$1="Rolling",AE12-AC12,0))*AC124 -> 0 | AD60: =IF(OR(AD$1="Reno Start", AD$1="Reno End"),AF12-AE12,IF(AD$1="Rolling",AF12-AD12,0))*AD124 -> 0 | ... CE60: =IF(OR(CE$1="Reno Start", CE$1="Reno End"),CG12-CF12,IF(CE$1="Rolling",CG12-CE12,0))*CE124 -> 0
Q61: =$Q$13 | R61: =SUMIF($X$2:$CE$2,R$2,$X61:$CE61) -> 0 | S61: =SUMIF($X$2:$CE$2,S$2,$X61:$CE61) -> 0 | T61: =SUMIF($X$2:$CE$2,T$2,$X61:$CE61) -> 0 | U61: =SUMIF($X$2:$CE$2,U$2,$X61:$CE61) -> 0 | V61: =SUMIF($X$2:$CE$2,V$2,$X61:$CE61) -> 0 | W61: =IF(OR(W$1="Reno Start", W$1="Reno End"),Y13-X13,IF(W$1="Rolling",Y13-W13,0))*W125 -> 0 | X61: =IF(OR(X$1="Reno Start", X$1="Reno End"),Z13-Y13,IF(X$1="Rolling",Z13-X13,0))*X125 -> 0 | Y61: =IF(OR(Y$1="Reno Start", Y$1="Reno End"),AA13-Z13,IF(Y$1="Rolling",AA13-Y13,0))*Y125 -> 0 | Z61: =IF(OR(Z$1="Reno Start", Z$1="Reno End"),AB13-AA13,IF(Z$1="Rolling",AB13-Z13,0))*Z125 -> 0 | AA61: =IF(OR(AA$1="Reno Start", AA$1="Reno End"),AC13-AB13,IF(AA$1="Rolling",AC13-AA13,0))*AA125 -> 0 | AB61: =IF(OR(AB$1="Reno Start", AB$1="Reno End"),AD13-AC13,IF(AB$1="Rolling",AD13-AB13,0))*AB125 -> 0 | AC61: =IF(OR(AC$1="Reno Start", AC$1="Reno End"),AE13-AD13,IF(AC$1="Rolling",AE13-AC13,0))*AC125 -> 0 | AD61: =IF(OR(AD$1="Reno Start", AD$1="Reno End"),AF13-AE13,IF(AD$1="Rolling",AF13-AD13,0))*AD125 -> 0 | ... CE61: =IF(OR(CE$1="Reno Start", CE$1="Reno End"),CG13-CF13,IF(CE$1="Rolling",CG13-CE13,0))*CE125 -> 0
Q62: =$Q$14 | R62: =SUMIF($X$2:$CE$2,R$2,$X62:$CE62) -> 0 | S62: =SUMIF($X$2:$CE$2,S$2,$X62:$CE62) -> 0 | T62: =SUMIF($X$2:$CE$2,T$2,$X62:$CE62) -> 0 | U62: =SUMIF($X$2:$CE$2,U$2,$X62:$CE62) -> 0 | V62: =SUMIF($X$2:$CE$2,V$2,$X62:$CE62) -> 0 | W62: =IF(OR(W$1="Reno Start", W$1="Reno End"),Y14-X14,IF(W$1="Rolling",Y14-W14,0))*W126 -> 0 | X62: =IF(OR(X$1="Reno Start", X$1="Reno End"),Z14-Y14,IF(X$1="Rolling",Z14-X14,0))*X126 -> 0 | Y62: =IF(OR(Y$1="Reno Start", Y$1="Reno End"),AA14-Z14,IF(Y$1="Rolling",AA14-Y14,0))*Y126 -> 0 | Z62: =IF(OR(Z$1="Reno Start", Z$1="Reno End"),AB14-AA14,IF(Z$1="Rolling",AB14-Z14,0))*Z126 -> 0 | AA62: =IF(OR(AA$1="Reno Start", AA$1="Reno End"),AC14-AB14,IF(AA$1="Rolling",AC14-AA14,0))*AA126 -> 0 | AB62: =IF(OR(AB$1="Reno Start", AB$1="Reno End"),AD14-AC14,IF(AB$1="Rolling",AD14-AB14,0))*AB126 -> 0 | AC62: =IF(OR(AC$1="Reno Start", AC$1="Reno End"),AE14-AD14,IF(AC$1="Rolling",AE14-AC14,0))*AC126 -> 0 | AD62: =IF(OR(AD$1="Reno Start", AD$1="Reno End"),AF14-AE14,IF(AD$1="Rolling",AF14-AD14,0))*AD126 -> 0 | ... CE62: =IF(OR(CE$1="Reno Start", CE$1="Reno End"),CG14-CF14,IF(CE$1="Rolling",CG14-CE14,0))*CE126 -> 0
Q63: =$Q$15 | R63: =SUMIF($X$2:$CE$2,R$2,$X63:$CE63) -> 0 | S63: =SUMIF($X$2:$CE$2,S$2,$X63:$CE63) -> 0 | T63: =SUMIF($X$2:$CE$2,T$2,$X63:$CE63) -> 0 | U63: =SUMIF($X$2:$CE$2,U$2,$X63:$CE63) -> 0 | V63: =SUMIF($X$2:$CE$2,V$2,$X63:$CE63) -> 0 | W63: =IF(OR(W$1="Reno Start", W$1="Reno End"),Y15-X15,IF(W$1="Rolling",Y15-W15,0))*W127 -> 0 | X63: =IF(OR(X$1="Reno Start", X$1="Reno End"),Z15-Y15,IF(X$1="Rolling",Z15-X15,0))*X127 -> 0 | Y63: =IF(OR(Y$1="Reno Start", Y$1="Reno End"),AA15-Z15,IF(Y$1="Rolling",AA15-Y15,0))*Y127 -> 0 | Z63: =IF(OR(Z$1="Reno Start", Z$1="Reno End"),AB15-AA15,IF(Z$1="Rolling",AB15-Z15,0))*Z127 -> 0 | AA63: =IF(OR(AA$1="Reno Start", AA$1="Reno End"),AC15-AB15,IF(AA$1="Rolling",AC15-AA15,0))*AA127 -> 0 | AB63: =IF(OR(AB$1="Reno Start", AB$1="Reno End"),AD15-AC15,IF(AB$1="Rolling",AD15-AB15,0))*AB127 -> 0 | AC63: =IF(OR(AC$1="Reno Start", AC$1="Reno End"),AE15-AD15,IF(AC$1="Rolling",AE15-AC15,0))*AC127 -> 0 | AD63: =IF(OR(AD$1="Reno Start", AD$1="Reno End"),AF15-AE15,IF(AD$1="Rolling",AF15-AD15,0))*AD127 -> 0 | ... CE63: =IF(OR(CE$1="Reno Start", CE$1="Reno End"),CG15-CF15,IF(CE$1="Rolling",CG15-CE15,0))*CE127 -> 0
Q64: =$Q$16 | R64: =SUMIF($X$2:$CE$2,R$2,$X64:$CE64) -> 0 | S64: =SUMIF($X$2:$CE$2,S$2,$X64:$CE64) -> 0 | T64: =SUMIF($X$2:$CE$2,T$2,$X64:$CE64) -> 0 | U64: =SUMIF($X$2:$CE$2,U$2,$X64:$CE64) -> 0 | V64: =SUMIF($X$2:$CE$2,V$2,$X64:$CE64) -> 0 | W64: =IF(OR(W$1="Reno Start", W$1="Reno End"),Y16-X16,IF(W$1="Rolling",Y16-W16,0))*W128 -> 0 | X64: =IF(OR(X$1="Reno Start", X$1="Reno End"),Z16-Y16,IF(X$1="Rolling",Z16-X16,0))*X128 -> 0 | Y64: =IF(OR(Y$1="Reno Start", Y$1="Reno End"),AA16-Z16,IF(Y$1="Rolling",AA16-Y16,0))*Y128 -> 0 | Z64: =IF(OR(Z$1="Reno Start", Z$1="Reno End"),AB16-AA16,IF(Z$1="Rolling",AB16-Z16,0))*Z128 -> 0 | AA64: =IF(OR(AA$1="Reno Start", AA$1="Reno End"),AC16-AB16,IF(AA$1="Rolling",AC16-AA16,0))*AA128 -> 0 | AB64: =IF(OR(AB$1="Reno Start", AB$1="Reno End"),AD16-AC16,IF(AB$1="Rolling",AD16-AB16,0))*AB128 -> 0 | AC64: =IF(OR(AC$1="Reno Start", AC$1="Reno End"),AE16-AD16,IF(AC$1="Rolling",AE16-AC16,0))*AC128 -> 0 | AD64: =IF(OR(AD$1="Reno Start", AD$1="Reno End"),AF16-AE16,IF(AD$1="Rolling",AF16-AD16,0))*AD128 -> 0 | ... CE64: =IF(OR(CE$1="Reno Start", CE$1="Reno End"),CG16-CF16,IF(CE$1="Rolling",CG16-CE16,0))*CE128 -> 0
Q65: =$Q$17 | R65: =SUMIF($X$2:$CE$2,R$2,$X65:$CE65) -> 0 | S65: =SUMIF($X$2:$CE$2,S$2,$X65:$CE65) -> 0 | T65: =SUMIF($X$2:$CE$2,T$2,$X65:$CE65) -> 0 | U65: =SUMIF($X$2:$CE$2,U$2,$X65:$CE65) -> 0 | V65: =SUMIF($X$2:$CE$2,V$2,$X65:$CE65) -> 0 | W65: =IF(OR(W$1="Reno Start", W$1="Reno End"),Y17-X17,IF(W$1="Rolling",Y17-W17,0))*W129 -> 0 | X65: =IF(OR(X$1="Reno Start", X$1="Reno End"),Z17-Y17,IF(X$1="Rolling",Z17-X17,0))*X129 -> 0 | Y65: =IF(OR(Y$1="Reno Start", Y$1="Reno End"),AA17-Z17,IF(Y$1="Rolling",AA17-Y17,0))*Y129 -> 0 | Z65: =IF(OR(Z$1="Reno Start", Z$1="Reno End"),AB17-AA17,IF(Z$1="Rolling",AB17-Z17,0))*Z129 -> 0 | AA65: =IF(OR(AA$1="Reno Start", AA$1="Reno End"),AC17-AB17,IF(AA$1="Rolling",AC17-AA17,0))*AA129 -> 0 | AB65: =IF(OR(AB$1="Reno Start", AB$1="Reno End"),AD17-AC17,IF(AB$1="Rolling",AD17-AB17,0))*AB129 -> 0 | AC65: =IF(OR(AC$1="Reno Start", AC$1="Reno End"),AE17-AD17,IF(AC$1="Rolling",AE17-AC17,0))*AC129 -> 0 | AD65: =IF(OR(AD$1="Reno Start", AD$1="Reno End"),AF17-AE17,IF(AD$1="Rolling",AF17-AD17,0))*AD129 -> 0 | ... CE65: =IF(OR(CE$1="Reno Start", CE$1="Reno End"),CG17-CF17,IF(CE$1="Rolling",CG17-CE17,0))*CE129 -> 0
Q66: =$Q$18 | R66: =SUMIF($X$2:$CE$2,R$2,$X66:$CE66) -> 0 | S66: =SUMIF($X$2:$CE$2,S$2,$X66:$CE66) -> 0 | T66: =SUMIF($X$2:$CE$2,T$2,$X66:$CE66) -> 0 | U66: =SUMIF($X$2:$CE$2,U$2,$X66:$CE66) -> 0 | V66: =SUMIF($X$2:$CE$2,V$2,$X66:$CE66) -> 0 | W66: =IF(OR(W$1="Reno Start", W$1="Reno End"),Y18-X18,IF(W$1="Rolling",Y18-W18,0))*W130 -> 0 | X66: =IF(OR(X$1="Reno Start", X$1="Reno End"),Z18-Y18,IF(X$1="Rolling",Z18-X18,0))*X130 -> 0 | Y66: =IF(OR(Y$1="Reno Start", Y$1="Reno End"),AA18-Z18,IF(Y$1="Rolling",AA18-Y18,0))*Y130 -> 0 | Z66: =IF(OR(Z$1="Reno Start", Z$1="Reno End"),AB18-AA18,IF(Z$1="Rolling",AB18-Z18,0))*Z130 -> 0 | AA66: =IF(OR(AA$1="Reno Start", AA$1="Reno End"),AC18-AB18,IF(AA$1="Rolling",AC18-AA18,0))*AA130 -> 0 | AB66: =IF(OR(AB$1="Reno Start", AB$1="Reno End"),AD18-AC18,IF(AB$1="Rolling",AD18-AB18,0))*AB130 -> 0 | AC66: =IF(OR(AC$1="Reno Start", AC$1="Reno End"),AE18-AD18,IF(AC$1="Rolling",AE18-AC18,0))*AC130 -> 0 | AD66: =IF(OR(AD$1="Reno Start", AD$1="Reno End"),AF18-AE18,IF(AD$1="Rolling",AF18-AD18,0))*AD130 -> 0 | ... CE66: =IF(OR(CE$1="Reno Start", CE$1="Reno End"),CG18-CF18,IF(CE$1="Rolling",CG18-CE18,0))*CE130 -> 0
Q67: =$Q$19 | R67: =SUMIF($X$2:$CE$2,R$2,$X67:$CE67) -> 0 | S67: =SUMIF($X$2:$CE$2,S$2,$X67:$CE67) -> 0 | T67: =SUMIF($X$2:$CE$2,T$2,$X67:$CE67) -> 0 | U67: =SUMIF($X$2:$CE$2,U$2,$X67:$CE67) -> 0 | V67: =SUMIF($X$2:$CE$2,V$2,$X67:$CE67) -> 0 | W67: =IF(OR(W$1="Reno Start", W$1="Reno End"),Y19-X19,IF(W$1="Rolling",Y19-W19,0))*W131 -> 0 | X67: =IF(OR(X$1="Reno Start", X$1="Reno End"),Z19-Y19,IF(X$1="Rolling",Z19-X19,0))*X131 -> 0 | Y67: =IF(OR(Y$1="Reno Start", Y$1="Reno End"),AA19-Z19,IF(Y$1="Rolling",AA19-Y19,0))*Y131 -> 0 | Z67: =IF(OR(Z$1="Reno Start", Z$1="Reno End"),AB19-AA19,IF(Z$1="Rolling",AB19-Z19,0))*Z131 -> 0 | AA67: =IF(OR(AA$1="Reno Start", AA$1="Reno End"),AC19-AB19,IF(AA$1="Rolling",AC19-AA19,0))*AA131 -> 0 | AB67: =IF(OR(AB$1="Reno Start", AB$1="Reno End"),AD19-AC19,IF(AB$1="Rolling",AD19-AB19,0))*AB131 -> 0 | AC67: =IF(OR(AC$1="Reno Start", AC$1="Reno End"),AE19-AD19,IF(AC$1="Rolling",AE19-AC19,0))*AC131 -> 0 | AD67: =IF(OR(AD$1="Reno Start", AD$1="Reno End"),AF19-AE19,IF(AD$1="Rolling",AF19-AD19,0))*AD131 -> 0 | ... CE67: =IF(OR(CE$1="Reno Start", CE$1="Reno End"),CG19-CF19,IF(CE$1="Rolling",CG19-CE19,0))*CE131 -> 0
Q68: =$Q$20 | R68: =SUMIF($X$2:$CE$2,R$2,$X68:$CE68) -> 0 | S68: =SUMIF($X$2:$CE$2,S$2,$X68:$CE68) -> 0 | T68: =SUMIF($X$2:$CE$2,T$2,$X68:$CE68) -> 0 | U68: =SUMIF($X$2:$CE$2,U$2,$X68:$CE68) -> 0 | V68: =SUMIF($X$2:$CE$2,V$2,$X68:$CE68) -> 0 | W68: =IF(OR(W$1="Reno Start", W$1="Reno End"),Y20-X20,IF(W$1="Rolling",Y20-W20,0))*W132 -> 0 | X68: =IF(OR(X$1="Reno Start", X$1="Reno End"),Z20-Y20,IF(X$1="Rolling",Z20-X20,0))*X132 -> 0 | Y68: =IF(OR(Y$1="Reno Start", Y$1="Reno End"),AA20-Z20,IF(Y$1="Rolling",AA20-Y20,0))*Y132 -> 0 | Z68: =IF(OR(Z$1="Reno Start", Z$1="Reno End"),AB20-AA20,IF(Z$1="Rolling",AB20-Z20,0))*Z132 -> 0 | AA68: =IF(OR(AA$1="Reno Start", AA$1="Reno End"),AC20-AB20,IF(AA$1="Rolling",AC20-AA20,0))*AA132 -> 0 | AB68: =IF(OR(AB$1="Reno Start", AB$1="Reno End"),AD20-AC20,IF(AB$1="Rolling",AD20-AB20,0))*AB132 -> 0 | AC68: =IF(OR(AC$1="Reno Start", AC$1="Reno End"),AE20-AD20,IF(AC$1="Rolling",AE20-AC20,0))*AC132 -> 0 | AD68: =IF(OR(AD$1="Reno Start", AD$1="Reno End"),AF20-AE20,IF(AD$1="Rolling",AF20-AD20,0))*AD132 -> 0 | ... CE68: =IF(OR(CE$1="Reno Start", CE$1="Reno End"),CG20-CF20,IF(CE$1="Rolling",CG20-CE20,0))*CE132 -> 0
Q69: Cumulative Reno Unit Vacancy Total | R69: =SUM(R70:R84) -> 0 | S69: =SUM(S70:S84) -> 0 | T69: =SUM(T70:T84) -> 0 | U69: =SUM(U70:U84) -> 0 | V69: =SUM(V70:V84) -> 0 | W69: =SUM(W70:W84) -> 0 | X69: =SUM(X70:X84) -> 0 | Y69: =SUM(Y70:Y84) -> 0 | ... CE69: =SUM(CE70:CE84) -> 0
Q70: =$Q$6 | R70: =_xlfn.MAXIFS($X70:$CE70,$X$2:$CE$2,R$2) -> 0 | S70: =_xlfn.MAXIFS($X70:$CE70,$X$2:$CE$2,S$2) -> 0 | T70: =_xlfn.MAXIFS($X70:$CE70,$X$2:$CE$2,T$2) -> 0 | U70: =_xlfn.MAXIFS($X70:$CE70,$X$2:$CE$2,U$2) -> 0 | V70: =_xlfn.MAXIFS($X70:$CE70,$X$2:$CE$2,V$2) -> 0 | W70: 0 | X70: {=OFFSET(X6:BS20,0,2)} -> 0 | Y70: 0 | Z70: 0 | AA70: 0 | AB70: 0 | AC70: 0 | AD70: 0 | AE70: 0 | AF70: 0 | AG70: 0 | AH70: 0 | AI70: 0 | AJ70: 0 | AK70: 0 | AL70: 0 | AM70: 0 | AN70: 0 | AO70: 0 | AP70: 0 | AQ70: 0 | AR70: 0 | AS70: 0 | AT70: 0 | AU70: 0 | AV70: 0 | AW70: 0 | AX70: 0 | AY70: 0 | AZ70: 0 | BA70: 0 | BB70: 0 | BC70: 0 | BD70: 0 | BE70: 0 | BF70: 0 | BG70: 0 | BH70: 0 | BI70: 0 | BJ70: 0 | BK70: 0 | BL70: 0 | BM70: 0 | BN70: 0 | BO70: 0 | BP70: 0 | BQ70: 0 | BR70: 0 | BS70: 0 | BT70: {=OFFSET(BT6:DO20,0,'UW Model'!BK$15-1)} -> 0 | BU70: 0 | BV70: 0 | BW70: 0 | BX70: 0 | BY70: 0 | BZ70: 0 | CA70: 0 | CB70: 0 | CC70: 0 | CD70: 0 | CE70: 0
Q71: =$Q$7 | R71: =_xlfn.MAXIFS($X71:$CE71,$X$2:$CE$2,R$2) -> 0 | S71: =_xlfn.MAXIFS($X71:$CE71,$X$2:$CE$2,S$2) -> 0 | T71: =_xlfn.MAXIFS($X71:$CE71,$X$2:$CE$2,T$2) -> 0 | U71: =_xlfn.MAXIFS($X71:$CE71,$X$2:$CE$2,U$2) -> 0 | V71: =_xlfn.MAXIFS($X71:$CE71,$X$2:$CE$2,V$2) -> 0 | W71: 0 | X71: 0 | Y71: 0 | Z71: 0 | AA71: 0 | AB71: 0 | AC71: 0 | AD71: 0 | AE71: 0 | AF71: 0 | AG71: 0 | AH71: 0 | AI71: 0 | AJ71: 0 | AK71: 0 | AL71: 0 | AM71: 0 | AN71: 0 | AO71: 0 | AP71: 0 | AQ71: 0 | AR71: 0 | AS71: 0 | AT71: 0 | AU71: 0 | AV71: 0 | AW71: 0 | AX71: 0 | AY71: 0 | AZ71: 0 | BA71: 0 | BB71: 0 | BC71: 0 | BD71: 0 | BE71: 0 | BF71: 0 | BG71: 0 | BH71: 0 | BI71: 0 | BJ71: 0 | BK71: 0 | BL71: 0 | BM71: 0 | BN71: 0 | BO71: 0 | BP71: 0 | BQ71: 0 | BR71: 0 | BS71: 0 | BT71: 0 | BU71: 0 | BV71: 0 | BW71: 0 | BX71: 0 | BY71: 0 | BZ71: 0 | CA71: 0 | CB71: 0 | CC71: 0 | CD71: 0 | CE71: 0
Q72: =$Q$8 | R72: =_xlfn.MAXIFS($X72:$CE72,$X$2:$CE$2,R$2) -> 0 | S72: =_xlfn.MAXIFS($X72:$CE72,$X$2:$CE$2,S$2) -> 0 | T72: =_xlfn.MAXIFS($X72:$CE72,$X$2:$CE$2,T$2) -> 0 | U72: =_xlfn.MAXIFS($X72:$CE72,$X$2:$CE$2,U$2) -> 0 | V72: =_xlfn.MAXIFS($X72:$CE72,$X$2:$CE$2,V$2) -> 0 | W72: 0 | X72: 0 | Y72: 0 | Z72: 0 | AA72: 0 | AB72: 0 | AC72: 0 | AD72: 0 | AE72: 0 | AF72: 0 | AG72: 0 | AH72: 0 | AI72: 0 | AJ72: 0 | AK72: 0 | AL72: 0 | AM72: 0 | AN72: 0 | AO72: 0 | AP72: 0 | AQ72: 0 | AR72: 0 | AS72: 0 | AT72: 0 | AU72: 0 | AV72: 0 | AW72: 0 | AX72: 0 | AY72: 0 | AZ72: 0 | BA72: 0 | BB72: 0 | BC72: 0 | BD72: 0 | BE72: 0 | BF72: 0 | BG72: 0 | BH72: 0 | BI72: 0 | BJ72: 0 | BK72: 0 | BL72: 0 | BM72: 0 | BN72: 0 | BO72: 0 | BP72: 0 | BQ72: 0 | BR72: 0 | BS72: 0 | BT72: 0 | BU72: 0 | BV72: 0 | BW72: 0 | BX72: 0 | BY72: 0 | BZ72: 0 | CA72: 0 | CB72: 0 | CC72: 0 | CD72: 0 | CE72: 0
Q73: =$Q$9 | R73: =_xlfn.MAXIFS($X73:$CE73,$X$2:$CE$2,R$2) -> 0 | S73: =_xlfn.MAXIFS($X73:$CE73,$X$2:$CE$2,S$2) -> 0 | T73: =_xlfn.MAXIFS($X73:$CE73,$X$2:$CE$2,T$2) -> 0 | U73: =_xlfn.MAXIFS($X73:$CE73,$X$2:$CE$2,U$2) -> 0 | V73: =_xlfn.MAXIFS($X73:$CE73,$X$2:$CE$2,V$2) -> 0 | W73: 0 | X73: 0 | Y73: 0 | Z73: 0 | AA73: 0 | AB73: 0 | AC73: 0 | AD73: 0 | AE73: 0 | AF73: 0 | AG73: 0 | AH73: 0 | AI73: 0 | AJ73: 0 | AK73: 0 | AL73: 0 | AM73: 0 | AN73: 0 | AO73: 0 | AP73: 0 | AQ73: 0 | AR73: 0 | AS73: 0 | AT73: 0 | AU73: 0 | AV73: 0 | AW73: 0 | AX73: 0 | AY73: 0 | AZ73: 0 | BA73: 0 | BB73: 0 | BC73: 0 | BD73: 0 | BE73: 0 | BF73: 0 | BG73: 0 | BH73: 0 | BI73: 0 | BJ73: 0 | BK73: 0 | BL73: 0 | BM73: 0 | BN73: 0 | BO73: 0 | BP73: 0 | BQ73: 0 | BR73: 0 | BS73: 0 | BT73: 0 | BU73: 0 | BV73: 0 | BW73: 0 | BX73: 0 | BY73: 0 | BZ73: 0 | CA73: 0 | CB73: 0 | CC73: 0 | CD73: 0 | CE73: 0
Q74: =$Q$10 | R74: =_xlfn.MAXIFS($X74:$CE74,$X$2:$CE$2,R$2) -> 0 | S74: =_xlfn.MAXIFS($X74:$CE74,$X$2:$CE$2,S$2) -> 0 | T74: =_xlfn.MAXIFS($X74:$CE74,$X$2:$CE$2,T$2) -> 0 | U74: =_xlfn.MAXIFS($X74:$CE74,$X$2:$CE$2,U$2) -> 0 | V74: =_xlfn.MAXIFS($X74:$CE74,$X$2:$CE$2,V$2) -> 0 | W74: 0 | X74: 0 | Y74: 0 | Z74: 0 | AA74: 0 | AB74: 0 | AC74: 0 | AD74: 0 | AE74: 0 | AF74: 0 | AG74: 0 | AH74: 0 | AI74: 0 | AJ74: 0 | AK74: 0 | AL74: 0 | AM74: 0 | AN74: 0 | AO74: 0 | AP74: 0 | AQ74: 0 | AR74: 0 | AS74: 0 | AT74: 0 | AU74: 0 | AV74: 0 | AW74: 0 | AX74: 0 | AY74: 0 | AZ74: 0 | BA74: 0 | BB74: 0 | BC74: 0 | BD74: 0 | BE74: 0 | BF74: 0 | BG74: 0 | BH74: 0 | BI74: 0 | BJ74: 0 | BK74: 0 | BL74: 0 | BM74: 0 | BN74: 0 | BO74: 0 | BP74: 0 | BQ74: 0 | BR74: 0 | BS74: 0 | BT74: 0 | BU74: 0 | BV74: 0 | BW74: 0 | BX74: 0 | BY74: 0 | BZ74: 0 | CA74: 0 | CB74: 0 | CC74: 0 | CD74: 0 | CE74: 0
Q75: =$Q$11 | R75: =_xlfn.MAXIFS($X75:$CE75,$X$2:$CE$2,R$2) -> 0 | S75: =_xlfn.MAXIFS($X75:$CE75,$X$2:$CE$2,S$2) -> 0 | T75: =_xlfn.MAXIFS($X75:$CE75,$X$2:$CE$2,T$2) -> 0 | U75: =_xlfn.MAXIFS($X75:$CE75,$X$2:$CE$2,U$2) -> 0 | V75: =_xlfn.MAXIFS($X75:$CE75,$X$2:$CE$2,V$2) -> 0 | W75: 0 | X75: 0 | Y75: 0 | Z75: 0 | AA75: 0 | AB75: 0 | AC75: 0 | AD75: 0 | AE75: 0 | AF75: 0 | AG75: 0 | AH75: 0 | AI75: 0 | AJ75: 0 | AK75: 0 | AL75: 0 | AM75: 0 | AN75: 0 | AO75: 0 | AP75: 0 | AQ75: 0 | AR75: 0 | AS75: 0 | AT75: 0 | AU75: 0 | AV75: 0 | AW75: 0 | AX75: 0 | AY75: 0 | AZ75: 0 | BA75: 0 | BB75: 0 | BC75: 0 | BD75: 0 | BE75: 0 | BF75: 0 | BG75: 0 | BH75: 0 | BI75: 0 | BJ75: 0 | BK75: 0 | BL75: 0 | BM75: 0 | BN75: 0 | BO75: 0 | BP75: 0 | BQ75: 0 | BR75: 0 | BS75: 0 | BT75: 0 | BU75: 0 | BV75: 0 | BW75: 0 | BX75: 0 | BY75: 0 | BZ75: 0 | CA75: 0 | CB75: 0 | CC75: 0 | CD75: 0 | CE75: 0
Q76: =$Q$12 | R76: =_xlfn.MAXIFS($X76:$CE76,$X$2:$CE$2,R$2) -> 0 | S76: =_xlfn.MAXIFS($X76:$CE76,$X$2:$CE$2,S$2) -> 0 | T76: =_xlfn.MAXIFS($X76:$CE76,$X$2:$CE$2,T$2) -> 0 | U76: =_xlfn.MAXIFS($X76:$CE76,$X$2:$CE$2,U$2) -> 0 | V76: =_xlfn.MAXIFS($X76:$CE76,$X$2:$CE$2,V$2) -> 0 | W76: 0 | X76: 0 | Y76: 0 | Z76: 0 | AA76: 0 | AB76: 0 | AC76: 0 | AD76: 0 | AE76: 0 | AF76: 0 | AG76: 0 | AH76: 0 | AI76: 0 | AJ76: 0 | AK76: 0 | AL76: 0 | AM76: 0 | AN76: 0 | AO76: 0 | AP76: 0 | AQ76: 0 | AR76: 0 | AS76: 0 | AT76: 0 | AU76: 0 | AV76: 0 | AW76: 0 | AX76: 0 | AY76: 0 | AZ76: 0 | BA76: 0 | BB76: 0 | BC76: 0 | BD76: 0 | BE76: 0 | BF76: 0 | BG76: 0 | BH76: 0 | BI76: 0 | BJ76: 0 | BK76: 0 | BL76: 0 | BM76: 0 | BN76: 0 | BO76: 0 | BP76: 0 | BQ76: 0 | BR76: 0 | BS76: 0 | BT76: 0 | BU76: 0 | BV76: 0 | BW76: 0 | BX76: 0 | BY76: 0 | BZ76: 0 | CA76: 0 | CB76: 0 | CC76: 0 | CD76: 0 | CE76: 0
Q77: =$Q$13 | R77: =_xlfn.MAXIFS($X77:$CE77,$X$2:$CE$2,R$2) -> 0 | S77: =_xlfn.MAXIFS($X77:$CE77,$X$2:$CE$2,S$2) -> 0 | T77: =_xlfn.MAXIFS($X77:$CE77,$X$2:$CE$2,T$2) -> 0 | U77: =_xlfn.MAXIFS($X77:$CE77,$X$2:$CE$2,U$2) -> 0 | V77: =_xlfn.MAXIFS($X77:$CE77,$X$2:$CE$2,V$2) -> 0 | W77: 0 | X77: 0 | Y77: 0 | Z77: 0 | AA77: 0 | AB77: 0 | AC77: 0 | AD77: 0 | AE77: 0 | AF77: 0 | AG77: 0 | AH77: 0 | AI77: 0 | AJ77: 0 | AK77: 0 | AL77: 0 | AM77: 0 | AN77: 0 | AO77: 0 | AP77: 0 | AQ77: 0 | AR77: 0 | AS77: 0 | AT77: 0 | AU77: 0 | AV77: 0 | AW77: 0 | AX77: 0 | AY77: 0 | AZ77: 0 | BA77: 0 | BB77: 0 | BC77: 0 | BD77: 0 | BE77: 0 | BF77: 0 | BG77: 0 | BH77: 0 | BI77: 0 | BJ77: 0 | BK77: 0 | BL77: 0 | BM77: 0 | BN77: 0 | BO77: 0 | BP77: 0 | BQ77: 0 | BR77: 0 | BS77: 0 | BT77: 0 | BU77: 0 | BV77: 0 | BW77: 0 | BX77: 0 | BY77: 0 | BZ77: 0 | CA77: 0 | CB77: 0 | CC77: 0 | CD77: 0 | CE77: 0
Q78: =$Q$14 | R78: =_xlfn.MAXIFS($X78:$CE78,$X$2:$CE$2,R$2) -> 0 | S78: =_xlfn.MAXIFS($X78:$CE78,$X$2:$CE$2,S$2) -> 0 | T78: =_xlfn.MAXIFS($X78:$CE78,$X$2:$CE$2,T$2) -> 0 | U78: =_xlfn.MAXIFS($X78:$CE78,$X$2:$CE$2,U$2) -> 0 | V78: =_xlfn.MAXIFS($X78:$CE78,$X$2:$CE$2,V$2) -> 0 | W78: 0 | X78: 0 | Y78: 0 | Z78: 0 | AA78: 0 | AB78: 0 | AC78: 0 | AD78: 0 | AE78: 0 | AF78: 0 | AG78: 0 | AH78: 0 | AI78: 0 | AJ78: 0 | AK78: 0 | AL78: 0 | AM78: 0 | AN78: 0 | AO78: 0 | AP78: 0 | AQ78: 0 | AR78: 0 | AS78: 0 | AT78: 0 | AU78: 0 | AV78: 0 | AW78: 0 | AX78: 0 | AY78: 0 | AZ78: 0 | BA78: 0 | BB78: 0 | BC78: 0 | BD78: 0 | BE78: 0 | BF78: 0 | BG78: 0 | BH78: 0 | BI78: 0 | BJ78: 0 | BK78: 0 | BL78: 0 | BM78: 0 | BN78: 0 | BO78: 0 | BP78: 0 | BQ78: 0 | BR78: 0 | BS78: 0 | BT78: 0 | BU78: 0 | BV78: 0 | BW78: 0 | BX78: 0 | BY78: 0 | BZ78: 0 | CA78: 0 | CB78: 0 | CC78: 0 | CD78: 0 | CE78: 0
Q79: =$Q$15 | R79: =_xlfn.MAXIFS($X79:$CE79,$X$2:$CE$2,R$2) -> 0 | S79: =_xlfn.MAXIFS($X79:$CE79,$X$2:$CE$2,S$2) -> 0 | T79: =_xlfn.MAXIFS($X79:$CE79,$X$2:$CE$2,T$2) -> 0 | U79: =_xlfn.MAXIFS($X79:$CE79,$X$2:$CE$2,U$2) -> 0 | V79: =_xlfn.MAXIFS($X79:$CE79,$X$2:$CE$2,V$2) -> 0 | W79: 0 | X79: 0 | Y79: 0 | Z79: 0 | AA79: 0 | AB79: 0 | AC79: 0 | AD79: 0 | AE79: 0 | AF79: 0 | AG79: 0 | AH79: 0 | AI79: 0 | AJ79: 0 | AK79: 0 | AL79: 0 | AM79: 0 | AN79: 0 | AO79: 0 | AP79: 0 | AQ79: 0 | AR79: 0 | AS79: 0 | AT79: 0 | AU79: 0 | AV79: 0 | AW79: 0 | AX79: 0 | AY79: 0 | AZ79: 0 | BA79: 0 | BB79: 0 | BC79: 0 | BD79: 0 | BE79: 0 | BF79: 0 | BG79: 0 | BH79: 0 | BI79: 0 | BJ79: 0 | BK79: 0 | BL79: 0 | BM79: 0 | BN79: 0 | BO79: 0 | BP79: 0 | BQ79: 0 | BR79: 0 | BS79: 0 | BT79: 0 | BU79: 0 | BV79: 0 | BW79: 0 | BX79: 0 | BY79: 0 | BZ79: 0 | CA79: 0 | CB79: 0 | CC79: 0 | CD79: 0 | CE79: 0
Q80: =$Q$16 | R80: =_xlfn.MAXIFS($X80:$CE80,$X$2:$CE$2,R$2) -> 0 | S80: =_xlfn.MAXIFS($X80:$CE80,$X$2:$CE$2,S$2) -> 0 | T80: =_xlfn.MAXIFS($X80:$CE80,$X$2:$CE$2,T$2) -> 0 | U80: =_xlfn.MAXIFS($X80:$CE80,$X$2:$CE$2,U$2) -> 0 | V80: =_xlfn.MAXIFS($X80:$CE80,$X$2:$CE$2,V$2) -> 0 | W80: 0 | X80: 0 | Y80: 0 | Z80: 0 | AA80: 0 | AB80: 0 | AC80: 0 | AD80: 0 | AE80: 0 | AF80: 0 | AG80: 0 | AH80: 0 | AI80: 0 | AJ80: 0 | AK80: 0 | AL80: 0 | AM80: 0 | AN80: 0 | AO80: 0 | AP80: 0 | AQ80: 0 | AR80: 0 | AS80: 0 | AT80: 0 | AU80: 0 | AV80: 0 | AW80: 0 | AX80: 0 | AY80: 0 | AZ80: 0 | BA80: 0 | BB80: 0 | BC80: 0 | BD80: 0 | BE80: 0 | BF80: 0 | BG80: 0 | BH80: 0 | BI80: 0 | BJ80: 0 | BK80: 0 | BL80: 0 | BM80: 0 | BN80: 0 | BO80: 0 | BP80: 0 | BQ80: 0 | BR80: 0 | BS80: 0 | BT80: 0 | BU80: 0 | BV80: 0 | BW80: 0 | BX80: 0 | BY80: 0 | BZ80: 0 | CA80: 0 | CB80: 0 | CC80: 0 | CD80: 0 | CE80: 0
Q81: =$Q$17 | R81: =_xlfn.MAXIFS($X81:$CE81,$X$2:$CE$2,R$2) -> 0 | S81: =_xlfn.MAXIFS($X81:$CE81,$X$2:$CE$2,S$2) -> 0 | T81: =_xlfn.MAXIFS($X81:$CE81,$X$2:$CE$2,T$2) -> 0 | U81: =_xlfn.MAXIFS($X81:$CE81,$X$2:$CE$2,U$2) -> 0 | V81: =_xlfn.MAXIFS($X81:$CE81,$X$2:$CE$2,V$2) -> 0 | W81: 0 | X81: 0 | Y81: 0 | Z81: 0 | AA81: 0 | AB81: 0 | AC81: 0 | AD81: 0 | AE81: 0 | AF81: 0 | AG81: 0 | AH81: 0 | AI81: 0 | AJ81: 0 | AK81: 0 | AL81: 0 | AM81: 0 | AN81: 0 | AO81: 0 | AP81: 0 | AQ81: 0 | AR81: 0 | AS81: 0 | AT81: 0 | AU81: 0 | AV81: 0 | AW81: 0 | AX81: 0 | AY81: 0 | AZ81: 0 | BA81: 0 | BB81: 0 | BC81: 0 | BD81: 0 | BE81: 0 | BF81: 0 | BG81: 0 | BH81: 0 | BI81: 0 | BJ81: 0 | BK81: 0 | BL81: 0 | BM81: 0 | BN81: 0 | BO81: 0 | BP81: 0 | BQ81: 0 | BR81: 0 | BS81: 0 | BT81: 0 | BU81: 0 | BV81: 0 | BW81: 0 | BX81: 0 | BY81: 0 | BZ81: 0 | CA81: 0 | CB81: 0 | CC81: 0 | CD81: 0 | CE81: 0
Q82: =$Q$18 | R82: =_xlfn.MAXIFS($X82:$CE82,$X$2:$CE$2,R$2) -> 0 | S82: =_xlfn.MAXIFS($X82:$CE82,$X$2:$CE$2,S$2) -> 0 | T82: =_xlfn.MAXIFS($X82:$CE82,$X$2:$CE$2,T$2) -> 0 | U82: =_xlfn.MAXIFS($X82:$CE82,$X$2:$CE$2,U$2) -> 0 | V82: =_xlfn.MAXIFS($X82:$CE82,$X$2:$CE$2,V$2) -> 0 | W82: 0 | X82: 0 | Y82: 0 | Z82: 0 | AA82: 0 | AB82: 0 | AC82: 0 | AD82: 0 | AE82: 0 | AF82: 0 | AG82: 0 | AH82: 0 | AI82: 0 | AJ82: 0 | AK82: 0 | AL82: 0 | AM82: 0 | AN82: 0 | AO82: 0 | AP82: 0 | AQ82: 0 | AR82: 0 | AS82: 0 | AT82: 0 | AU82: 0 | AV82: 0 | AW82: 0 | AX82: 0 | AY82: 0 | AZ82: 0 | BA82: 0 | BB82: 0 | BC82: 0 | BD82: 0 | BE82: 0 | BF82: 0 | BG82: 0 | BH82: 0 | BI82: 0 | BJ82: 0 | BK82: 0 | BL82: 0 | BM82: 0 | BN82: 0 | BO82: 0 | BP82: 0 | BQ82: 0 | BR82: 0 | BS82: 0 | BT82: 0 | BU82: 0 | BV82: 0 | BW82: 0 | BX82: 0 | BY82: 0 | BZ82: 0 | CA82: 0 | CB82: 0 | CC82: 0 | CD82: 0 | CE82: 0
Q83: =$Q$19 | R83: =_xlfn.MAXIFS($X83:$CE83,$X$2:$CE$2,R$2) -> 0 | S83: =_xlfn.MAXIFS($X83:$CE83,$X$2:$CE$2,S$2) -> 0 | T83: =_xlfn.MAXIFS($X83:$CE83,$X$2:$CE$2,T$2) -> 0 | U83: =_xlfn.MAXIFS($X83:$CE83,$X$2:$CE$2,U$2) -> 0 | V83: =_xlfn.MAXIFS($X83:$CE83,$X$2:$CE$2,V$2) -> 0 | W83: 0 | X83: 0 | Y83: 0 | Z83: 0 | AA83: 0 | AB83: 0 | AC83: 0 | AD83: 0 | AE83: 0 | AF83: 0 | AG83: 0 | AH83: 0 | AI83: 0 | AJ83: 0 | AK83: 0 | AL83: 0 | AM83: 0 | AN83: 0 | AO83: 0 | AP83: 0 | AQ83: 0 | AR83: 0 | AS83: 0 | AT83: 0 | AU83: 0 | AV83: 0 | AW83: 0 | AX83: 0 | AY83: 0 | AZ83: 0 | BA83: 0 | BB83: 0 | BC83: 0 | BD83: 0 | BE83: 0 | BF83: 0 | BG83: 0 | BH83: 0 | BI83: 0 | BJ83: 0 | BK83: 0 | BL83: 0 | BM83: 0 | BN83: 0 | BO83: 0 | BP83: 0 | BQ83: 0 | BR83: 0 | BS83: 0 | BT83: 0 | BU83: 0 | BV83: 0 | BW83: 0 | BX83: 0 | BY83: 0 | BZ83: 0 | CA83: 0 | CB83: 0 | CC83: 0 | CD83: 0 | CE83: 0
Q84: =$Q$20 | R84: =_xlfn.MAXIFS($X84:$CE84,$X$2:$CE$2,R$2) -> 0 | S84: =_xlfn.MAXIFS($X84:$CE84,$X$2:$CE$2,S$2) -> 0 | T84: =_xlfn.MAXIFS($X84:$CE84,$X$2:$CE$2,T$2) -> 0 | U84: =_xlfn.MAXIFS($X84:$CE84,$X$2:$CE$2,U$2) -> 0 | V84: =_xlfn.MAXIFS($X84:$CE84,$X$2:$CE$2,V$2) -> 0 | W84: 0 | X84: 0 | Y84: 0 | Z84: 0 | AA84: 0 | AB84: 0 | AC84: 0 | AD84: 0 | AE84: 0 | AF84: 0 | AG84: 0 | AH84: 0 | AI84: 0 | AJ84: 0 | AK84: 0 | AL84: 0 | AM84: 0 | AN84: 0 | AO84: 0 | AP84: 0 | AQ84: 0 | AR84: 0 | AS84: 0 | AT84: 0 | AU84: 0 | AV84: 0 | AW84: 0 | AX84: 0 | AY84: 0 | AZ84: 0 | BA84: 0 | BB84: 0 | BC84: 0 | BD84: 0 | BE84: 0 | BF84: 0 | BG84: 0 | BH84: 0 | BI84: 0 | BJ84: 0 | BK84: 0 | BL84: 0 | BM84: 0 | BN84: 0 | BO84: 0 | BP84: 0 | BQ84: 0 | BR84: 0 | BS84: 0 | BT84: 0 | BU84: 0 | BV84: 0 | BW84: 0 | BX84: 0 | BY84: 0 | BZ84: 0 | CA84: 0 | CB84: 0 | CC84: 0 | CD84: 0 | CE84: 0
P85: Gross Rents for Non-Renovated Units | Q85: Non Reno Units Total | R85: =SUM(R86:R100) -> 0 | S85: =SUM(S86:S100) -> 0 | T85: =SUM(T86:T100) -> 0 | U85: =SUM(U86:U100) -> 0 | V85: =SUM(V86:V100) -> 0 | W85: 0 | X85: =SUM(X86:X100) -> 0 | Y85: =SUM(Y86:Y100) -> 0 | Z85: =SUM(Z86:Z100) -> 0 | AA85: =SUM(AA86:AA100) -> 0 | AB85: =SUM(AB86:AB100) -> 0 | AC85: =SUM(AC86:AC100) -> 0 | AD85: =SUM(AD86:AD100) -> 0 | AE85: =SUM(AE86:AE100) -> 0 | ... CE85: =SUM(CE86:CE100) -> 0
Q86: =$Q$6 | R86: =_xlfn.MINIFS($X86:$CE86,$X$2:$CE$2,R$2) -> 0 | S86: =_xlfn.MINIFS($X86:$CE86,$X$2:$CE$2,S$2) -> 0 | T86: =_xlfn.MINIFS($X86:$CE86,$X$2:$CE$2,T$2) -> 0 | U86: =_xlfn.MINIFS($X86:$CE86,$X$2:$CE$2,U$2) -> 0 | V86: =_xlfn.MINIFS($X86:$CE86,$X$2:$CE$2,V$2) -> 0 | W86: 0 | X86: ='UW Model'!$H28-X6 -> 0 | Y86: ='UW Model'!$H28-Y6 -> 0 | Z86: ='UW Model'!$H28-Z6 -> 0 | AA86: ='UW Model'!$H28-AA6 -> 0 | AB86: ='UW Model'!$H28-AB6 -> 0 | AC86: ='UW Model'!$H28-AC6 -> 0 | AD86: ='UW Model'!$H28-AD6 -> 0 | AE86: ='UW Model'!$H28-AE6 -> 0 | ... CE86: ='UW Model'!$H28-CE6 -> 0
Q87: =$Q$7 | R87: =_xlfn.MINIFS($X87:$CE87,$X$2:$CE$2,R$2) -> 0 | S87: =_xlfn.MINIFS($X87:$CE87,$X$2:$CE$2,S$2) -> 0 | T87: =_xlfn.MINIFS($X87:$CE87,$X$2:$CE$2,T$2) -> 0 | U87: =_xlfn.MINIFS($X87:$CE87,$X$2:$CE$2,U$2) -> 0 | V87: =_xlfn.MINIFS($X87:$CE87,$X$2:$CE$2,V$2) -> 0 | W87: 0 | X87: ='UW Model'!$H29-X7 -> 0 | Y87: ='UW Model'!$H29-Y7 -> 0 | Z87: ='UW Model'!$H29-Z7 -> 0 | AA87: ='UW Model'!$H29-AA7 -> 0 | AB87: ='UW Model'!$H29-AB7 -> 0 | AC87: ='UW Model'!$H29-AC7 -> 0 | AD87: ='UW Model'!$H29-AD7 -> 0 | AE87: ='UW Model'!$H29-AE7 -> 0 | ... CE87: ='UW Model'!$H29-CE7 -> 0
Q88: =$Q$8 | R88: =_xlfn.MINIFS($X88:$CE88,$X$2:$CE$2,R$2) -> 0 | S88: =_xlfn.MINIFS($X88:$CE88,$X$2:$CE$2,S$2) -> 0 | T88: =_xlfn.MINIFS($X88:$CE88,$X$2:$CE$2,T$2) -> 0 | U88: =_xlfn.MINIFS($X88:$CE88,$X$2:$CE$2,U$2) -> 0 | V88: =_xlfn.MINIFS($X88:$CE88,$X$2:$CE$2,V$2) -> 0 | W88: 0 | X88: ='UW Model'!$H30-X8 -> 0 | Y88: ='UW Model'!$H30-Y8 -> 0 | Z88: ='UW Model'!$H30-Z8 -> 0 | AA88: ='UW Model'!$H30-AA8 -> 0 | AB88: ='UW Model'!$H30-AB8 -> 0 | AC88: ='UW Model'!$H30-AC8 -> 0 | AD88: ='UW Model'!$H30-AD8 -> 0 | AE88: ='UW Model'!$H30-AE8 -> 0 | ... CE88: ='UW Model'!$H30-CE8 -> 0
Q89: =$Q$9 | R89: =_xlfn.MINIFS($X89:$CE89,$X$2:$CE$2,R$2) -> 0 | S89: =_xlfn.MINIFS($X89:$CE89,$X$2:$CE$2,S$2) -> 0 | T89: =_xlfn.MINIFS($X89:$CE89,$X$2:$CE$2,T$2) -> 0 | U89: =_xlfn.MINIFS($X89:$CE89,$X$2:$CE$2,U$2) -> 0 | V89: =_xlfn.MINIFS($X89:$CE89,$X$2:$CE$2,V$2) -> 0 | W89: 0 | X89: ='UW Model'!$H31-X9 -> 0 | Y89: ='UW Model'!$H31-Y9 -> 0 | Z89: ='UW Model'!$H31-Z9 -> 0 | AA89: ='UW Model'!$H31-AA9 -> 0 | AB89: ='UW Model'!$H31-AB9 -> 0 | AC89: ='UW Model'!$H31-AC9 -> 0 | AD89: ='UW Model'!$H31-AD9 -> 0 | AE89: ='UW Model'!$H31-AE9 -> 0 | ... CE89: ='UW Model'!$H31-CE9 -> 0
Q90: =$Q$10 | R90: =_xlfn.MINIFS($X90:$CE90,$X$2:$CE$2,R$2) -> 0 | S90: =_xlfn.MINIFS($X90:$CE90,$X$2:$CE$2,S$2) -> 0 | T90: =_xlfn.MINIFS($X90:$CE90,$X$2:$CE$2,T$2) -> 0 | U90: =_xlfn.MINIFS($X90:$CE90,$X$2:$CE$2,U$2) -> 0 | V90: =_xlfn.MINIFS($X90:$CE90,$X$2:$CE$2,V$2) -> 0 | W90: 0 | X90: ='UW Model'!$H32-X10 -> 0 | Y90: ='UW Model'!$H32-Y10 -> 0 | Z90: ='UW Model'!$H32-Z10 -> 0 | AA90: ='UW Model'!$H32-AA10 -> 0 | AB90: ='UW Model'!$H32-AB10 -> 0 | AC90: ='UW Model'!$H32-AC10 -> 0 | AD90: ='UW Model'!$H32-AD10 -> 0 | AE90: ='UW Model'!$H32-AE10 -> 0 | ... CE90: ='UW Model'!$H32-CE10 -> 0
Q91: =$Q$11 | R91: =_xlfn.MINIFS($X91:$CE91,$X$2:$CE$2,R$2) -> 0 | S91: =_xlfn.MINIFS($X91:$CE91,$X$2:$CE$2,S$2) -> 0 | T91: =_xlfn.MINIFS($X91:$CE91,$X$2:$CE$2,T$2) -> 0 | U91: =_xlfn.MINIFS($X91:$CE91,$X$2:$CE$2,U$2) -> 0 | V91: =_xlfn.MINIFS($X91:$CE91,$X$2:$CE$2,V$2) -> 0 | W91: 0 | X91: ='UW Model'!$H33-X11 -> 0 | Y91: ='UW Model'!$H33-Y11 -> 0 | Z91: ='UW Model'!$H33-Z11 -> 0 | AA91: ='UW Model'!$H33-AA11 -> 0 | AB91: ='UW Model'!$H33-AB11 -> 0 | AC91: ='UW Model'!$H33-AC11 -> 0 | AD91: ='UW Model'!$H33-AD11 -> 0 | AE91: ='UW Model'!$H33-AE11 -> 0 | ... CE91: ='UW Model'!$H33-CE11 -> 0
Q92: =$Q$12 | R92: =_xlfn.MINIFS($X92:$CE92,$X$2:$CE$2,R$2) -> 0 | S92: =_xlfn.MINIFS($X92:$CE92,$X$2:$CE$2,S$2) -> 0 | T92: =_xlfn.MINIFS($X92:$CE92,$X$2:$CE$2,T$2) -> 0 | U92: =_xlfn.MINIFS($X92:$CE92,$X$2:$CE$2,U$2) -> 0 | V92: =_xlfn.MINIFS($X92:$CE92,$X$2:$CE$2,V$2) -> 0 | W92: 0 | X92: ='UW Model'!$H34-X12 -> 0 | Y92: ='UW Model'!$H34-Y12 -> 0 | Z92: ='UW Model'!$H34-Z12 -> 0 | AA92: ='UW Model'!$H34-AA12 -> 0 | AB92: ='UW Model'!$H34-AB12 -> 0 | AC92: ='UW Model'!$H34-AC12 -> 0 | AD92: ='UW Model'!$H34-AD12 -> 0 | AE92: ='UW Model'!$H34-AE12 -> 0 | ... CE92: ='UW Model'!$H34-CE12 -> 0
Q93: =$Q$13 | R93: =_xlfn.MINIFS($X93:$CE93,$X$2:$CE$2,R$2) -> 0 | S93: =_xlfn.MINIFS($X93:$CE93,$X$2:$CE$2,S$2) -> 0 | T93: =_xlfn.MINIFS($X93:$CE93,$X$2:$CE$2,T$2) -> 0 | U93: =_xlfn.MINIFS($X93:$CE93,$X$2:$CE$2,U$2) -> 0 | V93: =_xlfn.MINIFS($X93:$CE93,$X$2:$CE$2,V$2) -> 0 | W93: 0 | X93: ='UW Model'!$H35-X13 -> 0 | Y93: ='UW Model'!$H35-Y13 -> 0 | Z93: ='UW Model'!$H35-Z13 -> 0 | AA93: ='UW Model'!$H35-AA13 -> 0 | AB93: ='UW Model'!$H35-AB13 -> 0 | AC93: ='UW Model'!$H35-AC13 -> 0 | AD93: ='UW Model'!$H35-AD13 -> 0 | AE93: ='UW Model'!$H35-AE13 -> 0 | ... CE93: ='UW Model'!$H35-CE13 -> 0
Q94: =$Q$14 | R94: =_xlfn.MINIFS($X94:$CE94,$X$2:$CE$2,R$2) -> 0 | S94: =_xlfn.MINIFS($X94:$CE94,$X$2:$CE$2,S$2) -> 0 | T94: =_xlfn.MINIFS($X94:$CE94,$X$2:$CE$2,T$2) -> 0 | U94: =_xlfn.MINIFS($X94:$CE94,$X$2:$CE$2,U$2) -> 0 | V94: =_xlfn.MINIFS($X94:$CE94,$X$2:$CE$2,V$2) -> 0 | W94: 0 | X94: ='UW Model'!$H36-X14 -> 0 | Y94: ='UW Model'!$H36-Y14 -> 0 | Z94: ='UW Model'!$H36-Z14 -> 0 | AA94: ='UW Model'!$H36-AA14 -> 0 | AB94: ='UW Model'!$H36-AB14 -> 0 | AC94: ='UW Model'!$H36-AC14 -> 0 | AD94: ='UW Model'!$H36-AD14 -> 0 | AE94: ='UW Model'!$H36-AE14 -> 0 | ... CE94: ='UW Model'!$H36-CE14 -> 0
Q95: =$Q$15 | R95: =_xlfn.MINIFS($X95:$CE95,$X$2:$CE$2,R$2) -> 0 | S95: =_xlfn.MINIFS($X95:$CE95,$X$2:$CE$2,S$2) -> 0 | T95: =_xlfn.MINIFS($X95:$CE95,$X$2:$CE$2,T$2) -> 0 | U95: =_xlfn.MINIFS($X95:$CE95,$X$2:$CE$2,U$2) -> 0 | V95: =_xlfn.MINIFS($X95:$CE95,$X$2:$CE$2,V$2) -> 0 | W95: 0 | X95: ='UW Model'!$H37-X15 -> 0 | Y95: ='UW Model'!$H37-Y15 -> 0 | Z95: ='UW Model'!$H37-Z15 -> 0 | AA95: ='UW Model'!$H37-AA15 -> 0 | AB95: ='UW Model'!$H37-AB15 -> 0 | AC95: ='UW Model'!$H37-AC15 -> 0 | AD95: ='UW Model'!$H37-AD15 -> 0 | AE95: ='UW Model'!$H37-AE15 -> 0 | ... CE95: ='UW Model'!$H37-CE15 -> 0
Q96: =$Q$16 | R96: =_xlfn.MINIFS($X96:$CE96,$X$2:$CE$2,R$2) -> 0 | S96: =_xlfn.MINIFS($X96:$CE96,$X$2:$CE$2,S$2) -> 0 | T96: =_xlfn.MINIFS($X96:$CE96,$X$2:$CE$2,T$2) -> 0 | U96: =_xlfn.MINIFS($X96:$CE96,$X$2:$CE$2,U$2) -> 0 | V96: =_xlfn.MINIFS($X96:$CE96,$X$2:$CE$2,V$2) -> 0 | W96: 0 | X96: ='UW Model'!$H38-X16 -> 0 | Y96: ='UW Model'!$H38-Y16 -> 0 | Z96: ='UW Model'!$H38-Z16 -> 0 | AA96: ='UW Model'!$H38-AA16 -> 0 | AB96: ='UW Model'!$H38-AB16 -> 0 | AC96: ='UW Model'!$H38-AC16 -> 0 | AD96: ='UW Model'!$H38-AD16 -> 0 | AE96: ='UW Model'!$H38-AE16 -> 0 | ... CE96: ='UW Model'!$H38-CE16 -> 0
Q97: =$Q$17 | R97: =_xlfn.MINIFS($X97:$CE97,$X$2:$CE$2,R$2) -> 0 | S97: =_xlfn.MINIFS($X97:$CE97,$X$2:$CE$2,S$2) -> 0 | T97: =_xlfn.MINIFS($X97:$CE97,$X$2:$CE$2,T$2) -> 0 | U97: =_xlfn.MINIFS($X97:$CE97,$X$2:$CE$2,U$2) -> 0 | V97: =_xlfn.MINIFS($X97:$CE97,$X$2:$CE$2,V$2) -> 0 | W97: 0 | X97: ='UW Model'!$H39-X17 -> 0 | Y97: ='UW Model'!$H39-Y17 -> 0 | Z97: ='UW Model'!$H39-Z17 -> 0 | AA97: ='UW Model'!$H39-AA17 -> 0 | AB97: ='UW Model'!$H39-AB17 -> 0 | AC97: ='UW Model'!$H39-AC17 -> 0 | AD97: ='UW Model'!$H39-AD17 -> 0 | AE97: ='UW Model'!$H39-AE17 -> 0 | ... CE97: ='UW Model'!$H39-CE17 -> 0
Q98: =$Q$18 | R98: =_xlfn.MINIFS($X98:$CE98,$X$2:$CE$2,R$2) -> 0 | S98: =_xlfn.MINIFS($X98:$CE98,$X$2:$CE$2,S$2) -> 0 | T98: =_xlfn.MINIFS($X98:$CE98,$X$2:$CE$2,T$2) -> 0 | U98: =_xlfn.MINIFS($X98:$CE98,$X$2:$CE$2,U$2) -> 0 | V98: =_xlfn.MINIFS($X98:$CE98,$X$2:$CE$2,V$2) -> 0 | W98: 0 | X98: ='UW Model'!$H40-X18 -> 0 | Y98: ='UW Model'!$H40-Y18 -> 0 | Z98: ='UW Model'!$H40-Z18 -> 0 | AA98: ='UW Model'!$H40-AA18 -> 0 | AB98: ='UW Model'!$H40-AB18 -> 0 | AC98: ='UW Model'!$H40-AC18 -> 0 | AD98: ='UW Model'!$H40-AD18 -> 0 | AE98: ='UW Model'!$H40-AE18 -> 0 | ... CE98: ='UW Model'!$H40-CE18 -> 0
Q99: =$Q$19 | R99: =_xlfn.MINIFS($X99:$CE99,$X$2:$CE$2,R$2) -> 0 | S99: =_xlfn.MINIFS($X99:$CE99,$X$2:$CE$2,S$2) -> 0 | T99: =_xlfn.MINIFS($X99:$CE99,$X$2:$CE$2,T$2) -> 0 | U99: =_xlfn.MINIFS($X99:$CE99,$X$2:$CE$2,U$2) -> 0 | V99: =_xlfn.MINIFS($X99:$CE99,$X$2:$CE$2,V$2) -> 0 | W99: 0 | X99: ='UW Model'!$H41-X19 -> 0 | Y99: ='UW Model'!$H41-Y19 -> 0 | Z99: ='UW Model'!$H41-Z19 -> 0 | AA99: ='UW Model'!$H41-AA19 -> 0 | AB99: ='UW Model'!$H41-AB19 -> 0 | AC99: ='UW Model'!$H41-AC19 -> 0 | AD99: ='UW Model'!$H41-AD19 -> 0 | AE99: ='UW Model'!$H41-AE19 -> 0 | ... CE99: ='UW Model'!$H41-CE19 -> 0
Q100: =$Q$20 | R100: =_xlfn.MINIFS($X100:$CE100,$X$2:$CE$2,R$2) -> 0 | S100: =_xlfn.MINIFS($X100:$CE100,$X$2:$CE$2,S$2) -> 0 | T100: =_xlfn.MINIFS($X100:$CE100,$X$2:$CE$2,T$2) -> 0 | U100: =_xlfn.MINIFS($X100:$CE100,$X$2:$CE$2,U$2) -> 0 | V100: =_xlfn.MINIFS($X100:$CE100,$X$2:$CE$2,V$2) -> 0 | W100: 0 | X100: ='UW Model'!$H42-X20 -> 0 | Y100: ='UW Model'!$H42-Y20 -> 0 | Z100: ='UW Model'!$H42-Z20 -> 0 | AA100: ='UW Model'!$H42-AA20 -> 0 | AB100: ='UW Model'!$H42-AB20 -> 0 | AC100: ='UW Model'!$H42-AC20 -> 0 | AD100: ='UW Model'!$H42-AD20 -> 0 | AE100: ='UW Model'!$H42-AE20 -> 0 | ... CE100: ='UW Model'!$H42-CE20 -> 0
Q101: Non Reno Revenue Total | R101: =SUM(R102:R116) -> 0 | S101: =SUM(S102:S116) -> 0 | T101: =SUM(T102:T116) -> 0 | U101: =SUM(U102:U116) -> 0 | V101: =SUM(V102:V116) -> 0 | W101: =SUM(W102:W116) -> 0 | X101: =SUM(X102:X116) -> 0 | Y101: =SUM(Y102:Y116) -> 0 | ... CE101: =SUM(CE102:CE116) -> 0
Q102: =$Q$6 | R102: =SUMIF($X$2:$CE$2,R$2,$X102:$CE102) -> 0 | S102: =SUMIF($X$2:$CE$2,S$2,$X102:$CE102) -> 0 | T102: =SUMIF($X$2:$CE$2,T$2,$X102:$CE102) -> 0 | U102: =SUMIF($X$2:$CE$2,U$2,$X102:$CE102) -> 0 | V102: =SUMIF($X$2:$CE$2,V$2,$X102:$CE102) -> 0 | W102: 0 | X102: =X86*X118 -> 0 | Y102: =Y86*Y118 -> 0 | Z102: =Z86*Z118 -> 0 | AA102: =AA86*AA118 -> 0 | AB102: =AB86*AB118 -> 0 | AC102: =AC86*AC118 -> 0 | AD102: =AD86*AD118 -> 0 | AE102: =AE86*AE118 -> 0 | ... CE102: =CE86*CE118 -> 0
...

Sheet Version
B2: Version | C2: Date | D2: Change Description
B3: 1.01 | C3: 45037 | D3: UW Model tab • Added UW Notes section

Sheet Loans
A1: Primary Loan | R1: Refinance
G2: =IF(G3='UW Model'!$G$20,"SALE", IF(G3='UW Model'!$K$15,"REFI","")) | H2: =IF(H3='UW Model'!$G$20,"SALE", IF(H3='UW Model'!$K$15,"REFI","")) | I2: =IF(I3='UW Model'!$G$20,"SALE", IF(I3='UW Model'!$K$15,"REFI","")) | J2: =IF(J3='UW Model'!$G$20,"SALE", IF(J3='UW Model'!$K$15,"REFI","")) | K2: =IF(K3='UW Model'!$G$20,"SALE", IF(K3='UW Model'!$K$15,"REFI","")) -> SALE | L2: =IF(L3='UW Model'!$G$20,"SALE", IF(L3='UW Model'!$K$15,"REFI","")) | M2: =IF(M3='UW Model'!$G$20,"SALE", IF(M3='UW Model'!$K$15,"REFI","")) | N2: =IF(N3='UW Model'!$G$20,"SALE", IF(N3='UW Model'!$K$15,"REFI","")) | ... P2: =IF(P3='UW Model'!$G$20,"SALE", IF(P3='UW Model'!$K$15,"REFI","")) | T2: Funding Year | U2: ='UW Model'!K15 -> 0 | Z2: =IF(Z3='UW Model'!$G$20,"SALE", IF(Z3='UW Model'!$K$15,"REFI","")) | AA2: =IF(AA3='UW Model'!$G$20,"SALE", IF(AA3='UW Model'!$K$15,"REFI","")) | AB2: =IF(AB3='UW Model'!$G$20,"SALE", IF(AB3='UW Model'!$K$15,"REFI","")) -> SALE | AC2: =IF(AC3='UW Model'!$G$20,"SALE", IF(AC3='UW Model'!$K$15,"REFI","")) | AD2: =IF(AD3='UW Model'!$G$20,"SALE", IF(AD3='UW Model'!$K$15,"REFI","")) | AE2: =IF(AE3='UW Model'!$G$20,"SALE", IF(AE3='UW Model'!$K$15,"REFI","")) | AF2: =IF(AF3='UW Model'!$G$20,"SALE", IF(AF3='UW Model'!$K$15,"REFI","")) | AG2: =IF(AG3='UW Model'!$G$20,"SALE", IF(AG3='UW Model'!$K$15,"REFI",""))
C3: Loan Amount | D3: ='UW Model'!K7 -> 0 | F3: End of Year | G3: 1 | H3: =G3+1 -> 2 | I3: =H3+1 -> 3 | J3: =I3+1 -> 4 | K3: =J3+1 -> 5 | L3: =K3+1 -> 6 | M3: =L3+1 -> 7 | N3: =M3+1 -> 8 | O3: =N3+1 -> 9 | P3: =O3+1 -> 10 | T3: Loan Amount | U3: ='UW Model'!K14 -> 0 | W3: End of Year | X3: 1 | Y3: =X3+1 -> 2 | Z3: =Y3+1 -> 3 | AA3: =Z3+1 -> 4 | AB3: =AA3+1 -> 5 | AC3: =AB3+1 -> 6 | AD3: =AC3+1 -> 7 | AE3: =AD3+1 -> 8 | AF3: =AE3+1 -> 9 | AG3: =AF3+1 -> 10
C4: Interest Rate | D4: ='UW Model'!K9 -> 0 | F4: Principal | G4: =IFERROR(SUMIF($C$18:$C$137,G$3,$G$18:$G$137),0) -> 0 | H4: =IFERROR(SUMIF($C$18:$C$137,H$3,$G$18:$G$137),0) -> 0 | I4: =IFERROR(SUMIF($C$18:$C$137,I$3,$G$18:$G$137),0) -> 0 | J4: =IFERROR(SUMIF($C$18:$C$137,J$3,$G$18:$G$137),0) -> 0 | K4: =IFERROR(SUMIF($C$18:$C$137,K$3,$G$18:$G$137),0) -> 0 | L4: =IFERROR(SUMIF($C$18:$C$137,L$3,$G$18:$G$137),0) -> 0 | M4: =IFERROR(SUMIF($C$18:$C$137,M$3,$G$18:$G$137),0) -> 0 | N4: =IFERROR(SUMIF($C$18:$C$137,N$3,$G$18:$G$137),0) -> 0 | ... P4: =IFERROR(SUMIF($C$18:$C$137,P$3,$G$18:$G$137),0) -> 0 | T4: Interest Rate | U4: ='UW Model'!K17 -> 0.06 | W4: Principal | X4: =SUMIF($T$18:$T$377,X$3,$X$18:$X$377) -> 0 | Y4: =SUMIF($T$18:$T$377,Y$3,$X$18:$X$377) -> 0 | Z4: =SUMIF($T$18:$T$377,Z$3,$X$18:$X$377) -> 0 | AA4: =SUMIF($T$18:$T$377,AA$3,$X$18:$X$377) -> 0 | AB4: =SUMIF($T$18:$T$377,AB$3,$X$18:$X$377) -> 0 | AC4: =SUMIF($T$18:$T$377,AC$3,$X$18:$X$377) -> 0 | AD4: =SUMIF($T$18:$T$377,AD$3,$X$18:$X$377) -> 0 | AE4: =SUMIF($T$18:$T$377,AE$3,$X$18:$X$377) -> 0 | ... AG4: =SUMIF($T$18:$T$377,AG$3,$X$18:$X$377) -> 0
C5: Number of Years | D5: ='UW Model'!K12 -> 30 | F5: Interest | G5: =IFERROR(SUMIF($C$18:$C$137,G$3,$E$18:$E$137),0) -> 0 | H5: =IFERROR(SUMIF($C$18:$C$137,H$3,$E$18:$E$137),0) -> 0 | I5: =IFERROR(SUMIF($C$18:$C$137,I$3,$E$18:$E$137),0) -> 0 | J5: =IFERROR(SUMIF($C$18:$C$137,J$3,$E$18:$E$137),0) -> 0 | K5: =IFERROR(SUMIF($C$18:$C$137,K$3,$E$18:$E$137),0) -> 0 | L5: =IFERROR(SUMIF($C$18:$C$137,L$3,$E$18:$E$137),0) -> 0 | M5: =IFERROR(SUMIF($C$18:$C$137,M$3,$E$18:$E$137),0) -> 0 | N5: =IFERROR(SUMIF($C$18:$C$137,N$3,$E$18:$E$137),0) -> 0 | ... P5: =IFERROR(SUMIF($C$18:$C$137,P$3,$E$18:$E$137),0) -> 0 | T5: Number of Years | U5: ='UW Model'!K20 -> 30 | W5: Interest | X5: =SUMIF($T$18:$T$377,X$3,$V$18:$V$377) -> 0 | Y5: =SUMIF($T$18:$T$377,Y$3,$V$18:$V$377) -> 0 | Z5: =SUMIF($T$18:$T$377,Z$3,$V$18:$V$377) -> 0 | AA5: =SUMIF($T$18:$T$377,AA$3,$V$18:$V$377) -> 0 | AB5: =SUMIF($T$18:$T$377,AB$3,$V$18:$V$377) -> 0 | AC5: =SUMIF($T$18:$T$377,AC$3,$V$18:$V$377) -> 0 | AD5: =SUMIF($T$18:$T$377,AD$3,$V$18:$V$377) -> 0 | AE5: =SUMIF($T$18:$T$377,AE$3,$V$18:$V$377) -> 0 | ... AG5: =SUMIF($T$18:$T$377,AG$3,$V$18:$V$377) -> 0
C6: Interest-Only (Months) | D6: ='UW Model'!K11 -> 0 | E6: PMT(D4/12,(D5*12)-D6,-D3) | F6: Balance | G6: =IFERROR(VLOOKUP(G3*12,$B$16:$I$137,8,0),0) -> 0 | H6: =IFERROR(VLOOKUP(H3*12,$B$16:$I$137,8,0),0) -> 0 | I6: =IFERROR(VLOOKUP(I3*12,$B$16:$I$137,8,0),0) -> 0 | J6: =IFERROR(VLOOKUP(J3*12,$B$16:$I$137,8,0),0) -> 0 | K6: =IFERROR(VLOOKUP(K3*12,$B$16:$I$137,8,0),0) -> 0 | L6: =IFERROR(VLOOKUP(L3*12,$B$16:$I$137,8,0),0) -> 0 | M6: =IFERROR(VLOOKUP(M3*12,$B$16:$I$137,8,0),0) -> 0 | N6: =IFERROR(VLOOKUP(N3*12,$B$16:$I$137,8,0),0) -> 0 | ... P6: =IFERROR(VLOOKUP(P3*12,$B$16:$I$137,8,0),0) -> 0 | T6: Interest-Only (Months) | U6: ='UW Model'!K19 -> 0 | W6: Balance | X6: =IFERROR(INDEX($Z$18:$Z$377,MATCH(X3,$T$18:$T$377,0)+11),0) -> 0 | Y6: =IFERROR(INDEX($Z$18:$Z$377,MATCH(Y3,$T$18:$T$377,0)+11),0) -> 0 | Z6: =IFERROR(INDEX($Z$18:$Z$377,MATCH(Z3,$T$18:$T$377,0)+11),0) -> 0 | AA6: =IFERROR(INDEX($Z$18:$Z$377,MATCH(AA3,$T$18:$T$377,0)+11),0) -> 0 | AB6: =IFERROR(INDEX($Z$18:$Z$377,MATCH(AB3,$T$18:$T$377,0)+11),0) -> 0 | AC6: =IFERROR(INDEX($Z$18:$Z$377,MATCH(AC3,$T$18:$T$377,0)+11),0) -> 0 | AD6: =IFERROR(INDEX($Z$18:$Z$377,MATCH(AD3,$T$18:$T$377,0)+11),0) -> 0 | AE6: =IFERROR(INDEX($Z$18:$Z$377,MATCH(AE3,$T$18:$T$377,0)+11),0) -> 0 | ... AG6: =IFERROR(INDEX($Z$18:$Z$377,MATCH(AG3,$T$18:$T$377,0)+11),0) -> 0
C7: Monthly Payment | D7: =PMT(D4/12,(D5*12),-D3) -> 0 | E7: <- SHOULD Calc add back the missed principle during the IO period in order to pay off loan in 30yrs? Formula above | T7: Monthly Payment | U7: =PMT(U4/12,(U5*12),-U3) -> 0
B16: Month | C16: Year | D16: Payment Amount | E16: Interest | F16: Cumulative Interest | G16: Principal | H16: Principal Paid | I16: Balance | S16: Month | T16: Year | U16: Payment Amount | V16: Interest | W16: Cumulative Interest | X16: Principal | Y16: Principal Paid | Z16: Balance
I17: =D3 -> 0 | Z17: =U3 -> 0
B18: =IF(B17>=$D$5*12+$D$6,"",B17+1) -> 1 | C18: =ROUNDUP(B18/12,0) -> 1 | D18: =IF(B18="","-",IF(B18<=$D$6,E18, $D$7)) -> 0 | E18: =IF(B18="","-",$D$4/12*I17) -> 0 | F18: =IF(B18="","-",SUM($E$18:E18)) -> 0 | G18: =IF(B18="","-",D18-E18) -> 0 | H18: =IF(B18="","-",SUM($G$18:G18)) -> 0 | I18: =IF(B18="","-",I17-G18) -> 0 | S18: =IF(S17>=$U$5*12+$U$6,"",S17+1) -> 1 | T18: =ROUNDUP(S18/12,0)+$U$2 -> 1 | U18: =IF(S18="","-",IF(S18<=$U$6,V18, $U$7)) -> 0 | V18: =IF(S18="","-",$U$4/12*Z17) -> 0 | W18: =IF(S18="","-",SUM($V$18:V18)) -> 0 | X18: =IF(S18="","-",U18-V18) -> 0 | Y18: =IF(S18="","-",SUM($X$18:X18)) -> 0 | Z18: =IF(S18="","-",Z17-X18) -> 0
B19: =IF(B18>=$D$5*12+$D$6,"",B18+1) -> 2 | C19: =ROUNDUP(B19/12,0) -> 1 | D19: =IF(B19="","-",IF(B19<=$D$6,E19, $D$7)) -> 0 | E19: =IF(B19="","-",$D$4/12*I18) -> 0 | F19: =IF(B19="","-",SUM($E$18:E19)) -> 0 | G19: =IF(B19="","-",D19-E19) -> 0 | H19: =IF(B19="","-",SUM($G$18:G19)) -> 0 | I19: =IF(B19="","-",I18-G19) -> 0 | S19: =IF(S18>=$U$5*12+$U$6,"",S18+1) -> 2 | T19: =ROUNDUP(S19/12,0)+$U$2 -> 1 | U19: =IF(S19="","-",IF(S19<=$U$6,V19, $U$7)) -> 0 | V19: =IF(S19="","-",$U$4/12*Z18) -> 0 | W19: =IF(S19="","-",SUM($V$18:V19)) -> 0 | X19: =IF(S19="","-",U19-V19) -> 0 | Y19: =IF(S19="","-",SUM($X$18:X19)) -> 0 | Z19: =IF(S19="","-",Z18-X19) -> 0
B20: =IF(B19>=$D$5*12+$D$6,"",B19+1) -> 3 | C20: =ROUNDUP(B20/12,0) -> 1 | D20: =IF(B20="","-",IF(B20<=$D$6,E20, $D$7)) -> 0 | E20: =IF(B20="","-",$D$4/12*I19) -> 0 | F20: =IF(B20="","-",SUM($E$18:E20)) -> 0 | G20: =IF(B20="","-",D20-E20) -> 0 | H20: =IF(B20="","-",SUM($G$18:G20)) -> 0 | I20: =IF(B20="","-",I19-G20) -> 0 | S20: =IF(S19>=$U$5*12+$U$6,"",S19+1) -> 3 | T20: =ROUNDUP(S20/12,0)+$U$2 -> 1 | U20: =IF(S20="","-",IF(S20<=$U$6,V20, $U$7)) -> 0 | V20: =IF(S20="","-",$U$4/12*Z19) -> 0 | W20: =IF(S20="","-",SUM($V$18:V20)) -> 0 | X20: =IF(S20="","-",U20-V20) -> 0 | Y20: =IF(S20="","-",SUM($X$18:X20)) -> 0 | Z20: =IF(S20="","-",Z19-X20) -> 0
B21: =IF(B20>=$D$5*12+$D$6,"",B20+1) -> 4 | C21: =ROUNDUP(B21/12,0) -> 1 | D21: =IF(B21="","-",IF(B21<=$D$6,E21, $D$7)) -> 0 | E21: =IF(B21="","-",$D$4/12*I20) -> 0 | F21: =IF(B21="","-",SUM($E$18:E21)) -> 0 | G21: =IF(B21="","-",D21-E21) -> 0 | H21: =IF(B21="","-",SUM($G$18:G21)) -> 0 | I21: =IF(B21="","-",I20-G21) -> 0 | S21: =IF(S20>=$U$5*12+$U$6,"",S20+1) -> 4 | T21: =ROUNDUP(S21/12,0)+$U$2 -> 1 | U21: =IF(S21="","-",IF(S21<=$U$6,V21, $U$7)) -> 0 | V21: =IF(S21="","-",$U$4/12*Z20) -> 0 | W21: =IF(S21="","-",SUM($V$18:V21)) -> 0 | X21: =IF(S21="","-",U21-V21) -> 0 | Y21: =IF(S21="","-",SUM($X$18:X21)) -> 0 | Z21: =IF(S21="","-",Z20-X21) -> 0
B22: =IF(B21>=$D$5*12+$D$6,"",B21+1) -> 5 | C22: =ROUNDUP(B22/12,0) -> 1 | D22: =IF(B22="","-",IF(B22<=$D$6,E22, $D$7)) -> 0 | E22: =IF(B22="","-",$D$4/12*I21) -> 0 | F22: =IF(B22="","-",SUM($E$18:E22)) -> 0 | G22: =IF(B22="","-",D22-E22) -> 0 | H22: =IF(B22="","-",SUM($G$18:G22)) -> 0 | I22: =IF(B22="","-",I21-G22) -> 0 | S22: =IF(S21>=$U$5*12+$U$6,"",S21+1) -> 5 | T22: =ROUNDUP(S22/12,0)+$U$2 -> 1 | U22: =IF(S22="","-",IF(S22<=$U$6,V22, $U$7)) -> 0 | V22: =IF(S22="","-",$U$4/12*Z21) -> 0 | W22: =IF(S22="","-",SUM($V$18:V22)) -> 0 | X22: =IF(S22="","-",U22-V22) -> 0 | Y22: =IF(S22="","-",SUM($X$18:X22)) -> 0 | Z22: =IF(S22="","-",Z21-X22) -> 0
B23: =IF(B22>=$D$5*12+$D$6,"",B22+1) -> 6 | C23: =ROUNDUP(B23/12,0) -> 1 | D23: =IF(B23="","-",IF(B23<=$D$6,E23, $D$7)) -> 0 | E23: =IF(B23="","-",$D$4/12*I22) -> 0 | F23: =IF(B23="","-",SUM($E$18:E23)) -> 0 | G23: =IF(B23="","-",D23-E23) -> 0 | H23: =IF(B23="","-",SUM($G$18:G23)) -> 0 | I23: =IF(B23="","-",I22-G23) -> 0 | S23: =IF(S22>=$U$5*12+$U$6,"",S22+1) -> 6 | T23: =ROUNDUP(S23/12,0)+$U$2 -> 1 | U23: =IF(S23="","-",IF(S23<=$U$6,V23, $U$7)) -> 0 | V23: =IF(S23="","-",$U$4/12*Z22) -> 0 | W23: =IF(S23="","-",SUM($V$18:V23)) -> 0 | X23: =IF(S23="","-",U23-V23) -> 0 | Y23: =IF(S23="","-",SUM($X$18:X23)) -> 0 | Z23: =IF(S23="","-",Z22-X23) -> 0
B24: =IF(B23>=$D$5*12+$D$6,"",B23+1) -> 7 | C24: =ROUNDUP(B24/12,0) -> 1 | D24: =IF(B24="","-",IF(B24<=$D$6,E24, $D$7)) -> 0 | E24: =IF(B24="","-",$D$4/12*I23) -> 0 | F24: =IF(B24="","-",SUM($E$18:E24)) -> 0 | G24: =IF(B24="","-",D24-E24) -> 0 | H24: =IF(B24="","-",SUM($G$18:G24)) -> 0 | I24: =IF(B24="","-",I23-G24) -> 0 | S24: =IF(S23>=$U$5*12+$U$6,"",S23+1) -> 7 | T24: =ROUNDUP(S24/12,0)+$U$2 -> 1 | U24: =IF(S24="","-",IF(S24<=$U$6,V24, $U$7)) -> 0 | V24: =IF(S24="","-",$U$4/12*Z23) -> 0 | W24: =IF(S24="","-",SUM($V$18:V24)) -> 0 | X24: =IF(S24="","-",U24-V24) -> 0 | Y24: =IF(S24="","-",SUM($X$18:X24)) -> 0 | Z24: =IF(S24="","-",Z23-X24) -> 0
B25: =IF(B24>=$D$5*12+$D$6,"",B24+1) -> 8 | C25: =ROUNDUP(B25/12,0) -> 1 | D25: =IF(B25="","-",IF(B25<=$D$6,E25, $D$7)) -> 0 | E25: =IF(B25="","-",$D$4/12*I24) -> 0 | F25: =IF(B25="","-",SUM($E$18:E25)) -> 0 | G25: =IF(B25="","-",D25-E25) -> 0 | H25: =IF(B25="","-",SUM($G$18:G25)) -> 0 | I25: =IF(B25="","-",I24-G25) -> 0 | S25: =IF(S24>=$U$5*12+$U$6,"",S24+1) -> 8 | T25: =ROUNDUP(S25/12,0)+$U$2 -> 1 | U25: =IF(S25="","-",IF(S25<=$U$6,V25, $U$7)) -> 0 | V25: =IF(S25="","-",$U$4/12*Z24) -> 0 | W25: =IF(S25="","-",SUM($V$18:V25)) -> 0 | X25: =IF(S25="","-",U25-V25) -> 0 | Y25: =IF(S25="","-",SUM($X$18:X25)) -> 0 | Z25: =IF(S25="","-",Z24-X25) -> 0
B26: =IF(B25>=$D$5*12+$D$6,"",B25+1) -> 9 | C26: =ROUNDUP(B26/12,0) -> 1 | D26: =IF(B26="","-",IF(B26<=$D$6,E26, $D$7)) -> 0 | E26: =IF(B26="","-",$D$4/12*I25) -> 0 | F26: =IF(B26="","-",SUM($E$18:E26)) -> 0 | G26: =IF(B26="","-",D26-E26) -> 0 | H26: =IF(B26="","-",SUM($G$18:G26)) -> 0 | I26: =IF(B26="","-",I25-G26) -> 0 | S26: =IF(S25>=$U$5*12+$U$6,"",S25+1) -> 9 | T26: =ROUNDUP(S26/12,0)+$U$2 -> 1 | U26: =IF(S26="","-",IF(S26<=$U$6,V26, $U$7)) -> 0 | V26: =IF(S26="","-",$U$4/12*Z25) -> 0 | W26: =IF(S26="","-",SUM($V$18:V26)) -> 0 | X26: =IF(S26="","-",U26-V26) -> 0 | Y26: =IF(S26="","-",SUM($X$18:X26)) -> 0 | Z26: =IF(S26="","-",Z25-X26) -> 0
B27: =IF(B26>=$D$5*12+$D$6,"",B26+1) -> 10 | C27: =ROUNDUP(B27/12,0) -> 1 | D27: =IF(B27="","-",IF(B27<=$D$6,E27, $D$7)) -> 0 | E27: =IF(B27="","-",$D$4/12*I26) -> 0 | F27: =IF(B27="","-",SUM($E$18:E27)) -> 0 | G27: =IF(B27="","-",D27-E27) -> 0 | H27: =IF(B27="","-",SUM($G$18:G27)) -> 0 | I27: =IF(B27="","-",I26-G27) -> 0 | S27: =IF(S26>=$U$5*12+$U$6,"",S26+1) -> 10 | T27: =ROUNDUP(S27/12,0)+$U$2 -> 1 | U27: =IF(S27="","-",IF(S27<=$U$6,V27, $U$7)) -> 0 | V27: =IF(S27="","-",$U$4/12*Z26) -> 0 | W27: =IF(S27="","-",SUM($V$18:V27)) -> 0 | X27: =IF(S27="","-",U27-V27) -> 0 | Y27: =IF(S27="","-",SUM($X$18:X27)) -> 0 | Z27: =IF(S27="","-",Z26-X27) -> 0
B28: =IF(B27>=$D$5*12+$D$6,"",B27+1) -> 11 | C28: =ROUNDUP(B28/12,0) -> 1 | D28: =IF(B28="","-",IF(B28<=$D$6,E28, $D$7)) -> 0 | E28: =IF(B28="","-",$D$4/12*I27) -> 0 | F28: =IF(B28="","-",SUM($E$18:E28)) -> 0 | G28: =IF(B28="","-",D28-E28) -> 0 | H28: =IF(B28="","-",SUM($G$18:G28)) -> 0 | I28: =IF(B28="","-",I27-G28) -> 0 | S28: =IF(S27>=$U$5*12+$U$6,"",S27+1) -> 11 | T28: =ROUNDUP(S28/12,0)+$U$2 -> 1 | U28: =IF(S28="","-",IF(S28<=$U$6,V28, $U$7)) -> 0 | V28: =IF(S28="","-",$U$4/12*Z27) -> 0 | W28: =IF(S28="","-",SUM($V$18:V28)) -> 0 | X28: =IF(S28="","-",U28-V28) -> 0 | Y28: =IF(S28="","-",SUM($X$18:X28)) -> 0 | Z28: =IF(S28="","-",Z27-X28) -> 0
B29: =IF(B28>=$D$5*12+$D$6,"",B28+1) -> 12 | C29: =ROUNDUP(B29/12,0) -> 1 | D29: =IF(B29="","-",IF(B29<=$D$6,E29, $D$7)) -> 0 | E29: =IF(B29="","-",$D$4/12*I28) -> 0 | F29: =IF(B29="","-",SUM($E$18:E29)) -> 0 | G29: =IF(B29="","-",D29-E29) -> 0 | H29: =IF(B29="","-",SUM($G$18:G29)) -> 0 | I29: =IF(B29="","-",I28-G29) -> 0 | S29: =IF(S28>=$U$5*12+$U$6,"",S28+1) -> 12 | T29: =ROUNDUP(S29/12,0)+$U$2 -> 1 | U29: =IF(S29="","-",IF(S29<=$U$6,V29, $U$7)) -> 0 | V29: =IF(S29="","-",$U$4/12*Z28) -> 0 | W29: =IF(S29="","-",SUM($V$18:V29)) -> 0 | X29: =IF(S29="","-",U29-V29) -> 0 | Y29: =IF(S29="","-",SUM($X$18:X29)) -> 0 | Z29: =IF(S29="","-",Z28-X29) -> 0
B30: =IF(B29>=$D$5*12,"",B29+1) -> 13 | C30: =ROUNDUP(B30/12,0) -> 2 | D30: =IF(B30="","-",IF(B30<=$D$6,E30, $D$7)) -> 0 | E30: =IF(B30="","-",$D$4/12*I29) -> 0 | F30: =IF(B30="","-",SUM($E$18:E30)) -> 0 | G30: =IF(B30="","-",D30-E30) -> 0 | H30: =IF(B30="","-",SUM($G$18:G30)) -> 0 | I30: =IF(B30="","-",I29-G30) -> 0 | S30: =IF(S29>=$U$5*12+$U$6,"",S29+1) -> 13 | T30: =ROUNDUP(S30/12,0)+$U$2 -> 2 | U30: =IF(S30="","-",IF(S30<=$U$6,V30, $U$7)) -> 0 | V30: =IF(S30="","-",$U$4/12*Z29) -> 0 | W30: =IF(S30="","-",SUM($V$18:V30)) -> 0 | X30: =IF(S30="","-",U30-V30) -> 0 | Y30: =IF(S30="","-",SUM($X$18:X30)) -> 0 | Z30: =IF(S30="","-",Z29-X30) -> 0
B31: =IF(B30>=$D$5*12,"",B30+1) -> 14 | C31: =ROUNDUP(B31/12,0) -> 2 | D31: =IF(B31="","-",IF(B31<=$D$6,E31, $D$7)) -> 0 | E31: =IF(B31="","-",$D$4/12*I30) -> 0 | F31: =IF(B31="","-",SUM($E$18:E31)) -> 0 | G31: =IF(B31="","-",D31-E31) -> 0 | H31: =IF(B31="","-",SUM($G$18:G31)) -> 0 | I31: =IF(B31="","-",I30-G31) -> 0 | S31: =IF(S30>=$U$5*12+$U$6,"",S30+1) -> 14 | T31: =ROUNDUP(S31/12,0)+$U$2 -> 2 | U31: =IF(S31="","-",IF(S31<=$U$6,V31, $U$7)) -> 0 | V31: =IF(S31="","-",$U$4/12*Z30) -> 0 | W31: =IF(S31="","-",SUM($V$18:V31)) -> 0 | X31: =IF(S31="","-",U31-V31) -> 0 | Y31: =IF(S31="","-",SUM($X$18:X31)) -> 0 | Z31: =IF(S31="","-",Z30-X31) -> 0
B32: =IF(B31>=$D$5*12,"",B31+1) -> 15 | C32: =ROUNDUP(B32/12,0) -> 2 | D32: =IF(B32="","-",IF(B32<=$D$6,E32, $D$7)) -> 0 | E32: =IF(B32="","-",$D$4/12*I31) -> 0 | F32: =IF(B32="","-",SUM($E$18:E32)) -> 0 | G32: =IF(B32="","-",D32-E32) -> 0 | H32: =IF(B32="","-",SUM($G$18:G32)) -> 0 | I32: =IF(B32="","-",I31-G32) -> 0 | S32: =IF(S31>=$U$5*12+$U$6,"",S31+1) -> 15 | T32: =ROUNDUP(S32/12,0)+$U$2 -> 2 | U32: =IF(S32="","-",IF(S32<=$U$6,V32, $U$7)) -> 0 | V32: =IF(S32="","-",$U$4/12*Z31) -> 0 | W32: =IF(S32="","-",SUM($V$18:V32)) -> 0 | X32: =IF(S32="","-",U32-V32) -> 0 | Y32: =IF(S32="","-",SUM($X$18:X32)) -> 0 | Z32: =IF(S32="","-",Z31-X32) -> 0
B33: =IF(B32>=$D$5*12,"",B32+1) -> 16 | C33: =ROUNDUP(B33/12,0) -> 2 | D33: =IF(B33="","-",IF(B33<=$D$6,E33, $D$7)) -> 0 | E33: =IF(B33="","-",$D$4/12*I32) -> 0 | F33: =IF(B33="","-",SUM($E$18:E33)) -> 0 | G33: =IF(B33="","-",D33-E33) -> 0 | H33: =IF(B33="","-",SUM($G$18:G33)) -> 0 | I33: =IF(B33="","-",I32-G33) -> 0 | S33: =IF(S32>=$U$5*12+$U$6,"",S32+1) -> 16 | T33: =ROUNDUP(S33/12,0)+$U$2 -> 2 | U33: =IF(S33="","-",IF(S33<=$U$6,V33, $U$7)) -> 0 | V33: =IF(S33="","-",$U$4/12*Z32) -> 0 | W33: =IF(S33="","-",SUM($V$18:V33)) -> 0 | X33: =IF(S33="","-",U33-V33) -> 0 | Y33: =IF(S33="","-",SUM($X$18:X33)) -> 0 | Z33: =IF(S33="","-",Z32-X33) -> 0
B34: =IF(B33>=$D$5*12,"",B33+1) -> 17 | C34: =ROUNDUP(B34/12,0) -> 2 | D34: =IF(B34="","-",IF(B34<=$D$6,E34, $D$7)) -> 0 | E34: =IF(B34="","-",$D$4/12*I33) -> 0 | F34: =IF(B34="","-",SUM($E$18:E34)) -> 0 | G34: =IF(B34="","-",D34-E34) -> 0 | H34: =IF(B34="","-",SUM($G$18:G34)) -> 0 | I34: =IF(B34="","-",I33-G34) -> 0 | S34: =IF(S33>=$U$5*12+$U$6,"",S33+1) -> 17 | T34: =ROUNDUP(S34/12,0)+$U$2 -> 2 | U34: =IF(S34="","-",IF(S34<=$U$6,V34, $U$7)) -> 0 | V34: =IF(S34="","-",$U$4/12*Z33) -> 0 | W34: =IF(S34="","-",SUM($V$18:V34)) -> 0 | X34: =IF(S34="","-",U34-V34) -> 0 | Y34: =IF(S34="","-",SUM($X$18:X34)) -> 0 | Z34: =IF(S34="","-",Z33-X34) -> 0
B35: =IF(B34>=$D$5*12,"",B34+1) -> 18 | C35: =ROUNDUP(B35/12,0) -> 2 | D35: =IF(B35="","-",IF(B35<=$D$6,E35, $D$7)) -> 0 | E35: =IF(B35="","-",$D$4/12*I34) -> 0 | F35: =IF(B35="","-",SUM($E$18:E35)) -> 0 | G35: =IF(B35="","-",D35-E35) -> 0 | H35: =IF(B35="","-",SUM($G$18:G35)) -> 0 | I35: =IF(B35="","-",I34-G35) -> 0 | S35: =IF(S34>=$U$5*12+$U$6,"",S34+1) -> 18 | T35: =ROUNDUP(S35/12,0)+$U$2 -> 2 | U35: =IF(S35="","-",IF(S35<=$U$6,V35, $U$7)) -> 0 | V35: =IF(S35="","-",$U$4/12*Z34) -> 0 | W35: =IF(S35="","-",SUM($V$18:V35)) -> 0 | X35: =IF(S35="","-",U35-V35) -> 0 | Y35: =IF(S35="","-",SUM($X$18:X35)) -> 0 | Z35: =IF(S35="","-",Z34-X35) -> 0
B36: =IF(B35>=$D$5*12,"",B35+1) -> 19 | C36: =ROUNDUP(B36/12,0) -> 2 | D36: =IF(B36="","-",IF(B36<=$D$6,E36, $D$7)) -> 0 | E36: =IF(B36="","-",$D$4/12*I35) -> 0 | F36: =IF(B36="","-",SUM($E$18:E36)) -> 0 | G36: =IF(B36="","-",D36-E36) -> 0 | H36: =IF(B36="","-",SUM($G$18:G36)) -> 0 | I36: =IF(B36="","-",I35-G36) -> 0 | S36: =IF(S35>=$U$5*12+$U$6,"",S35+1) -> 19 | T36: =ROUNDUP(S36/12,0)+$U$2 -> 2 | U36: =IF(S36="","-",IF(S36<=$U$6,V36, $U$7)) -> 0 | V36: =IF(S36="","-",$U$4/12*Z35) -> 0 | W36: =IF(S36="","-",SUM($V$18:V36)) -> 0 | X36: =IF(S36="","-",U36-V36) -> 0 | Y36: =IF(S36="","-",SUM($X$18:X36)) -> 0 | Z36: =IF(S36="","-",Z35-X36) -> 0
B37: =IF(B36>=$D$5*12,"",B36+1) -> 20 | C37: =ROUNDUP(B37/12,0) -> 2 | D37: =IF(B37="","-",IF(B37<=$D$6,E37, $D$7)) -> 0 | E37: =IF(B37="","-",$D$4/12*I36) -> 0 | F37: =IF(B37="","-",SUM($E$18:E37)) -> 0 | G37: =IF(B37="","-",D37-E37) -> 0 | H37: =IF(B37="","-",SUM($G$18:G37)) -> 0 | I37: =IF(B37="","-",I36-G37) -> 0 | S37: =IF(S36>=$U$5*12+$U$6,"",S36+1) -> 20 | T37: =ROUNDUP(S37/12,0)+$U$2 -> 2 | U37: =IF(S37="","-",IF(S37<=$U$6,V37, $U$7)) -> 0 | V37: =IF(S37="","-",$U$4/12*Z36) -> 0 | W37: =IF(S37="","-",SUM($V$18:V37)) -> 0 | X37: =IF(S37="","-",U37-V37) -> 0 | Y37: =IF(S37="","-",SUM($X$18:X37)) -> 0 | Z37: =IF(S37="","-",Z36-X37) -> 0
B38: =IF(B37>=$D$5*12,"",B37+1) -> 21 | C38: =ROUNDUP(B38/12,0) -> 2 | D38: =IF(B38="","-",IF(B38<=$D$6,E38, $D$7)) -> 0 | E38: =IF(B38="","-",$D$4/12*I37) -> 0 | F38: =IF(B38="","-",SUM($E$18:E38)) -> 0 | G38: =IF(B38="","-",D38-E38) -> 0 | H38: =IF(B38="","-",SUM($G$18:G38)) -> 0 | I38: =IF(B38="","-",I37-G38) -> 0 | S38: =IF(S37>=$U$5*12+$U$6,"",S37+1) -> 21 | T38: =ROUNDUP(S38/12,0)+$U$2 -> 2 | U38: =IF(S38="","-",IF(S38<=$U$6,V38, $U$7)) -> 0 | V38: =IF(S38="","-",$U$4/12*Z37) -> 0 | W38: =IF(S38="","-",SUM($V$18:V38)) -> 0 | X38: =IF(S38="","-",U38-V38) -> 0 | Y38: =IF(S38="","-",SUM($X$18:X38)) -> 0 | Z38: =IF(S38="","-",Z37-X38) -> 0
B39: =IF(B38>=$D$5*12,"",B38+1) -> 22 | C39: =ROUNDUP(B39/12,0) -> 2 | D39: =IF(B39="","-",IF(B39<=$D$6,E39, $D$7)) -> 0 | E39: =IF(B39="","-",$D$4/12*I38) -> 0 | F39: =IF(B39="","-",SUM($E$18:E39)) -> 0 | G39: =IF(B39="","-",D39-E39) -> 0 | H39: =IF(B39="","-",SUM($G$18:G39)) -> 0 | I39: =IF(B39="","-",I38-G39) -> 0 | S39: =IF(S38>=$U$5*12+$U$6,"",S38+1) -> 22 | T39: =ROUNDUP(S39/12,0)+$U$2 -> 2 | U39: =IF(S39="","-",IF(S39<=$U$6,V39, $U$7)) -> 0 | V39: =IF(S39="","-",$U$4/12*Z38) -> 0 | W39: =IF(S39="","-",SUM($V$18:V39)) -> 0 | X39: =IF(S39="","-",U39-V39) -> 0 | Y39: =IF(S39="","-",SUM($X$18:X39)) -> 0 | Z39: =IF(S39="","-",Z38-X39) -> 0
B40: =IF(B39>=$D$5*12,"",B39+1) -> 23 | C40: =ROUNDUP(B40/12,0) -> 2 | D40: =IF(B40="","-",IF(B40<=$D$6,E40, $D$7)) -> 0 | E40: =IF(B40="","-",$D$4/12*I39) -> 0 | F40: =IF(B40="","-",SUM($E$18:E40)) -> 0 | G40: =IF(B40="","-",D40-E40) -> 0 | H40: =IF(B40="","-",SUM($G$18:G40)) -> 0 | I40: =IF(B40="","-",I39-G40) -> 0 | S40: =IF(S39>=$U$5*12+$U$6,"",S39+1) -> 23 | T40: =ROUNDUP(S40/12,0)+$U$2 -> 2 | U40: =IF(S40="","-",IF(S40<=$U$6,V40, $U$7)) -> 0 | V40: =IF(S40="","-",$U$4/12*Z39) -> 0 | W40: =IF(S40="","-",SUM($V$18:V40)) -> 0 | X40: =IF(S40="","-",U40-V40) -> 0 | Y40: =IF(S40="","-",SUM($X$18:X40)) -> 0 | Z40: =IF(S40="","-",Z39-X40) -> 0
B41: =IF(B40>=$D$5*12,"",B40+1) -> 24 | C41: =ROUNDUP(B41/12,0) -> 2 | D41: =IF(B41="","-",IF(B41<=$D$6,E41, $D$7)) -> 0 | E41: =IF(B41="","-",$D$4/12*I40) -> 0 | F41: =IF(B41="","-",SUM($E$18:E41)) -> 0 | G41: =IF(B41="","-",D41-E41) -> 0 | H41: =IF(B41="","-",SUM($G$18:G41)) -> 0 | I41: =IF(B41="","-",I40-G41) -> 0 | S41: =IF(S40>=$U$5*12+$U$6,"",S40+1) -> 24 | T41: =ROUNDUP(S41/12,0)+$U$2 -> 2 | U41: =IF(S41="","-",IF(S41<=$U$6,V41, $U$7)) -> 0 | V41: =IF(S41="","-",$U$4/12*Z40) -> 0 | W41: =IF(S41="","-",SUM($V$18:V41)) -> 0 | X41: =IF(S41="","-",U41-V41) -> 0 | Y41: =IF(S41="","-",SUM($X$18:X41)) -> 0 | Z41: =IF(S41="","-",Z40-X41) -> 0
... B137: =IF(B136>=$D$5*12,"",B136+1) -> 120 | C137: =ROUNDUP(B137/12,0) -> 10 | D137: =IF(B137="","-",IF(B137<=$D$6,E137, $D$7)) -> 0 | E137: =IF(B137="","-",$D$4/12*I136) -> 0 | F137: =IF(B137="","-",SUM($E$18:E137)) -> 0 | G137: =IF(B137="","-",D137-E137) -> 0 | H137: =IF(B137="","-",SUM($G$18:G137)) -> 0 | I137: =IF(B137="","-",I136-G137) -> 0 | S137: =IF(S136>=$U$5*12+$U$6,"",S136+1) -> 120 | T137: =ROUNDUP(S137/12,0)+$U$2 -> 10 | U137: =IF(S137="","-",IF(S137<=$U$6,V137, $U$7)) -> 0 | V137: =IF(S137="","-",$U$4/12*Z136) -> 0 | W137: =IF(S137="","-",SUM($V$18:V137)) -> 0 | X137: =IF(S137="","-",U137-V137) -> 0 | Y137: =IF(S137="","-",SUM($X$18:X137)) -> 0 | Z137: =IF(S137="","-",Z136-X137) -> 0
