Workbook

Sheet Author
O2: <<< Click Logo to visit the Tactica website
P5: Learn How To Use This Spreadsheet:
P6: https://www.tacticares.com/blog-feed/multifamily-apartment-proforma-excel-template
C18: Disclaimer: Workbook may contain errors and inaccuracies. Please verify formulas, calculations and logic for yourself. The workbook is meant to be utilized as a learning tool and should not be depended on when making financial decisions and assessing the feasibility of an investment.
C20: This template contains affiliate links and we may earn a commission if you transact with our affiliate patners.
C23: Please pay attention to your emails from Tactica RES as there will be updates on bug fixes, improved functionality, and new proforma models.
C28: Copyright © 2023 Tactica RES LLC. All Rights Reserved.

Sheet Summary
B2: General Property Information
B3: Name: | C3: - | E3: Address: | F3: -
B4: Units: | C4: ='Unit Mix'!C10 -> 0 | E4: City/State: | F4: -
B5: ="Total Rentable " &IF($F$7="U.S.","SF","SM")&":" -> Total Rentable SF: | C5: =C6*C4 -> #DIV/0! | E5: Parking Spaces: | F5: 0
B6: ="Avg. " &IF($F$7="U.S.","SF ","SM ")&"Per Unit:" -> Avg. SF Per Unit: | C6: ='Unit Mix'!D10 -> #DIV/0! | E6: Parking Ratio: | F6: =F5/C4 -> #DIV/0!
B7: Occupancy: | C7: ='Unit Mix'!L2/Summary!C4 -> #DIV/0! | E7: Measurement: | F7: U.S.
B9: Pricing | E9: Closing/Residual Assumptions
B10: Price: | C10: 0
B11: Price Per Unit: | C11: =C10/C4 -> #DIV/0! | E11: Escrow/Closing Costs (Year 0) | F11: 0
B12: ="Price Per " &IF($F$7="U.S.","SF","SM")&":" -> Price Per SF: | C12: =C10/C5 -> #DIV/0!
B13: Hold Period (Years): | C13: 5 | E13: Stabilized Cap Today: | F13: 0
B14: Leveraged IRR: | C14: =SUMIF(Valuation!$G$1:$P$1,Summary!$C$13,Valuation!$G$57:$P$57) -> #VALUE! | E14: Increment/Yr: | F14: 0
B15: Equity Multiple: | C15: =SUMIF(Valuation!$G$1:$P$1,Summary!$C$13,Valuation!$G$69:$P$69) -> #NUM!
B16: Cap Rates | E16: Brokerage Commission: | F16: 0
B17: T3/T12: | C17: =VLOOKUP(B17,Valuation!$E$8:$F$13,2,FALSE) -> #DIV/0! | E17: Other Closing Costs Upon Sale: | F17: 0
B18: FY1: | C18: =VLOOKUP(B18,Valuation!$E$8:$F$13,2,FALSE) -> #VALUE! | E18: Total Residual Sale Cost: | F18: =F17+F16 -> 0
B19: FY1 Adjusted: Post-Sale RE Tax: | C19: =VLOOKUP(B19,Valuation!$E$8:$F$13,2,FALSE) -> #VALUE!
B21: Financing Loan 1 | E21: Residual Assumptions
B22: Debt Name: | C22: - | E22: Residual NOI: | F22: =SUMIF(Valuation!$G$1:$P$1,Summary!$C$13,Valuation!$G$19:$P$19) -> #VALUE!
B23: LTV: | C23: 0 | E23: Residual Cap Rate: | F23: =SUMIF(Valuation!$G$1:$P$1,Summary!$C$13,Valuation!$G$36:$P$36) -> 0
B24: Loan Amount: | C24: =C23*C10 -> 0 | E24: Residual Sales Price: | F24: =SUMIF(Valuation!$G$1:$P$1,Summary!$C$13,Valuation!$G$37:$P$37) -> #VALUE!
B25: Int. Rate: | C25: 0 | E25: Residual Sales Price Per Unit: | F25: =F24/$C$4 -> #VALUE!
B26: Term: | C26: 0 | E26: Residual Sales Price Per SF: | F26: =F24/$C$5 -> #VALUE!
B27: Amortization: | C27: 0 | E27: Projected Aggregate Appreciation: | F27: =F24/C10-1 -> #VALUE!
B28: Loan Cost: | C28: 0 | E28: Projected Appreciation Annualized: | F28: =RATE(C13,,-C10,F24,,) -> #VALUE!
B29: Interest Only Months: | C29: 0
B30: Assumption? | C30: Yes | E30: Loan Paydown: | F30: =SUMIF(Valuation!$G$1:$P$1,Summary!$C$13,Valuation!$G$40:$P$40)+SUMIF(Valuation!$G$1:$P$1,Summary!$C$13,Valuation!$G$42:$P$42) -> #NUM!
B31: Assumption Month: | C31: 0 | E31: Sale Cost: | F31: =SUMIF(Valuation!$G$1:$P$1,Summary!$C$13,Valuation!$G$38:$P$38) -> #VALUE!
E32: Total Sales Proceeds: | F32: =F31+F30+F24 -> #VALUE!
B33: Financing Loan 2
B34: Debt Name: | C34: 0
B35: LTV: | C35: 0
B36: Loan Amount: | C36: =C35*C10 -> 0
B37: Int. Rate: | C37: 0
B38: Term: | C38: 0
B39: Amortization: | C39: 0
B40: Loan Cost: | C40: 0
B41: Interest Only Months: | C41: 0
B42: Assumption? | C42: Yes
B43: Assumption Month: | C43: 0

Sheet Unit Mix
K2: Occupied Units: | L2: 0
B3: Type | C3: Unit Count | D3: =IF(Summary!$F$7="U.S.","SF","SM") -> SF | E3: =IF(Summary!$F$7="U.S.","Total SF","Total SM") -> Total SF | F3: Average Rent | G3: =IF(Summary!$F$7="U.S.","Avg. Rent PSF","Avg. Rent PSM") -> Avg. Rent PSF | H3: Monthly Rent | K3: Vacant Units: | L3: =C10-L2 -> 0
B4: Studio | C4: 0 | D4: 0 | E4: =D4*C4 -> 0 | F4: 0 | G4: =F4/D4 -> #DIV/0! | H4: =F4*C4 -> 0
B5: One BR | C5: 0 | D5: 0 | E5: =D5*C5 -> 0 | F5: 0 | G5: =F5/D5 -> #DIV/0! | H5: =F5*C5 -> 0
B6: One BR + Den | C6: 0 | D6: 0 | E6: =D6*C6 -> 0 | F6: 0 | G6: =F6/D6 -> #DIV/0! | H6: =F6*C6 -> 0
B7: Two BR/One BA | C7: 0 | D7: 0 | E7: =D7*C7 -> 0 | F7: 0 | G7: =F7/D7 -> #DIV/0! | H7: =F7*C7 -> 0
B8: Two BR/Two BA | C8: 0 | D8: 0 | E8: =D8*C8 -> 0 | F8: 0 | G8: =F8/D8 -> #DIV/0! | H8: =F8*C8 -> 0
B9: Three BR/Two BA | C9: 0 | D9: 0 | E9: =D9*C9 -> 0 | F9: 0 | G9: =F9/D9 -> #DIV/0! | H9: =F9*C9 -> 0
B10: Total/Avg: | C10: =SUM(C4:C9) -> 0 | D10: =SUMPRODUCT(D4:D9,C4:C9)/C10 -> #DIV/0! | E10: =SUM(E4:E9) -> 0 | F10: =H10/C10 -> #DIV/0! | G10: =F10/D10 -> #DIV/0! | H10: =SUM(H4:H9) -> 0

Sheet Financials
P1: Units: | Q1: ='Unit Mix'!C10 -> 0
P2: =IF(Summary!$F$7="U.S.","Rentable SF","Rentable SM") -> Rentable SF | Q2: ='Unit Mix'!E10 -> 0
C4: Historical Financials | I4: =I5&" Metrics" -> T3/T12 Metrics | M4: Rev/Exp Trends | P4: FY1 Metrics | V4: Assumptions FY1-FY11 | AM4: 10-Year Cashflow
E5: 2021 | F5: 2022 | G5: T12 | H5: T3 | I5: T3/T12 | J5: Per Unit | K5: % GPR or EGI | L5: =IF(Summary!$F$7="U.S.","Per SF","Per SM") -> Per SF | M5: =E5&" to "&F5 -> 2021 to 2022 | N5: =F5&" to "&G5 -> 2022 to T12 | O5: =G5&" to "&H5 -> T12 to T3 | P5: FY1 | Q5: Per Unit | R5: % GPR or EGI | S5: =IF(Summary!$F$7="U.S.","Per SF","Per SM") -> Per SF | T5: =I5& " to FY1" -> T3/T12 to FY1 | W5: ="FY1 %Δ "&I5 -> FY1 %Δ T3/T12 | X5: % GPR or EGI | Y5: Per Unit | Z5: ="FY2 %Δ "&P5 -> FY2 %Δ FY1 | AA5: % GPR or EGI | AB5: Per Unit | AC5: FY3 | AD5: FY4 | AE5: FY5 | AF5: FY6 | AG5: FY7 | AH5: FY8 | AI5: FY9 | AJ5: FY10 | AK5: FY11 | AN5: FY1 | AO5: FY2 | AP5: FY3 | AQ5: FY4 | AR5: FY5 | AS5: FY6 | AT5: FY7 | AU5: FY8 | AV5: FY9 | AW5: FY10 | AX5: FY11
C6: Income | AM6: =IF(C6<>"",C6,D6) -> Income
D7: Gross Potential Rent | I7: =H7*4 -> 0 | J7: =I7/$Q$1 -> #DIV/0! | K7: =I7/$I$7 -> #DIV/0! | L7: =I7/$Q$2 -> #DIV/0! | M7: =IFERROR(F7/E7-1,"") | N7: =IFERROR(G7/F7-1,"") | O7: =IFERROR(I7/G7-1,"") | P7: ='Unit Mix'!H10*12*(1+W7) -> 0 | Q7: =P7/$Q$1 -> #DIV/0! | R7: =P7/$P$7 -> #DIV/0! | S7: =P7/$Q$2 -> #DIV/0! | T7: =IFERROR(P7/I7-1,"") | V7: =IF(C7<>"",C7,D7) -> Gross Potential Rent | X7: over rent roll | AD7: =AC7 -> 0 | AE7: =AD7 -> 0 | AF7: =AE7 -> 0 | AG7: =AF7 -> 0 | AH7: =AG7 -> 0 | AI7: =AH7 -> 0 | AJ7: =AI7 -> 0 | AK7: =AJ7 -> 0 | AM7: =IF(C7<>"",C7,D7) -> Gross Potential Rent | AN7: =P7 -> 0 | AO7: =AN7*(1+Z7) -> 0 | AP7: =AO7*(1+AC7) -> 0 | AQ7: =AP7*(1+AD7) -> 0 | AR7: =AQ7*(1+AE7) -> 0 | AS7: =AR7*(1+AF7) -> 0 | AT7: =AS7*(1+AG7) -> 0 | AU7: =AT7*(1+AH7) -> 0 | AV7: =AU7*(1+AI7) -> 0 | AW7: =AV7*(1+AJ7) -> 0 | AX7: =AW7*(1+AK7) -> 0
D8: Gain (Loss) to Lease | I8: =H8*4 -> 0 | J8: =I8/$Q$1 -> #DIV/0! | K8: =I8/$I$7 -> #DIV/0! | L8: =I8/$Q$2 -> #DIV/0! | M8: =IFERROR(F8/E8-1,"") | N8: =IFERROR(G8/F8-1,"") | O8: =IFERROR(I8/G8-1,"") | P8: 0 | Q8: =P8/$Q$1 -> #DIV/0! | R8: =P8/$P$7 -> #DIV/0! | S8: =P8/$Q$2 -> #DIV/0! | T8: =IFERROR(P8/I8-1,"") | V8: =IF(C8<>"",C8,D8) -> Gain (Loss) to Lease | AD8: =AC8 -> 0 | AE8: =AD8 -> 0 | AF8: =AE8 -> 0 | AG8: =AF8 -> 0 | AH8: =AG8 -> 0 | AI8: =AH8 -> 0 | AJ8: =AI8 -> 0 | AK8: =AJ8 -> 0 | AM8: =IF(C8<>"",C8,D8) -> Gain (Loss) to Lease | AN8: =P8 -> 0 | AO8: =AN8*(1+Z8) -> 0 | AP8: =AO8*(1+AC8) -> 0 | AQ8: =AP8*(1+AD8) -> 0 | AR8: =AQ8*(1+AE8) -> 0 | AS8: =AR8*(1+AF8) -> 0 | AT8: =AS8*(1+AG8) -> 0 | AU8: =AT8*(1+AH8) -> 0 | AV8: =AU8*(1+AI8) -> 0 | AW8: =AV8*(1+AJ8) -> 0 | AX8: =AW8*(1+AK8) -> 0
C9: Total GPR | E9: =SUM(E7:E8) -> 0 | F9: =SUM(F7:F8) -> 0 | G9: =SUM(G7:G8) -> 0 | H9: =SUM(H7:H8) -> 0 | I9: =SUM(I7:I8) -> 0 | J9: =SUM(J7:J8) -> #DIV/0! | K9: =SUM(K7:K8) -> #DIV/0! | L9: =SUM(L7:L8) -> #DIV/0! | M9: =IFERROR(F9/E9-1,"") | N9: =IFERROR(G9/F9-1,"") | O9: =IFERROR(I9/G9-1,"") | P9: =SUM(P7:P8) -> 0 | Q9: =P9/$Q$1 -> #DIV/0! | R9: =P9/$P$7 -> #DIV/0! | S9: =SUM(S7:S8) -> #DIV/0! | T9: =P9/I9-1 -> #DIV/0! | AM9: =IF(C9<>"",C9,D9) -> Total GPR | AN9: =SUM(AN7:AN8) -> 0 | AO9: =SUM(AO7:AO8) -> 0 | AP9: =SUM(AP7:AP8) -> 0 | AQ9: =SUM(AQ7:AQ8) -> 0 | AR9: =SUM(AR7:AR8) -> 0 | AS9: =SUM(AS7:AS8) -> 0 | AT9: =SUM(AT7:AT8) -> 0 | AU9: =SUM(AU7:AU8) -> 0 | ... AX9: =SUM(AX7:AX8) -> 0
D10: Concession | I10: =H10*4 -> 0 | J10: =I10/$Q$1 -> #DIV/0! | K10: =I10/$I$7 -> #DIV/0! | L10: =I10/$Q$2 -> #DIV/0! | M10: =IFERROR(F10/E10-1,"") | N10: =IFERROR(G10/F10-1,"") | O10: =IFERROR(I10/G10-1,"") | P10: =IF(W10<>"",I10*(1+W10),IF(X10<>"",X10*$P$9,Y10*$Q$1)) -> 0 | Q10: =P10/$Q$1 -> #DIV/0! | R10: =P10/$P$7 -> #DIV/0! | S10: =P10/$Q$2 -> #DIV/0! | T10: =IFERROR(P10/I10-1,"") | V10: =IF(C10<>"",C10,D10) -> Concession | AD10: =AC10 -> 0 | AE10: =AD10 -> 0 | AF10: =AE10 -> 0 | AG10: =AF10 -> 0 | AH10: =AG10 -> 0 | AI10: =AH10 -> 0 | AJ10: =AI10 -> 0 | AK10: =AJ10 -> 0 | AM10: =IF(C10<>"",C10,D10) -> Concession | AN10: =P10 -> 0 | AO10: =IF(Z10<>"",AN10*(1+Z10),IF(AA10<>"",AO9*AA10,AB10*$Q$1)) -> 0 | AP10: =AO10*(1+AC10) -> 0 | AQ10: =AP10*(1+AD10) -> 0 | AR10: =AQ10*(1+AE10) -> 0 | AS10: =AR10*(1+AF10) -> 0 | AT10: =AS10*(1+AG10) -> 0 | AU10: =AT10*(1+AH10) -> 0 | AV10: =AU10*(1+AI10) -> 0 | AW10: =AV10*(1+AJ10) -> 0 | AX10: =AW10*(1+AK10) -> 0
D11: Vacancy Loss | I11: =H11*4 -> 0 | J11: =I11/$Q$1 -> #DIV/0! | K11: =I11/$I$7 -> #DIV/0! | L11: =I11/$Q$2 -> #DIV/0! | M11: =IFERROR(F11/E11-1,"") | N11: =IFERROR(G11/F11-1,"") | O11: =IFERROR(I11/G11-1,"") | P11: =IF(W11<>"",I11*(1+W11),IF(X11<>"",X11*$P$9,Y11*$Q$1)) -> 0 | Q11: =P11/$Q$1 -> #DIV/0! | R11: =P11/$P$7 -> #DIV/0! | S11: =P11/$Q$2 -> #DIV/0! | T11: =IFERROR(P11/I11-1,"") | V11: =IF(C11<>"",C11,D11)&"*" -> Vacancy Loss* | AD11: =AC11 -> 0 | AE11: =AD11 -> 0 | AF11: =AE11 -> 0 | AG11: =AF11 -> 0 | AH11: =AG11 -> 0 | AI11: =AH11 -> 0 | AJ11: =AI11 -> 0 | AK11: =AJ11 -> 0 | AM11: =IF(C11<>"",C11,D11) -> Vacancy Loss | AN11: =P11 -> 0 | AO11: =IF(Z11<>"",AN11*(1+Z11),IF(AA11<>"",AO$9*AA11,AB11*$Q$1)) -> 0 | AP11: =AC11*AP$7 -> 0 | AQ11: =AD11*AQ$7 -> 0 | AR11: =AE11*AR$7 -> 0 | AS11: =AF11*AS$7 -> 0 | AT11: =AG11*AT$7 -> 0 | AU11: =AH11*AU$7 -> 0 | AV11: =AI11*AV$7 -> 0 | AW11: =AJ11*AW$7 -> 0 | AX11: =AK11*AX$7 -> 0
D12: Bad Debt | I12: =H12*4 -> 0 | J12: =I12/$Q$1 -> #DIV/0! | K12: =I12/$I$7 -> #DIV/0! | L12: =I12/$Q$2 -> #DIV/0! | M12: =IFERROR(F12/E12-1,"") | N12: =IFERROR(G12/F12-1,"") | O12: =IFERROR(I12/G12-1,"") | P12: =IF(W12<>"",I12*(1+W12),IF(X12<>"",X12*$P$9,Y12*$Q$1)) -> 0 | Q12: =P12/$Q$1 -> #DIV/0! | R12: =P12/$P$7 -> #DIV/0! | S12: =P12/$Q$2 -> #DIV/0! | T12: =IFERROR(P12/I12-1,"") | V12: =IF(C12<>"",C12,D12)&"*" -> Bad Debt* | AD12: =AC12 -> 0 | AE12: =AD12 -> 0 | AF12: =AE12 -> 0 | AG12: =AF12 -> 0 | AH12: =AG12 -> 0 | AI12: =AH12 -> 0 | AJ12: =AI12 -> 0 | AK12: =AJ12 -> 0 | AM12: =IF(C12<>"",C12,D12) -> Bad Debt | AN12: =P12 -> 0 | AO12: =IF(Z12<>"",AN12*(1+Z12),IF(AA12<>"",AO$9*AA12,AB12*$Q$1)) -> 0 | AP12: =AC12*AP$9 -> 0 | AQ12: =AD12*AQ$9 -> 0 | AR12: =AE12*AR$9 -> 0 | AS12: =AF12*AS$9 -> 0 | AT12: =AG12*AT$9 -> 0 | AU12: =AH12*AU$9 -> 0 | AV12: =AI12*AV$9 -> 0 | AW12: =AJ12*AW$9 -> 0 | AX12: =AK12*AX$9 -> 0
C13: Net Effective | E13: =SUM(E9:E12) -> 0 | F13: =SUM(F9:F12) -> 0 | G13: =SUM(G9:G12) -> 0 | H13: =SUM(H9:H12) -> 0 | I13: =SUM(I9:I12) -> 0 | J13: =SUM(J9:J12) -> #DIV/0! | K13: =SUM(K9:K12) -> #DIV/0! | L13: =SUM(L9:L12) -> #DIV/0! | M13: =IFERROR(F13/E13-1,"") | N13: =IFERROR(G13/F13-1,"") | O13: =IFERROR(I13/G13-1,"") | P13: =SUM(P9:P12) -> 0 | Q13: =SUM(Q9:Q12) -> #DIV/0! | R13: =P13/$P$7 -> #DIV/0! | S13: =SUM(S9:S12) -> #DIV/0! | T13: =P13/I13-1 -> #DIV/0! | AM13: =IF(C13<>"",C13,D13) -> Net Effective | AN13: =SUM(AN9:AN12) -> 0 | AO13: =SUM(AO9:AO12) -> 0 | AP13: =SUM(AP9:AP12) -> 0 | AQ13: =SUM(AQ9:AQ12) -> 0 | AR13: =SUM(AR9:AR12) -> 0 | AS13: =SUM(AS9:AS12) -> 0 | AT13: =SUM(AT9:AT12) -> 0 | AU13: =SUM(AU9:AU12) -> 0 | ... AX13: =SUM(AX9:AX12) -> 0
D14: Employee Discounts | I14: =H14*4 -> 0 | J14: =I14/$Q$1 -> #DIV/0! | K14: =I14/$I$7 -> #DIV/0! | L14: =I14/$Q$2 -> #DIV/0! | M14: =IFERROR(F14/E14-1,"") | N14: =IFERROR(G14/F14-1,"") | O14: =IFERROR(I14/G14-1,"") | P14: =IF(W14<>"",I14*(1+W14),IF(X14<>"",X14*$P$9,Y14*$Q$1)) -> 0 | Q14: =P14/$Q$1 -> #DIV/0! | R14: =P14/$P$7 -> #DIV/0! | S14: =P14/$Q$2 -> #DIV/0! | T14: =IFERROR(P14/I14-1,"") | V14: =IF(C14<>"",C14,D14) -> Employee Discounts | AD14: =AC14 -> 0 | AE14: =AD14 -> 0 | AF14: =AE14 -> 0 | AG14: =AF14 -> 0 | AH14: =AG14 -> 0 | AI14: =AH14 -> 0 | AJ14: =AI14 -> 0 | AK14: =AJ14 -> 0 | AM14: =IF(C14<>"",C14,D14) -> Employee Discounts | AN14: =P14 -> 0 | AO14: =IF(Z14<>"",AN14*(1+Z14),IF(AA14<>"",AO$9*AA14,AB14*$Q$1)) -> 0 | AP14: =AO14*(1+AC14) -> 0 | AQ14: =AP14*(1+AD14) -> 0 | AR14: =AQ14*(1+AE14) -> 0 | AS14: =AR14*(1+AF14) -> 0 | AT14: =AS14*(1+AG14) -> 0 | AU14: =AT14*(1+AH14) -> 0 | AV14: =AU14*(1+AI14) -> 0 | AW14: =AV14*(1+AJ14) -> 0 | AX14: =AW14*(1+AK14) -> 0
D15: Model Unit Loss | I15: =H15*4 -> 0 | J15: =I15/$Q$1 -> #DIV/0! | K15: =I15/$I$7 -> #DIV/0! | L15: =I15/$Q$2 -> #DIV/0! | M15: =IFERROR(F15/E15-1,"") | N15: =IFERROR(G15/F15-1,"") | O15: =IFERROR(I15/G15-1,"") | P15: =IF(W15<>"",I15*(1+W15),IF(X15<>"",X15*$P$9,Y15*$Q$1)) -> 0 | Q15: =P15/$Q$1 -> #DIV/0! | R15: =P15/$P$7 -> #DIV/0! | S15: =P15/$Q$2 -> #DIV/0! | T15: =IFERROR(P15/I15-1,"") | V15: =IF(C15<>"",C15,D15) -> Model Unit Loss | AD15: =AC15 -> 0 | AE15: =AD15 -> 0 | AF15: =AE15 -> 0 | AG15: =AF15 -> 0 | AH15: =AG15 -> 0 | AI15: =AH15 -> 0 | AJ15: =AI15 -> 0 | AK15: =AJ15 -> 0 | AM15: =IF(C15<>"",C15,D15) -> Model Unit Loss | AN15: =P15 -> 0 | AO15: =IF(Z15<>"",AN15*(1+Z15),IF(AA15<>"",AO$9*AA15,AB15*$Q$1)) -> 0 | AP15: =AO15*(1+AC15) -> 0 | AQ15: =AP15*(1+AD15) -> 0 | AR15: =AQ15*(1+AE15) -> 0 | AS15: =AR15*(1+AF15) -> 0 | AT15: =AS15*(1+AG15) -> 0 | AU15: =AT15*(1+AH15) -> 0 | AV15: =AU15*(1+AI15) -> 0 | AW15: =AV15*(1+AJ15) -> 0 | AX15: =AW15*(1+AK15) -> 0
D16: Garage/Parking | I16: =H16*4 -> 0 | J16: =I16/$Q$1 -> #DIV/0! | K16: =I16/$I$7 -> #DIV/0! | L16: =I16/$Q$2 -> #DIV/0! | M16: =IFERROR(F16/E16-1,"") | N16: =IFERROR(G16/F16-1,"") | O16: =IFERROR(I16/G16-1,"") | P16: =IF(W16<>"",I16*(1+W16),IF(X16<>"",X16*$P$9,Y16*$Q$1)) -> 0 | Q16: =P16/$Q$1 -> #DIV/0! | R16: =P16/$P$7 -> #DIV/0! | S16: =P16/$Q$2 -> #DIV/0! | T16: =IFERROR(P16/I16-1,"") | V16: =IF(C16<>"",C16,D16) -> Garage/Parking | AD16: =AC16 -> 0 | AE16: =AD16 -> 0 | AF16: =AE16 -> 0 | AG16: =AF16 -> 0 | AH16: =AG16 -> 0 | AI16: =AH16 -> 0 | AJ16: =AI16 -> 0 | AK16: =AJ16 -> 0 | AM16: =IF(C16<>"",C16,D16) -> Garage/Parking | AN16: =P16 -> 0 | AO16: =IF(Z16<>"",AN16*(1+Z16),IF(AA16<>"",AO$9*AA16,AB16*$Q$1)) -> 0 | AP16: =AO16*(1+AC16) -> 0 | AQ16: =AP16*(1+AD16) -> 0 | AR16: =AQ16*(1+AE16) -> 0 | AS16: =AR16*(1+AF16) -> 0 | AT16: =AS16*(1+AG16) -> 0 | AU16: =AT16*(1+AH16) -> 0 | AV16: =AU16*(1+AI16) -> 0 | AW16: =AV16*(1+AJ16) -> 0 | AX16: =AW16*(1+AK16) -> 0
D17: Laundry | I17: =H17*4 -> 0 | J17: =I17/$Q$1 -> #DIV/0! | K17: =I17/$I$7 -> #DIV/0! | L17: =I17/$Q$2 -> #DIV/0! | M17: =IFERROR(F17/E17-1,"") | N17: =IFERROR(G17/F17-1,"") | O17: =IFERROR(I17/G17-1,"") | P17: =IF(W17<>"",I17*(1+W17),IF(X17<>"",X17*$P$9,Y17*$Q$1)) -> 0 | Q17: =P17/$Q$1 -> #DIV/0! | R17: =P17/$P$7 -> #DIV/0! | S17: =P17/$Q$2 -> #DIV/0! | T17: =IFERROR(P17/I17-1,"") | V17: =IF(C17<>"",C17,D17) -> Laundry | AD17: =AC17 -> 0 | AE17: =AD17 -> 0 | AF17: =AE17 -> 0 | AG17: =AF17 -> 0 | AH17: =AG17 -> 0 | AI17: =AH17 -> 0 | AJ17: =AI17 -> 0 | AK17: =AJ17 -> 0 | AM17: =IF(C17<>"",C17,D17) -> Laundry | AN17: =P17 -> 0 | AO17: =IF(Z17<>"",AN17*(1+Z17),IF(AA17<>"",AO$9*AA17,AB17*$Q$1)) -> 0 | AP17: =AO17*(1+AC17) -> 0 | AQ17: =AP17*(1+AD17) -> 0 | AR17: =AQ17*(1+AE17) -> 0 | AS17: =AR17*(1+AF17) -> 0 | AT17: =AS17*(1+AG17) -> 0 | AU17: =AT17*(1+AH17) -> 0 | AV17: =AU17*(1+AI17) -> 0 | AW17: =AV17*(1+AJ17) -> 0 | AX17: =AW17*(1+AK17) -> 0
D18: Utility Reimbursement | I18: =H18*4 -> 0 | J18: =I18/$Q$1 -> #DIV/0! | K18: =I18/$I$7 -> #DIV/0! | L18: =I18/$Q$2 -> #DIV/0! | M18: =IFERROR(F18/E18-1,"") | N18: =IFERROR(G18/F18-1,"") | O18: =IFERROR(I18/G18-1,"") | P18: =IF(W18<>"",I18*(1+W18),IF(X18<>"",X18*$P$9,Y18*$Q$1)) -> 0 | Q18: =P18/$Q$1 -> #DIV/0! | R18: =P18/$P$7 -> #DIV/0! | S18: =P18/$Q$2 -> #DIV/0! | T18: =IFERROR(P18/I18-1,"") | V18: =IF(C18<>"",C18,D18) -> Utility Reimbursement | AD18: =AC18 -> 0 | AE18: =AD18 -> 0 | AF18: =AE18 -> 0 | AG18: =AF18 -> 0 | AH18: =AG18 -> 0 | AI18: =AH18 -> 0 | AJ18: =AI18 -> 0 | AK18: =AJ18 -> 0 | AM18: =IF(C18<>"",C18,D18) -> Utility Reimbursement | AN18: =P18 -> 0 | AO18: =IF(Z18<>"",AN18*(1+Z18),IF(AA18<>"",AO$9*AA18,AB18*$Q$1)) -> 0 | AP18: =AO18*(1+AC18) -> 0 | AQ18: =AP18*(1+AD18) -> 0 | AR18: =AQ18*(1+AE18) -> 0 | AS18: =AR18*(1+AF18) -> 0 | AT18: =AS18*(1+AG18) -> 0 | AU18: =AT18*(1+AH18) -> 0 | AV18: =AU18*(1+AI18) -> 0 | AW18: =AV18*(1+AJ18) -> 0 | AX18: =AW18*(1+AK18) -> 0
D19: Water/Sewer | I19: =H19*4 -> 0 | J19: =I19/$Q$1 -> #DIV/0! | K19: =I19/$I$7 -> #DIV/0! | L19: =I19/$Q$2 -> #DIV/0! | M19: =IFERROR(F19/E19-1,"") | N19: =IFERROR(G19/F19-1,"") | O19: =IFERROR(I19/G19-1,"") | P19: =IF(W19<>"",I19*(1+W19),IF(X19<>"",X19*$P$9,Y19*$Q$1)) -> 0 | Q19: =P19/$Q$1 -> #DIV/0! | R19: =P19/$P$7 -> #DIV/0! | S19: =P19/$Q$2 -> #DIV/0! | T19: =IFERROR(P19/I19-1,"") | V19: =IF(C19<>"",C19,D19) -> Water/Sewer | AD19: =AC19 -> 0 | AE19: =AD19 -> 0 | AF19: =AE19 -> 0 | AG19: =AF19 -> 0 | AH19: =AG19 -> 0 | AI19: =AH19 -> 0 | AJ19: =AI19 -> 0 | AK19: =AJ19 -> 0 | AM19: =IF(C19<>"",C19,D19) -> Water/Sewer | AN19: =P19 -> 0 | AO19: =IF(Z19<>"",AN19*(1+Z19),IF(AA19<>"",AO$9*AA19,AB19*$Q$1)) -> 0 | AP19: =AO19*(1+AC19) -> 0 | AQ19: =AP19*(1+AD19) -> 0 | AR19: =AQ19*(1+AE19) -> 0 | AS19: =AR19*(1+AF19) -> 0 | AT19: =AS19*(1+AG19) -> 0 | AU19: =AT19*(1+AH19) -> 0 | AV19: =AU19*(1+AI19) -> 0 | AW19: =AV19*(1+AJ19) -> 0 | AX19: =AW19*(1+AK19) -> 0
D20: Trash | I20: =H20*4 -> 0 | J20: =I20/$Q$1 -> #DIV/0! | K20: =I20/$I$7 -> #DIV/0! | L20: =I20/$Q$2 -> #DIV/0! | M20: =IFERROR(F20/E20-1,"") | N20: =IFERROR(G20/F20-1,"") | O20: =IFERROR(I20/G20-1,"") | P20: =IF(W20<>"",I20*(1+W20),IF(X20<>"",X20*$P$9,Y20*$Q$1)) -> 0 | Q20: =P20/$Q$1 -> #DIV/0! | R20: =P20/$P$7 -> #DIV/0! | S20: =P20/$Q$2 -> #DIV/0! | T20: =IFERROR(P20/I20-1,"") | V20: =IF(C20<>"",C20,D20) -> Trash | AD20: =AC20 -> 0 | AE20: =AD20 -> 0 | AF20: =AE20 -> 0 | AG20: =AF20 -> 0 | AH20: =AG20 -> 0 | AI20: =AH20 -> 0 | AJ20: =AI20 -> 0 | AK20: =AJ20 -> 0 | AM20: =IF(C20<>"",C20,D20) -> Trash | AN20: =P20 -> 0 | AO20: =IF(Z20<>"",AN20*(1+Z20),IF(AA20<>"",AO$9*AA20,AB20*$Q$1)) -> 0 | AP20: =AO20*(1+AC20) -> 0 | AQ20: =AP20*(1+AD20) -> 0 | AR20: =AQ20*(1+AE20) -> 0 | AS20: =AR20*(1+AF20) -> 0 | AT20: =AS20*(1+AG20) -> 0 | AU20: =AT20*(1+AH20) -> 0 | AV20: =AU20*(1+AI20) -> 0 | AW20: =AV20*(1+AJ20) -> 0 | AX20: =AW20*(1+AK20) -> 0
D21: Gas | I21: =H21*4 -> 0 | J21: =I21/$Q$1 -> #DIV/0! | K21: =I21/$I$7 -> #DIV/0! | L21: =I21/$Q$2 -> #DIV/0! | M21: =IFERROR(F21/E21-1,"") | N21: =IFERROR(G21/F21-1,"") | O21: =IFERROR(I21/G21-1,"") | P21: =IF(W21<>"",I21*(1+W21),IF(X21<>"",X21*$P$9,Y21*$Q$1)) -> 0 | Q21: =P21/$Q$1 -> #DIV/0! | R21: =P21/$P$7 -> #DIV/0! | S21: =P21/$Q$2 -> #DIV/0! | T21: =IFERROR(P21/I21-1,"") | V21: =IF(C21<>"",C21,D21) -> Gas | AD21: =AC21 -> 0 | AE21: =AD21 -> 0 | AF21: =AE21 -> 0 | AG21: =AF21 -> 0 | AH21: =AG21 -> 0 | AI21: =AH21 -> 0 | AJ21: =AI21 -> 0 | AK21: =AJ21 -> 0 | AM21: =IF(C21<>"",C21,D21) -> Gas | AN21: =P21 -> 0 | AO21: =IF(Z21<>"",AN21*(1+Z21),IF(AA21<>"",AO$9*AA21,AB21*$Q$1)) -> 0 | AP21: =AO21*(1+AC21) -> 0 | AQ21: =AP21*(1+AD21) -> 0 | AR21: =AQ21*(1+AE21) -> 0 | AS21: =AR21*(1+AF21) -> 0 | AT21: =AS21*(1+AG21) -> 0 | AU21: =AT21*(1+AH21) -> 0 | AV21: =AU21*(1+AI21) -> 0 | AW21: =AV21*(1+AJ21) -> 0 | AX21: =AW21*(1+AK21) -> 0
D22: Electricity | I22: =H22*4 -> 0 | J22: =I22/$Q$1 -> #DIV/0! | K22: =I22/$I$7 -> #DIV/0! | L22: =I22/$Q$2 -> #DIV/0! | M22: =IFERROR(F22/E22-1,"") | N22: =IFERROR(G22/F22-1,"") | O22: =IFERROR(I22/G22-1,"") | P22: =IF(W22<>"",I22*(1+W22),IF(X22<>"",X22*$P$9,Y22*$Q$1)) -> 0 | Q22: =P22/$Q$1 -> #DIV/0! | R22: =P22/$P$7 -> #DIV/0! | S22: =P22/$Q$2 -> #DIV/0! | T22: =IFERROR(P22/I22-1,"") | V22: =IF(C22<>"",C22,D22) -> Electricity | AD22: =AC22 -> 0 | AE22: =AD22 -> 0 | AF22: =AE22 -> 0 | AG22: =AF22 -> 0 | AH22: =AG22 -> 0 | AI22: =AH22 -> 0 | AJ22: =AI22 -> 0 | AK22: =AJ22 -> 0 | AM22: =IF(C22<>"",C22,D22) -> Electricity | AN22: =P22 -> 0 | AO22: =IF(Z22<>"",AN22*(1+Z22),IF(AA22<>"",AO$9*AA22,AB22*$Q$1)) -> 0 | AP22: =AO22*(1+AC22) -> 0 | AQ22: =AP22*(1+AD22) -> 0 | AR22: =AQ22*(1+AE22) -> 0 | AS22: =AR22*(1+AF22) -> 0 | AT22: =AS22*(1+AG22) -> 0 | AU22: =AT22*(1+AH22) -> 0 | AV22: =AU22*(1+AI22) -> 0 | AW22: =AV22*(1+AJ22) -> 0 | AX22: =AW22*(1+AK22) -> 0
D23: Other | I23: =H23*4 -> 0 | J23: =I23/$Q$1 -> #DIV/0! | K23: =I23/$I$7 -> #DIV/0! | L23: =I23/$Q$2 -> #DIV/0! | M23: =IFERROR(F23/E23-1,"") | N23: =IFERROR(G23/F23-1,"") | O23: =IFERROR(I23/G23-1,"") | P23: =IF(W23<>"",I23*(1+W23),IF(X23<>"",X23*$P$9,Y23*$Q$1)) -> 0 | Q23: =P23/$Q$1 -> #DIV/0! | R23: =P23/$P$7 -> #DIV/0! | S23: =P23/$Q$2 -> #DIV/0! | T23: =IFERROR(P23/I23-1,"") | V23: =IF(C23<>"",C23,D23) -> Other | AD23: =AC23 -> 0 | AE23: =AD23 -> 0 | AF23: =AE23 -> 0 | AG23: =AF23 -> 0 | AH23: =AG23 -> 0 | AI23: =AH23 -> 0 | AJ23: =AI23 -> 0 | AK23: =AJ23 -> 0 | AM23: =IF(C23<>"",C23,D23) -> Other | AN23: =P23 -> 0 | AO23: =IF(Z23<>"",AN23*(1+Z23),IF(AA23<>"",AO$9*AA23,AB23*$Q$1)) -> 0 | AP23: =AO23*(1+AC23) -> 0 | AQ23: =AP23*(1+AD23) -> 0 | AR23: =AQ23*(1+AE23) -> 0 | AS23: =AR23*(1+AF23) -> 0 | AT23: =AS23*(1+AG23) -> 0 | AU23: =AT23*(1+AH23) -> 0 | AV23: =AU23*(1+AI23) -> 0 | AW23: =AV23*(1+AJ23) -> 0 | AX23: =AW23*(1+AK23) -> 0
D24: Other | I24: =H24*4 -> 0 | J24: =I24/$Q$1 -> #DIV/0! | K24: =I24/$I$7 -> #DIV/0! | L24: =I24/$Q$2 -> #DIV/0! | M24: =IFERROR(F24/E24-1,"") | N24: =IFERROR(G24/F24-1,"") | O24: =IFERROR(I24/G24-1,"") | P24: =IF(W24<>"",I24*(1+W24),IF(X24<>"",X24*$P$9,Y24*$Q$1)) -> 0 | Q24: =P24/$Q$1 -> #DIV/0! | R24: =P24/$P$7 -> #DIV/0! | S24: =P24/$Q$2 -> #DIV/0! | T24: =IFERROR(P24/I24-1,"") | V24: =IF(C24<>"",C24,D24) -> Other | AD24: =AC24 -> 0 | AE24: =AD24 -> 0 | AF24: =AE24 -> 0 | AG24: =AF24 -> 0 | AH24: =AG24 -> 0 | AI24: =AH24 -> 0 | AJ24: =AI24 -> 0 | AK24: =AJ24 -> 0 | AM24: =IF(C24<>"",C24,D24) -> Other | AN24: =P24 -> 0 | AO24: =IF(Z24<>"",AN24*(1+Z24),IF(AA24<>"",AO$9*AA24,AB24*$Q$1)) -> 0 | AP24: =AO24*(1+AC24) -> 0 | AQ24: =AP24*(1+AD24) -> 0 | AR24: =AQ24*(1+AE24) -> 0 | AS24: =AR24*(1+AF24) -> 0 | AT24: =AS24*(1+AG24) -> 0 | AU24: =AT24*(1+AH24) -> 0 | AV24: =AU24*(1+AI24) -> 0 | AW24: =AV24*(1+AJ24) -> 0 | AX24: =AW24*(1+AK24) -> 0
D25: Other | I25: =H25*4 -> 0 | J25: =I25/$Q$1 -> #DIV/0! | K25: =I25/$I$7 -> #DIV/0! | L25: =I25/$Q$2 -> #DIV/0! | M25: =IFERROR(F25/E25-1,"") | N25: =IFERROR(G25/F25-1,"") | O25: =IFERROR(I25/G25-1,"") | P25: =IF(W25<>"",I25*(1+W25),IF(X25<>"",X25*$P$9,Y25*$Q$1)) -> 0 | Q25: =P25/$Q$1 -> #DIV/0! | R25: =P25/$P$7 -> #DIV/0! | S25: =P25/$Q$2 -> #DIV/0! | T25: =IFERROR(P25/I25-1,"") | V25: =IF(C25<>"",C25,D25) -> Other | AD25: =AC25 -> 0 | AE25: =AD25 -> 0 | AF25: =AE25 -> 0 | AG25: =AF25 -> 0 | AH25: =AG25 -> 0 | AI25: =AH25 -> 0 | AJ25: =AI25 -> 0 | AK25: =AJ25 -> 0 | AM25: =IF(C25<>"",C25,D25) -> Other | AN25: =P25 -> 0 | AO25: =IF(Z25<>"",AN25*(1+Z25),IF(AA25<>"",AO$9*AA25,AB25*$Q$1)) -> 0 | AP25: =AO25*(1+AC25) -> 0 | AQ25: =AP25*(1+AD25) -> 0 | AR25: =AQ25*(1+AE25) -> 0 | AS25: =AR25*(1+AF25) -> 0 | AT25: =AS25*(1+AG25) -> 0 | AU25: =AT25*(1+AH25) -> 0 | AV25: =AU25*(1+AI25) -> 0 | AW25: =AV25*(1+AJ25) -> 0 | AX25: =AW25*(1+AK25) -> 0
D26: Other | I26: =H26*4 -> 0 | J26: =I26/$Q$1 -> #DIV/0! | K26: =I26/$I$7 -> #DIV/0! | L26: =I26/$Q$2 -> #DIV/0! | M26: =IFERROR(F26/E26-1,"") | N26: =IFERROR(G26/F26-1,"") | O26: =IFERROR(I26/G26-1,"") | P26: =IF(W26<>"",I26*(1+W26),IF(X26<>"",X26*$P$9,Y26*$Q$1)) -> 0 | Q26: =P26/$Q$1 -> #DIV/0! | R26: =P26/$P$7 -> #DIV/0! | S26: =P26/$Q$2 -> #DIV/0! | T26: =IFERROR(P26/I26-1,"") | V26: =IF(C26<>"",C26,D26) -> Other | AD26: =AC26 -> 0 | AE26: =AD26 -> 0 | AF26: =AE26 -> 0 | AG26: =AF26 -> 0 | AH26: =AG26 -> 0 | AI26: =AH26 -> 0 | AJ26: =AI26 -> 0 | AK26: =AJ26 -> 0 | AM26: =IF(C26<>"",C26,D26) -> Other | AN26: =P26 -> 0 | AO26: =IF(Z26<>"",AN26*(1+Z26),IF(AA26<>"",AO$9*AA26,AB26*$Q$1)) -> 0 | AP26: =AO26*(1+AC26) -> 0 | AQ26: =AP26*(1+AD26) -> 0 | AR26: =AQ26*(1+AE26) -> 0 | AS26: =AR26*(1+AF26) -> 0 | AT26: =AS26*(1+AG26) -> 0 | AU26: =AT26*(1+AH26) -> 0 | AV26: =AU26*(1+AI26) -> 0 | AW26: =AV26*(1+AJ26) -> 0 | AX26: =AW26*(1+AK26) -> 0
C27: Effective Gross Income | E27: =SUM(E13:E26) -> 0 | F27: =SUM(F13:F26) -> 0 | G27: =SUM(G13:G26) -> 0 | H27: =SUM(H13:H26) -> 0 | I27: =SUM(I13:I26) -> 0 | J27: =SUM(J13:J26) -> #DIV/0! | K27: =SUM(K13:K26) -> #DIV/0! | L27: =SUM(L13:L26) -> #DIV/0! | M27: =IFERROR(F27/E27-1,"") | N27: =IFERROR(G27/F27-1,"") | O27: =IFERROR(I27/G27-1,"") | P27: =SUM(P13:P26) -> 0 | Q27: =SUM(Q13:Q26) -> #DIV/0! | R27: =SUM(R13:R26) -> #DIV/0! | S27: =SUM(S13:S18)+SUM(S24:S26) -> #DIV/0! | T27: =P27/I27-1 -> #DIV/0! | V27: *Starting FY3 Vacancy and Bad Debt assumptions are by % of GPR | AM27: =IF(C27<>"",C27,D27) -> Effective Gross Income | AN27: =SUM(AN13:AN26) -> 0 | AO27: =SUM(AO13:AO26) -> 0 | AP27: =SUM(AP13:AP26) -> 0 | AQ27: =SUM(AQ13:AQ26) -> 0 | AR27: =SUM(AR13:AR26) -> 0 | AS27: =SUM(AS13:AS26) -> 0 | AT27: =SUM(AT13:AT26) -> 0 | AU27: =SUM(AU13:AU26) -> 0 | ... AX27: =SUM(AX13:AX26) -> 0
C29: Expenses | AM29: =IF(C29<>"",C29,D29) -> Expenses
D30: Administrative | I30: =G30 -> 0 | J30: =I30/$Q$1 -> #DIV/0! | K30: =I30/$I$27 -> #DIV/0! | L30: =I30/$Q$2 -> #DIV/0! | M30: =IFERROR(F30/E30-1,"") | N30: =IFERROR(G30/F30-1,"") | P30: =IF(W30<>"",I30*(1+W30),IF(X30<>"",X30*$P$27,Y30*$Q$1)) -> 0 | Q30: =P30/$Q$1 -> #DIV/0! | R30: =P30/$P$27 -> #DIV/0! | S30: =P30/$Q$2 -> #DIV/0! | T30: =IFERROR(P30/I30-1,"") | V30: =IF(C30<>"",C30,D30) -> Administrative | AD30: =AC30 -> 0 | AE30: =AD30 -> 0 | AF30: =AE30 -> 0 | AG30: =AF30 -> 0 | AH30: =AG30 -> 0 | AI30: =AH30 -> 0 | AJ30: =AI30 -> 0 | AK30: =AJ30 -> 0 | AM30: =IF(C30<>"",C30,D30) -> Administrative | AN30: =P30 -> 0 | AO30: =IF(Z30<>"",AN30*(1+Z30),IF(AA30<>"",AO$27*AA30,AB30*$Q$1)) -> 0 | AP30: =AO30*(1+AC30) -> 0 | AQ30: =AP30*(1+AD30) -> 0 | AR30: =AQ30*(1+AE30) -> 0 | AS30: =AR30*(1+AF30) -> 0 | AT30: =AS30*(1+AG30) -> 0 | AU30: =AT30*(1+AH30) -> 0 | AV30: =AU30*(1+AI30) -> 0 | AW30: =AV30*(1+AJ30) -> 0 | AX30: =AW30*(1+AK30) -> 0
D31: Marketing | I31: =G31 -> 0 | J31: =I31/$Q$1 -> #DIV/0! | K31: =I31/$I$27 -> #DIV/0! | L31: =I31/$Q$2 -> #DIV/0! | M31: =IFERROR(F31/E31-1,"") | N31: =IFERROR(G31/F31-1,"") | P31: =IF(W31<>"",I31*(1+W31),IF(X31<>"",X31*$P$27,Y31*$Q$1)) -> 0 | Q31: =P31/$Q$1 -> #DIV/0! | R31: =P31/$P$27 -> #DIV/0! | S31: =P31/$Q$2 -> #DIV/0! | T31: =IFERROR(P31/I31-1,"") | V31: =IF(C31<>"",C31,D31) -> Marketing | AD31: =AC31 -> 0 | AE31: =AD31 -> 0 | AF31: =AE31 -> 0 | AG31: =AF31 -> 0 | AH31: =AG31 -> 0 | AI31: =AH31 -> 0 | AJ31: =AI31 -> 0 | AK31: =AJ31 -> 0 | AM31: =IF(C31<>"",C31,D31) -> Marketing | AN31: =P31 -> 0 | AO31: =IF(Z31<>"",AN31*(1+Z31),IF(AA31<>"",AO$27*AA31,AB31*$Q$1)) -> 0 | AP31: =AO31*(1+AC31) -> 0 | AQ31: =AP31*(1+AD31) -> 0 | AR31: =AQ31*(1+AE31) -> 0 | AS31: =AR31*(1+AF31) -> 0 | AT31: =AS31*(1+AG31) -> 0 | AU31: =AT31*(1+AH31) -> 0 | AV31: =AU31*(1+AI31) -> 0 | AW31: =AV31*(1+AJ31) -> 0 | AX31: =AW31*(1+AK31) -> 0
D32: Management Fee | I32: =G32 -> 0 | J32: =I32/$Q$1 -> #DIV/0! | K32: =I32/$I$27 -> #DIV/0! | L32: =I32/$Q$2 -> #DIV/0! | M32: =IFERROR(F32/E32-1,"") | N32: =IFERROR(G32/F32-1,"") | P32: =IF(W32<>"",I32*(1+W32),IF(X32<>"",X32*$P$27,Y32*$Q$1)) -> 0 | Q32: =P32/$Q$1 -> #DIV/0! | R32: =P32/$P$27 -> #DIV/0! | S32: =P32/$Q$2 -> #DIV/0! | T32: =IFERROR(P32/I32-1,"") | V32: =IF(C32<>"",C32,D32)&"*" -> Management Fee* | AD32: =AC32 -> 0 | AE32: =AD32 -> 0 | AF32: =AE32 -> 0 | AG32: =AF32 -> 0 | AH32: =AG32 -> 0 | AI32: =AH32 -> 0 | AJ32: =AI32 -> 0 | AK32: =AJ32 -> 0 | AM32: =IF(C32<>"",C32,D32) -> Management Fee | AN32: =P32 -> 0 | AO32: =IF(Z32<>"",AN32*(1+Z32),IF(AA32<>"",AO$27*AA32,AB32*$Q$1)) -> 0 | AP32: =AC32*AP$27 -> 0 | AQ32: =AD32*AQ27 -> 0 | AR32: =AE32*AR27 -> 0 | AS32: =AF32*AS27 -> 0 | AT32: =AG32*AT27 -> 0 | AU32: =AH32*AU27 -> 0 | AV32: =AI32*AV27 -> 0 | AW32: =AJ32*AW27 -> 0 | AX32: =AK32*AX27 -> 0
D33: Payroll | I33: =G33 -> 0 | J33: =I33/$Q$1 -> #DIV/0! | K33: =I33/$I$27 -> #DIV/0! | L33: =I33/$Q$2 -> #DIV/0! | M33: =IFERROR(F33/E33-1,"") | N33: =IFERROR(G33/F33-1,"") | P33: =IF(W33<>"",I33*(1+W33),IF(X33<>"",X33*$P$27,Y33*$Q$1)) -> 0 | Q33: =P33/$Q$1 -> #DIV/0! | R33: =P33/$P$27 -> #DIV/0! | S33: =P33/$Q$2 -> #DIV/0! | T33: =IFERROR(P33/I33-1,"") | V33: =IF(C33<>"",C33,D33) -> Payroll | AD33: =AC33 -> 0 | AE33: =AD33 -> 0 | AF33: =AE33 -> 0 | AG33: =AF33 -> 0 | AH33: =AG33 -> 0 | AI33: =AH33 -> 0 | AJ33: =AI33 -> 0 | AK33: =AJ33 -> 0 | AM33: =IF(C33<>"",C33,D33) -> Payroll | AN33: =P33 -> 0 | AO33: =IF(Z33<>"",AN33*(1+Z33),IF(AA33<>"",AO$27*AA33,AB33*$Q$1)) -> 0 | AP33: =AO33*(1+AC33) -> 0 | AQ33: =AP33*(1+AD33) -> 0 | AR33: =AQ33*(1+AE33) -> 0 | AS33: =AR33*(1+AF33) -> 0 | AT33: =AS33*(1+AG33) -> 0 | AU33: =AT33*(1+AH33) -> 0 | AV33: =AU33*(1+AI33) -> 0 | AW33: =AV33*(1+AJ33) -> 0 | AX33: =AW33*(1+AK33) -> 0
D34: Utilities | I34: =G34 -> 0 | J34: =I34/$Q$1 -> #DIV/0! | K34: =I34/$I$27 -> #DIV/0! | L34: =I34/$Q$2 -> #DIV/0! | M34: =IFERROR(F34/E34-1,"") | N34: =IFERROR(G34/F34-1,"") | P34: =IF(W34<>"",I34*(1+W34),IF(X34<>"",X34*$P$27,Y34*$Q$1)) -> 0 | Q34: =P34/$Q$1 -> #DIV/0! | R34: =P34/$P$27 -> #DIV/0! | S34: =P34/$Q$2 -> #DIV/0! | T34: =IFERROR(P34/I34-1,"") | V34: =IF(C34<>"",C34,D34) -> Utilities | AD34: =AC34 -> 0 | AE34: =AD34 -> 0 | AF34: =AE34 -> 0 | AG34: =AF34 -> 0 | AH34: =AG34 -> 0 | AI34: =AH34 -> 0 | AJ34: =AI34 -> 0 | AK34: =AJ34 -> 0 | AM34: =IF(C34<>"",C34,D34) -> Utilities | AN34: =P34 -> 0 | AO34: =IF(Z34<>"",AN34*(1+Z34),IF(AA34<>"",AO$27*AA34,AB34*$Q$1)) -> 0 | AP34: =AO34*(1+AC34) -> 0 | AQ34: =AP34*(1+AD34) -> 0 | AR34: =AQ34*(1+AE34) -> 0 | AS34: =AR34*(1+AF34) -> 0 | AT34: =AS34*(1+AG34) -> 0 | AU34: =AT34*(1+AH34) -> 0 | AV34: =AU34*(1+AI34) -> 0 | AW34: =AV34*(1+AJ34) -> 0 | AX34: =AW34*(1+AK34) -> 0
D35: Water/Sewer | I35: =G35 -> 0 | J35: =I35/$Q$1 -> #DIV/0! | K35: =I35/$I$27 -> #DIV/0! | L35: =I35/$Q$2 -> #DIV/0! | M35: =IFERROR(F35/E35-1,"") | N35: =IFERROR(G35/F35-1,"") | P35: =IF(W35<>"",I35*(1+W35),IF(X35<>"",X35*$P$27,Y35*$Q$1)) -> 0 | Q35: =P35/$Q$1 -> #DIV/0! | R35: =P35/$P$27 -> #DIV/0! | S35: =P35/$Q$2 -> #DIV/0! | T35: =IFERROR(P35/I35-1,"") | V35: =IF(C35<>"",C35,D35) -> Water/Sewer | AD35: =AC35 -> 0 | AE35: =AD35 -> 0 | AF35: =AE35 -> 0 | AG35: =AF35 -> 0 | AH35: =AG35 -> 0 | AI35: =AH35 -> 0 | AJ35: =AI35 -> 0 | AK35: =AJ35 -> 0 | AM35: =IF(C35<>"",C35,D35) -> Water/Sewer | AN35: =P35 -> 0 | AO35: =IF(Z35<>"",AN35*(1+Z35),IF(AA35<>"",AO$27*AA35,AB35*$Q$1)) -> 0 | AP35: =AO35*(1+AC35) -> 0 | AQ35: =AP35*(1+AD35) -> 0 | AR35: =AQ35*(1+AE35) -> 0 | AS35: =AR35*(1+AF35) -> 0 | AT35: =AS35*(1+AG35) -> 0 | AU35: =AT35*(1+AH35) -> 0 | AV35: =AU35*(1+AI35) -> 0 | AW35: =AV35*(1+AJ35) -> 0 | AX35: =AW35*(1+AK35) -> 0
D36: Trash | I36: =G36 -> 0 | J36: =I36/$Q$1 -> #DIV/0! | K36: =I36/$I$27 -> #DIV/0! | L36: =I36/$Q$2 -> #DIV/0! | M36: =IFERROR(F36/E36-1,"") | N36: =IFERROR(G36/F36-1,"") | P36: =IF(W36<>"",I36*(1+W36),IF(X36<>"",X36*$P$27,Y36*$Q$1)) -> 0 | Q36: =P36/$Q$1 -> #DIV/0! | R36: =P36/$P$27 -> #DIV/0! | S36: =P36/$Q$2 -> #DIV/0! | T36: =IFERROR(P36/I36-1,"") | V36: =IF(C36<>"",C36,D36) -> Trash | AD36: =AC36 -> 0 | AE36: =AD36 -> 0 | AF36: =AE36 -> 0 | AG36: =AF36 -> 0 | AH36: =AG36 -> 0 | AI36: =AH36 -> 0 | AJ36: =AI36 -> 0 | AK36: =AJ36 -> 0 | AM36: =IF(C36<>"",C36,D36) -> Trash | AN36: =P36 -> 0 | AO36: =IF(Z36<>"",AN36*(1+Z36),IF(AA36<>"",AO$27*AA36,AB36*$Q$1)) -> 0 | AP36: =AO36*(1+AC36) -> 0 | AQ36: =AP36*(1+AD36) -> 0 | AR36: =AQ36*(1+AE36) -> 0 | AS36: =AR36*(1+AF36) -> 0 | AT36: =AS36*(1+AG36) -> 0 | AU36: =AT36*(1+AH36) -> 0 | AV36: =AU36*(1+AI36) -> 0 | AW36: =AV36*(1+AJ36) -> 0 | AX36: =AW36*(1+AK36) -> 0
D37: Gas | I37: =G37 -> 0 | J37: =I37/$Q$1 -> #DIV/0! | K37: =I37/$I$27 -> #DIV/0! | L37: =I37/$Q$2 -> #DIV/0! | M37: =IFERROR(F37/E37-1,"") | N37: =IFERROR(G37/F37-1,"") | P37: =IF(W37<>"",I37*(1+W37),IF(X37<>"",X37*$P$27,Y37*$Q$1)) -> 0 | Q37: =P37/$Q$1 -> #DIV/0! | R37: =P37/$P$27 -> #DIV/0! | S37: =P37/$Q$2 -> #DIV/0! | T37: =IFERROR(P37/I37-1,"") | V37: =IF(C37<>"",C37,D37) -> Gas | AD37: =AC37 -> 0 | AE37: =AD37 -> 0 | AF37: =AE37 -> 0 | AG37: =AF37 -> 0 | AH37: =AG37 -> 0 | AI37: =AH37 -> 0 | AJ37: =AI37 -> 0 | AK37: =AJ37 -> 0 | AM37: =IF(C37<>"",C37,D37) -> Gas | AN37: =P37 -> 0 | AO37: =IF(Z37<>"",AN37*(1+Z37),IF(AA37<>"",AO$27*AA37,AB37*$Q$1)) -> 0 | AP37: =AO37*(1+AC37) -> 0 | AQ37: =AP37*(1+AD37) -> 0 | AR37: =AQ37*(1+AE37) -> 0 | AS37: =AR37*(1+AF37) -> 0 | AT37: =AS37*(1+AG37) -> 0 | AU37: =AT37*(1+AH37) -> 0 | AV37: =AU37*(1+AI37) -> 0 | AW37: =AV37*(1+AJ37) -> 0 | AX37: =AW37*(1+AK37) -> 0
D38: Electricity | I38: =G38 -> 0 | J38: =I38/$Q$1 -> #DIV/0! | K38: =I38/$I$27 -> #DIV/0! | L38: =I38/$Q$2 -> #DIV/0! | M38: =IFERROR(F38/E38-1,"") | N38: =IFERROR(G38/F38-1,"") | P38: =IF(W38<>"",I38*(1+W38),IF(X38<>"",X38*$P$27,Y38*$Q$1)) -> 0 | Q38: =P38/$Q$1 -> #DIV/0! | R38: =P38/$P$27 -> #DIV/0! | S38: =P38/$Q$2 -> #DIV/0! | T38: =IFERROR(P38/I38-1,"") | V38: =IF(C38<>"",C38,D38) -> Electricity | AD38: =AC38 -> 0 | AE38: =AD38 -> 0 | AF38: =AE38 -> 0 | AG38: =AF38 -> 0 | AH38: =AG38 -> 0 | AI38: =AH38 -> 0 | AJ38: =AI38 -> 0 | AK38: =AJ38 -> 0 | AM38: =IF(C38<>"",C38,D38) -> Electricity | AN38: =P38 -> 0 | AO38: =IF(Z38<>"",AN38*(1+Z38),IF(AA38<>"",AO$27*AA38,AB38*$Q$1)) -> 0 | AP38: =AO38*(1+AC38) -> 0 | AQ38: =AP38*(1+AD38) -> 0 | AR38: =AQ38*(1+AE38) -> 0 | AS38: =AR38*(1+AF38) -> 0 | AT38: =AS38*(1+AG38) -> 0 | AU38: =AT38*(1+AH38) -> 0 | AV38: =AU38*(1+AI38) -> 0 | AW38: =AV38*(1+AJ38) -> 0 | AX38: =AW38*(1+AK38) -> 0
D39: R&M | I39: =G39 -> 0 | J39: =I39/$Q$1 -> #DIV/0! | K39: =I39/$I$27 -> #DIV/0! | L39: =I39/$Q$2 -> #DIV/0! | M39: =IFERROR(F39/E39-1,"") | N39: =IFERROR(G39/F39-1,"") | P39: =IF(W39<>"",I39*(1+W39),IF(X39<>"",X39*$P$27,Y39*$Q$1)) -> 0 | Q39: =P39/$Q$1 -> #DIV/0! | R39: =P39/$P$27 -> #DIV/0! | S39: =P39/$Q$2 -> #DIV/0! | T39: =IFERROR(P39/I39-1,"") | V39: =IF(C39<>"",C39,D39) -> R&M | AD39: =AC39 -> 0 | AE39: =AD39 -> 0 | AF39: =AE39 -> 0 | AG39: =AF39 -> 0 | AH39: =AG39 -> 0 | AI39: =AH39 -> 0 | AJ39: =AI39 -> 0 | AK39: =AJ39 -> 0 | AM39: =IF(C39<>"",C39,D39) -> R&M | AN39: =P39 -> 0 | AO39: =IF(Z39<>"",AN39*(1+Z39),IF(AA39<>"",AO$27*AA39,AB39*$Q$1)) -> 0 | AP39: =AO39*(1+AC39) -> 0 | AQ39: =AP39*(1+AD39) -> 0 | AR39: =AQ39*(1+AE39) -> 0 | AS39: =AR39*(1+AF39) -> 0 | AT39: =AS39*(1+AG39) -> 0 | AU39: =AT39*(1+AH39) -> 0 | AV39: =AU39*(1+AI39) -> 0 | AW39: =AV39*(1+AJ39) -> 0 | AX39: =AW39*(1+AK39) -> 0
D40: Turnover | I40: =G40 -> 0 | J40: =I40/$Q$1 -> #DIV/0! | K40: =I40/$I$27 -> #DIV/0! | L40: =I40/$Q$2 -> #DIV/0! | M40: =IFERROR(F40/E40-1,"") | N40: =IFERROR(G40/F40-1,"") | P40: =IF(W40<>"",I40*(1+W40),IF(X40<>"",X40*$P$27,Y40*$Q$1)) -> 0 | Q40: =P40/$Q$1 -> #DIV/0! | R40: =P40/$P$27 -> #DIV/0! | S40: =P40/$Q$2 -> #DIV/0! | T40: =IFERROR(P40/I40-1,"") | V40: =IF(C40<>"",C40,D40) -> Turnover | AD40: =AC40 -> 0 | AE40: =AD40 -> 0 | AF40: =AE40 -> 0 | AG40: =AF40 -> 0 | AH40: =AG40 -> 0 | AI40: =AH40 -> 0 | AJ40: =AI40 -> 0 | AK40: =AJ40 -> 0 | AM40: =IF(C40<>"",C40,D40) -> Turnover | AN40: =P40 -> 0 | AO40: =IF(Z40<>"",AN40*(1+Z40),IF(AA40<>"",AO$27*AA40,AB40*$Q$1)) -> 0 | AP40: =AO40*(1+AC40) -> 0 | AQ40: =AP40*(1+AD40) -> 0 | AR40: =AQ40*(1+AE40) -> 0 | AS40: =AR40*(1+AF40) -> 0 | AT40: =AS40*(1+AG40) -> 0 | AU40: =AT40*(1+AH40) -> 0 | AV40: =AU40*(1+AI40) -> 0 | AW40: =AV40*(1+AJ40) -> 0 | AX40: =AW40*(1+AK40) -> 0
D41: Contract Services | I41: =G41 -> 0 | J41: =I41/$Q$1 -> #DIV/0! | K41: =I41/$I$27 -> #DIV/0! | L41: =I41/$Q$2 -> #DIV/0! | M41: =IFERROR(F41/E41-1,"") | N41: =IFERROR(G41/F41-1,"") | P41: =IF(W41<>"",I41*(1+W41),IF(X41<>"",X41*$P$27,Y41*$Q$1)) -> 0 | Q41: =P41/$Q$1 -> #DIV/0! | R41: =P41/$P$27 -> #DIV/0! | S41: =P41/$Q$2 -> #DIV/0! | T41: =IFERROR(P41/I41-1,"") | V41: =IF(C41<>"",C41,D41) -> Contract Services | AD41: =AC41 -> 0 | AE41: =AD41 -> 0 | AF41: =AE41 -> 0 | AG41: =AF41 -> 0 | AH41: =AG41 -> 0 | AI41: =AH41 -> 0 | AJ41: =AI41 -> 0 | AK41: =AJ41 -> 0 | AM41: =IF(C41<>"",C41,D41) -> Contract Services | AN41: =P41 -> 0 | AO41: =IF(Z41<>"",AN41*(1+Z41),IF(AA41<>"",AO$27*AA41,AB41*$Q$1)) -> 0 | AP41: =AO41*(1+AC41) -> 0 | AQ41: =AP41*(1+AD41) -> 0 | AR41: =AQ41*(1+AE41) -> 0 | AS41: =AR41*(1+AF41) -> 0 | AT41: =AS41*(1+AG41) -> 0 | AU41: =AT41*(1+AH41) -> 0 | AV41: =AU41*(1+AI41) -> 0 | AW41: =AV41*(1+AJ41) -> 0 | AX41: =AW41*(1+AK41) -> 0
D42: Insurance | I42: =G42 -> 0 | J42: =I42/$Q$1 -> #DIV/0! | K42: =I42/$I$27 -> #DIV/0! | L42: =I42/$Q$2 -> #DIV/0! | M42: =IFERROR(F42/E42-1,"") | N42: =IFERROR(G42/F42-1,"") | P42: =IF(W42<>"",I42*(1+W42),IF(X42<>"",X42*$P$27,Y42*$Q$1)) -> 0 | Q42: =P42/$Q$1 -> #DIV/0! | R42: =P42/$P$27 -> #DIV/0! | S42: =P42/$Q$2 -> #DIV/0! | T42: =IFERROR(P42/I42-1,"") | V42: =IF(C42<>"",C42,D42) -> Insurance | AD42: =AC42 -> 0 | AE42: =AD42 -> 0 | AF42: =AE42 -> 0 | AG42: =AF42 -> 0 | AH42: =AG42 -> 0 | AI42: =AH42 -> 0 | AJ42: =AI42 -> 0 | AK42: =AJ42 -> 0 | AM42: =IF(C42<>"",C42,D42) -> Insurance | AN42: =P42 -> 0 | AO42: =IF(Z42<>"",AN42*(1+Z42),IF(AA42<>"",AO$27*AA42,AB42*$Q$1)) -> 0 | AP42: =AO42*(1+AC42) -> 0 | AQ42: =AP42*(1+AD42) -> 0 | AR42: =AQ42*(1+AE42) -> 0 | AS42: =AR42*(1+AF42) -> 0 | AT42: =AS42*(1+AG42) -> 0 | AU42: =AT42*(1+AH42) -> 0 | AV42: =AU42*(1+AI42) -> 0 | AW42: =AV42*(1+AJ42) -> 0 | AX42: =AW42*(1+AK42) -> 0
D43: Apt. RE Taxes | I43: =G43 -> 0 | J43: =I43/$Q$1 -> #DIV/0! | K43: =I43/$I$27 -> #DIV/0! | L43: =I43/$Q$2 -> #DIV/0! | M43: =IFERROR(F43/E43-1,"") | N43: =IFERROR(G43/F43-1,"") | P43: ='Real Estate Tax'!M15 -> #VALUE! | Q43: =P43/$Q$1 -> #VALUE! | R43: =P43/$P$27 -> #VALUE! | S43: =P43/$Q$2 -> #VALUE! | T43: =IFERROR(P43/I43-1,"") | V43: =IF(C43<>"",C43,D43) -> Apt. RE Taxes | W43: =T43 | X43: =R43 -> #VALUE! | Y43: =Q43 -> #VALUE! | Z43: =AO43/AN43-1 -> #VALUE! | AA43: =AO43/AO$27 -> #VALUE! | AB43: =AO43/$Q$1 -> #VALUE! | AC43: =AP43/AO43-1 -> #VALUE! | AD43: =AQ43/AP43-1 -> #VALUE! | AE43: =AR43/AQ43-1 -> #VALUE! | AF43: =AS43/AR43-1 -> #VALUE! | AG43: =AT43/AS43-1 -> #VALUE! | AH43: =AU43/AT43-1 -> #VALUE! | AI43: =AV43/AU43-1 -> #VALUE! | AJ43: =AW43/AV43-1 -> #VALUE! | AK43: =AX43/AW43-1 -> #VALUE! | AM43: =IF(C43<>"",C43,D43) -> Apt. RE Taxes | AN43: =P43 -> #VALUE! | AO43: ='Real Estate Tax'!M16 -> #VALUE! | AP43: ='Real Estate Tax'!M17 -> #VALUE! | AQ43: ='Real Estate Tax'!M18 -> #VALUE! | AR43: ='Real Estate Tax'!M19 -> #VALUE! | AS43: ='Real Estate Tax'!M20 -> #VALUE! | AT43: ='Real Estate Tax'!M21 -> #VALUE! | AU43: ='Real Estate Tax'!M22 -> #VALUE! | AV43: ='Real Estate Tax'!M23 -> #VALUE! | AW43: ='Real Estate Tax'!M24 -> #VALUE! | AX43: ='Real Estate Tax'!M25 -> #VALUE!
D44: Other | I44: =G44 -> 0 | J44: =I44/$Q$1 -> #DIV/0! | K44: =I44/$I$27 -> #DIV/0! | L44: =I44/$Q$2 -> #DIV/0! | M44: =IFERROR(F44/E44-1,"") | N44: =IFERROR(G44/F44-1,"") | P44: =IF(W44<>"",I44*(1+W44),IF(X44<>"",X44*$P$9,Y44*$Q$1)) -> 0 | Q44: =P44/$Q$1 -> #DIV/0! | R44: =P44/$P$27 -> #DIV/0! | S44: =P44/$Q$2 -> #DIV/0! | T44: =IFERROR(P44/I44-1,"") | V44: =IF(C44<>"",C44,D44) -> Other | AD44: =AC44 -> 0 | AE44: =AD44 -> 0 | AF44: =AE44 -> 0 | AG44: =AF44 -> 0 | AH44: =AG44 -> 0 | AI44: =AH44 -> 0 | AJ44: =AI44 -> 0 | AK44: =AJ44 -> 0 | AM44: =IF(C44<>"",C44,D44) -> Other | AN44: =P44 -> 0 | AO44: =IF(Z44<>"",AN44*(1+Z44),IF(AA44<>"",AO$27*AA44,AB44*$Q$1)) -> 0 | AP44: =AO44*(1+AC44) -> 0 | AQ44: =AP44*(1+AD44) -> 0 | AR44: =AQ44*(1+AE44) -> 0 | AS44: =AR44*(1+AF44) -> 0 | AT44: =AS44*(1+AG44) -> 0 | AU44: =AT44*(1+AH44) -> 0 | AV44: =AU44*(1+AI44) -> 0 | AW44: =AV44*(1+AJ44) -> 0 | AX44: =AW44*(1+AK44) -> 0
D45: Other | I45: =G45 -> 0 | J45: =I45/$Q$1 -> #DIV/0! | K45: =I45/$I$27 -> #DIV/0! | L45: =I45/$Q$2 -> #DIV/0! | M45: =IFERROR(F45/E45-1,"") | N45: =IFERROR(G45/F45-1,"") | P45: =IF(W45<>"",I45*(1+W45),IF(X45<>"",X45*$P$9,Y45*$Q$1)) -> 0 | Q45: =P45/$Q$1 -> #DIV/0! | R45: =P45/$P$27 -> #DIV/0! | S45: =P45/$Q$2 -> #DIV/0! | T45: =IFERROR(P45/I45-1,"") | V45: =IF(C45<>"",C45,D45) -> Other | AD45: =AC45 -> 0 | AE45: =AD45 -> 0 | AF45: =AE45 -> 0 | AG45: =AF45 -> 0 | AH45: =AG45 -> 0 | AI45: =AH45 -> 0 | AJ45: =AI45 -> 0 | AK45: =AJ45 -> 0 | AM45: =IF(C45<>"",C45,D45) -> Other | AN45: =P45 -> 0 | AO45: =IF(Z45<>"",AN45*(1+Z45),IF(AA45<>"",AO$27*AA45,AB45*$Q$1)) -> 0 | AP45: =AO45*(1+AC45) -> 0 | AQ45: =AP45*(1+AD45) -> 0 | AR45: =AQ45*(1+AE45) -> 0 | AS45: =AR45*(1+AF45) -> 0 | AT45: =AS45*(1+AG45) -> 0 | AU45: =AT45*(1+AH45) -> 0 | AV45: =AU45*(1+AI45) -> 0 | AW45: =AV45*(1+AJ45) -> 0 | AX45: =AW45*(1+AK45) -> 0
D46: Other | I46: =G46 -> 0 | J46: =I46/$Q$1 -> #DIV/0! | K46: =I46/$I$27 -> #DIV/0! | L46: =I46/$Q$2 -> #DIV/0! | M46: =IFERROR(F46/E46-1,"") | N46: =IFERROR(G46/F46-1,"") | P46: =IF(W46<>"",I46*(1+W46),IF(X46<>"",X46*$P$9,Y46*$Q$1)) -> 0 | Q46: =P46/$Q$1 -> #DIV/0! | R46: =P46/$P$27 -> #DIV/0! | S46: =P46/$Q$2 -> #DIV/0! | T46: =IFERROR(P46/I46-1,"") | V46: =IF(C46<>"",C46,D46) -> Other | AD46: =AC46 -> 0 | AE46: =AD46 -> 0 | AF46: =AE46 -> 0 | AG46: =AF46 -> 0 | AH46: =AG46 -> 0 | AI46: =AH46 -> 0 | AJ46: =AI46 -> 0 | AK46: =AJ46 -> 0 | AM46: =IF(C46<>"",C46,D46) -> Other | AN46: =P46 -> 0 | AO46: =IF(Z46<>"",AN46*(1+Z46),IF(AA46<>"",AO$27*AA46,AB46*$Q$1)) -> 0 | AP46: =AO46*(1+AC46) -> 0 | AQ46: =AP46*(1+AD46) -> 0 | AR46: =AQ46*(1+AE46) -> 0 | AS46: =AR46*(1+AF46) -> 0 | AT46: =AS46*(1+AG46) -> 0 | AU46: =AT46*(1+AH46) -> 0 | AV46: =AU46*(1+AI46) -> 0 | AW46: =AV46*(1+AJ46) -> 0 | AX46: =AW46*(1+AK46) -> 0
C47: Total Expenses | E47: =SUM(E30:E46) -> 0 | F47: =SUM(F30:F46) -> 0 | G47: =SUM(G30:G46) -> 0 | I47: =SUM(I30:I46) -> 0 | J47: =SUM(J30:J46) -> #DIV/0! | K47: =I47/I27 -> #DIV/0! | L47: =SUM(L30:L46) -> #DIV/0! | M47: =IFERROR(F47/E47-1,"") | N47: =IFERROR(G47/F47-1,"") | P47: =SUM(P30:P46) -> #VALUE! | Q47: =SUM(Q30:Q46) -> #DIV/0! | R47: =P47/P27 -> #VALUE! | S47: =SUM(S30:S46) -> #DIV/0! | T47: =P47/I47-1 -> #VALUE! | V47: Reserves | Y47: 300 | AM47: =IF(C47<>"",C47,D47) -> Total Expenses | AN47: =SUM(AN30:AN46) -> #VALUE! | AO47: =SUM(AO30:AO46) -> #VALUE! | AP47: =SUM(AP30:AP46) -> #VALUE! | AQ47: =SUM(AQ30:AQ46) -> #VALUE! | AR47: =SUM(AR30:AR46) -> #VALUE! | AS47: =SUM(AS30:AS46) -> #VALUE! | AT47: =SUM(AT30:AT46) -> #VALUE! | AU47: =SUM(AU30:AU46) -> #VALUE! | ... AX47: =SUM(AX30:AX46) -> #VALUE!
V48: *Always % of EGI
C49: Net Operating Income | E49: =E27-E47 -> 0 | F49: =F27-F47 -> 0 | G49: =G27-G47 -> 0 | H49: =H27-H47 -> 0 | I49: =I27-I47 -> 0 | J49: =J27-J47 -> #DIV/0! | K49: =I49/I27 -> #DIV/0! | L49: =L27-L47 -> #DIV/0! | M49: =IFERROR(F49/E49-1,"") | N49: =IFERROR(G49/F49-1,"") | O49: =IFERROR(I49/G49-1,"") | P49: =P27-P47 -> #VALUE! | Q49: =Q27-Q47 -> #DIV/0! | R49: =P49/P27 -> #VALUE! | S49: =S27-S47 -> #DIV/0! | T49: =P49/I49-1 -> #VALUE! | V49: Key: | Y49: Assumption made above | AM49: =IF(C49<>"",C49,D49) -> Net Operating Income | AN49: =AN27-AN47 -> #VALUE! | AO49: =AO27-AO47 -> #VALUE! | AP49: =AP27-AP47 -> #VALUE! | AQ49: =AQ27-AQ47 -> #VALUE! | AR49: =AR27-AR47 -> #VALUE! | AS49: =AS27-AS47 -> #VALUE! | AT49: =AT27-AT47 -> #VALUE! | AU49: =AU27-AU47 -> #VALUE! | ... AX49: =AX27-AX47 -> #VALUE!
X50: Assumption made elsewhere and summarized above
C51: Reserves | E51: =P51 -> 0 | F51: =P51 -> 0 | G51: =P51 -> 0 | I51: =P51 -> 0 | J51: =I51/$Q$1 -> #DIV/0! | K51: =I51/I27 -> #DIV/0! | L51: =I51/$Q$2 -> #DIV/0! | P51: =IF(W47<>"",I51*(1+W47),IF(X47<>"",X47*$P$9,Y47*$Q$1)) -> 0 | Q51: =P51/$Q$1 -> #DIV/0! | R51: =P51/P27 -> #DIV/0! | S51: =P51/$Q$2 -> #DIV/0! | T51: =P51/I51-1 -> #DIV/0! | AM51: =IF(C51<>"",C51,D51) -> Reserves | AN51: =$P$51 -> 0 | AO51: =$P$51 -> 0 | AP51: =$P$51 -> 0 | AQ51: =$P$51 -> 0 | AR51: =$P$51 -> 0 | AS51: =$P$51 -> 0 | AT51: =$P$51 -> 0 | AU51: =$P$51 -> 0 | ... AX51: =$P$51 -> 0
C53: NOI After Reserves | E53: =E49-E51 -> 0 | F53: =F49-F51 -> 0 | G53: =G49-G51 -> 0 | H53: =H49-H51 -> 0 | I53: =I49-I51 -> 0 | J53: =J49-J51 -> #DIV/0! | K53: =K49-K51 -> #DIV/0! | L53: =L49-L51 -> #DIV/0! | M53: =IFERROR(F53/E53-1,"") | N53: =IFERROR(G53/F53-1,"") | O53: =IFERROR(I53/G53-1,"") | P53: =P49-P51 -> #VALUE! | Q53: =Q49-Q51 -> #DIV/0! | R53: =R49-R51 -> #VALUE! | S53: =S49-S51 -> #DIV/0! | T53: =P53/I53-1 -> #VALUE! | AM53: =IF(C53<>"",C53,D53) -> NOI After Reserves | AN53: =AN49-AN51 -> #VALUE! | AO53: =AO49-AO51 -> #VALUE! | AP53: =AP49-AP51 -> #VALUE! | AQ53: =AQ49-AQ51 -> #VALUE! | AR53: =AR49-AR51 -> #VALUE! | AS53: =AS49-AS51 -> #VALUE! | AT53: =AT49-AT51 -> #VALUE! | AU53: =AU49-AU51 -> #VALUE! | ... AX53: =AX49-AX51 -> #VALUE!

Sheet Real Estate Tax
E2: Price: | H2: =Summary!C10 -> 0 | J2: Parcel(s): | K2: 12-234-567-8910
E3: Reassessment Post Sale: | H3: 0 | K3: 12-234-567-8910
E4: Reassessment Year: | H4: 0 | K4: 12-234-567-8910
E5: RE Tax Increase Non-Reassessment Years: | H5: 0
E7: Known Tax Info
E8: Assessment Year | F8: Payable Year | G8: Assessment Amount | H8: Payable | I8: Tax Rate | J8: Discount | K8: Special Assessment | L8: Net Payable
C9: =IF(E9<>"",E9&"/"&F9,"") -> 2021/2022 | E9: 2021 | F9: 2022 | G9: 0 | H9: 0 | I9: =IF(G9<>"",IF(AND(G9<>"",H9<>""),H9/G9,I8),"") -> #DIV/0! | J9: 0 | K9: 0 | L9: =IF(G9<>"",IF(H9<>"",H9*(1-J9)+K9,I9*G9*(1-J9)+K9),"") -> 0
C10: =IF(E10<>"",E10&"/"&F10,"") -> 2022/2023 | E10: =E9+1 -> 2022 | F10: 2023 | G10: 0 | H10: 0 | I10: =IF(G10<>"",IF(AND(G10<>"",H10<>""),H10/G10,I9),"") -> #DIV/0! | J10: 0 | K10: 0 | L10: =IF(G10<>"",IF(H10<>"",H10*(1-J10)+K10,I10*G10*(1-J10)+K10),"") -> 0
C11: =IF(E11<>"",E11&"/"&F11,"") -> 2023/2024 | E11: 2023 | F11: 2024 | G11: 0 | I11: =IF(G11<>"",IF(AND(G11<>"",H11<>""),H11/G11,I10),"") -> #DIV/0! | J11: 0 | K11: 0 | L11: =IF(G11<>"",IF(H11<>"",H11*(1-J11)+K11,I11*G11*(1-J11)+K11),"") -> #DIV/0!
C12: =IF(E12<>"",E12&"/"&F12,"") | I12: =IF(G12<>"",IF(AND(G12<>"",H12<>""),H12/G12,I11),"") | L12: =IF(G12<>"",IF(H12<>"",H12*(1-J12)+K12,I12*G12*(1-J12)+K12),"")
E14: Proforma Year | F14: Assessment/Payable Year | G14: Assessment | H14: Assessment Increase | I14: Tax Rate | J14: Payable | K14: Discount | L14: Special Assessment | M14: Net Payable
B15: =LEFT(F15,4) -> 2022 | C15: =RIGHT(F15,4) -> 2023 | E15: 1 | F15: 2022/2023 | G15: =VLOOKUP(F15,$C$9:$G$11,5,FALSE) -> 0 | H15: =G15/G9-1 -> #DIV/0! | I15: =IFERROR(VLOOKUP(F15,$C$9:$I$11,7,FALSE),I14) -> Tax Rate | J15: =G15*I15 -> #VALUE! | K15: =$J$9 -> 0 | L15: =$K$9 -> 0 | M15: =J15*(1-K15)+L15 -> #VALUE!
B16: =B15+1 -> 2023 | C16: =C15+1 -> 2024 | E16: 2 | F16: =B16&"/"&C16 -> 2023/2024 | G16: =IFERROR(VLOOKUP(F16,$C$9:$G$11,5,FALSE),IF(E16=$H$4,$H$3*$H$2,G15*(1+$H$5))) -> 0 | H16: =G16/G15-1 -> #DIV/0! | I16: =IFERROR(VLOOKUP(F16,$C$9:$I$11,7,FALSE),I15) -> Tax Rate | J16: =G16*I16 -> #VALUE! | K16: =$J$9 -> 0 | L16: =$K$9 -> 0 | M16: =J16*(1-K16)+L16 -> #VALUE!
B17: =B16+1 -> 2024 | C17: =C16+1 -> 2025 | E17: 3 | F17: =B17&"/"&C17 -> 2024/2025 | G17: =IFERROR(VLOOKUP(F17,$C$9:$G$11,5,FALSE),IF(E17=$H$4,$H$3*$H$2,G16*(1+$H$5))) -> 0 | H17: =G17/G16-1 -> #DIV/0! | I17: =IFERROR(VLOOKUP(F17,$C$9:$I$11,7,FALSE),I16) -> Tax Rate | J17: =G17*I17 -> #VALUE! | K17: =$J$9 -> 0 | L17: =$K$9 -> 0 | M17: =J17*(1-K17)+L17 -> #VALUE!
B18: =B17+1 -> 2025 | C18: =C17+1 -> 2026 | E18: 4 | F18: =B18&"/"&C18 -> 2025/2026 | G18: =IFERROR(VLOOKUP(F18,$C$9:$G$11,5,FALSE),IF(E18=$H$4,$H$3*$H$2,G17*(1+$H$5))) -> 0 | H18: =G18/G17-1 -> #DIV/0! | I18: =IFERROR(VLOOKUP(F18,$C$9:$I$11,7,FALSE),I17) -> Tax Rate | J18: =G18*I18 -> #VALUE! | K18: =$J$9 -> 0 | L18: =$K$9 -> 0 | M18: =J18*(1-K18)+L18 -> #VALUE!
B19: =B18+1 -> 2026 | C19: =C18+1 -> 2027 | E19: 5 | F19: =B19&"/"&C19 -> 2026/2027 | G19: =IFERROR(VLOOKUP(F19,$C$9:$G$11,5,FALSE),IF(E19=$H$4,$H$3*$H$2,G18*(1+$H$5))) -> 0 | H19: =G19/G18-1 -> #DIV/0! | I19: =IFERROR(VLOOKUP(F19,$C$9:$I$11,7,FALSE),I18) -> Tax Rate | J19: =G19*I19 -> #VALUE! | K19: =$J$9 -> 0 | L19: =$K$9 -> 0 | M19: =J19*(1-K19)+L19 -> #VALUE!
B20: =B19+1 -> 2027 | C20: =C19+1 -> 2028 | E20: 6 | F20: =B20&"/"&C20 -> 2027/2028 | G20: =IFERROR(VLOOKUP(F20,$C$9:$G$11,5,FALSE),IF(E20=$H$4,$H$3*$H$2,G19*(1+$H$5))) -> 0 | H20: =G20/G19-1 -> #DIV/0! | I20: =IFERROR(VLOOKUP(F20,$C$9:$I$11,7,FALSE),I19) -> Tax Rate | J20: =G20*I20 -> #VALUE! | K20: =$J$9 -> 0 | L20: =$K$9 -> 0 | M20: =J20*(1-K20)+L20 -> #VALUE!
B21: =B20+1 -> 2028 | C21: =C20+1 -> 2029 | E21: 7 | F21: =B21&"/"&C21 -> 2028/2029 | G21: =IFERROR(VLOOKUP(F21,$C$9:$G$11,5,FALSE),IF(E21=$H$4,$H$3*$H$2,G20*(1+$H$5))) -> 0 | H21: =G21/G20-1 -> #DIV/0! | I21: =IFERROR(VLOOKUP(F21,$C$9:$I$11,7,FALSE),I20) -> Tax Rate | J21: =G21*I21 -> #VALUE! | K21: =$J$9 -> 0 | L21: =$K$9 -> 0 | M21: =J21*(1-K21)+L21 -> #VALUE!
B22: =B21+1 -> 2029 | C22: =C21+1 -> 2030 | E22: 8 | F22: =B22&"/"&C22 -> 2029/2030 | G22: =IFERROR(VLOOKUP(F22,$C$9:$G$11,5,FALSE),IF(E22=$H$4,$H$3*$H$2,G21*(1+$H$5))) -> 0 | H22: =G22/G21-1 -> #DIV/0! | I22: =IFERROR(VLOOKUP(F22,$C$9:$I$11,7,FALSE),I21) -> Tax Rate | J22: =G22*I22 -> #VALUE! | K22: =$J$9 -> 0 | L22: =$K$9 -> 0 | M22: =J22*(1-K22)+L22 -> #VALUE!
B23: =B22+1 -> 2030 | C23: =C22+1 -> 2031 | E23: 9 | F23: =B23&"/"&C23 -> 2030/2031 | G23: =IFERROR(VLOOKUP(F23,$C$9:$G$11,5,FALSE),IF(E23=$H$4,$H$3*$H$2,G22*(1+$H$5))) -> 0 | H23: =G23/G22-1 -> #DIV/0! | I23: =IFERROR(VLOOKUP(F23,$C$9:$I$11,7,FALSE),I22) -> Tax Rate | J23: =G23*I23 -> #VALUE! | K23: =$J$9 -> 0 | L23: =$K$9 -> 0 | M23: =J23*(1-K23)+L23 -> #VALUE!
B24: =B23+1 -> 2031 | C24: =C23+1 -> 2032 | E24: 10 | F24: =B24&"/"&C24 -> 2031/2032 | G24: =IFERROR(VLOOKUP(F24,$C$9:$G$11,5,FALSE),IF(E24=$H$4,$H$3*$H$2,G23*(1+$H$5))) -> 0 | H24: =G24/G23-1 -> #DIV/0! | I24: =IFERROR(VLOOKUP(F24,$C$9:$I$11,7,FALSE),I23) -> Tax Rate | J24: =G24*I24 -> #VALUE! | K24: =$J$9 -> 0 | L24: =$K$9 -> 0 | M24: =J24*(1-K24)+L24 -> #VALUE!
B25: =B24+1 -> 2032 | C25: =C24+1 -> 2033 | E25: 11 | F25: =B25&"/"&C25 -> 2032/2033 | G25: =IFERROR(VLOOKUP(F25,$C$9:$G$11,5,FALSE),IF(E25=$H$4,$H$3*$H$2,G24*(1+$H$5))) -> 0 | H25: =G25/G24-1 -> #DIV/0! | I25: =IFERROR(VLOOKUP(F25,$C$9:$I$11,7,FALSE),I24) -> Tax Rate | J25: =G25*I25 -> #VALUE! | K25: =$J$9 -> 0 | L25: =$K$9 -> 0 | M25: =J25*(1-K25)+L25 -> #VALUE!

Sheet Valuation
G1: 1 | H1: 2 | I1: 3 | J1: 4 | K1: 5 | L1: 6 | M1: 7 | N1: 8 | O1: 9 | P1: 10
B2: Price: | C2: =Summary!C10 -> 0
E3: Price | F3: =C2 -> 0 | H3: Capital Assumptions | L3: Financing | M3: Source 1 | O3: =L3 -> Financing | P3: Source 2
B4: Financing | E4: Price Per Unit: | F4: =F3/Financials!$Q$1 -> #DIV/0! | H4: Working Capital Amount: | J4: =C10 -> 0 | L4: =Debt!C3 -> Debt Name: | M4: =Debt!D3 -> - | O4: =L4 -> Debt Name: | P4: =Debt!X3 -> 0
B5: Primary Financing | C5: Yes | E5: =IF(Summary!F7="U.S.","Price Per SF:","Price Per SM:") -> Price Per SF: | F5: =F3/'Unit Mix'!E10 -> #DIV/0! | H5: Number of Years: | J5: =C11 -> 0 | L5: =Debt!C5 -> LTV: | M5: =Debt!D5 -> 0 | O5: =L5 -> LTV: | P5: =Debt!X5 -> 0
B6: Secondary Financing | C6: No | L6: =Debt!C6 -> Loan Amount: | M6: =Debt!D6 -> 0 | O6: =L6 -> Loan Amount: | P6: =Debt!X6 -> 0
B7: Total LTV | C7: =-SUM(F40:F42)/F34 -> #DIV/0! | E7: Cap Rates | H7: Closing/Residual Assumptions | L7: =Debt!C7 -> Int. Rate: | M7: =Debt!D7 -> 0 | O7: =L7 -> Int. Rate: | P7: =Debt!X7 -> 0
E8: =Financials!G5&":" -> T12: | F8: =Financials!G53/-Valuation!F34 -> #DIV/0! | H8: Escrow Costs (Year 0): | J8: =Summary!$F$11 -> 0 | L8: =Debt!C8 -> Term: | M8: =Debt!D8 -> 0 | O8: =L8 -> Term: | P8: =Debt!X8 -> 0
B9: Capital Contingencies | E9: =Financials!$I$5&":" -> T3/T12: | F9: =Financials!I53/-Valuation!F34 -> #DIV/0! | H9: Stabilized Cap Rate Today: | J9: =Summary!F13 -> 0 | L9: =Debt!C9 -> Amortization: | M9: =Debt!D9 -> 0 | O9: =L9 -> Amortization: | P9: =Debt!X9 -> 0
B10: Working Capital Amount | C10: 0 | E10: =Financials!$I$5&" Adjusted: FY1 RE Tax:" -> T3/T12 Adjusted: FY1 RE Tax: | F10: =(Financials!I53+(Financials!$I$43-Financials!$P$43))/-Valuation!F34 -> #VALUE! | H10: Cap Rate Increment/Year: | J10: =Summary!F14 -> 0 | L10: =Debt!C10 -> Loan Cost: | M10: =Debt!D10 -> 0 | O10: =L10 -> Loan Cost: | P10: =Debt!X10 -> 0
B11: Number of Years | C11: 0 | E11: =Financials!$I$5&" Adjusted: Post-Sale RE Tax:" -> T3/T12 Adjusted: Post-Sale RE Tax: | F11: =(Financials!I53-(VLOOKUP('Real Estate Tax'!$H$4,'Real Estate Tax'!$E$15:$J$25,6,FALSE)-Financials!I43))/Valuation!C2 -> #N/A | H11: Brokerage Commission @ Sale: | J11: =Summary!F16 -> 0 | L11: =Debt!F3 -> Assumption: | M11: =Debt!G3 -> Yes | O11: =L11 -> Assumption: | P11: =Debt!AA3 -> Yes
E12: FY1: | F12: =Financials!P53/-Valuation!F34 -> #VALUE! | H12: Other Closing Costs: | J12: =Summary!F17 -> 0
E13: FY1 Adjusted: Post-Sale RE Tax: | F13: =(Financials!P53-(VLOOKUP('Real Estate Tax'!$H$4,'Real Estate Tax'!$E$15:$J$25,6,FALSE)-Financials!P43))/Valuation!C2 -> #VALUE!
F15: Purchase | G15: FY1 | H15: FY2 | I15: FY3 | J15: FY4 | K15: FY5 | L15: FY6 | M15: FY7 | N15: FY8 | O15: FY9 | P15: FY10 | Q15: FY11
E16: Effective Gross Income | G16: =Financials!AN27 -> 0 | H16: =Financials!AO27 -> 0 | I16: =Financials!AP27 -> 0 | J16: =Financials!AQ27 -> 0 | K16: =Financials!AR27 -> 0 | L16: =Financials!AS27 -> 0 | M16: =Financials!AT27 -> 0 | N16: =Financials!AU27 -> 0 | ... Q16: =Financials!AX27 -> 0
E17: Total Expenses | G17: =Financials!AN47 -> #VALUE! | H17: =Financials!AO47 -> #VALUE! | I17: =Financials!AP47 -> #VALUE! | J17: =Financials!AQ47 -> #VALUE! | K17: =Financials!AR47 -> #VALUE! | L17: =Financials!AS47 -> #VALUE! | M17: =Financials!AT47 -> #VALUE! | N17: =Financials!AU47 -> #VALUE! | ... Q17: =Financials!AX47 -> #VALUE!
E18: Reserves | G18: =Financials!AN51 -> 0 | H18: =Financials!AO51 -> 0 | I18: =Financials!AP51 -> 0 | J18: =Financials!AQ51 -> 0 | K18: =Financials!AR51 -> 0 | L18: =Financials!AS51 -> 0 | M18: =Financials!AT51 -> 0 | N18: =Financials!AU51 -> 0 | ... Q18: =Financials!AX51 -> 0
E19: NOI After Reserves | G19: =Financials!AN53 -> #VALUE! | H19: =Financials!AO53 -> #VALUE! | I19: =Financials!AP53 -> #VALUE! | J19: =Financials!AQ53 -> #VALUE! | K19: =Financials!AR53 -> #VALUE! | L19: =Financials!AS53 -> #VALUE! | M19: =Financials!AT53 -> #VALUE! | N19: =Financials!AU53 -> #VALUE! | ... Q19: =Financials!AX53 -> #VALUE!
E21: Capital
E22: Additional Working Capital | G22: =IF(G1<=$C$11,-$C$10/$C$11,0) -> 0 | H22: =IF(H1<=$C$11,-$C$10/$C$11,0) -> 0 | I22: =IF(I1<=$C$11,-$C$10/$C$11,0) -> 0 | J22: =IF(J1<=$C$11,-$C$10/$C$11,0) -> 0 | K22: =IF(K1<=$C$11,-$C$10/$C$11,0) -> 0 | L22: =IF(L1<=$C$11,-$C$10/$C$11,0) -> 0 | M22: =IF(M1<=$C$11,-$C$10/$C$11,0) -> 0 | N22: =IF(N1<=$C$11,-$C$10/$C$11,0) -> 0 | ... P22: =IF(P1<=$C$11,-$C$10/$C$11,0) -> 0
E23: Operating Cash Flow | G23: =SUM(G22:G22)+G19 -> #VALUE! | H23: =SUM(H22:H22)+H19 -> #VALUE! | I23: =SUM(I22:I22)+I19 -> #VALUE! | J23: =SUM(J22:J22)+J19 -> #VALUE! | K23: =SUM(K22:K22)+K19 -> #VALUE! | L23: =SUM(L22:L22)+L19 -> #VALUE! | M23: =SUM(M22:M22)+M19 -> #VALUE! | N23: =SUM(N22:N22)+N19 -> #VALUE! | ... P23: =SUM(P22:P22)+P19 -> #VALUE!
E25: Financing
E26: =Debt!$D$3&" Loan Principal" -> - Loan Principal | G26: =IF($C$5<>"Yes",0,-IF(Debt!$G$10=1,Debt!L4,IF(Debt!$G$10=2,Debt!L10,Debt!L16))) -> #NUM! | H26: =IF($C$5<>"Yes",0,-IF(Debt!$G$10=1,Debt!M4,IF(Debt!$G$10=2,Debt!M10,Debt!M16))) -> #NUM! | I26: =IF($C$5<>"Yes",0,-IF(Debt!$G$10=1,Debt!N4,IF(Debt!$G$10=2,Debt!N10,Debt!N16))) -> #NUM! | J26: =IF($C$5<>"Yes",0,-IF(Debt!$G$10=1,Debt!O4,IF(Debt!$G$10=2,Debt!O10,Debt!O16))) -> #NUM! | K26: =IF($C$5<>"Yes",0,-IF(Debt!$G$10=1,Debt!P4,IF(Debt!$G$10=2,Debt!P10,Debt!P16))) -> #NUM! | L26: =IF($C$5<>"Yes",0,-IF(Debt!$G$10=1,Debt!Q4,IF(Debt!$G$10=2,Debt!Q10,Debt!Q16))) -> #NUM! | M26: =IF($C$5<>"Yes",0,-IF(Debt!$G$10=1,Debt!R4,IF(Debt!$G$10=2,Debt!R10,Debt!R16))) -> #NUM! | N26: =IF($C$5<>"Yes",0,-IF(Debt!$G$10=1,Debt!S4,IF(Debt!$G$10=2,Debt!S10,Debt!S16))) -> #NUM! | ... P26: =IF($C$5<>"Yes",0,-IF(Debt!$G$10=1,Debt!U4,IF(Debt!$G$10=2,Debt!U10,Debt!U16))) -> #NUM!
E27: =Debt!$D$3&" Loan Interest" -> - Loan Interest | G27: =IF($C$5<>"Yes",0,-IF(Debt!$G$10=1,Debt!L5,IF(Debt!$G$10=2,Debt!L11,Debt!L17))) -> #NUM! | H27: =IF($C$5<>"Yes",0,-IF(Debt!$G$10=1,Debt!M5,IF(Debt!$G$10=2,Debt!M11,Debt!M17))) -> #NUM! | I27: =IF($C$5<>"Yes",0,-IF(Debt!$G$10=1,Debt!N5,IF(Debt!$G$10=2,Debt!N11,Debt!N17))) -> #NUM! | J27: =IF($C$5<>"Yes",0,-IF(Debt!$G$10=1,Debt!O5,IF(Debt!$G$10=2,Debt!O11,Debt!O17))) -> #NUM! | K27: =IF($C$5<>"Yes",0,-IF(Debt!$G$10=1,Debt!P5,IF(Debt!$G$10=2,Debt!P11,Debt!P17))) -> #NUM! | L27: =IF($C$5<>"Yes",0,-IF(Debt!$G$10=1,Debt!Q5,IF(Debt!$G$10=2,Debt!Q11,Debt!Q17))) -> #NUM! | M27: =IF($C$5<>"Yes",0,-IF(Debt!$G$10=1,Debt!R5,IF(Debt!$G$10=2,Debt!R11,Debt!R17))) -> #NUM! | N27: =IF($C$5<>"Yes",0,-IF(Debt!$G$10=1,Debt!S5,IF(Debt!$G$10=2,Debt!S11,Debt!S17))) -> #NUM! | ... P27: =IF($C$5<>"Yes",0,-IF(Debt!$G$10=1,Debt!U5,IF(Debt!$G$10=2,Debt!U11,Debt!U17))) -> #NUM!
E28: =Debt!$X$3&" Loan Principal" -> 0 Loan Principal | G28: =IF($C$6<>"Yes",0,-IF(Debt!$AA$10=1,Debt!AF4,IF(Debt!$AA$10=2,Debt!AF10,Debt!AF16))) -> 0 | H28: =IF($C$6<>"Yes",0,-IF(Debt!$AA$10=1,Debt!AG4,IF(Debt!$AA$10=2,Debt!AG10,Debt!AG16))) -> 0 | I28: =IF($C$6<>"Yes",0,-IF(Debt!$AA$10=1,Debt!AH4,IF(Debt!$AA$10=2,Debt!AH10,Debt!AH16))) -> 0 | J28: =IF($C$6<>"Yes",0,-IF(Debt!$AA$10=1,Debt!AI4,IF(Debt!$AA$10=2,Debt!AI10,Debt!AI16))) -> 0 | K28: =IF($C$6<>"Yes",0,-IF(Debt!$AA$10=1,Debt!AJ4,IF(Debt!$AA$10=2,Debt!AJ10,Debt!AJ16))) -> 0 | L28: =IF($C$6<>"Yes",0,-IF(Debt!$AA$10=1,Debt!AK4,IF(Debt!$AA$10=2,Debt!AK10,Debt!AK16))) -> 0 | M28: =IF($C$6<>"Yes",0,-IF(Debt!$AA$10=1,Debt!AL4,IF(Debt!$AA$10=2,Debt!AL10,Debt!AL16))) -> 0 | N28: =IF($C$6<>"Yes",0,-IF(Debt!$AA$10=1,Debt!AM4,IF(Debt!$AA$10=2,Debt!AM10,Debt!AM16))) -> 0 | ... P28: =IF($C$6<>"Yes",0,-IF(Debt!$AA$10=1,Debt!AO4,IF(Debt!$AA$10=2,Debt!AO10,Debt!AO16))) -> 0
E29: =Debt!$X$3&" Loan Interest" -> 0 Loan Interest | G29: =IF($C$6<>"Yes",0,-IF(Debt!$AA$10=1,Debt!AF5,IF(Debt!$AA$10=2,Debt!AF11,Debt!AF17))) -> 0 | H29: =IF($C$6<>"Yes",0,-IF(Debt!$AA$10=1,Debt!AG5,IF(Debt!$AA$10=2,Debt!AG11,Debt!AG17))) -> 0 | I29: =IF($C$6<>"Yes",0,-IF(Debt!$AA$10=1,Debt!AH5,IF(Debt!$AA$10=2,Debt!AH11,Debt!AH17))) -> 0 | J29: =IF($C$6<>"Yes",0,-IF(Debt!$AA$10=1,Debt!AI5,IF(Debt!$AA$10=2,Debt!AI11,Debt!AI17))) -> 0 | K29: =IF($C$6<>"Yes",0,-IF(Debt!$AA$10=1,Debt!AJ5,IF(Debt!$AA$10=2,Debt!AJ11,Debt!AJ17))) -> 0 | L29: =IF($C$6<>"Yes",0,-IF(Debt!$AA$10=1,Debt!AK5,IF(Debt!$AA$10=2,Debt!AK11,Debt!AK17))) -> 0 | M29: =IF($C$6<>"Yes",0,-IF(Debt!$AA$10=1,Debt!AL5,IF(Debt!$AA$10=2,Debt!AL11,Debt!AL17))) -> 0 | N29: =IF($C$6<>"Yes",0,-IF(Debt!$AA$10=1,Debt!AM5,IF(Debt!$AA$10=2,Debt!AM11,Debt!AM17))) -> 0 | ... P29: =IF($C$6<>"Yes",0,-IF(Debt!$AA$10=1,Debt!AO5,IF(Debt!$AA$10=2,Debt!AO11,Debt!AO17))) -> 0
E30: Cash Flow After Debt | G30: =SUM(G25:G29)+G23 -> #NUM! | H30: =SUM(H25:H29)+H23 -> #NUM! | I30: =SUM(I25:I29)+I23 -> #NUM! | J30: =SUM(J25:J29)+J23 -> #NUM! | K30: =SUM(K25:K29)+K23 -> #NUM! | L30: =SUM(L25:L29)+L23 -> #NUM! | M30: =SUM(M25:M29)+M23 -> #NUM! | N30: =SUM(N25:N29)+N23 -> #NUM! | ... P30: =SUM(P25:P29)+P23 -> #NUM!
E31: DSCR | G31: =G19/(IF($C$5="yes",Debt!$D$15,0)+IF($C$6="yes",Debt!$X$15,0)) -> #VALUE! | H31: =H19/(IF($C$5="yes",Debt!$D$15,0)+IF($C$6="yes",Debt!$X$15,0)) -> #VALUE! | I31: =I19/(IF($C$5="yes",Debt!$D$15,0)+IF($C$6="yes",Debt!$X$15,0)) -> #VALUE! | J31: =J19/(IF($C$5="yes",Debt!$D$15,0)+IF($C$6="yes",Debt!$X$15,0)) -> #VALUE! | K31: =K19/(IF($C$5="yes",Debt!$D$15,0)+IF($C$6="yes",Debt!$X$15,0)) -> #VALUE! | L31: =L19/(IF($C$5="yes",Debt!$D$15,0)+IF($C$6="yes",Debt!$X$15,0)) -> #VALUE! | M31: =M19/(IF($C$5="yes",Debt!$D$15,0)+IF($C$6="yes",Debt!$X$15,0)) -> #VALUE! | N31: =N19/(IF($C$5="yes",Debt!$D$15,0)+IF($C$6="yes",Debt!$X$15,0)) -> #VALUE! | ... P31: =P19/(IF($C$5="yes",Debt!$D$15,0)+IF($C$6="yes",Debt!$X$15,0)) -> #VALUE!
E33: Purchase/Disposition
E34: Acquisition | F34: =-$C$2 -> 0
E35: Escrow/Closing | F35: =-Summary!F11 -> 0
E36: Residual Cap Rate | G36: =Summary!F13+Summary!F14 -> 0 | H36: =G36+Summary!$F$14 -> 0 | I36: =H36+Summary!$F$14 -> 0 | J36: =I36+Summary!$F$14 -> 0 | K36: =J36+Summary!$F$14 -> 0 | L36: =K36+Summary!$F$14 -> 0 | M36: =L36+Summary!$F$14 -> 0 | N36: =M36+Summary!$F$14 -> 0 | O36: =N36+Summary!$F$14 -> 0 | P36: =O36+Summary!$F$14 -> 0
E37: Residual Value | G37: =H19/G36 -> #VALUE! | H37: =I19/H36 -> #VALUE! | I37: =J19/I36 -> #VALUE! | J37: =K19/J36 -> #VALUE! | K37: =L19/K36 -> #VALUE! | L37: =M19/L36 -> #VALUE! | M37: =N19/M36 -> #VALUE! | N37: =O19/N36 -> #VALUE! | ... P37: =Q19/P36 -> #VALUE!
E38: Cost of Sale | G38: =-(Summary!$F$18*Valuation!G37) -> #VALUE! | H38: =-(Summary!$F$18*Valuation!H37) -> #VALUE! | I38: =-(Summary!$F$18*Valuation!I37) -> #VALUE! | J38: =-(Summary!$F$18*Valuation!J37) -> #VALUE! | K38: =-(Summary!$F$18*Valuation!K37) -> #VALUE! | L38: =-(Summary!$F$18*Valuation!L37) -> #VALUE! | M38: =-(Summary!$F$18*Valuation!M37) -> #VALUE! | N38: =-(Summary!$F$18*Valuation!N37) -> #VALUE! | ... P38: =-(Summary!$F$18*Valuation!P37) -> #VALUE!
E39: =Debt!$D$3&" Loan Cost" -> - Loan Cost | F39: =IF($C$5<>"Yes",0,F40*-Summary!$C$28) -> 0
E40: =Debt!$D$3&" Loan Payoff" -> - Loan Payoff | F40: =IF($C$5<>"Yes",0,IF(Debt!$G$10=1,Debt!K4,IF(Debt!$G$10=2,Debt!K10,Debt!K16))) -> 0 | G40: =IF($C$5<>"Yes",0,IF(Debt!$G$10=1,Debt!L6,IF(Debt!$G$10=2,Debt!L12,Debt!L18))) -> #NUM! | H40: =IF($C$5<>"Yes",0,IF(Debt!$G$10=1,Debt!M6,IF(Debt!$G$10=2,Debt!M12,Debt!M18))) -> #NUM! | I40: =IF($C$5<>"Yes",0,IF(Debt!$G$10=1,Debt!N6,IF(Debt!$G$10=2,Debt!N12,Debt!N18))) -> #NUM! | J40: =IF($C$5<>"Yes",0,IF(Debt!$G$10=1,Debt!O6,IF(Debt!$G$10=2,Debt!O12,Debt!O18))) -> #NUM! | K40: =IF($C$5<>"Yes",0,IF(Debt!$G$10=1,Debt!P6,IF(Debt!$G$10=2,Debt!P12,Debt!P18))) -> #NUM! | L40: =IF($C$5<>"Yes",0,IF(Debt!$G$10=1,Debt!Q6,IF(Debt!$G$10=2,Debt!Q12,Debt!Q18))) -> #NUM! | M40: =IF($C$5<>"Yes",0,IF(Debt!$G$10=1,Debt!R6,IF(Debt!$G$10=2,Debt!R12,Debt!R18))) -> #NUM! | N40: =IF($C$5<>"Yes",0,IF(Debt!$G$10=1,Debt!S6,IF(Debt!$G$10=2,Debt!S12,Debt!S18))) -> #NUM! | ... P40: =IF($C$5<>"Yes",0,IF(Debt!$G$10=1,Debt!U6,IF(Debt!$G$10=2,Debt!U12,Debt!U18))) -> #NUM!
E41: =Debt!$X$3&" Loan Cost" -> 0 Loan Cost | F41: =IF($C$5<>"Yes",0,F42*-Summary!$C$40) -> 0
E42: =Debt!$X$3&" Loan Payoff" -> 0 Loan Payoff | F42: =IF($C$6<>"Yes",0,IF(Debt!$AA$10=1,Debt!AE4,IF(Debt!$AA$10=2,Debt!$AE$10,Debt!$AE$16))) -> 0 | G42: =IF($C$6<>"Yes",0,IF(Debt!$AA$10=1,Debt!AF6,IF(Debt!$AA$10=2,Debt!AF12,Debt!AF18))) -> 0 | H42: =IF($C$6<>"Yes",0,IF(Debt!$AA$10=1,Debt!AG6,IF(Debt!$AA$10=2,Debt!AG12,Debt!AG18))) -> 0 | I42: =IF($C$6<>"Yes",0,IF(Debt!$AA$10=1,Debt!AH6,IF(Debt!$AA$10=2,Debt!AH12,Debt!AH18))) -> 0 | J42: =IF($C$6<>"Yes",0,IF(Debt!$AA$10=1,Debt!AI6,IF(Debt!$AA$10=2,Debt!AI12,Debt!AI18))) -> 0 | K42: =IF($C$6<>"Yes",0,IF(Debt!$AA$10=1,Debt!AJ6,IF(Debt!$AA$10=2,Debt!AJ12,Debt!AJ18))) -> 0 | L42: =IF($C$6<>"Yes",0,IF(Debt!$AA$10=1,Debt!AK6,IF(Debt!$AA$10=2,Debt!AK12,Debt!AK18))) -> 0 | M42: =IF($C$6<>"Yes",0,IF(Debt!$AA$10=1,Debt!AL6,IF(Debt!$AA$10=2,Debt!AL12,Debt!AL18))) -> 0 | N42: =IF($C$6<>"Yes",0,IF(Debt!$AA$10=1,Debt!AM6,IF(Debt!$AA$10=2,Debt!AM12,Debt!AM18))) -> 0 | ... P42: =IF($C$6<>"Yes",0,IF(Debt!$AA$10=1,Debt!AO6,IF(Debt!$AA$10=2,Debt!AO12,Debt!AO18))) -> 0
E43: Net Sale Proceeds | F43: =SUM(F34:F42) -> 0 | G43: =SUM(G37:G42) -> #VALUE! | H43: =SUM(H37:H42) -> #VALUE! | I43: =SUM(I37:I42) -> #VALUE! | J43: =SUM(J37:J42) -> #VALUE! | K43: =SUM(K37:K42) -> #VALUE! | L43: =SUM(L37:L42) -> #VALUE! | M43: =SUM(M37:M42) -> #VALUE! | N43: =SUM(N37:N42) -> #VALUE! | ... P43: =SUM(P37:P42) -> #VALUE!
E45: All Cash IRR: | G45: =IRR(G46:G56) -> #VALUE! | H45: =IRR(H46:H56) -> #VALUE! | I45: =IRR(I46:I56) -> #VALUE! | J45: =IRR(J46:J56) -> #VALUE! | K45: =IRR(K46:K56) -> #VALUE! | L45: =IRR(L46:L56) -> #VALUE! | M45: =IRR(M46:M56) -> #VALUE! | N45: =IRR(N46:N56) -> #VALUE! | ... P45: =IRR(P46:P56) -> #VALUE!
F46: 0 | G46: =SUM($F$34:$F$35) -> 0 | H46: =SUM($F$34:$F$35) -> 0 | I46: =SUM($F$34:$F$35) -> 0 | J46: =SUM($F$34:$F$35) -> 0 | K46: =SUM($F$34:$F$35) -> 0 | L46: =SUM($F$34:$F$35) -> 0 | M46: =SUM($F$34:$F$35) -> 0 | N46: =SUM($F$34:$F$35) -> 0 | ... P46: =SUM($F$34:$F$35) -> 0
F47: 1 | G47: =$G$23+G37+G38 -> #VALUE! | H47: =$G$23 -> #VALUE! | I47: =$G$23 -> #VALUE! | J47: =$G$23 -> #VALUE! | K47: =$G$23 -> #VALUE! | L47: =$G$23 -> #VALUE! | M47: =$G$23 -> #VALUE! | N47: =$G$23 -> #VALUE! | O47: =$G$23 -> #VALUE! | P47: =$G$23 -> #VALUE!
F48: 2 | H48: =$H$23+H37+H38 -> #VALUE! | I48: =$H$23 -> #VALUE! | J48: =$H$23 -> #VALUE! | K48: =$H$23 -> #VALUE! | L48: =$H$23 -> #VALUE! | M48: =$H$23 -> #VALUE! | N48: =$H$23 -> #VALUE! | O48: =$H$23 -> #VALUE! | P48: =$H$23 -> #VALUE!
F49: 3 | I49: =$I$23+I37+I38 -> #VALUE! | J49: =$I$23 -> #VALUE! | K49: =$I$23 -> #VALUE! | L49: =$I$23 -> #VALUE! | M49: =$I$23 -> #VALUE! | N49: =$I$23 -> #VALUE! | O49: =$I$23 -> #VALUE! | P49: =$I$23 -> #VALUE!
F50: 4 | J50: =$J$23+J37+J38 -> #VALUE! | K50: =$J$23 -> #VALUE! | L50: =$J$23 -> #VALUE! | M50: =$J$23 -> #VALUE! | N50: =$J$23 -> #VALUE! | O50: =$J$23 -> #VALUE! | P50: =$J$23 -> #VALUE!
F51: 5 | K51: =$K$23+K37+K38 -> #VALUE! | L51: =$K$23 -> #VALUE! | M51: =$K$23 -> #VALUE! | N51: =$K$23 -> #VALUE! | O51: =$K$23 -> #VALUE! | P51: =$K$23 -> #VALUE!
F52: 6 | L52: =$L$23+L37+L38 -> #VALUE! | M52: =$L$23 -> #VALUE! | N52: =$L$23 -> #VALUE! | O52: =$L$23 -> #VALUE! | P52: =$L$23 -> #VALUE!
F53: 7 | M53: =$M$23+M37+M38 -> #VALUE! | N53: =$M$23 -> #VALUE! | O53: =$M$23 -> #VALUE! | P53: =$M$23 -> #VALUE!
F54: 8 | N54: =$N$23+N37+N38 -> #VALUE! | O54: =$N$23 -> #VALUE! | P54: =$N$23 -> #VALUE!
F55: 9 | O55: =$O$23+O37+O38 -> #VALUE! | P55: =$O$23 -> #VALUE!
F56: 10 | P56: =$P$23+P37+P38 -> #VALUE!
E57: Levered IRR: | G57: =IRR(G58:G68) -> #VALUE! | H57: =IRR(H58:H68) -> #VALUE! | I57: =IRR(I58:I68) -> #VALUE! | J57: =IRR(J58:J68) -> #VALUE! | K57: =IRR(K58:K68) -> #VALUE! | L57: =IRR(L58:L68) -> #VALUE! | M57: =IRR(M58:M68) -> #VALUE! | N57: =IRR(N58:N68) -> #VALUE! | ... P57: =IRR(P58:P68) -> #VALUE!
F58: 0 | G58: =$F$43 -> 0 | H58: =$F$43 -> 0 | I58: =$F$43 -> 0 | J58: =$F$43 -> 0 | K58: =$F$43 -> 0 | L58: =$F$43 -> 0 | M58: =$F$43 -> 0 | N58: =$F$43 -> 0 | ... P58: =$F$43 -> 0
F59: 1 | G59: =$G$30+G43 -> #NUM! | H59: =$G$30 -> #NUM! | I59: =$G$30 -> #NUM! | J59: =$G$30 -> #NUM! | K59: =$G$30 -> #NUM! | L59: =$G$30 -> #NUM! | M59: =$G$30 -> #NUM! | N59: =$G$30 -> #NUM! | O59: =$G$30 -> #NUM! | P59: =$G$30 -> #NUM!
F60: 2 | H60: =$H$30+H43 -> #NUM! | I60: =$H$30 -> #NUM! | J60: =$H$30 -> #NUM! | K60: =$H$30 -> #NUM! | L60: =$H$30 -> #NUM! | M60: =$H$30 -> #NUM! | N60: =$H$30 -> #NUM! | O60: =$H$30 -> #NUM! | P60: =$H$30 -> #NUM!
F61: 3 | I61: =$I$30+I43 -> #NUM! | J61: =$I$30 -> #NUM! | K61: =$I$30 -> #NUM! | L61: =$I$30 -> #NUM! | M61: =$I$30 -> #NUM! | N61: =$I$30 -> #NUM! | O61: =$I$30 -> #NUM! | P61: =$I$30 -> #NUM!
F62: 4 | J62: =$J$30+J43 -> #NUM! | K62: =$J$30 -> #NUM! | L62: =$J$30 -> #NUM! | M62: =$J$30 -> #NUM! | N62: =$J$30 -> #NUM! | O62: =$J$30 -> #NUM! | P62: =$J$30 -> #NUM!
F63: 5 | K63: =$K$30+K43 -> #NUM! | L63: =$K$30 -> #NUM! | M63: =$K$30 -> #NUM! | N63: =$K$30 -> #NUM! | O63: =$K$30 -> #NUM! | P63: =$K$30 -> #NUM!
F64: 6 | L64: =$L$30+L43 -> #NUM! | M64: =$L$30 -> #NUM! | N64: =$L$30 -> #NUM! | O64: =$L$30 -> #NUM! | P64: =$L$30 -> #NUM!
F65: 7 | M65: =$M$30+M43 -> #NUM! | N65: =$M$30 -> #NUM! | O65: =$M$30 -> #NUM! | P65: =$M$30 -> #NUM!
F66: 8 | N66: =$N$30+N43 -> #NUM! | O66: =$N$30 -> #NUM! | P66: =$N$30 -> #NUM!
F67: 9 | O67: =$O$30+O43 -> #NUM! | P67: =$O$30 -> #NUM!
F68: 10 | P68: =$P$30+P43 -> #NUM!
E69: Equity Multiple: | G69: =(SUM($G$30:G30)+G43)/-$F$43 -> #NUM! | H69: =(SUM($G$30:H30)+H43)/-$F$43 -> #NUM! | I69: =(SUM($G$30:I30)+I43)/-$F$43 -> #NUM! | J69: =(SUM($G$30:J30)+J43)/-$F$43 -> #NUM! | K69: =(SUM($G$30:K30)+K43)/-$F$43 -> #NUM! | L69: =(SUM($G$30:L30)+L43)/-$F$43 -> #NUM! | M69: =(SUM($G$30:M30)+M43)/-$F$43 -> #NUM! | N69: =(SUM($G$30:N30)+N43)/-$F$43 -> #NUM! | ... P69: =(SUM($G$30:P30)+P43)/-$F$43 -> #NUM!
E71: All Cash Return: | G71: =G19/G73 -> #VALUE! | H71: =H19/H73 -> #VALUE! | I71: =I19/I73 -> #VALUE! | J71: =J19/J73 -> #VALUE! | K71: =K19/K73 -> #VALUE! | L71: =L19/L73 -> #VALUE! | M71: =M19/M73 -> #VALUE! | N71: =N19/N73 -> #VALUE! | ... P71: =P19/P73 -> #VALUE!
E72: Cash on Cash Return: | G72: =(G30-G22)/G74 -> #NUM! | H72: =(H30-H22)/H74 -> #NUM! | I72: =(I30-I22)/I74 -> #NUM! | J72: =(J30-J22)/J74 -> #NUM! | K72: =(K30-K22)/K74 -> #NUM! | L72: =(L30-L22)/L74 -> #NUM! | M72: =(M30-M22)/M74 -> #NUM! | N72: =(N30-N22)/N74 -> #NUM! | ... P72: =(P30-P22)/P74 -> #NUM!
E73: All-Cash Basis | F73: =-F34-F35 -> 0 | G73: =F73-SUM(G22:G22) -> 0 | H73: =G73-SUM(H22:H22) -> 0 | I73: =H73-SUM(I22:I22) -> 0 | J73: =I73-SUM(J22:J22) -> 0 | K73: =J73-SUM(K22:K22) -> 0 | L73: =K73-SUM(L22:L22) -> 0 | M73: =L73-SUM(M22:M22) -> 0 | N73: =M73-SUM(N22:N22) -> 0 | ... P73: =O73-SUM(P22:P22) -> 0
E74: Leveraged Basis | F74: =-F43 -> 0 | G74: =F74-SUM(G22:G22) -> 0 | H74: =G74-SUM(H22:H22) -> 0 | I74: =H74-SUM(I22:I22) -> 0 | J74: =I74-SUM(J22:J22) -> 0 | K74: =J74-SUM(K22:K22) -> 0 | L74: =K74-SUM(L22:L22) -> 0 | M74: =L74-SUM(M22:M22) -> 0 | N74: =M74-SUM(N22:N22) -> 0 | ... P74: =O74-SUM(P22:P22) -> 0

Sheet Debt
B1: Loan 1 | V1: Loan 2
J2: (1) Free & Clear | AD2: (1) Free & Clear
C3: Debt Name: | D3: =Summary!C22 -> - | F3: Assumption: | G3: =Summary!C30 -> Yes | K3: 0 | L3: 1 | M3: 2 | N3: 3 | O3: 4 | P3: 5 | Q3: 6 | R3: 7 | S3: 8 | T3: 9 | U3: 10 | W3: Debt Name: | X3: =Summary!C34 -> 0 | Z3: Assumption: | AA3: =Summary!C42 -> Yes | AE3: 0 | AF3: 1 | AG3: 2 | AH3: 3 | AI3: 4 | AJ3: 5 | AK3: 6 | AL3: 7 | AM3: 8 | AN3: 9 | AO3: 10
C4: Price: | D4: =Valuation!C2 -> 0 | F4: Ass. Month: | G4: =Summary!C31 -> 0 | J4: Loan 1 Principal | K4: =G14 -> 0 | L4: =IF(L3*12<=$G$6,0,IF(AND($G$6>K3*12,$G$6<M3*12),SUM(OFFSET($F$57,,,(L3*12)-$G$6+1,)),SUM(OFFSET($F$57,K3*12-$G$6+1,,12,)))) -> #NUM! | M4: =IF(M3*12<=$G$6,0,IF(AND($G$6>L3*12,$G$6<N3*12),SUM(OFFSET($F$57,,,(M3*12)-$G$6+1,)),SUM(OFFSET($F$57,L3*12-$G$6+1,,12,)))) -> #NUM! | N4: =IF(N3*12<=$G$6,0,IF(AND($G$6>M3*12,$G$6<O3*12),SUM(OFFSET($F$57,,,(N3*12)-$G$6+1,)),SUM(OFFSET($F$57,M3*12-$G$6+1,,12,)))) -> #NUM! | O4: =IF(O3*12<=$G$6,0,IF(AND($G$6>N3*12,$G$6<P3*12),SUM(OFFSET($F$57,,,(O3*12)-$G$6+1,)),SUM(OFFSET($F$57,N3*12-$G$6+1,,12,)))) -> #NUM! | P4: =IF(P3*12<=$G$6,0,IF(AND($G$6>O3*12,$G$6<Q3*12),SUM(OFFSET($F$57,,,(P3*12)-$G$6+1,)),SUM(OFFSET($F$57,O3*12-$G$6+1,,12,)))) -> #NUM! | Q4: =IF(Q3*12<=$G$6,0,IF(AND($G$6>P3*12,$G$6<R3*12),SUM(OFFSET($F$57,,,(Q3*12)-$G$6+1,)),SUM(OFFSET($F$57,P3*12-$G$6+1,,12,)))) -> #NUM! | R4: =IF(R3*12<=$G$6,0,IF(AND($G$6>Q3*12,$G$6<S3*12),SUM(OFFSET($F$57,,,(R3*12)-$G$6+1,)),SUM(OFFSET($F$57,Q3*12-$G$6+1,,12,)))) -> #NUM! | S4: =IF(S3*12<=$G$6,0,IF(AND($G$6>R3*12,$G$6<T3*12),SUM(OFFSET($F$57,,,(S3*12)-$G$6+1,)),SUM(OFFSET($F$57,R3*12-$G$6+1,,12,)))) -> #NUM! | ... U4: =IF(U3*12<=$G$6,0,IF(AND($G$6>T3*12,$G$6<V3*12),SUM(OFFSET($F$57,,,(U3*12)-$G$6+1,)),SUM(OFFSET($F$57,T3*12-$G$6+1,,12,)))) -> #NUM! | W4: Price: | X4: =D4 -> 0 | Z4: Ass. Month: | AA4: =Summary!C43 -> 0 | AD4: Loan 1 Principal | AE4: =AA14 -> 0 | AF4: =IF(AF3*12<=$AA$6,0,IF(AND($AA$6>AE3*12,$AA$6<AG3*12),SUM(OFFSET($Z$57,,,(AF3*12)-$AA$6+1,)),SUM(OFFSET($Z$57,AE3*12-$AA$6+1,,12,)))) -> #NUM! | AG4: =IF(AG3*12<=$AA$6,0,IF(AND($AA$6>AF3*12,$AA$6<AH3*12),SUM(OFFSET($Z$57,,,(AG3*12)-$AA$6+1,)),SUM(OFFSET($Z$57,AF3*12-$AA$6+1,,12,)))) -> #NUM! | AH4: =IF(AH3*12<=$AA$6,0,IF(AND($AA$6>AG3*12,$AA$6<AI3*12),SUM(OFFSET($Z$57,,,(AH3*12)-$AA$6+1,)),SUM(OFFSET($Z$57,AG3*12-$AA$6+1,,12,)))) -> #NUM! | AI4: =IF(AI3*12<=$AA$6,0,IF(AND($AA$6>AH3*12,$AA$6<AJ3*12),SUM(OFFSET($Z$57,,,(AI3*12)-$AA$6+1,)),SUM(OFFSET($Z$57,AH3*12-$AA$6+1,,12,)))) -> #NUM! | AJ4: =IF(AJ3*12<=$AA$6,0,IF(AND($AA$6>AI3*12,$AA$6<AK3*12),SUM(OFFSET($Z$57,,,(AJ3*12)-$AA$6+1,)),SUM(OFFSET($Z$57,AI3*12-$AA$6+1,,12,)))) -> #NUM! | AK4: =IF(AK3*12<=$AA$6,0,IF(AND($AA$6>AJ3*12,$AA$6<AL3*12),SUM(OFFSET($Z$57,,,(AK3*12)-$AA$6+1,)),SUM(OFFSET($Z$57,AJ3*12-$AA$6+1,,12,)))) -> #NUM! | AL4: =IF(AL3*12<=$AA$6,0,IF(AND($AA$6>AK3*12,$AA$6<AM3*12),SUM(OFFSET($Z$57,,,(AL3*12)-$AA$6+1,)),SUM(OFFSET($Z$57,AK3*12-$AA$6+1,,12,)))) -> #NUM! | AM4: =IF(AM3*12<=$AA$6,0,IF(AND($AA$6>AL3*12,$AA$6<AN3*12),SUM(OFFSET($Z$57,,,(AM3*12)-$AA$6+1,)),SUM(OFFSET($Z$57,AL3*12-$AA$6+1,,12,)))) -> #NUM! | ... AO4: =IF(AO3*12<=$AA$6,0,IF(AND($AA$6>AN3*12,$AA$6<AP3*12),SUM(OFFSET($Z$57,,,(AO3*12)-$AA$6+1,)),SUM(OFFSET($Z$57,AN3*12-$AA$6+1,,12,)))) -> #NUM!
C5: LTV: | D5: =Summary!C23 -> 0 | J5: Loan 1 Interest | L5: =IF(L3*12<=$G$6,$G$7*12,IF(AND($G$6>K3*12,$G$6<M3*12),($G$6-(K3*12))*$G$7+SUM(OFFSET($E$57,,,(L3*12)-$G$6+1,)),SUM(OFFSET($E$57,K3*12-$G$6+1,,12,)))) -> #NUM! | M5: =IF(M3*12<=$G$6,$G$7*12,IF(AND($G$6>L3*12,$G$6<N3*12),($G$6-(L3*12))*$G$7+SUM(OFFSET($E$57,,,(M3*12)-$G$6+1,)),SUM(OFFSET($E$57,L3*12-$G$6+1,,12,)))) -> #NUM! | N5: =IF(N3*12<=$G$6,$G$7*12,IF(AND($G$6>M3*12,$G$6<O3*12),($G$6-(M3*12))*$G$7+SUM(OFFSET($E$57,,,(N3*12)-$G$6+1,)),SUM(OFFSET($E$57,M3*12-$G$6+1,,12,)))) -> #NUM! | O5: =IF(O3*12<=$G$6,$G$7*12,IF(AND($G$6>N3*12,$G$6<P3*12),($G$6-(N3*12))*$G$7+SUM(OFFSET($E$57,,,(O3*12)-$G$6+1,)),SUM(OFFSET($E$57,N3*12-$G$6+1,,12,)))) -> #NUM! | P5: =IF(P3*12<=$G$6,$G$7*12,IF(AND($G$6>O3*12,$G$6<Q3*12),($G$6-(O3*12))*$G$7+SUM(OFFSET($E$57,,,(P3*12)-$G$6+1,)),SUM(OFFSET($E$57,O3*12-$G$6+1,,12,)))) -> #NUM! | Q5: =IF(Q3*12<=$G$6,$G$7*12,IF(AND($G$6>P3*12,$G$6<R3*12),($G$6-(P3*12))*$G$7+SUM(OFFSET($E$57,,,(Q3*12)-$G$6+1,)),SUM(OFFSET($E$57,P3*12-$G$6+1,,12,)))) -> #NUM! | R5: =IF(R3*12<=$G$6,$G$7*12,IF(AND($G$6>Q3*12,$G$6<S3*12),($G$6-(Q3*12))*$G$7+SUM(OFFSET($E$57,,,(R3*12)-$G$6+1,)),SUM(OFFSET($E$57,Q3*12-$G$6+1,,12,)))) -> #NUM! | S5: =IF(S3*12<=$G$6,$G$7*12,IF(AND($G$6>R3*12,$G$6<T3*12),($G$6-(R3*12))*$G$7+SUM(OFFSET($E$57,,,(S3*12)-$G$6+1,)),SUM(OFFSET($E$57,R3*12-$G$6+1,,12,)))) -> #NUM! | ... U5: =IF(U3*12<=$G$6,$G$7*12,IF(AND($G$6>T3*12,$G$6<V3*12),($G$6-(T3*12))*$G$7+SUM(OFFSET($E$57,,,(U3*12)-$G$6+1,)),SUM(OFFSET($E$57,T3*12-$G$6+1,,12,)))) -> #NUM! | W5: LTV: | X5: =Summary!C35 -> 0 | AD5: Loan 1 Interest | AF5: =IF(AF3*12<=$AA$6,$AA$7*12,IF(AND($AA$6>AE3*12,$AA$6<AG3*12),($AA$6-(AE3*12))*$AA$7+SUM(OFFSET($Y$57,,,(AF3*12)-$AA$6+1,)),SUM(OFFSET($Y$57,AE3*12-$AA$6+1,,12,)))) -> #NUM! | AG5: =IF(AG3*12<=$AA$6,$AA$7*12,IF(AND($AA$6>AF3*12,$AA$6<AH3*12),($AA$6-(AF3*12))*$AA$7+SUM(OFFSET($Y$57,,,(AG3*12)-$AA$6+1,)),SUM(OFFSET($Y$57,AF3*12-$AA$6+1,,12,)))) -> #NUM! | AH5: =IF(AH3*12<=$AA$6,$AA$7*12,IF(AND($AA$6>AG3*12,$AA$6<AI3*12),($AA$6-(AG3*12))*$AA$7+SUM(OFFSET($Y$57,,,(AH3*12)-$AA$6+1,)),SUM(OFFSET($Y$57,AG3*12-$AA$6+1,,12,)))) -> #NUM! | AI5: =IF(AI3*12<=$AA$6,$AA$7*12,IF(AND($AA$6>AH3*12,$AA$6<AJ3*12),($AA$6-(AH3*12))*$AA$7+SUM(OFFSET($Y$57,,,(AI3*12)-$AA$6+1,)),SUM(OFFSET($Y$57,AH3*12-$AA$6+1,,12,)))) -> #NUM! | AJ5: =IF(AJ3*12<=$AA$6,$AA$7*12,IF(AND($AA$6>AI3*12,$AA$6<AK3*12),($AA$6-(AI3*12))*$AA$7+SUM(OFFSET($Y$57,,,(AJ3*12)-$AA$6+1,)),SUM(OFFSET($Y$57,AI3*12-$AA$6+1,,12,)))) -> #NUM! | AK5: =IF(AK3*12<=$AA$6,$AA$7*12,IF(AND($AA$6>AJ3*12,$AA$6<AL3*12),($AA$6-(AJ3*12))*$AA$7+SUM(OFFSET($Y$57,,,(AK3*12)-$AA$6+1,)),SUM(OFFSET($Y$57,AJ3*12-$AA$6+1,,12,)))) -> #NUM! | AL5: =IF(AL3*12<=$AA$6,$AA$7*12,IF(AND($AA$6>AK3*12,$AA$6<AM3*12),($AA$6-(AK3*12))*$AA$7+SUM(OFFSET($Y$57,,,(AL3*12)-$AA$6+1,)),SUM(OFFSET($Y$57,AK3*12-$AA$6+1,,12,)))) -> #NUM! | AM5: =IF(AM3*12<=$AA$6,$AA$7*12,IF(AND($AA$6>AL3*12,$AA$6<AN3*12),($AA$6-(AL3*12))*$AA$7+SUM(OFFSET($Y$57,,,(AM3*12)-$AA$6+1,)),SUM(OFFSET($Y$57,AL3*12-$AA$6+1,,12,)))) -> #NUM! | ... AO5: =IF(AO3*12<=$AA$6,$AA$7*12,IF(AND($AA$6>AN3*12,$AA$6<AP3*12),($AA$6-(AN3*12))*$AA$7+SUM(OFFSET($Y$57,,,(AO3*12)-$AA$6+1,)),SUM(OFFSET($Y$57,AN3*12-$AA$6+1,,12,)))) -> #NUM!
C6: Loan Amount: | D6: =Summary!C24 -> 0 | F6: I/O (Months): | G6: =Summary!C29 -> 0 | J6: Loan 1 Payoff | K6: =-OFFSET($G$14,K3,,,) -> 0 | L6: =IF(L4=0,K6,K6+L4) -> #NUM! | M6: =IF(M4=0,L6,L6+M4) -> #NUM! | N6: =IF(N4=0,M6,M6+N4) -> #NUM! | O6: =IF(O4=0,N6,N6+O4) -> #NUM! | P6: =IF(P4=0,O6,O6+P4) -> #NUM! | Q6: =IF(Q4=0,P6,P6+Q4) -> #NUM! | R6: =IF(R4=0,Q6,Q6+R4) -> #NUM! | S6: =IF(S4=0,R6,R6+S4) -> #NUM! | ... U6: =IF(U4=0,T6,T6+U4) -> #NUM! | W6: Loan Amount: | X6: =X5*X4 -> 0 | Z6: I/O (Months): | AA6: =Summary!C41 -> 0 | AD6: Loan 1 Payoff | AE6: =-OFFSET($AA$14,AE3,,,) -> 0 | AF6: =IF(AF4=0,AE6,AE6+AF4) -> #NUM! | AG6: =IF(AG4=0,AF6,AF6+AG4) -> #NUM! | AH6: =IF(AH4=0,AG6,AG6+AH4) -> #NUM! | AI6: =IF(AI4=0,AH6,AH6+AI4) -> #NUM! | AJ6: =IF(AJ4=0,AI6,AI6+AJ4) -> #NUM! | AK6: =IF(AK4=0,AJ6,AJ6+AK4) -> #NUM! | AL6: =IF(AL4=0,AK6,AK6+AL4) -> #NUM! | AM6: =IF(AM4=0,AL6,AL6+AM4) -> #NUM! | ... AO6: =IF(AO4=0,AN6,AN6+AO4) -> #NUM!
C7: Int. Rate: | D7: =Summary!C25 -> 0 | F7: I/O Mon.PMT: | G7: =D7/12*D6 -> 0 | W7: Int. Rate: | X7: =Summary!C37 -> 0 | Z7: I/O Mon.PMT: | AA7: =X7/12*X6 -> 0
C8: Term: | D8: =Summary!C26 -> 0 | F8: I/O Months Left: | G8: =MAX(G6-G4+1,0) -> 1 | J8: (2) Assumption | W8: Term: | X8: =Summary!C38 -> 0 | Z8: I/O Months Left: | AA8: =MAX(AA6-AA4+1,0) -> 1 | AD8: (2) Assumption
C9: Amortization: | D9: =Summary!C27 -> 0 | K9: 0 | L9: 1 | M9: 2 | N9: 3 | O9: 4 | P9: 5 | Q9: 6 | R9: 7 | S9: 8 | T9: 9 | U9: 10 | W9: Amortization: | X9: =Summary!C39 -> 0 | AE9: 0 | AF9: 1 | AG9: 2 | AH9: 3 | AI9: 4 | AJ9: 5 | AK9: 6 | AL9: 7 | AM9: 8 | AN9: 9 | AO9: 10
C10: Loan Cost: | D10: =Summary!C28 -> 0 | F10: *Scenario: | G10: =IF(Summary!$C$30="No",1,IF(Summary!$C$29<Summary!$C$31,2,3)) -> 3 | J10: Loan 1 Principal | K10: =IF($G$4<1,K4,OFFSET($G$57,G4-G6-1,,,)) -> 0 | L10: =IF($G$4<1,L4,SUM(OFFSET($F$57,(L9*12)+($G$4-$G$6-12),,12,))) -> #NUM! | M10: =IF($G$4<1,M4,SUM(OFFSET($F$57,(M9*12)+($G$4-$G$6-12),,12,))) -> #NUM! | N10: =IF($G$4<1,N4,SUM(OFFSET($F$57,(N9*12)+($G$4-$G$6-12),,12,))) -> #NUM! | O10: =IF($G$4<1,O4,SUM(OFFSET($F$57,(O9*12)+($G$4-$G$6-12),,12,))) -> #NUM! | P10: =IF($G$4<1,P4,SUM(OFFSET($F$57,(P9*12)+($G$4-$G$6-12),,12,))) -> #NUM! | Q10: =IF($G$4<1,Q4,SUM(OFFSET($F$57,(Q9*12)+($G$4-$G$6-12),,12,))) -> #NUM! | R10: =IF($G$4<1,R4,SUM(OFFSET($F$57,(R9*12)+($G$4-$G$6-12),,12,))) -> #NUM! | S10: =IF($G$4<1,S4,SUM(OFFSET($F$57,(S9*12)+($G$4-$G$6-12),,12,))) -> #NUM! | ... U10: =IF($G$4<1,U4,SUM(OFFSET($F$57,(U9*12)+($G$4-$G$6-12),,12,))) -> #NUM! | W10: Loan Cost: | X10: =Summary!C40 -> 0 | Z10: *Scenario: | AA10: =IF(Summary!$C$42="No",1,IF(Summary!$C$41<Summary!$C$43,2,3)) -> 3 | AD10: Loan 1 Principal | AE10: =IF($AA$4<1,AE4,OFFSET($AA$57,AA4-AA6-1,,,)) -> 0 | AF10: =IF($AA$4<1,AF4,SUM(OFFSET($Z$57,(AF9*12)+($AA$4-$AA$6-12),,12,))) -> #NUM! | AG10: =IF($AA$4<1,AG4,SUM(OFFSET($Z$57,(AG9*12)+($AA$4-$AA$6-12),,12,))) -> #NUM! | AH10: =IF($AA$4<1,AH4,SUM(OFFSET($Z$57,(AH9*12)+($AA$4-$AA$6-12),,12,))) -> #NUM! | AI10: =IF($AA$4<1,AI4,SUM(OFFSET($Z$57,(AI9*12)+($AA$4-$AA$6-12),,12,))) -> #NUM! | AJ10: =IF($AA$4<1,AJ4,SUM(OFFSET($Z$57,(AJ9*12)+($AA$4-$AA$6-12),,12,))) -> #NUM! | AK10: =IF($AA$4<1,AK4,SUM(OFFSET($Z$57,(AK9*12)+($AA$4-$AA$6-12),,12,))) -> #NUM! | AL10: =IF($AA$4<1,AL4,SUM(OFFSET($Z$57,(AL9*12)+($AA$4-$AA$6-12),,12,))) -> #NUM! | AM10: =IF($AA$4<1,AM4,SUM(OFFSET($Z$57,(AM9*12)+($AA$4-$AA$6-12),,12,))) -> #NUM! | ... AO10: =IF($AA$4<1,AO4,SUM(OFFSET($Z$57,(AO9*12)+($AA$4-$AA$6-12),,12,))) -> #NUM!
F11: *Scenario that flows into proforma | J11: Loan 1 Interest | L11: =IF($G$4<1,L5,SUM(OFFSET($E$57,(L9*12+$G$4-$G$6-12),,12,))) -> #NUM! | M11: =IF($G$4<1,M5,SUM(OFFSET($E$57,(M9*12+$G$4-$G$6-12),,12,))) -> #NUM! | N11: =IF($G$4<1,N5,SUM(OFFSET($E$57,(N9*12+$G$4-$G$6-12),,12,))) -> #NUM! | O11: =IF($G$4<1,O5,SUM(OFFSET($E$57,(O9*12+$G$4-$G$6-12),,12,))) -> #NUM! | P11: =IF($G$4<1,P5,SUM(OFFSET($E$57,(P9*12+$G$4-$G$6-12),,12,))) -> #NUM! | Q11: =IF($G$4<1,Q5,SUM(OFFSET($E$57,(Q9*12+$G$4-$G$6-12),,12,))) -> #NUM! | R11: =IF($G$4<1,R5,SUM(OFFSET($E$57,(R9*12+$G$4-$G$6-12),,12,))) -> #NUM! | S11: =IF($G$4<1,S5,SUM(OFFSET($E$57,(S9*12+$G$4-$G$6-12),,12,))) -> #NUM! | ... U11: =IF($G$4<1,U5,SUM(OFFSET($E$57,(U9*12+$G$4-$G$6-12),,12,))) -> #NUM! | Z11: *Scenario that flows into proforma | AD11: Loan 1 Interest | AF11: =IF($AA$4<1,AF5,SUM(OFFSET($Y$58,(AF9*12+$AA$4-$AA$6-12),,12,))) -> #NUM! | AG11: =IF($AA$4<1,AG5,SUM(OFFSET($Y$58,(AG9*12+$AA$4-$AA$6-12),,12,))) -> #NUM! | AH11: =IF($AA$4<1,AH5,SUM(OFFSET($Y$58,(AH9*12+$AA$4-$AA$6-12),,12,))) -> #NUM! | AI11: =IF($AA$4<1,AI5,SUM(OFFSET($Y$58,(AI9*12+$AA$4-$AA$6-12),,12,))) -> #NUM! | AJ11: =IF($AA$4<1,AJ5,SUM(OFFSET($Y$58,(AJ9*12+$AA$4-$AA$6-12),,12,))) -> #NUM! | AK11: =IF($AA$4<1,AK5,SUM(OFFSET($Y$58,(AK9*12+$AA$4-$AA$6-12),,12,))) -> #NUM! | AL11: =IF($AA$4<1,AL5,SUM(OFFSET($Y$58,(AL9*12+$AA$4-$AA$6-12),,12,))) -> #NUM! | AM11: =IF($AA$4<1,AM5,SUM(OFFSET($Y$58,(AM9*12+$AA$4-$AA$6-12),,12,))) -> #NUM! | ... AO11: =IF($AA$4<1,AO5,SUM(OFFSET($Y$58,(AO9*12+$AA$4-$AA$6-12),,12,))) -> #NUM!
J12: Loan 1 Payoff | K12: =IF(G4<1,K6,-OFFSET($G$57,G4-G6-1,,,)) -> 0 | L12: =IF(L10=0,K12,K12+L10) -> #NUM! | M12: =IF(M10=0,L12,L12+M10) -> #NUM! | N12: =IF(N10=0,M12,M12+N10) -> #NUM! | O12: =IF(O10=0,N12,N12+O10) -> #NUM! | P12: =IF(P10=0,O12,O12+P10) -> #NUM! | Q12: =IF(Q10=0,P12,P12+Q10) -> #NUM! | R12: =IF(R10=0,Q12,Q12+R10) -> #NUM! | S12: =IF(S10=0,R12,R12+S10) -> #NUM! | ... U12: =IF(U10=0,T12,T12+U10) -> #NUM! | AD12: Loan 1 Payoff | AE12: =IF(AA4<1,AE6,-OFFSET($AA$57,AA4-AA6-1,,,)) -> 0 | AF12: =IF(AF10=0,AE12,AE12+AF10) -> #NUM! | AG12: =IF(AG10=0,AF12,AF12+AG10) -> #NUM! | AH12: =IF(AH10=0,AG12,AG12+AH10) -> #NUM! | AI12: =IF(AI10=0,AH12,AH12+AI10) -> #NUM! | AJ12: =IF(AJ10=0,AI12,AI12+AJ10) -> #NUM! | AK12: =IF(AK10=0,AJ12,AJ12+AK10) -> #NUM! | AL12: =IF(AL10=0,AK12,AK12+AL10) -> #NUM! | AM12: =IF(AM10=0,AL12,AL12+AM10) -> #NUM! | ... AO12: =IF(AO10=0,AN12,AN12+AO10) -> #NUM!
B13: Yr | C13: Beg. Balance | D13: PMT | E13: Interest | F13: Principal | G13: End Balance | H13: PMT Left | V13: Yr | W13: Beg. Balance | X13: PMT | Y13: Interest | Z13: Principal | AA13: End Balance | AB13: PMT Left
B14: 0 | G14: =D6 -> 0 | H14: =D9*12 -> 0 | J14: (3) Assumption During IO Period | V14: 0 | AA14: =X6 -> 0 | AB14: =X9*12 -> 0 | AD14: (3) Assumption During IO Period
B15: 1 | C15: =G14 -> 0 | D15: =-PMT($D$7/12,$D$9*12,$D$6,,)*12 -> #NUM! | E15: =D15-F15 -> #NUM! | F15: =C15-G15 -> #NUM! | G15: =-PV($D$7/12,H15,D15/12) -> #NUM! | H15: =H14-12 -> -12 | K15: 0 | L15: 1 | M15: 2 | N15: 3 | O15: 4 | P15: 5 | Q15: 6 | R15: 7 | S15: 8 | T15: 9 | U15: 10 | V15: 1 | W15: =AA14 -> 0 | X15: =-PMT($X$7/12,$X$9*12,$X$6,,)*12 -> #NUM! | Y15: =X15-Z15 -> #NUM! | Z15: =W15-AA15 -> #NUM! | AA15: =-PV($X$7/12,AB15,X15/12) -> #NUM! | AB15: =AB14-12 -> -12 | AE15: 0 | AF15: 1 | AG15: 2 | AH15: 3 | AI15: 4 | AJ15: 5 | AK15: 6 | AL15: 7 | AM15: 8 | AN15: 9 | AO15: 10
B16: 2 | C16: =G15 -> #NUM! | D16: =-PMT($D$7/12,$D$9*12,$D$6,,)*12 -> #NUM! | E16: =D16-F16 -> #NUM! | F16: =C16-G16 -> #NUM! | G16: =-PV($D$7/12,H16,D16/12) -> #NUM! | H16: =H15-12 -> -24 | J16: Loan 1 Principal | K16: =D6 -> 0 | L16: =IF(L15*12<=$G$8,0,IF(AND($G$8>K15*12,$G$8<M15*12),SUM(OFFSET($F$57,,,(L15*12)-$G$8+1,)),SUM(OFFSET($F$57,K15*12-$G$8+1,,12,)))) -> #NUM! | M16: =IF(M15*12<=$G$8,0,IF(AND($G$8>L15*12,$G$8<N15*12),SUM(OFFSET($F$57,,,(M15*12)-$G$8+1,)),SUM(OFFSET($F$57,L15*12-$G$8+1,,12,)))) -> #NUM! | N16: =IF(N15*12<=$G$8,0,IF(AND($G$8>M15*12,$G$8<O15*12),SUM(OFFSET($F$57,,,(N15*12)-$G$8+1,)),SUM(OFFSET($F$57,M15*12-$G$8+1,,12,)))) -> #NUM! | O16: =IF(O15*12<=$G$8,0,IF(AND($G$8>N15*12,$G$8<P15*12),SUM(OFFSET($F$57,,,(O15*12)-$G$8+1,)),SUM(OFFSET($F$57,N15*12-$G$8+1,,12,)))) -> #NUM! | P16: =IF(P15*12<=$G$8,0,IF(AND($G$8>O15*12,$G$8<Q15*12),SUM(OFFSET($F$57,,,(P15*12)-$G$8+1,)),SUM(OFFSET($F$57,O15*12-$G$8+1,,12,)))) -> #NUM! | Q16: =IF(Q15*12<=$G$8,0,IF(AND($G$8>P15*12,$G$8<R15*12),SUM(OFFSET($F$57,,,(Q15*12)-$G$8+1,)),SUM(OFFSET($F$57,P15*12-$G$8+1,,12,)))) -> #NUM! | R16: =IF(R15*12<=$G$8,0,IF(AND($G$8>Q15*12,$G$8<S15*12),SUM(OFFSET($F$57,,,(R15*12)-$G$8+1,)),SUM(OFFSET($F$57,Q15*12-$G$8+1,,12,)))) -> #NUM! | S16: =IF(S15*12<=$G$8,0,IF(AND($G$8>R15*12,$G$8<T15*12),SUM(OFFSET($F$57,,,(S15*12)-$G$8+1,)),SUM(OFFSET($F$57,R15*12-$G$8+1,,12,)))) -> #NUM! | ... U16: =IF(U15*12<=$G$8,0,IF(AND($G$8>T15*12,$G$8<V15*12),SUM(OFFSET($F$57,,,(U15*12)-$G$8+1,)),SUM(OFFSET($F$57,T15*12-$G$8+1,,12,)))) -> #NUM! | V16: 2 | W16: =AA15 -> #NUM! | X16: =-PMT($X$7/12,$X$9*12,$X$6,,)*12 -> #NUM! | Y16: =X16-Z16 -> #NUM! | Z16: =W16-AA16 -> #NUM! | AA16: =-PV($X$7/12,AB16,X16/12) -> #NUM! | AB16: =AB15-12 -> -24 | AD16: Loan 1 Principal | AE16: =X6 -> 0 | AF16: =IF(AF15*12<=$AA$8,0,IF(AND($AA$8>AE15*12,$AA$8<AG15*12),SUM(OFFSET($Z$57,,,(AF15*12)-$AA$8+1,)),SUM(OFFSET($Z$57,AE15*12-$AA$8+1,,12,)))) -> #NUM! | AG16: =IF(AG15*12<=$AA$8,0,IF(AND($AA$8>AF15*12,$AA$8<AH15*12),SUM(OFFSET($Z$57,,,(AG15*12)-$AA$8+1,)),SUM(OFFSET($Z$57,AF15*12-$AA$8+1,,12,)))) -> #NUM! | AH16: =IF(AH15*12<=$AA$8,0,IF(AND($AA$8>AG15*12,$AA$8<AI15*12),SUM(OFFSET($Z$57,,,(AH15*12)-$AA$8+1,)),SUM(OFFSET($Z$57,AG15*12-$AA$8+1,,12,)))) -> #NUM! | AI16: =IF(AI15*12<=$AA$8,0,IF(AND($AA$8>AH15*12,$AA$8<AJ15*12),SUM(OFFSET($Z$57,,,(AI15*12)-$AA$8+1,)),SUM(OFFSET($Z$57,AH15*12-$AA$8+1,,12,)))) -> #NUM! | AJ16: =IF(AJ15*12<=$AA$8,0,IF(AND($AA$8>AI15*12,$AA$8<AK15*12),SUM(OFFSET($Z$57,,,(AJ15*12)-$AA$8+1,)),SUM(OFFSET($Z$57,AI15*12-$AA$8+1,,12,)))) -> #NUM! | AK16: =IF(AK15*12<=$AA$8,0,IF(AND($AA$8>AJ15*12,$AA$8<AL15*12),SUM(OFFSET($Z$57,,,(AK15*12)-$AA$8+1,)),SUM(OFFSET($Z$57,AJ15*12-$AA$8+1,,12,)))) -> #NUM! | AL16: =IF(AL15*12<=$AA$8,0,IF(AND($AA$8>AK15*12,$AA$8<AM15*12),SUM(OFFSET($Z$57,,,(AL15*12)-$AA$8+1,)),SUM(OFFSET($Z$57,AK15*12-$AA$8+1,,12,)))) -> #NUM! | AM16: =IF(AM15*12<=$AA$8,0,IF(AND($AA$8>AL15*12,$AA$8<AN15*12),SUM(OFFSET($Z$57,,,(AM15*12)-$AA$8+1,)),SUM(OFFSET($Z$57,AL15*12-$AA$8+1,,12,)))) -> #NUM! | ... AO16: =IF(AO15*12<=$AA$8,0,IF(AND($AA$8>AN15*12,$AA$8<AP15*12),SUM(OFFSET($Z$57,,,(AO15*12)-$AA$8+1,)),SUM(OFFSET($Z$57,AN15*12-$AA$8+1,,12,)))) -> #NUM!
B17: 3 | C17: =G16 -> #NUM! | D17: =-PMT($D$7/12,$D$9*12,$D$6,,)*12 -> #NUM! | E17: =D17-F17 -> #NUM! | F17: =C17-G17 -> #NUM! | G17: =-PV($D$7/12,H17,D17/12) -> #NUM! | H17: =H16-12 -> -36 | J17: Loan 1 Interest | L17: =IF(L15*12<=$G$8,$G$7*12,IF(AND($G$8>K15*12,$G$8<M15*12),($G$8-(K15*12))*$G$7+SUM(OFFSET($E$57,,,(L15*12)-$G$8+1,)),SUM(OFFSET($E$57,K15*12-$G$8+1,,12,)))) -> #NUM! | M17: =IF(M15*12<=$G$8,$G$7*12,IF(AND($G$8>L15*12,$G$8<N15*12),($G$8-(L15*12))*$G$7+SUM(OFFSET($E$57,,,(M15*12)-$G$8+1,)),SUM(OFFSET($E$57,L15*12-$G$8+1,,12,)))) -> #NUM! | N17: =IF(N15*12<=$G$8,$G$7*12,IF(AND($G$8>M15*12,$G$8<O15*12),($G$8-(M15*12))*$G$7+SUM(OFFSET($E$57,,,(N15*12)-$G$8+1,)),SUM(OFFSET($E$57,M15*12-$G$8+1,,12,)))) -> #NUM! | O17: =IF(O15*12<=$G$8,$G$7*12,IF(AND($G$8>N15*12,$G$8<P15*12),($G$8-(N15*12))*$G$7+SUM(OFFSET($E$57,,,(O15*12)-$G$8+1,)),SUM(OFFSET($E$57,N15*12-$G$8+1,,12,)))) -> #NUM! | P17: =IF(P15*12<=$G$8,$G$7*12,IF(AND($G$8>O15*12,$G$8<Q15*12),($G$8-(O15*12))*$G$7+SUM(OFFSET($E$57,,,(P15*12)-$G$8+1,)),SUM(OFFSET($E$57,O15*12-$G$8+1,,12,)))) -> #NUM! | Q17: =IF(Q15*12<=$G$8,$G$7*12,IF(AND($G$8>P15*12,$G$8<R15*12),($G$8-(P15*12))*$G$7+SUM(OFFSET($E$57,,,(Q15*12)-$G$8+1,)),SUM(OFFSET($E$57,P15*12-$G$8+1,,12,)))) -> #NUM! | R17: =IF(R15*12<=$G$8,$G$7*12,IF(AND($G$8>Q15*12,$G$8<S15*12),($G$8-(Q15*12))*$G$7+SUM(OFFSET($E$57,,,(R15*12)-$G$8+1,)),SUM(OFFSET($E$57,Q15*12-$G$8+1,,12,)))) -> #NUM! | S17: =IF(S15*12<=$G$8,$G$7*12,IF(AND($G$8>R15*12,$G$8<T15*12),($G$8-(R15*12))*$G$7+SUM(OFFSET($E$57,,,(S15*12)-$G$8+1,)),SUM(OFFSET($E$57,R15*12-$G$8+1,,12,)))) -> #NUM! | ... U17: =IF(U15*12<=$G$8,$G$7*12,IF(AND($G$8>T15*12,$G$8<V15*12),($G$8-(T15*12))*$G$7+SUM(OFFSET($E$57,,,(U15*12)-$G$8+1,)),SUM(OFFSET($E$57,T15*12-$G$8+1,,12,)))) -> #NUM! | V17: 3 | W17: =AA16 -> #NUM! | X17: =-PMT($X$7/12,$X$9*12,$X$6,,)*12 -> #NUM! | Y17: =X17-Z17 -> #NUM! | Z17: =W17-AA17 -> #NUM! | AA17: =-PV($X$7/12,AB17,X17/12) -> #NUM! | AB17: =AB16-12 -> -36 | AD17: Loan 1 Interest | AF17: =IF(AF15*12<=$AA$8,$AA$7*12,IF(AND($AA$8>AE15*12,$AA$8<AG15*12),($AA$8-(AE15*12))*$AA$7+SUM(OFFSET($Y$57,,,(AF15*12)-$AA$8+1,)),SUM(OFFSET($Y$57,AE15*12-$AA$8+1,,12,)))) -> #NUM! | AG17: =IF(AG15*12<=$AA$8,$AA$7*12,IF(AND($AA$8>AF15*12,$AA$8<AH15*12),($AA$8-(AF15*12))*$AA$7+SUM(OFFSET($Y$57,,,(AG15*12)-$AA$8+1,)),SUM(OFFSET($Y$57,AF15*12-$AA$8+1,,12,)))) -> #NUM! | AH17: =IF(AH15*12<=$AA$8,$AA$7*12,IF(AND($AA$8>AG15*12,$AA$8<AI15*12),($AA$8-(AG15*12))*$AA$7+SUM(OFFSET($Y$57,,,(AH15*12)-$AA$8+1,)),SUM(OFFSET($Y$57,AG15*12-$AA$8+1,,12,)))) -> #NUM! | AI17: =IF(AI15*12<=$AA$8,$AA$7*12,IF(AND($AA$8>AH15*12,$AA$8<AJ15*12),($AA$8-(AH15*12))*$AA$7+SUM(OFFSET($Y$57,,,(AI15*12)-$AA$8+1,)),SUM(OFFSET($Y$57,AH15*12-$AA$8+1,,12,)))) -> #NUM! | AJ17: =IF(AJ15*12<=$AA$8,$AA$7*12,IF(AND($AA$8>AI15*12,$AA$8<AK15*12),($AA$8-(AI15*12))*$AA$7+SUM(OFFSET($Y$57,,,(AJ15*12)-$AA$8+1,)),SUM(OFFSET($Y$57,AI15*12-$AA$8+1,,12,)))) -> #NUM! | AK17: =IF(AK15*12<=$AA$8,$AA$7*12,IF(AND($AA$8>AJ15*12,$AA$8<AL15*12),($AA$8-(AJ15*12))*$AA$7+SUM(OFFSET($Y$57,,,(AK15*12)-$AA$8+1,)),SUM(OFFSET($Y$57,AJ15*12-$AA$8+1,,12,)))) -> #NUM! | AL17: =IF(AL15*12<=$AA$8,$AA$7*12,IF(AND($AA$8>AK15*12,$AA$8<AM15*12),($AA$8-(AK15*12))*$AA$7+SUM(OFFSET($Y$57,,,(AL15*12)-$AA$8+1,)),SUM(OFFSET($Y$57,AK15*12-$AA$8+1,,12,)))) -> #NUM! | AM17: =IF(AM15*12<=$AA$8,$AA$7*12,IF(AND($AA$8>AL15*12,$AA$8<AN15*12),($AA$8-(AL15*12))*$AA$7+SUM(OFFSET($Y$57,,,(AM15*12)-$AA$8+1,)),SUM(OFFSET($Y$57,AL15*12-$AA$8+1,,12,)))) -> #NUM! | ... AO17: =IF(AO15*12<=$AA$8,$AA$7*12,IF(AND($AA$8>AN15*12,$AA$8<AP15*12),($AA$8-(AN15*12))*$AA$7+SUM(OFFSET($Y$57,,,(AO15*12)-$AA$8+1,)),SUM(OFFSET($Y$57,AN15*12-$AA$8+1,,12,)))) -> #NUM!
B18: 4 | C18: =G17 -> #NUM! | D18: =-PMT($D$7/12,$D$9*12,$D$6,,)*12 -> #NUM! | E18: =D18-F18 -> #NUM! | F18: =C18-G18 -> #NUM! | G18: =-PV($D$7/12,H18,D18/12) -> #NUM! | H18: =H17-12 -> -48 | J18: Loan 1 Payoff | K18: =-OFFSET($G$14,K15,,,) -> 0 | L18: =IF(L16=0,K18,K18+L16) -> #NUM! | M18: =IF(M16=0,L18,L18+M16) -> #NUM! | N18: =IF(N16=0,M18,M18+N16) -> #NUM! | O18: =IF(O16=0,N18,N18+O16) -> #NUM! | P18: =IF(P16=0,O18,O18+P16) -> #NUM! | Q18: =IF(Q16=0,P18,P18+Q16) -> #NUM! | R18: =IF(R16=0,Q18,Q18+R16) -> #NUM! | S18: =IF(S16=0,R18,R18+S16) -> #NUM! | ... U18: =IF(U16=0,T18,T18+U16) -> #NUM! | V18: 4 | W18: =AA17 -> #NUM! | X18: =-PMT($X$7/12,$X$9*12,$X$6,,)*12 -> #NUM! | Y18: =X18-Z18 -> #NUM! | Z18: =W18-AA18 -> #NUM! | AA18: =-PV($X$7/12,AB18,X18/12) -> #NUM! | AB18: =AB17-12 -> -48 | AD18: Loan 1 Payoff | AE18: =-OFFSET($AA$14,AE15,,,) -> 0 | AF18: =IF(AF16=0,AE18,AE18+AF16) -> #NUM! | AG18: =IF(AG16=0,AF18,AF18+AG16) -> #NUM! | AH18: =IF(AH16=0,AG18,AG18+AH16) -> #NUM! | AI18: =IF(AI16=0,AH18,AH18+AI16) -> #NUM! | AJ18: =IF(AJ16=0,AI18,AI18+AJ16) -> #NUM! | AK18: =IF(AK16=0,AJ18,AJ18+AK16) -> #NUM! | AL18: =IF(AL16=0,AK18,AK18+AL16) -> #NUM! | AM18: =IF(AM16=0,AL18,AL18+AM16) -> #NUM! | ... AO18: =IF(AO16=0,AN18,AN18+AO16) -> #NUM!
B19: 5 | C19: =G18 -> #NUM! | D19: =-PMT($D$7/12,$D$9*12,$D$6,,)*12 -> #NUM! | E19: =D19-F19 -> #NUM! | F19: =C19-G19 -> #NUM! | G19: =-PV($D$7/12,H19,D19/12) -> #NUM! | H19: =H18-12 -> -60 | V19: 5 | W19: =AA18 -> #NUM! | X19: =-PMT($X$7/12,$X$9*12,$X$6,,)*12 -> #NUM! | Y19: =X19-Z19 -> #NUM! | Z19: =W19-AA19 -> #NUM! | AA19: =-PV($X$7/12,AB19,X19/12) -> #NUM! | AB19: =AB18-12 -> -60
B20: 6 | C20: =G19 -> #NUM! | D20: =-PMT($D$7/12,$D$9*12,$D$6,,)*12 -> #NUM! | E20: =D20-F20 -> #NUM! | F20: =C20-G20 -> #NUM! | G20: =-PV($D$7/12,H20,D20/12) -> #NUM! | H20: =H19-12 -> -72 | V20: 6 | W20: =AA19 -> #NUM! | X20: =-PMT($X$7/12,$X$9*12,$X$6,,)*12 -> #NUM! | Y20: =X20-Z20 -> #NUM! | Z20: =W20-AA20 -> #NUM! | AA20: =-PV($X$7/12,AB20,X20/12) -> #NUM! | AB20: =AB19-12 -> -72
B21: 7 | C21: =G20 -> #NUM! | D21: =-PMT($D$7/12,$D$9*12,$D$6,,)*12 -> #NUM! | E21: =D21-F21 -> #NUM! | F21: =C21-G21 -> #NUM! | G21: =-PV($D$7/12,H21,D21/12) -> #NUM! | H21: =H20-12 -> -84 | V21: 7 | W21: =AA20 -> #NUM! | X21: =-PMT($X$7/12,$X$9*12,$X$6,,)*12 -> #NUM! | Y21: =X21-Z21 -> #NUM! | Z21: =W21-AA21 -> #NUM! | AA21: =-PV($X$7/12,AB21,X21/12) -> #NUM! | AB21: =AB20-12 -> -84
B22: 8 | C22: =G21 -> #NUM! | D22: =-PMT($D$7/12,$D$9*12,$D$6,,)*12 -> #NUM! | E22: =D22-F22 -> #NUM! | F22: =C22-G22 -> #NUM! | G22: =-PV($D$7/12,H22,D22/12) -> #NUM! | H22: =H21-12 -> -96 | V22: 8 | W22: =AA21 -> #NUM! | X22: =-PMT($X$7/12,$X$9*12,$X$6,,)*12 -> #NUM! | Y22: =X22-Z22 -> #NUM! | Z22: =W22-AA22 -> #NUM! | AA22: =-PV($X$7/12,AB22,X22/12) -> #NUM! | AB22: =AB21-12 -> -96
B23: 9 | C23: =G22 -> #NUM! | D23: =-PMT($D$7/12,$D$9*12,$D$6,,)*12 -> #NUM! | E23: =D23-F23 -> #NUM! | F23: =C23-G23 -> #NUM! | G23: =-PV($D$7/12,H23,D23/12) -> #NUM! | H23: =H22-12 -> -108 | V23: 9 | W23: =AA22 -> #NUM! | X23: =-PMT($X$7/12,$X$9*12,$X$6,,)*12 -> #NUM! | Y23: =X23-Z23 -> #NUM! | Z23: =W23-AA23 -> #NUM! | AA23: =-PV($X$7/12,AB23,X23/12) -> #NUM! | AB23: =AB22-12 -> -108
B24: 10 | C24: =G23 -> #NUM! | D24: =-PMT($D$7/12,$D$9*12,$D$6,,)*12 -> #NUM! | E24: =D24-F24 -> #NUM! | F24: =C24-G24 -> #NUM! | G24: =-PV($D$7/12,H24,D24/12) -> #NUM! | H24: =H23-12 -> -120 | V24: 10 | W24: =AA23 -> #NUM! | X24: =-PMT($X$7/12,$X$9*12,$X$6,,)*12 -> #NUM! | Y24: =X24-Z24 -> #NUM! | Z24: =W24-AA24 -> #NUM! | AA24: =-PV($X$7/12,AB24,X24/12) -> #NUM! | AB24: =AB23-12 -> -120
B25: 11 | C25: =G24 -> #NUM! | D25: =-PMT($D$7/12,$D$9*12,$D$6,,)*12 -> #NUM! | E25: =D25-F25 -> #NUM! | F25: =C25-G25 -> #NUM! | G25: =-PV($D$7/12,H25,D25/12) -> #NUM! | H25: =H24-12 -> -132 | V25: 11 | W25: =AA24 -> #NUM! | X25: =-PMT($X$7/12,$X$9*12,$X$6,,)*12 -> #NUM! | Y25: =X25-Z25 -> #NUM! | Z25: =W25-AA25 -> #NUM! | AA25: =-PV($X$7/12,AB25,X25/12) -> #NUM! | AB25: =AB24-12 -> -132
B26: 12 | C26: =G25 -> #NUM! | D26: =-PMT($D$7/12,$D$9*12,$D$6,,)*12 -> #NUM! | E26: =D26-F26 -> #NUM! | F26: =C26-G26 -> #NUM! | G26: =-PV($D$7/12,H26,D26/12) -> #NUM! | H26: =H25-12 -> -144 | V26: 12 | W26: =AA25 -> #NUM! | X26: =-PMT($X$7/12,$X$9*12,$X$6,,)*12 -> #NUM! | Y26: =X26-Z26 -> #NUM! | Z26: =W26-AA26 -> #NUM! | AA26: =-PV($X$7/12,AB26,X26/12) -> #NUM! | AB26: =AB25-12 -> -144
B27: 13 | C27: =G26 -> #NUM! | D27: =-PMT($D$7/12,$D$9*12,$D$6,,)*12 -> #NUM! | E27: =D27-F27 -> #NUM! | F27: =C27-G27 -> #NUM! | G27: =-PV($D$7/12,H27,D27/12) -> #NUM! | H27: =H26-12 -> -156 | V27: 13 | W27: =AA26 -> #NUM! | X27: =-PMT($X$7/12,$X$9*12,$X$6,,)*12 -> #NUM! | Y27: =X27-Z27 -> #NUM! | Z27: =W27-AA27 -> #NUM! | AA27: =-PV($X$7/12,AB27,X27/12) -> #NUM! | AB27: =AB26-12 -> -156
B28: 14 | C28: =G27 -> #NUM! | D28: =-PMT($D$7/12,$D$9*12,$D$6,,)*12 -> #NUM! | E28: =D28-F28 -> #NUM! | F28: =C28-G28 -> #NUM! | G28: =-PV($D$7/12,H28,D28/12) -> #NUM! | H28: =H27-12 -> -168 | V28: 14 | W28: =AA27 -> #NUM! | X28: =-PMT($X$7/12,$X$9*12,$X$6,,)*12 -> #NUM! | Y28: =X28-Z28 -> #NUM! | Z28: =W28-AA28 -> #NUM! | AA28: =-PV($X$7/12,AB28,X28/12) -> #NUM! | AB28: =AB27-12 -> -168
B29: 15 | C29: =G28 -> #NUM! | D29: =-PMT($D$7/12,$D$9*12,$D$6,,)*12 -> #NUM! | E29: =D29-F29 -> #NUM! | F29: =C29-G29 -> #NUM! | G29: =-PV($D$7/12,H29,D29/12) -> #NUM! | H29: =H28-12 -> -180 | V29: 15 | W29: =AA28 -> #NUM! | X29: =-PMT($X$7/12,$X$9*12,$X$6,,)*12 -> #NUM! | Y29: =X29-Z29 -> #NUM! | Z29: =W29-AA29 -> #NUM! | AA29: =-PV($X$7/12,AB29,X29/12) -> #NUM! | AB29: =AB28-12 -> -180
B30: 16 | C30: =G29 -> #NUM! | D30: =-PMT($D$7/12,$D$9*12,$D$6,,)*12 -> #NUM! | E30: =D30-F30 -> #NUM! | F30: =C30-G30 -> #NUM! | G30: =-PV($D$7/12,H30,D30/12) -> #NUM! | H30: =H29-12 -> -192 | V30: 16 | W30: =AA29 -> #NUM! | X30: =-PMT($X$7/12,$X$9*12,$X$6,,)*12 -> #NUM! | Y30: =X30-Z30 -> #NUM! | Z30: =W30-AA30 -> #NUM! | AA30: =-PV($X$7/12,AB30,X30/12) -> #NUM! | AB30: =AB29-12 -> -192
... B54: 40 | C54: =G53 -> #NUM! | D54: =-PMT($D$7/12,$D$9*12,$D$6,,)*12 -> #NUM! | E54: =D54-F54 -> #NUM! | F54: =C54-G54 -> #NUM! | G54: =-PV($D$7/12,H54,D54/12) -> #NUM! | H54: =H53-12 -> -480 | V54: 40 | W54: =AA53 -> #NUM! | X54: =-PMT($X$7/12,$X$9*12,$X$6,,)*12 -> #NUM! | Y54: =X54-Z54 -> #NUM! | Z54: =W54-AA54 -> #NUM! | AA54: =-PV($X$7/12,AB54,X54/12) -> #NUM! | AB54: =AB53-12 -> -480
B56: Month | C56: Beg. Balance | D56: PMT | E56: Interest | F56: Principal | G56: End Balance | V56: Month | W56: Beg. Balance | X56: PMT | Y56: Interest | Z56: Principal | AA56: End Balance
B57: 0 | G57: =$D$6 -> 0 | V57: 0 | AA57: =$X$6 -> 0
B58: 1 | C58: =G57 -> 0 | D58: =-PMT($D$7/12,$D$9*12,$D$6,,) -> #NUM! | E58: =C58*$D$7/12 -> 0 | F58: =D58-E58 -> #NUM! | G58: =C58-F58 -> #NUM! | V58: 1 | W58: =AA57 -> 0 | X58: =-PMT($X$7/12,$X$9*12,$X$6,,) -> #NUM! | Y58: =W58*$X$7/12 -> 0 | Z58: =X58-Y58 -> #NUM! | AA58: =W58-Z58 -> #NUM!
B59: 2 | C59: =G58 -> #NUM! | D59: =-PMT($D$7/12,$D$9*12,$D$6,,) -> #NUM! | E59: =C59*$D$7/12 -> #NUM! | F59: =D59-E59 -> #NUM! | G59: =C59-F59 -> #NUM! | V59: 2 | W59: =AA58 -> #NUM! | X59: =-PMT($X$7/12,$X$9*12,$X$6,,) -> #NUM! | Y59: =W59*$X$7/12 -> #NUM! | Z59: =X59-Y59 -> #NUM! | AA59: =W59-Z59 -> #NUM!
B60: 3 | C60: =G59 -> #NUM! | D60: =-PMT($D$7/12,$D$9*12,$D$6,,) -> #NUM! | E60: =C60*$D$7/12 -> #NUM! | F60: =D60-E60 -> #NUM! | G60: =C60-F60 -> #NUM! | V60: 3 | W60: =AA59 -> #NUM! | X60: =-PMT($X$7/12,$X$9*12,$X$6,,) -> #NUM! | Y60: =W60*$X$7/12 -> #NUM! | Z60: =X60-Y60 -> #NUM! | AA60: =W60-Z60 -> #NUM!
B61: 4 | C61: =G60 -> #NUM! | D61: =-PMT($D$7/12,$D$9*12,$D$6,,) -> #NUM! | E61: =C61*$D$7/12 -> #NUM! | F61: =D61-E61 -> #NUM! | G61: =C61-F61 -> #NUM! | V61: 4 | W61: =AA60 -> #NUM! | X61: =-PMT($X$7/12,$X$9*12,$X$6,,) -> #NUM! | Y61: =W61*$X$7/12 -> #NUM! | Z61: =X61-Y61 -> #NUM! | AA61: =W61-Z61 -> #NUM!
B62: 5 | C62: =G61 -> #NUM! | D62: =-PMT($D$7/12,$D$9*12,$D$6,,) -> #NUM! | E62: =C62*$D$7/12 -> #NUM! | F62: =D62-E62 -> #NUM! | G62: =C62-F62 -> #NUM! | V62: 5 | W62: =AA61 -> #NUM! | X62: =-PMT($X$7/12,$X$9*12,$X$6,,) -> #NUM! | Y62: =W62*$X$7/12 -> #NUM! | Z62: =X62-Y62 -> #NUM! | AA62: =W62-Z62 -> #NUM!
B63: 6 | C63: =G62 -> #NUM! | D63: =-PMT($D$7/12,$D$9*12,$D$6,,) -> #NUM! | E63: =C63*$D$7/12 -> #NUM! | F63: =D63-E63 -> #NUM! | G63: =C63-F63 -> #NUM! | V63: 6 | W63: =AA62 -> #NUM! | X63: =-PMT($X$7/12,$X$9*12,$X$6,,) -> #NUM! | Y63: =W63*$X$7/12 -> #NUM! | Z63: =X63-Y63 -> #NUM! | AA63: =W63-Z63 -> #NUM!
B64: 7 | C64: =G63 -> #NUM! | D64: =-PMT($D$7/12,$D$9*12,$D$6,,) -> #NUM! | E64: =C64*$D$7/12 -> #NUM! | F64: =D64-E64 -> #NUM! | G64: =C64-F64 -> #NUM! | V64: 7 | W64: =AA63 -> #NUM! | X64: =-PMT($X$7/12,$X$9*12,$X$6,,) -> #NUM! | Y64: =W64*$X$7/12 -> #NUM! | Z64: =X64-Y64 -> #NUM! | AA64: =W64-Z64 -> #NUM!
B65: 8 | C65: =G64 -> #NUM! | D65: =-PMT($D$7/12,$D$9*12,$D$6,,) -> #NUM! | E65: =C65*$D$7/12 -> #NUM! | F65: =D65-E65 -> #NUM! | G65: =C65-F65 -> #NUM! | V65: 8 | W65: =AA64 -> #NUM! | X65: =-PMT($X$7/12,$X$9*12,$X$6,,) -> #NUM! | Y65: =W65*$X$7/12 -> #NUM! | Z65: =X65-Y65 -> #NUM! | AA65: =W65-Z65 -> #NUM!
B66: 9 | C66: =G65 -> #NUM! | D66: =-PMT($D$7/12,$D$9*12,$D$6,,) -> #NUM! | E66: =C66*$D$7/12 -> #NUM! | F66: =D66-E66 -> #NUM! | G66: =C66-F66 -> #NUM! | V66: 9 | W66: =AA65 -> #NUM! | X66: =-PMT($X$7/12,$X$9*12,$X$6,,) -> #NUM! | Y66: =W66*$X$7/12 -> #NUM! | Z66: =X66-Y66 -> #NUM! | AA66: =W66-Z66 -> #NUM!
B67: 10 | C67: =G66 -> #NUM! | D67: =-PMT($D$7/12,$D$9*12,$D$6,,) -> #NUM! | E67: =C67*$D$7/12 -> #NUM! | F67: =D67-E67 -> #NUM! | G67: =C67-F67 -> #NUM! | V67: 10 | W67: =AA66 -> #NUM! | X67: =-PMT($X$7/12,$X$9*12,$X$6,,) -> #NUM! | Y67: =W67*$X$7/12 -> #NUM! | Z67: =X67-Y67 -> #NUM! | AA67: =W67-Z67 -> #NUM!
B68: 11 | C68: =G67 -> #NUM! | D68: =-PMT($D$7/12,$D$9*12,$D$6,,) -> #NUM! | E68: =C68*$D$7/12 -> #NUM! | F68: =D68-E68 -> #NUM! | G68: =C68-F68 -> #NUM! | V68: 11 | W68: =AA67 -> #NUM! | X68: =-PMT($X$7/12,$X$9*12,$X$6,,) -> #NUM! | Y68: =W68*$X$7/12 -> #NUM! | Z68: =X68-Y68 -> #NUM! | AA68: =W68-Z68 -> #NUM!
B69: 12 | C69: =G68 -> #NUM! | D69: =-PMT($D$7/12,$D$9*12,$D$6,,) -> #NUM! | E69: =C69*$D$7/12 -> #NUM! | F69: =D69-E69 -> #NUM! | G69: =C69-F69 -> #NUM! | V69: 12 | W69: =AA68 -> #NUM! | X69: =-PMT($X$7/12,$X$9*12,$X$6,,) -> #NUM! | Y69: =W69*$X$7/12 -> #NUM! | Z69: =X69-Y69 -> #NUM! | AA69: =W69-Z69 -> #NUM!
... B537: 480 | C537: =G536 -> #NUM! | D537: =-PMT($D$7/12,$D$9*12,$D$6,,) -> #NUM! | E537: =C537*$D$7/12 -> #NUM! | F537: =D537-E537 -> #NUM! | G537: =C537-F537 -> #NUM! | V537: 480 | W537: =AA536 -> #NUM! | X537: =-PMT($X$7/12,$X$9*12,$X$6,,) -> #NUM! | Y537: =W537*$X$7/12 -> #NUM! | Z537: =X537-Y537 -> #NUM! | AA537: =W537-Z537 -> #NUM!
